Workbook

Sheet README
A1: README / START
A2: Добавлены реальные импортированные позиции из PRICE_MASTER
A3: Смотри листы: IMPORT_SUMMARY, PRICE_MASTER_REAL, WORK_MASTER_REAL, MATERIAL_MASTER_REAL, MATERIAL_VARIANTS_REAL, RAW_MAPPING_REAL
A4: Листы REAL_TARIFF_DEFAULTS_* содержат только безопасные стартовые правила 1:1 и требуют ручной настройки.
A5: Листы REAL_NORMALIZATION_REVIEW и REAL_GAPS показывают, где ещё нужна ручная доработка.
A6: 3) MATERIAL_MASTER — канонические материалы/семейства.
A7: 4) MATERIAL_VARIANTS — варианты материала (толщина, цвет, фаска, класс нагрузки, цена).
A8: 5) RAW_MAPPING — связь сырых строк из старых прайсов с каноническими сущностями и вариантами.
A10: Базовые правила:
A11: • RawName хранить как пришло из исходника; не делать его универсальным.
A12: • CanonicalWork / CanonicalMaterial — единая нормализованная сущность.
A13: • RowNumber использовать только как след старой структуры, а не как ключ новой базы.
... A62: Смысл: шаблон перестроен из «набора примеров» в более полный каркас движка генератора КП.

Sheet CRITIQUE_AND_GAPS
A1: Layer | B1: CurrentWeakness | C1: WhyItBreaksTheGenerator | D1: WhatWasAddedInV5 | E1: Priority | F1: Status
A2: 1. Архитектура расчета | B2: Не была явно зафиксирована очередность применения правил и коэффициентов | C2: Без порядка приоритета модель начинает по-разному считать одну и ту же строку | D2: Добавлен лист CALC_PRECEDENCE с порядком применения: override → variant → site → tariff → reserve → rounding → min charges → VAT | E2: Critical | F2: Added
A3: 2. Условия объекта | B3: Были грунт/рельеф, но не было расстояния, сезона, срочности и налогового режима | C3: Коммерческая цена и логистика поедут даже при верных работах и материалах | D3: OBJECT_CONDITIONS расширен: distance, season, urgency, tax, VAT | E3: Critical | F3: Added
A4: 3. Логистика и операционные коэффициенты | B4: Отсутствовали distance/season/urgency коэффициенты | C4: Занижение маленьких, дальних и срочных объектов | D4: Добавлен OPERATING_COEFFS | E4: High | F4: Added
A5: 4. Закупка материалов | B5: Был запас, но не было правил округления закупки, MOQ и шагов заказа | C5: Генератор может посчитать правильный расход и все равно неверно заказать | D5: Добавлен PROCUREMENT_RULES | E5: Critical | F5: Added
A6: 5. Минимальные коммерческие пороги | B6: Не было minimum charge, mobilization, visit charge, floor для маленьких объектов | C6: Мелкие заказы будут системно недооценены | D6: Добавлен COMMERCIAL_POLICY | E6: Critical | F6: Added
A7: 6. Совместимость и автодобавления | B7: Не было явного слоя dependency/compatibility | C7: Смета может собрать невозможную комбинацию | D7: Добавлен DEPENDENCY_RULES | E7: High | F7: Added
A8: 7. Вывод клиенту | B8: Не было отдельной политики вывода по разделам и типам строк | C8: КП может быть либо перегружено, либо слишком пусто | D8: Добавлен OUTPUT_RULES | E8: Medium | F8: Added
A9: 8. Контроль качества данных | B9: Не было валидации обязательных полей и конфликтов | C9: Ошибки останутся тихими до момента отправки КП | D9: Добавлены VALIDATION_RULES и VALIDATION_EXAMPLE | E9: Critical | F9: Added
A10: 9. Юридические и коммерческие оговорки | B10: Не было библиотеки стандартных inclusion/exclusion/assumption | C10: Даже верная цифра без условий порождает спор с клиентом | D10: Добавлен EXCLUSIONS_LIBRARY | E10: High | F10: Added
A11: 10. Управление ценами | B11: В каталогах не хватало price source/validity/tax/lead time | C11: Нельзя контролировать устаревшие цены и происхождение цифры | D11: Расширены WORK_MASTER и MATERIAL_VARIANTS | E11: High | F11: Added
A12: 11. Внутренний и клиентский контур | B12: Не были разделены коммерческие коэффициенты и налоговый режим | C12: Смешивание sell-logic и tax приводит к двойному/нулевому НДС | D12: Добавлены TAX_MODES и логика VAT в примерах | E12: High | F12: Added
A13: 12. Итоговый пример расчета | B13: Пример был полезным, но не отражал полный расчетный стек | C13: Пользователь не видит, как сходятся все правила вместе | D13: Добавлен KP_ENGINE_V5_EXAMPLE | E13: Critical | F13: Added

Sheet CALC_PRECEDENCE
A1: StepNo | B1: Layer | C1: AppliedWhen | D1: RuleSource | E1: OutputField | F1: PriorityLogic | G1: FormulaSkeleton | H1: WhyNeeded | I1: Notes
A2: 1 | B2: Direct override | C2: Если задан ManualOverridePrice или explicit PreferredVariantID | D2: WORK_VARIANTS / ручной ввод | E2: BaseUnitPrice / Variant | F2: Override всегда бьет базу | G2: Price = ManualOverridePrice | H2: Позволяет не ломать модель там, где коэффициентами не описать | I2: Для rare cases
A3: 2 | B3: Variant resolution | C3: Когда есть Method/Variant/Tariff rules | D3: WORK_VARIANTS / MATERIAL_VARIANTS / *_TARIFF_RULES | E3: ResolvedVariantID / MethodCoeff | F3: Выбрать прямую цену варианта до общих коэффициентов | G3: Base = VariantPrice or MasterBasePrice | H3: Иначе база и вариант конфликтуют
A4: 3 | B4: Site factors | C4: Когда строка чувствительна к условиям участка | D4: WORK_FACTOR_APPLICABILITY / MATERIAL_FACTOR_APPLICABILITY / OBJECT_CONDITIONS | E4: SiteCoeff | F4: Только для чувствительных позиций | G4: Adj = 1 + Σ(weight*(coeff-1)) | H4: Иначе будет двойной учет
A5: 4 | B5: Operating factors | C5: Дальность, сезон, срочность | D5: OPERATING_COEFFS / OBJECT_CONDITIONS | E5: OperatingCoeff | F5: Применять только к work/logistics и частично к material delivery | G5: Adj = Distance*Season*Urgency | H5: Учитывает эксплуатационную реальность
A6: 5 | B6: Tariff rules | C6: Всегда при выбранном тарифе | D6: TARIFF_PROFILES / *_TARIFF_RULES | E6: TariffCoeff / display | F6: Override строки сильнее профиля тарифа | G6: Adj = TariffOverride or TariffProfile | H6: Тариф меняет не только цену, но и вывод
A7: 6 | B7: Reserve / waste | C7: Только для материалов | D7: MATERIAL_ALLOWANCES + тариф bias | E7: ReserveCoeff | F7: Сначала физический расход, затем bias тарифа | G7: PurchaseNet = NetQty * ReserveCoeff | H7: Разных причин потерь нельзя смешивать
A8: 7 | B8: Procurement rounding | C8: Только для материалов/логистики | D8: PROCUREMENT_RULES | E8: PurchaseQty | F8: Округление после запаса | G8: PurchaseQty = ROUNDUP(...) | H8: Иначе расход верный, закупка неверная
A9: 8 | B9: Commercial floors | C9: Малые объекты, выезды, мобилизация | D9: COMMERCIAL_POLICY | E9: MinCharge / Mobilization | F9: После построчного расчета и до НДС | G9: Subtotal = MAX(sum, MinQuoteValue)+charges | H9: Иначе маленькие объекты убыточны
A10: 9 | B10: VAT / tax | C10: В конце | D10: TAX_MODES / OBJECT_CONDITIONS | E10: PriceIncVAT | F10: НДС последним слоем поверх ex VAT | G10: IncVAT = ExVAT*(1+VATRate) | H10: Иначе высокий риск двойного учета
A11: 10 | B11: Output assembly | C11: После расчета | D11: OUTPUT_RULES / EXCLUSIONS_LIBRARY | E11: Client lines and notes | F11: Не меняет математику, меняет упаковку | G11: Bundle, hide, reorder, append notes | H11: Иначе хороший расчет плохо продается

Sheet DICTIONARIES
A1: Sections | B1: PositionTypes | C1: Units | D1: DisplayModes | E1: ExecutionMethods | F1: PricingModels | G1: YesNo | H1: EntityTypes | I1: MappingConfidence | J1: MappingStatus | K1: LoadClass | L1: Surface | M1: EdgeType | N1: Colors | O1: MaterialTypes | P1: SoilWorkability | Q1: SoilMoisture | R1: DebrisLevel | S1: SlopeClass | T1: UnevennessClass | U1: AccessClass | V1: TurnSpace | W1: ProximityClass | X1: MachineryAllowed | Y1: RuleAction | Z1: RuleScope | AB1: ConditionFields | AC1: AllowanceGroups | AD1: AllowanceTypes | AE1: MaterialCalcModes | AF1: GeometryComplexity | AG1: PurchaseUnits | AH1: MaterialScopeType | AI1: MaterialConditionFields | AJ1: Tariffs | AK1: TariffScope | AL1: TariffDisplayMode | AM1: SeasonClass | AN1: UrgencyClass | AO1: DistanceClass | AP1: TaxModes | AQ1: RoundingModes | AR1: PurchaseRoundBasis | AS1: Severity | AT1: ValidationRuleType | AU1: KPLineTypes | AV1: BundleModes | AW1: InclusionType | AX1: ApprovalLevel | AY1: PriceSourceType | AZ1: SortProfile
A2: Мощение | B2: Работа | C2: м2 | D2: Показать строкой | E2: Стандарт | F2: за м2 | G2: Да | H2: Work | I2: High | J2: Approved | K2: Пешеходная | L2: Гладкая | M2: Без фаски | N2: Серый | O2: Покрытие | P2: Лёгкая | Q2: Сухая | R2: Нет | S2: 0-3% | T2: Низкая | U2: Свободный | V2: Достаточно | W2: Нет влияния | X2: Да | Y2: ForceMethod | Z2: Work | AB2: SoilWorkability | AC2: Сыпучие с уплотнением | AD2: Разрыхление/уплотнение | AE2: NetQty x BaseReserveCoeff | AF2: Простая | AG2: м2 | AH2: MaterialType | AI2: GeometryComplexity | AJ2: Эконом | AK2: Work | AL2: Свернуть в раздел | AM2: Низкий сезон | AN2: Планово | AO2: До 10 км | AP2: Без НДС | AQ2: UP | AR2: По упаковке | AS2: Info | AT2: Required | AU2: Work | AV2: Минимум | AW2: Inclusion | AX2: Менеджер | AY2: Прайс поставщика | AZ2: Эконом
A3: Газон | B3: Материал | C3: м.п. | D3: Свернуть в раздел | E3: Ручной | F3: за м.п. | G3: Нет | H3: Material | I3: Medium | J3: Review | K3: Легковой транспорт | L3: Фактурная | M3: С фаской | N3: Красный | O3: Сыпучий материал | P3: Средняя | Q3: Нормальная | R3: Умеренно | S3: 3-8% | T3: Средняя | U3: Ограниченный | V3: Ограниченно | W3: Близко | X3: Частично | Y3: PreferMethod | Z3: Section | AB3: SoilMoisture | AC3: Сыпучие без уплотнения | AD3: Запас на подрезку | AE3: NetQty x BaseReserveCoeff x SiteReserveCoeff | AF3: Средняя | AG3: шт | AH3: MaterialFamily | AI3: SlopeClass | AJ3: Стандарт | AK3: Material | AL3: Показать строкой | AM3: Базовый сезон | AN3: Ускоренно | AO3: 10-30 км | AP3: С НДС 20% | AQ3: NEAREST | AR3: По паллете | AS3: Warn | AT3: AllowedList | AU3: Material | AV3: База | AW3: Exclusion | AX3: Прораб | AY3: Историческая цена | AZ3: Стандарт
A4: Дренаж | B4: Техника | C4: шт | D4: Скрыть из клиентской версии | E4: Механизированный | F4: за шт | I4: Low | J4: Draft | K4: Повышенная нагрузка | L4: Не задано | M4: Не задано | N4: Коричневый | O4: Бортовой элемент | P4: Тяжёлая | Q4: Влажная | R4: Высоко | S4: 8-15% | T4: Высокая | U4: Очень стеснённый | V4: Нет | W4: Очень близко | X4: Нет | Y4: AddNote | Z4: Material | AB4: DebrisLevel | AC4: Штучное покрытие | AD4: Запас на нахлест | AE4: DesignCompactedVolume x BaseReserveCoeff | AF4: Сложная | AG4: рулон | AH4: MaterialID | AI4: SurfaceUnevenness | AJ4: Премиум | AK4: Section | AL4: Показать строкой | AM4: Высокий сезон | AN4: Срочно | AO4: 30-60 км | AP4: С НДС 10% | AQ4: DOWN | AR4: По рулону/листу | AS4: Block | AT4: NonNegative | AU4: Logistics | AV4: Детально | AW4: Assumption | AX4: Финдир | AY4: Ручной ввод | AZ4: Премиум
A5: Ливневая канализация | B5: Логистика | C5: м3 | E5: Смешанный | F5: за м3 | K5: Не задан | N5: Черный | O5: Сетка / текстиль | P5: Очень тяжёлая | Q5: Переувлажнённая | S5: >15% | Y5: AddWork | AB5: SlopeClass | AC5: Рулонный текстиль | AD5: Запас на стыковку/подгонку | AE5: DesignCompactedVolume x BaseReserveCoeff x SiteReserveCoeff | AF5: Очень сложная | AG5: лист | AH5: AllowanceGroup | AI5: AccessClass | AM5: Зимние условия | AO5: 60+ км | AR5: По рейсу | AT5: Compatibility | AU5: Overhead | AX5: Руководитель | AY5: Расчетная | AZ5: Внутренний
A6: Освещение | B6: Накладные | C6: компл | F6: фикс | N6: Не задано | O6: Прочее | Y6: AddMaterial | AB6: SurfaceUnevenness | AC6: Рулонный газон / турф | AD6: Бой/технологический запас | AG6: пачка | AI6: ProximityToBuildings | AR6: Без округления | AT6: Flag | AU6: Service
A7: Земляные и планировочные работы | B7: Услуга | C7: смена | F7: % | O7: Пленка / мембрана | AB7: AccessClass | AC7: Пленка / мембрана | AD7: Торцовка/раскрой | AG7: м3
A8: Ступени / пандусы / бетонные элементы | C8: % | F8: по запросу | O8: Погонаж / доска | AB8: TurnSpace | AC8: Погонаж / доска | AD8: Технологический запас | AG8: м.п.
A9: Закладные / коммуникации | C9: усл. | O9: Рулонный газон | AB9: ProximityToBuildings | AC9: Линейный / штучный без существенной подрезки
A10: Демонтаж и расчистка | C10: м | AB10: MachineryAllowed
A11: Посадки и уход | C11: т
A12: Полив | C12: кг
A13: Вывоз и утилизация | C13: рулон
A14: Временные сооружения и обеспечение | C14: лист
A15: Логистика и снабжение | C15: пачка
A16: Накладные / коэффициенты
A17: Сопровождение проекта / услуги

Sheet WORK_MASTER
A1: WorkID | B1: CanonicalWork | C1: CommercialName | D1: Section | E1: Subsection | F1: PositionType | G1: Unit | H1: PricingModel | I1: BasePrice | J1: BaseMethod | K1: ClientDisplayMode | L1: Keywords | M1: BundleEligible | N1: IsActive | O1: Notes | P1: TariffSensitive | Q1: PriceSource | R1: PriceValidFrom | S1: PriceValidTo | T1: TaxMode | U1: CrewType | V1: MinCrewDays
A2: WORK-0001 | B2: Выборка ложа | C2: Подготовка ложа | D2: Мощение | E2: Подготовка основания | F2: Работа | G2: м2 | H2: за м2 | I2: 350 | J2: Стандарт | K2: Показать строкой | L2: выборка, ложе, основание | M2: Да | N2: Да | O2: Пример канонической работы | P2: Да | Q2: Историческая цена | R2: 46023 | S2: 46387 | T2: Без НДС | U2: Бригада мощения | V2: 1
A3: WORK-0002 | B3: Устройство газонного ложа | C3: Устройство газонного основания | D3: Газон | E3: Подготовка основания | F3: Работа | G3: м2 | H3: за м2 | I3: 320 | J3: Стандарт | K3: Показать строкой | L3: газонное ложе, основание газона | M3: Да | N3: Да | O3: Пример для работы с вариантами метода | P3: Да
A4: WORK-0003 | B4: Копка траншеи | C4: Разработка траншеи | D4: Закладные / коммуникации | E4: Траншеи | F4: Работа | G4: м.п. | H4: за м.п. | I4: 0 | J4: Стандарт | K4: Показать строкой | L4: траншея, кабель, копка | M4: Да | N4: Да | O4: Базовую цену заполнить | P4: Да
A5: WORK-0004 | B5: Монтаж бордюра бетонного | C5: Монтаж бордюра | D5: Мощение | E5: Бордюры | F5: Работа | G5: м.п. | H5: за м.п. | I5: 0 | J5: Стандарт | K5: Показать строкой | L5: бордюр, монтаж | M5: Да | N5: Да | P5: Да

Sheet WORK_VARIANTS
A1: VariantID | B1: WorkID | C1: ExecutionMethod | D1: ConditionTag | E1: MethodCoeff | F1: ConditionCoeff | G1: ManualOverridePrice | H1: EffectiveUnitPrice | I1: IsDefault | J1: IsActive | K1: Notes
A2: WV-0001 | B2: WORK-0001 | C2: Ручной | D2: Стандарт | E2: 1.2 | F2: 1 | I2: Нет | J2: Да | K2: Пример: коэффициент только для демонстрации
A3: WV-0002 | B3: WORK-0001 | C3: Механизированный | D3: Стандарт | E3: 0.9 | F3: 1 | I3: Нет | J3: Да
A4: WV-0003 | B4: WORK-0002 | C4: Стандарт | D4: Стандарт | E4: 1 | F4: 1 | I4: Да | J4: Да | K4: База
A5: WV-0004 | B5: WORK-0002 | C5: Ручной | D5: Стандарт | E5: 1.25 | F5: 1 | I5: Нет | J5: Да | K5: Пример, который нужно калибровать
A6: WV-0005 | B6: WORK-0002 | C6: Механизированный | D6: Стандарт | E6: 0.85 | F6: 1 | I6: Нет | J6: Да | K6: Пример, который нужно калибровать
A7: WV-0006 | B7: WORK-0002 | C7: Ручной | D7: Стесненные условия | E7: 1.25 | F7: 1.15 | I7: Нет | J7: Да | K7: Пример 2-го слоя коэффициентов

Sheet MATERIAL_MASTER
A1: MaterialID | B1: MaterialFamily | C1: CanonicalMaterial | D1: CommercialBaseName | E1: Section | F1: Subsection | G1: PositionType | H1: BaseUnit | I1: LengthMM | J1: WidthMM | K1: MaterialType | L1: DefaultClientDisplayMode | M1: IsActive | N1: Notes | O1: AllowanceGroup | P1: BaseReserveCoeff | Q1: AllowanceCalcMode | R1: TariffSensitive
A2: MAT-0001 | B2: Брусчатка бетонная | C2: Брусчатка бетонная 200x100 | D2: Брусчатка бетонная | E2: Мощение | F2: Покрытие | G2: Материал | H2: м2 | I2: 200 | J2: 100 | K2: Покрытие | L2: Показать строкой | M2: Да | N2: Одна сущность, а толщина/цвет/фаска идут в варианты | O2: Штучное покрытие | P2: 1.05 | Q2: NetQty x BaseReserveCoeff x SiteReserveCoeff | R2: Да
A3: MAT-0002 | B3: Бордюр бетонный | C3: Бордюр бетонный 1000x200x80 | D3: Бордюр бетонный | E3: Мощение | F3: Бордюры | G3: Материал | H3: шт | I3: 1000 | J3: 200 | K3: Бортовой элемент | L3: Показать строкой | M3: Да | N3: Размеры можно хранить по бизнес-логике | O3: Линейный / штучный без существенной подрезки | P3: 1.02 | Q3: NetQty x BaseReserveCoeff | R3: Да
A4: MAT-0003 | B4: Геотекстиль | C4: Геотекстиль 200 г/м2 | D4: Геотекстиль | E4: Дренаж | F4: Разделительный слой | G4: Материал | H4: м2 | K4: Сетка / текстиль | L4: Свернуть в раздел | M4: Да | N4: Базовый пример рулонного материала с нахлестом и подрезкой | O4: Рулонный текстиль | P4: 1.133 | Q4: NetQty x BaseReserveCoeff x SiteReserveCoeff | R4: Да
A5: MAT-0004 | B5: Газон рулонный | C5: Газон рулонный стандарт | D5: Газон рулонный | E5: Газон | F5: Покрытие | G5: Материал | H5: м2 | K5: Рулонный газон | L5: Показать строкой | M5: Да | N5: Запас нужен на подрезку и подгонку по геометрии | O5: Рулонный газон / турф | P5: 1.05 | Q5: NetQty x BaseReserveCoeff x SiteReserveCoeff | R5: Да
A6: MAT-0005 | B6: Пленка / мембрана | C6: Пленка / мембрана защитная | D6: Пленка / мембрана | E6: Дренаж | F6: Изоляция | G6: Материал | H6: м2 | K6: Пленка / мембрана | L6: Свернуть в раздел | M6: Да | N6: Обычно есть нахлест и подрезка | O6: Пленка / мембрана | P6: 1.154 | Q6: NetQty x BaseReserveCoeff x SiteReserveCoeff | R6: Да
A7: MAT-0006 | B7: Террасная доска | C7: Террасная доска стандарт | D7: Террасная доска | E7: Мощение | F7: Деревянные покрытия | G7: Материал | H7: м2 | K7: Погонаж / доска | L7: Показать строкой | M7: Да | N7: Нужен запас на торцовку и раскрой | O7: Погонаж / доска | P7: 1.1 | Q7: NetQty x BaseReserveCoeff x SiteReserveCoeff | R7: Да
A8: MAT-0007 | B8: Щебень фр. 20-40 | C8: Щебень фр. 20-40 | D8: Щебень | E8: Мощение | F8: Основание | G8: Материал | H8: м3 | K8: Сыпучий материал | L8: Свернуть в раздел | M8: Да | N8: От проектного уплотненного объема к закупке через коэффициент | O8: Сыпучие с уплотнением | P8: 1.18 | Q8: DesignCompactedVolume x BaseReserveCoeff x SiteReserveCoeff | R8: Да

Sheet MATERIAL_VARIANTS
A1: VariantID | B1: MaterialID | C1: ThicknessMM | D1: Color | E1: Surface | F1: EdgeType | G1: LoadClass | H1: Manufacturer | I1: PricePerUnit | J1: ClientName | K1: ClientDisplayMode | L1: IsDefault | M1: IsActive | N1: Notes | O1: PurchaseUnit | P1: CoveragePerPurchaseUnit | Q1: CoverageUnit | R1: Supplier | S1: LeadTimeDays | T1: PriceSource | U1: PriceValidFrom | V1: PriceValidTo | W1: TaxMode | X1: MOQ | Y1: OrderStepQty
A2: MV-0001 | B2: MAT-0001 | C2: 40 | D2: Серый | E2: Гладкая | F2: Без фаски | G2: Пешеходная | I2: 0 | J2: Брусчатка бетонная 200x100x40 мм | K2: Показать строкой | L2: Нет | M2: Да | N2: Пример варианта; цену заполнить | O2: м2 | P2: 1 | Q2: м2 | R2: Поставщик A | S2: 5 | T2: Прайс поставщика | U2: 46082 | V2: 46112 | W2: С НДС 20% | X2: 10 | Y2: 10
A3: MV-0002 | B3: MAT-0001 | C3: 60 | D3: Серый | E3: Гладкая | F3: Без фаски | G3: Легковой транспорт | I3: 0 | J3: Брусчатка бетонная 200x100x60 мм | K3: Показать строкой | L3: Да | M3: Да | N3: Базовый вариант для частного участка | O3: м2 | P3: 1 | Q3: м2
A4: MV-0003 | B4: MAT-0001 | C4: 80 | D4: Серый | E4: Гладкая | F4: Без фаски | G4: Повышенная нагрузка | I4: 0 | J4: Брусчатка бетонная 200x100x80 мм | K4: Показать строкой | L4: Нет | M4: Да | O4: м2 | P4: 1 | Q4: м2
A5: MV-0004 | B5: MAT-0003 | I5: 0 | J5: Геотекстиль 200 г/м2 | K5: Свернуть в раздел | L5: Да | M5: Да | N5: Площадь рулона заполни по поставщику | O5: рулон | P5: 0 | Q5: м2
A6: MV-0005 | B6: MAT-0004 | I6: 0 | J6: Газон рулонный стандарт | K6: Показать строкой | L6: Да | M6: Да | N6: Размер рулона заполни по поставщику | O6: рулон | P6: 0 | Q6: м2
A7: MV-0006 | B7: MAT-0005 | I7: 0 | J7: Пленка / мембрана защитная | K7: Свернуть в раздел | L7: Да | M7: Да | N7: Ширину рулона и покрытие укажи по поставщику | O7: рулон | P7: 0 | Q7: м2
A8: MV-0007 | B8: MAT-0006 | I8: 0 | J8: Террасная доска стандарт | K8: Показать строкой | L8: Да | M8: Да | N8: Укажи покрытие одной пачки или одной доски | O8: пачка | P8: 0 | Q8: м2
A9: MV-0008 | B9: MAT-0007 | I9: 0 | J9: Щебень фр. 20-40 | K9: Свернуть в раздел | L9: Да | M9: Да | N9: Закупка обычно в м3 или т; приведи к своей схеме | O9: м3 | P9: 1 | Q9: м3

Sheet RAW_MAPPING
A1: SourceRowID | B1: RawName | C1: SourceSheet | D1: SourceRowNumber | E1: SourceSection | F1: EntityType | G1: MasterID | H1: VariantID | I1: MappingConfidence | J1: MappingStatus | K1: NeedsReview | L1: Notes
A2: SRC-0001 | B2: Выборка ложа | C2: PRICE_MASTER | D2: 101 | E2: Мощение | F2: Work | G2: WORK-0001 | I2: High | J2: Approved | K2: Нет | L2: Прямое сопоставление
A3: SRC-0002 | B3: Устройство газонного ложа | C3: PRICE_MASTER | D3: 205 | E3: Газон | F3: Work | G3: WORK-0002 | I3: High | J3: Approved | K3: Нет | L3: Прямое сопоставление
A4: SRC-0003 | B4: Брусчатка 200*100*60 серая | C4: PRICE_MASTER | D4: 305 | E4: Мощение | F4: Material | G4: MAT-0001 | H4: MV-0002 | I4: High | J4: Approved | K4: Нет | L4: Материал связан и с Master, и с Variant

Sheet VALIDATION_RULES
A1: RuleID | B1: Scope | C1: RuleType | D1: FieldName | E1: Condition | F1: Severity | G1: UserMessage | H1: SuggestedFix | I1: Notes
A2: VR-0001 | B2: OBJECT | C2: Required | D2: SelectedTariff | E2: Всегда | F2: Block | G2: Не выбран тариф объекта | H2: Заполнить SelectedTariff в OBJECT_CONDITIONS
A3: VR-0002 | B3: OBJECT | C3: Required | D3: TaxMode | E3: Всегда | F3: Block | G3: Не указан налоговый режим | H3: Выбрать TaxMode
A4: VR-0003 | B4: OBJECT | C4: Required | D4: DistanceClass | E4: Когда есть логистика/доставка | F4: Warn | G4: Не указан класс расстояния | H4: Заполнить DistanceClass
A5: VR-0004 | B5: WORK | C5: NonNegative | D5: BasePrice | E5: Всегда | F5: Block | G5: У работы отрицательная или пустая базовая цена | H5: Заполнить BasePrice >= 0
A6: VR-0005 | B6: MATERIAL | C6: Compatibility | D6: PurchaseUnit vs CoveragePerPurchaseUnit | E6: Если материал активен | F6: Warn | G6: Не заполнены единицы закупки/покрытия | H6: Заполнить PurchaseUnit и CoveragePerPurchaseUnit
A7: VR-0006 | B7: MATERIAL | C7: Compatibility | D7: AllowanceGroup vs ProcurementRule | E7: Если материал активен | F7: Warn | G7: Нет правила закупки для AllowanceGroup | H7: Добавить PROCUREMENT_RULES
A8: VR-0007 | B8: QUOTE | C8: Flag | D8: MinQuoteValue | E8: Если итог < порога | F8: Warn | G8: Итог ниже минимальной коммерческой планки | H8: Применить floor/mobilization

Sheet VALIDATION_EXAMPLE
A1: ObjectID | B1: QuoteTariff | C1: CheckName | D1: Severity | E1: IsTriggered | F1: CheckValue | G1: ThresholdOrRule | H1: UserMessage | I1: Comment
A2: OBJ-0001 | B2: =IF($A2="","",INDEX(OBJECT_CONDITIONS!$X:$X,MATCH($A2,OBJECT_CONDITIONS!$A:$A,0))) | C2: Тариф выбран | D2: Block | E2: =IF($A2="","",IF($B2="","TRIGGER","OK")) | F2: =IF($A2="","",IF($B2="","", $B2)) | G2: SelectedTariff not blank | H2: Должен быть выбран тариф объекта
A3: OBJ-0001 | B3: =IF($A3="","",INDEX(OBJECT_CONDITIONS!$AM:$AM,MATCH($A3,OBJECT_CONDITIONS!$A:$A,0))) | C3: Налоговый режим выбран | D3: Block | E3: =IF($A3="","",IF($B3="","TRIGGER","OK")) | F3: =IF($A3="","",IF($B3="","",$B3)) | G3: TaxMode not blank | H3: Должен быть указан налоговый режим
A4: OBJ-0001 | B4: =IF($A4="","",INDEX(OBJECT_CONDITIONS!$AG:$AG,MATCH($A4,OBJECT_CONDITIONS!$A:$A,0))) | C4: Класс расстояния заполнен | D4: Warn | E4: =IF($A4="","",IF($B4="","TRIGGER","OK")) | F4: =IF($A4="","",IF($B4="","",$B4)) | G4: DistanceClass not blank | H4: Для логистики нужен класс расстояния
A5: OBJ-0001 | B5: Премиум | C5: Итог КП >= min quote floor | D5: Warn | E5: =IF(SUM(KP_ENGINE_V5_EXAMPLE!$U$2:$U$20)<INDEX(COMMERCIAL_POLICY!$B:$B,MATCH($B5,COMMERCIAL_POLICY!$A:$A,0)),"TRIGGER","OK") | F5: =SUM(KP_ENGINE_V5_EXAMPLE!$U$2:$U$20) | G5: =INDEX(COMMERCIAL_POLICY!$B:$B,MATCH($B5,COMMERCIAL_POLICY!$A:$A,0)) | H5: Итог ниже минимальной планки

Sheet OBJECT_CONDITIONS
A1: ObjectID | B1: ObjectName | C1: SoilWorkability | D1: SoilCoeff | E1: SoilMoisture | F1: MoistureCoeff | G1: DebrisLevel | H1: DebrisCoeff | I1: SlopeClass | J1: SlopeCoeff | K1: SurfaceUnevenness | L1: UnevennessCoeff | M1: AccessClass | N1: AccessCoeff | O1: TurnSpace | P1: TurnSpaceCoeff | Q1: ProximityToBuildings | R1: ProximityCoeff | S1: MachineryAllowed | T1: MachineryCoeff | U1: Notes | V1: GeometryComplexity | W1: GeometryCoeff | X1: SelectedTariff | Y1: TariffWorkCoeff | Z1: TariffMaterialCoeff | AA1: TariffLogisticsCoeff | AB1: TariffOverheadCoeff | AC1: TariffReserveBiasCoeff | AD1: TariffDisplayMode | AE1: TariffNotes | AF1: DistanceFromBaseKM | AG1: DistanceClass | AH1: DistanceCoeff | AI1: SeasonClass | AJ1: SeasonCoeff | AK1: UrgencyClass | AL1: UrgencyCoeff | AM1: TaxMode | AN1: VATRate | AO1: LogisticsTrips | AP1: DisposalDistanceKM
A2: OBJ-0001 | B2: Частный участок — базовый сложный кейс | C2: Тяжёлая | D2: =IF($C2="","",SUMIFS(SITE_COEFFS!$C:$C,SITE_COEFFS!$A:$A,"SoilWorkability",SITE_COEFFS!$B:$B,$C2)) | E2: Влажная | F2: =IF($E2="","",SUMIFS(SITE_COEFFS!$C:$C,SITE_COEFFS!$A:$A,"SoilMoisture",SITE_COEFFS!$B:$B,$E2)) | G2: Умеренно | H2: =IF($G2="","",SUMIFS(SITE_COEFFS!$C:$C,SITE_COEFFS!$A:$A,"DebrisLevel",SITE_COEFFS!$B:$B,$G2)) | I2: 8-15% | J2: =IF($I2="","",SUMIFS(SITE_COEFFS!$C:$C,SITE_COEFFS!$A:$A,"SlopeClass",SITE_COEFFS!$B:$B,$I2)) | K2: Средняя | L2: =IF($K2="","",SUMIFS(SITE_COEFFS!$C:$C,SITE_COEFFS!$A:$A,"SurfaceUnevenness",SITE_COEFFS!$B:$B,$K2)) | M2: Ограниченный | N2: =IF($M2="","",SUMIFS(SITE_COEFFS!$C:$C,SITE_COEFFS!$A:$A,"AccessClass",SITE_COEFFS!$B:$B,$M2)) | O2: Ограниченно | P2: =IF($O2="","",SUMIFS(SITE_COEFFS!$C:$C,SITE_COEFFS!$A:$A,"TurnSpace",SITE_COEFFS!$B:$B,$O2)) | Q2: Близко | R2: =IF($Q2="","",SUMIFS(SITE_COEFFS!$C:$C,SITE_COEFFS!$A:$A,"ProximityToBuildings",SITE_COEFFS!$B:$B,$Q2)) | S2: Частично | T2: =IF($S2="","",SUMIFS(SITE_COEFFS!$C:$C,SITE_COEFFS!$A:$A,"MachineryAllowed",SITE_COEFFS!$B:$B,$S2)) | U2: Пример объекта для проверки формул | V2: Сложная | W2: =IF($V2="","",SUMIFS(SITE_COEFFS!$C:$C,SITE_COEFFS!$A:$A,"GeometryComplexity",SITE_COEFFS!$B:$B,$V2)) | Y2: =IF($X2="","",SUMIFS(TARIFF_PROFILES!$D:$D,TARIFF_PROFILES!$A:$A,$X2)) | Z2: =IF($X2="","",SUMIFS(TARIFF_PROFILES!$E:$E,TARIFF_PROFILES!$A:$A,$X2)) | AA2: =IF($X2="","",SUMIFS(TARIFF_PROFILES!$F:$F,TARIFF_PROFILES!$A:$A,$X2)) | AB2: =IF($X2="","",SUMIFS(TARIFF_PROFILES!$G:$G,TARIFF_PROFILES!$A:$A,$X2)) | AC2: =IF($X2="","",SUMIFS(TARIFF_PROFILES!$H:$H,TARIFF_PROFILES!$A:$A,$X2)) | AD2: =IF($X2="","",INDEX(TARIFF_PROFILES!$J:$J,MATCH($X2,TARIFF_PROFILES!$A:$A,0))) | AE2: =IF($X2="","",INDEX(TARIFF_PROFILES!$K:$K,MATCH($X2,TARIFF_PROFILES!$A:$A,0))) | AF2: 35 | AG2: 30-60 км | AH2: =IF($AG2="","",SUMIFS(OPERATING_COEFFS!$C:$C,OPERATING_COEFFS!$A:$A,"DistanceClass",OPERATING_COEFFS!$B:$B,$AG2)) | AI2: Высокий сезон | AJ2: =IF($AI2="","",SUMIFS(OPERATING_COEFFS!$C:$C,OPERATING_COEFFS!$A:$A,"SeasonClass",OPERATING_COEFFS!$B:$B,$AI2)) | AK2: Ускоренно | AL2: =IF($AK2="","",SUMIFS(OPERATING_COEFFS!$C:$C,OPERATING_COEFFS!$A:$A,"UrgencyClass",OPERATING_COEFFS!$B:$B,$AK2)) | AM2: С НДС 20% | AN2: =IF($AM2="","",INDEX(TAX_MODES!$B:$B,MATCH($AM2,TAX_MODES!$A:$A,0))) | AO2: 3 | AP2: 25
A3: OBJ-0002 | B3: Частный участок — лёгкие условия | C3: Лёгкая | D3: =IF($C3="","",SUMIFS(SITE_COEFFS!$C:$C,SITE_COEFFS!$A:$A,"SoilWorkability",SITE_COEFFS!$B:$B,$C3)) | E3: Нормальная | F3: =IF($E3="","",SUMIFS(SITE_COEFFS!$C:$C,SITE_COEFFS!$A:$A,"SoilMoisture",SITE_COEFFS!$B:$B,$E3)) | G3: Нет | H3: =IF($G3="","",SUMIFS(SITE_COEFFS!$C:$C,SITE_COEFFS!$A:$A,"DebrisLevel",SITE_COEFFS!$B:$B,$G3)) | I3: 0-3% | J3: =IF($I3="","",SUMIFS(SITE_COEFFS!$C:$C,SITE_COEFFS!$A:$A,"SlopeClass",SITE_COEFFS!$B:$B,$I3)) | K3: Низкая | L3: =IF($K3="","",SUMIFS(SITE_COEFFS!$C:$C,SITE_COEFFS!$A:$A,"SurfaceUnevenness",SITE_COEFFS!$B:$B,$K3)) | M3: Свободный | N3: =IF($M3="","",SUMIFS(SITE_COEFFS!$C:$C,SITE_COEFFS!$A:$A,"AccessClass",SITE_COEFFS!$B:$B,$M3)) | O3: Достаточно | P3: =IF($O3="","",SUMIFS(SITE_COEFFS!$C:$C,SITE_COEFFS!$A:$A,"TurnSpace",SITE_COEFFS!$B:$B,$O3)) | Q3: Нет влияния | R3: =IF($Q3="","",SUMIFS(SITE_COEFFS!$C:$C,SITE_COEFFS!$A:$A,"ProximityToBuildings",SITE_COEFFS!$B:$B,$Q3)) | S3: Да | T3: =IF($S3="","",SUMIFS(SITE_COEFFS!$C:$C,SITE_COEFFS!$A:$A,"MachineryAllowed",SITE_COEFFS!$B:$B,$S3)) | U3: Ровный участок с нормальным доступом | V3: Простая | W3: =IF($V3="","",SUMIFS(SITE_COEFFS!$C:$C,SITE_COEFFS!$A:$A,"GeometryComplexity",SITE_COEFFS!$B:$B,$V3)) | Y3: =IF($X3="","",SUMIFS(TARIFF_PROFILES!$D:$D,TARIFF_PROFILES!$A:$A,$X3)) | Z3: =IF($X3="","",SUMIFS(TARIFF_PROFILES!$E:$E,TARIFF_PROFILES!$A:$A,$X3)) | AA3: =IF($X3="","",SUMIFS(TARIFF_PROFILES!$F:$F,TARIFF_PROFILES!$A:$A,$X3)) | AB3: =IF($X3="","",SUMIFS(TARIFF_PROFILES!$G:$G,TARIFF_PROFILES!$A:$A,$X3)) | AC3: =IF($X3="","",SUMIFS(TARIFF_PROFILES!$H:$H,TARIFF_PROFILES!$A:$A,$X3)) | AD3: =IF($X3="","",INDEX(TARIFF_PROFILES!$J:$J,MATCH($X3,TARIFF_PROFILES!$A:$A,0))) | AE3: =IF($X3="","",INDEX(TARIFF_PROFILES!$K:$K,MATCH($X3,TARIFF_PROFILES!$A:$A,0))) | AF3: 8 | AG3: До 10 км | AH3: =IF($AG3="","",SUMIFS(OPERATING_COEFFS!$C:$C,OPERATING_COEFFS!$A:$A,"DistanceClass",OPERATING_COEFFS!$B:$B,$AG3)) | AI3: Базовый сезон | AJ3: =IF($AI3="","",SUMIFS(OPERATING_COEFFS!$C:$C,OPERATING_COEFFS!$A:$A,"SeasonClass",OPERATING_COEFFS!$B:$B,$AI3)) | AK3: Планово | AL3: =IF($AK3="","",SUMIFS(OPERATING_COEFFS!$C:$C,OPERATING_COEFFS!$A:$A,"UrgencyClass",OPERATING_COEFFS!$B:$B,$AK3)) | AM3: Без НДС | AN3: =IF($AM3="","",INDEX(TAX_MODES!$B:$B,MATCH($AM3,TAX_MODES!$A:$A,0))) | AO3: 1 | AP3: 5
D4: =IF($C4="","",SUMIFS(SITE_COEFFS!$C:$C,SITE_COEFFS!$A:$A,"SoilWorkability",SITE_COEFFS!$B:$B,$C4)) | F4: =IF($E4="","",SUMIFS(SITE_COEFFS!$C:$C,SITE_COEFFS!$A:$A,"SoilMoisture",SITE_COEFFS!$B:$B,$E4)) | H4: =IF($G4="","",SUMIFS(SITE_COEFFS!$C:$C,SITE_COEFFS!$A:$A,"DebrisLevel",SITE_COEFFS!$B:$B,$G4)) | J4: =IF($I4="","",SUMIFS(SITE_COEFFS!$C:$C,SITE_COEFFS!$A:$A,"SlopeClass",SITE_COEFFS!$B:$B,$I4)) | L4: =IF($K4="","",SUMIFS(SITE_COEFFS!$C:$C,SITE_COEFFS!$A:$A,"SurfaceUnevenness",SITE_COEFFS!$B:$B,$K4)) | N4: =IF($M4="","",SUMIFS(SITE_COEFFS!$C:$C,SITE_COEFFS!$A:$A,"AccessClass",SITE_COEFFS!$B:$B,$M4)) | P4: =IF($O4="","",SUMIFS(SITE_COEFFS!$C:$C,SITE_COEFFS!$A:$A,"TurnSpace",SITE_COEFFS!$B:$B,$O4)) | R4: =IF($Q4="","",SUMIFS(SITE_COEFFS!$C:$C,SITE_COEFFS!$A:$A,"ProximityToBuildings",SITE_COEFFS!$B:$B,$Q4)) | T4: =IF($S4="","",SUMIFS(SITE_COEFFS!$C:$C,SITE_COEFFS!$A:$A,"MachineryAllowed",SITE_COEFFS!$B:$B,$S4)) | W4: =IF($V4="","",SUMIFS(SITE_COEFFS!$C:$C,SITE_COEFFS!$A:$A,"GeometryComplexity",SITE_COEFFS!$B:$B,$V4)) | Y4: =IF($X4="","",SUMIFS(TARIFF_PROFILES!$D:$D,TARIFF_PROFILES!$A:$A,$X4)) | Z4: =IF($X4="","",SUMIFS(TARIFF_PROFILES!$E:$E,TARIFF_PROFILES!$A:$A,$X4)) | AA4: =IF($X4="","",SUMIFS(TARIFF_PROFILES!$F:$F,TARIFF_PROFILES!$A:$A,$X4)) | AB4: =IF($X4="","",SUMIFS(TARIFF_PROFILES!$G:$G,TARIFF_PROFILES!$A:$A,$X4)) | AC4: =IF($X4="","",SUMIFS(TARIFF_PROFILES!$H:$H,TARIFF_PROFILES!$A:$A,$X4)) | AD4: =IF($X4="","",INDEX(TARIFF_PROFILES!$J:$J,MATCH($X4,TARIFF_PROFILES!$A:$A,0))) | AE4: =IF($X4="","",INDEX(TARIFF_PROFILES!$K:$K,MATCH($X4,TARIFF_PROFILES!$A:$A,0))) | AH4: =IF($AG4="","",SUMIFS(OPERATING_COEFFS!$C:$C,OPERATING_COEFFS!$A:$A,"DistanceClass",OPERATING_COEFFS!$B:$B,$AG4)) | AJ4: =IF($AI4="","",SUMIFS(OPERATING_COEFFS!$C:$C,OPERATING_COEFFS!$A:$A,"SeasonClass",OPERATING_COEFFS!$B:$B,$AI4)) | AL4: =IF($AK4="","",SUMIFS(OPERATING_COEFFS!$C:$C,OPERATING_COEFFS!$A:$A,"UrgencyClass",OPERATING_COEFFS!$B:$B,$AK4)) | AN4: =IF($AM4="","",INDEX(TAX_MODES!$B:$B,MATCH($AM4,TAX_MODES!$A:$A,0)))
D5: =IF($C5="","",SUMIFS(SITE_COEFFS!$C:$C,SITE_COEFFS!$A:$A,"SoilWorkability",SITE_COEFFS!$B:$B,$C5)) | F5: =IF($E5="","",SUMIFS(SITE_COEFFS!$C:$C,SITE_COEFFS!$A:$A,"SoilMoisture",SITE_COEFFS!$B:$B,$E5)) | H5: =IF($G5="","",SUMIFS(SITE_COEFFS!$C:$C,SITE_COEFFS!$A:$A,"DebrisLevel",SITE_COEFFS!$B:$B,$G5)) | J5: =IF($I5="","",SUMIFS(SITE_COEFFS!$C:$C,SITE_COEFFS!$A:$A,"SlopeClass",SITE_COEFFS!$B:$B,$I5)) | L5: =IF($K5="","",SUMIFS(SITE_COEFFS!$C:$C,SITE_COEFFS!$A:$A,"SurfaceUnevenness",SITE_COEFFS!$B:$B,$K5)) | N5: =IF($M5="","",SUMIFS(SITE_COEFFS!$C:$C,SITE_COEFFS!$A:$A,"AccessClass",SITE_COEFFS!$B:$B,$M5)) | P5: =IF($O5="","",SUMIFS(SITE_COEFFS!$C:$C,SITE_COEFFS!$A:$A,"TurnSpace",SITE_COEFFS!$B:$B,$O5)) | R5: =IF($Q5="","",SUMIFS(SITE_COEFFS!$C:$C,SITE_COEFFS!$A:$A,"ProximityToBuildings",SITE_COEFFS!$B:$B,$Q5)) | T5: =IF($S5="","",SUMIFS(SITE_COEFFS!$C:$C,SITE_COEFFS!$A:$A,"MachineryAllowed",SITE_COEFFS!$B:$B,$S5)) | W5: =IF($V5="","",SUMIFS(SITE_COEFFS!$C:$C,SITE_COEFFS!$A:$A,"GeometryComplexity",SITE_COEFFS!$B:$B,$V5)) | Y5: =IF($X5="","",SUMIFS(TARIFF_PROFILES!$D:$D,TARIFF_PROFILES!$A:$A,$X5)) | Z5: =IF($X5="","",SUMIFS(TARIFF_PROFILES!$E:$E,TARIFF_PROFILES!$A:$A,$X5)) | AA5: =IF($X5="","",SUMIFS(TARIFF_PROFILES!$F:$F,TARIFF_PROFILES!$A:$A,$X5)) | AB5: =IF($X5="","",SUMIFS(TARIFF_PROFILES!$G:$G,TARIFF_PROFILES!$A:$A,$X5)) | AC5: =IF($X5="","",SUMIFS(TARIFF_PROFILES!$H:$H,TARIFF_PROFILES!$A:$A,$X5)) | AD5: =IF($X5="","",INDEX(TARIFF_PROFILES!$J:$J,MATCH($X5,TARIFF_PROFILES!$A:$A,0))) | AE5: =IF($X5="","",INDEX(TARIFF_PROFILES!$K:$K,MATCH($X5,TARIFF_PROFILES!$A:$A,0))) | AH5: =IF($AG5="","",SUMIFS(OPERATING_COEFFS!$C:$C,OPERATING_COEFFS!$A:$A,"DistanceClass",OPERATING_COEFFS!$B:$B,$AG5)) | AJ5: =IF($AI5="","",SUMIFS(OPERATING_COEFFS!$C:$C,OPERATING_COEFFS!$A:$A,"SeasonClass",OPERATING_COEFFS!$B:$B,$AI5)) | AL5: =IF($AK5="","",SUMIFS(OPERATING_COEFFS!$C:$C,OPERATING_COEFFS!$A:$A,"UrgencyClass",OPERATING_COEFFS!$B:$B,$AK5)) | AN5: =IF($AM5="","",INDEX(TAX_MODES!$B:$B,MATCH($AM5,TAX_MODES!$A:$A,0)))
D6: =IF($C6="","",SUMIFS(SITE_COEFFS!$C:$C,SITE_COEFFS!$A:$A,"SoilWorkability",SITE_COEFFS!$B:$B,$C6)) | F6: =IF($E6="","",SUMIFS(SITE_COEFFS!$C:$C,SITE_COEFFS!$A:$A,"SoilMoisture",SITE_COEFFS!$B:$B,$E6)) | H6: =IF($G6="","",SUMIFS(SITE_COEFFS!$C:$C,SITE_COEFFS!$A:$A,"DebrisLevel",SITE_COEFFS!$B:$B,$G6)) | J6: =IF($I6="","",SUMIFS(SITE_COEFFS!$C:$C,SITE_COEFFS!$A:$A,"SlopeClass",SITE_COEFFS!$B:$B,$I6)) | L6: =IF($K6="","",SUMIFS(SITE_COEFFS!$C:$C,SITE_COEFFS!$A:$A,"SurfaceUnevenness",SITE_COEFFS!$B:$B,$K6)) | N6: =IF($M6="","",SUMIFS(SITE_COEFFS!$C:$C,SITE_COEFFS!$A:$A,"AccessClass",SITE_COEFFS!$B:$B,$M6)) | P6: =IF($O6="","",SUMIFS(SITE_COEFFS!$C:$C,SITE_COEFFS!$A:$A,"TurnSpace",SITE_COEFFS!$B:$B,$O6)) | R6: =IF($Q6="","",SUMIFS(SITE_COEFFS!$C:$C,SITE_COEFFS!$A:$A,"ProximityToBuildings",SITE_COEFFS!$B:$B,$Q6)) | T6: =IF($S6="","",SUMIFS(SITE_COEFFS!$C:$C,SITE_COEFFS!$A:$A,"MachineryAllowed",SITE_COEFFS!$B:$B,$S6)) | W6: =IF($V6="","",SUMIFS(SITE_COEFFS!$C:$C,SITE_COEFFS!$A:$A,"GeometryComplexity",SITE_COEFFS!$B:$B,$V6)) | Y6: =IF($X6="","",SUMIFS(TARIFF_PROFILES!$D:$D,TARIFF_PROFILES!$A:$A,$X6)) | Z6: =IF($X6="","",SUMIFS(TARIFF_PROFILES!$E:$E,TARIFF_PROFILES!$A:$A,$X6)) | AA6: =IF($X6="","",SUMIFS(TARIFF_PROFILES!$F:$F,TARIFF_PROFILES!$A:$A,$X6)) | AB6: =IF($X6="","",SUMIFS(TARIFF_PROFILES!$G:$G,TARIFF_PROFILES!$A:$A,$X6)) | AC6: =IF($X6="","",SUMIFS(TARIFF_PROFILES!$H:$H,TARIFF_PROFILES!$A:$A,$X6)) | AD6: =IF($X6="","",INDEX(TARIFF_PROFILES!$J:$J,MATCH($X6,TARIFF_PROFILES!$A:$A,0))) | AE6: =IF($X6="","",INDEX(TARIFF_PROFILES!$K:$K,MATCH($X6,TARIFF_PROFILES!$A:$A,0))) | AH6: =IF($AG6="","",SUMIFS(OPERATING_COEFFS!$C:$C,OPERATING_COEFFS!$A:$A,"DistanceClass",OPERATING_COEFFS!$B:$B,$AG6)) | AJ6: =IF($AI6="","",SUMIFS(OPERATING_COEFFS!$C:$C,OPERATING_COEFFS!$A:$A,"SeasonClass",OPERATING_COEFFS!$B:$B,$AI6)) | AL6: =IF($AK6="","",SUMIFS(OPERATING_COEFFS!$C:$C,OPERATING_COEFFS!$A:$A,"UrgencyClass",OPERATING_COEFFS!$B:$B,$AK6)) | AN6: =IF($AM6="","",INDEX(TAX_MODES!$B:$B,MATCH($AM6,TAX_MODES!$A:$A,0)))
D7: =IF($C7="","",SUMIFS(SITE_COEFFS!$C:$C,SITE_COEFFS!$A:$A,"SoilWorkability",SITE_COEFFS!$B:$B,$C7)) | F7: =IF($E7="","",SUMIFS(SITE_COEFFS!$C:$C,SITE_COEFFS!$A:$A,"SoilMoisture",SITE_COEFFS!$B:$B,$E7)) | H7: =IF($G7="","",SUMIFS(SITE_COEFFS!$C:$C,SITE_COEFFS!$A:$A,"DebrisLevel",SITE_COEFFS!$B:$B,$G7)) | J7: =IF($I7="","",SUMIFS(SITE_COEFFS!$C:$C,SITE_COEFFS!$A:$A,"SlopeClass",SITE_COEFFS!$B:$B,$I7)) | L7: =IF($K7="","",SUMIFS(SITE_COEFFS!$C:$C,SITE_COEFFS!$A:$A,"SurfaceUnevenness",SITE_COEFFS!$B:$B,$K7)) | N7: =IF($M7="","",SUMIFS(SITE_COEFFS!$C:$C,SITE_COEFFS!$A:$A,"AccessClass",SITE_COEFFS!$B:$B,$M7)) | P7: =IF($O7="","",SUMIFS(SITE_COEFFS!$C:$C,SITE_COEFFS!$A:$A,"TurnSpace",SITE_COEFFS!$B:$B,$O7)) | R7: =IF($Q7="","",SUMIFS(SITE_COEFFS!$C:$C,SITE_COEFFS!$A:$A,"ProximityToBuildings",SITE_COEFFS!$B:$B,$Q7)) | T7: =IF($S7="","",SUMIFS(SITE_COEFFS!$C:$C,SITE_COEFFS!$A:$A,"MachineryAllowed",SITE_COEFFS!$B:$B,$S7)) | W7: =IF($V7="","",SUMIFS(SITE_COEFFS!$C:$C,SITE_COEFFS!$A:$A,"GeometryComplexity",SITE_COEFFS!$B:$B,$V7)) | Y7: =IF($X7="","",SUMIFS(TARIFF_PROFILES!$D:$D,TARIFF_PROFILES!$A:$A,$X7)) | Z7: =IF($X7="","",SUMIFS(TARIFF_PROFILES!$E:$E,TARIFF_PROFILES!$A:$A,$X7)) | AA7: =IF($X7="","",SUMIFS(TARIFF_PROFILES!$F:$F,TARIFF_PROFILES!$A:$A,$X7)) | AB7: =IF($X7="","",SUMIFS(TARIFF_PROFILES!$G:$G,TARIFF_PROFILES!$A:$A,$X7)) | AC7: =IF($X7="","",SUMIFS(TARIFF_PROFILES!$H:$H,TARIFF_PROFILES!$A:$A,$X7)) | AD7: =IF($X7="","",INDEX(TARIFF_PROFILES!$J:$J,MATCH($X7,TARIFF_PROFILES!$A:$A,0))) | AE7: =IF($X7="","",INDEX(TARIFF_PROFILES!$K:$K,MATCH($X7,TARIFF_PROFILES!$A:$A,0))) | AH7: =IF($AG7="","",SUMIFS(OPERATING_COEFFS!$C:$C,OPERATING_COEFFS!$A:$A,"DistanceClass",OPERATING_COEFFS!$B:$B,$AG7)) | AJ7: =IF($AI7="","",SUMIFS(OPERATING_COEFFS!$C:$C,OPERATING_COEFFS!$A:$A,"SeasonClass",OPERATING_COEFFS!$B:$B,$AI7)) | AL7: =IF($AK7="","",SUMIFS(OPERATING_COEFFS!$C:$C,OPERATING_COEFFS!$A:$A,"UrgencyClass",OPERATING_COEFFS!$B:$B,$AK7)) | AN7: =IF($AM7="","",INDEX(TAX_MODES!$B:$B,MATCH($AM7,TAX_MODES!$A:$A,0)))
D8: =IF($C8="","",SUMIFS(SITE_COEFFS!$C:$C,SITE_COEFFS!$A:$A,"SoilWorkability",SITE_COEFFS!$B:$B,$C8)) | F8: =IF($E8="","",SUMIFS(SITE_COEFFS!$C:$C,SITE_COEFFS!$A:$A,"SoilMoisture",SITE_COEFFS!$B:$B,$E8)) | H8: =IF($G8="","",SUMIFS(SITE_COEFFS!$C:$C,SITE_COEFFS!$A:$A,"DebrisLevel",SITE_COEFFS!$B:$B,$G8)) | J8: =IF($I8="","",SUMIFS(SITE_COEFFS!$C:$C,SITE_COEFFS!$A:$A,"SlopeClass",SITE_COEFFS!$B:$B,$I8)) | L8: =IF($K8="","",SUMIFS(SITE_COEFFS!$C:$C,SITE_COEFFS!$A:$A,"SurfaceUnevenness",SITE_COEFFS!$B:$B,$K8)) | N8: =IF($M8="","",SUMIFS(SITE_COEFFS!$C:$C,SITE_COEFFS!$A:$A,"AccessClass",SITE_COEFFS!$B:$B,$M8)) | P8: =IF($O8="","",SUMIFS(SITE_COEFFS!$C:$C,SITE_COEFFS!$A:$A,"TurnSpace",SITE_COEFFS!$B:$B,$O8)) | R8: =IF($Q8="","",SUMIFS(SITE_COEFFS!$C:$C,SITE_COEFFS!$A:$A,"ProximityToBuildings",SITE_COEFFS!$B:$B,$Q8)) | T8: =IF($S8="","",SUMIFS(SITE_COEFFS!$C:$C,SITE_COEFFS!$A:$A,"MachineryAllowed",SITE_COEFFS!$B:$B,$S8)) | W8: =IF($V8="","",SUMIFS(SITE_COEFFS!$C:$C,SITE_COEFFS!$A:$A,"GeometryComplexity",SITE_COEFFS!$B:$B,$V8)) | Y8: =IF($X8="","",SUMIFS(TARIFF_PROFILES!$D:$D,TARIFF_PROFILES!$A:$A,$X8)) | Z8: =IF($X8="","",SUMIFS(TARIFF_PROFILES!$E:$E,TARIFF_PROFILES!$A:$A,$X8)) | AA8: =IF($X8="","",SUMIFS(TARIFF_PROFILES!$F:$F,TARIFF_PROFILES!$A:$A,$X8)) | AB8: =IF($X8="","",SUMIFS(TARIFF_PROFILES!$G:$G,TARIFF_PROFILES!$A:$A,$X8)) | AC8: =IF($X8="","",SUMIFS(TARIFF_PROFILES!$H:$H,TARIFF_PROFILES!$A:$A,$X8)) | AD8: =IF($X8="","",INDEX(TARIFF_PROFILES!$J:$J,MATCH($X8,TARIFF_PROFILES!$A:$A,0))) | AE8: =IF($X8="","",INDEX(TARIFF_PROFILES!$K:$K,MATCH($X8,TARIFF_PROFILES!$A:$A,0))) | AH8: =IF($AG8="","",SUMIFS(OPERATING_COEFFS!$C:$C,OPERATING_COEFFS!$A:$A,"DistanceClass",OPERATING_COEFFS!$B:$B,$AG8)) | AJ8: =IF($AI8="","",SUMIFS(OPERATING_COEFFS!$C:$C,OPERATING_COEFFS!$A:$A,"SeasonClass",OPERATING_COEFFS!$B:$B,$AI8)) | AL8: =IF($AK8="","",SUMIFS(OPERATING_COEFFS!$C:$C,OPERATING_COEFFS!$A:$A,"UrgencyClass",OPERATING_COEFFS!$B:$B,$AK8)) | AN8: =IF($AM8="","",INDEX(TAX_MODES!$B:$B,MATCH($AM8,TAX_MODES!$A:$A,0)))
D9: =IF($C9="","",SUMIFS(SITE_COEFFS!$C:$C,SITE_COEFFS!$A:$A,"SoilWorkability",SITE_COEFFS!$B:$B,$C9)) | F9: =IF($E9="","",SUMIFS(SITE_COEFFS!$C:$C,SITE_COEFFS!$A:$A,"SoilMoisture",SITE_COEFFS!$B:$B,$E9)) | H9: =IF($G9="","",SUMIFS(SITE_COEFFS!$C:$C,SITE_COEFFS!$A:$A,"DebrisLevel",SITE_COEFFS!$B:$B,$G9)) | J9: =IF($I9="","",SUMIFS(SITE_COEFFS!$C:$C,SITE_COEFFS!$A:$A,"SlopeClass",SITE_COEFFS!$B:$B,$I9)) | L9: =IF($K9="","",SUMIFS(SITE_COEFFS!$C:$C,SITE_COEFFS!$A:$A,"SurfaceUnevenness",SITE_COEFFS!$B:$B,$K9)) | N9: =IF($M9="","",SUMIFS(SITE_COEFFS!$C:$C,SITE_COEFFS!$A:$A,"AccessClass",SITE_COEFFS!$B:$B,$M9)) | P9: =IF($O9="","",SUMIFS(SITE_COEFFS!$C:$C,SITE_COEFFS!$A:$A,"TurnSpace",SITE_COEFFS!$B:$B,$O9)) | R9: =IF($Q9="","",SUMIFS(SITE_COEFFS!$C:$C,SITE_COEFFS!$A:$A,"ProximityToBuildings",SITE_COEFFS!$B:$B,$Q9)) | T9: =IF($S9="","",SUMIFS(SITE_COEFFS!$C:$C,SITE_COEFFS!$A:$A,"MachineryAllowed",SITE_COEFFS!$B:$B,$S9)) | W9: =IF($V9="","",SUMIFS(SITE_COEFFS!$C:$C,SITE_COEFFS!$A:$A,"GeometryComplexity",SITE_COEFFS!$B:$B,$V9)) | Y9: =IF($X9="","",SUMIFS(TARIFF_PROFILES!$D:$D,TARIFF_PROFILES!$A:$A,$X9)) | Z9: =IF($X9="","",SUMIFS(TARIFF_PROFILES!$E:$E,TARIFF_PROFILES!$A:$A,$X9)) | AA9: =IF($X9="","",SUMIFS(TARIFF_PROFILES!$F:$F,TARIFF_PROFILES!$A:$A,$X9)) | AB9: =IF($X9="","",SUMIFS(TARIFF_PROFILES!$G:$G,TARIFF_PROFILES!$A:$A,$X9)) | AC9: =IF($X9="","",SUMIFS(TARIFF_PROFILES!$H:$H,TARIFF_PROFILES!$A:$A,$X9)) | AD9: =IF($X9="","",INDEX(TARIFF_PROFILES!$J:$J,MATCH($X9,TARIFF_PROFILES!$A:$A,0))) | AE9: =IF($X9="","",INDEX(TARIFF_PROFILES!$K:$K,MATCH($X9,TARIFF_PROFILES!$A:$A,0))) | AH9: =IF($AG9="","",SUMIFS(OPERATING_COEFFS!$C:$C,OPERATING_COEFFS!$A:$A,"DistanceClass",OPERATING_COEFFS!$B:$B,$AG9)) | AJ9: =IF($AI9="","",SUMIFS(OPERATING_COEFFS!$C:$C,OPERATING_COEFFS!$A:$A,"SeasonClass",OPERATING_COEFFS!$B:$B,$AI9)) | AL9: =IF($AK9="","",SUMIFS(OPERATING_COEFFS!$C:$C,OPERATING_COEFFS!$A:$A,"UrgencyClass",OPERATING_COEFFS!$B:$B,$AK9)) | AN9: =IF($AM9="","",INDEX(TAX_MODES!$B:$B,MATCH($AM9,TAX_MODES!$A:$A,0)))
D10: =IF($C10="","",SUMIFS(SITE_COEFFS!$C:$C,SITE_COEFFS!$A:$A,"SoilWorkability",SITE_COEFFS!$B:$B,$C10)) | F10: =IF($E10="","",SUMIFS(SITE_COEFFS!$C:$C,SITE_COEFFS!$A:$A,"SoilMoisture",SITE_COEFFS!$B:$B,$E10)) | H10: =IF($G10="","",SUMIFS(SITE_COEFFS!$C:$C,SITE_COEFFS!$A:$A,"DebrisLevel",SITE_COEFFS!$B:$B,$G10)) | J10: =IF($I10="","",SUMIFS(SITE_COEFFS!$C:$C,SITE_COEFFS!$A:$A,"SlopeClass",SITE_COEFFS!$B:$B,$I10)) | L10: =IF($K10="","",SUMIFS(SITE_COEFFS!$C:$C,SITE_COEFFS!$A:$A,"SurfaceUnevenness",SITE_COEFFS!$B:$B,$K10)) | N10: =IF($M10="","",SUMIFS(SITE_COEFFS!$C:$C,SITE_COEFFS!$A:$A,"AccessClass",SITE_COEFFS!$B:$B,$M10)) | P10: =IF($O10="","",SUMIFS(SITE_COEFFS!$C:$C,SITE_COEFFS!$A:$A,"TurnSpace",SITE_COEFFS!$B:$B,$O10)) | R10: =IF($Q10="","",SUMIFS(SITE_COEFFS!$C:$C,SITE_COEFFS!$A:$A,"ProximityToBuildings",SITE_COEFFS!$B:$B,$Q10)) | T10: =IF($S10="","",SUMIFS(SITE_COEFFS!$C:$C,SITE_COEFFS!$A:$A,"MachineryAllowed",SITE_COEFFS!$B:$B,$S10)) | W10: =IF($V10="","",SUMIFS(SITE_COEFFS!$C:$C,SITE_COEFFS!$A:$A,"GeometryComplexity",SITE_COEFFS!$B:$B,$V10)) | Y10: =IF($X10="","",SUMIFS(TARIFF_PROFILES!$D:$D,TARIFF_PROFILES!$A:$A,$X10)) | Z10: =IF($X10="","",SUMIFS(TARIFF_PROFILES!$E:$E,TARIFF_PROFILES!$A:$A,$X10)) | AA10: =IF($X10="","",SUMIFS(TARIFF_PROFILES!$F:$F,TARIFF_PROFILES!$A:$A,$X10)) | AB10: =IF($X10="","",SUMIFS(TARIFF_PROFILES!$G:$G,TARIFF_PROFILES!$A:$A,$X10)) | AC10: =IF($X10="","",SUMIFS(TARIFF_PROFILES!$H:$H,TARIFF_PROFILES!$A:$A,$X10)) | AD10: =IF($X10="","",INDEX(TARIFF_PROFILES!$J:$J,MATCH($X10,TARIFF_PROFILES!$A:$A,0))) | AE10: =IF($X10="","",INDEX(TARIFF_PROFILES!$K:$K,MATCH($X10,TARIFF_PROFILES!$A:$A,0))) | AH10: =IF($AG10="","",SUMIFS(OPERATING_COEFFS!$C:$C,OPERATING_COEFFS!$A:$A,"DistanceClass",OPERATING_COEFFS!$B:$B,$AG10)) | AJ10: =IF($AI10="","",SUMIFS(OPERATING_COEFFS!$C:$C,OPERATING_COEFFS!$A:$A,"SeasonClass",OPERATING_COEFFS!$B:$B,$AI10)) | AL10: =IF($AK10="","",SUMIFS(OPERATING_COEFFS!$C:$C,OPERATING_COEFFS!$A:$A,"UrgencyClass",OPERATING_COEFFS!$B:$B,$AK10)) | AN10: =IF($AM10="","",INDEX(TAX_MODES!$B:$B,MATCH($AM10,TAX_MODES!$A:$A,0)))
D11: =IF($C11="","",SUMIFS(SITE_COEFFS!$C:$C,SITE_COEFFS!$A:$A,"SoilWorkability",SITE_COEFFS!$B:$B,$C11)) | F11: =IF($E11="","",SUMIFS(SITE_COEFFS!$C:$C,SITE_COEFFS!$A:$A,"SoilMoisture",SITE_COEFFS!$B:$B,$E11)) | H11: =IF($G11="","",SUMIFS(SITE_COEFFS!$C:$C,SITE_COEFFS!$A:$A,"DebrisLevel",SITE_COEFFS!$B:$B,$G11)) | J11: =IF($I11="","",SUMIFS(SITE_COEFFS!$C:$C,SITE_COEFFS!$A:$A,"SlopeClass",SITE_COEFFS!$B:$B,$I11)) | L11: =IF($K11="","",SUMIFS(SITE_COEFFS!$C:$C,SITE_COEFFS!$A:$A,"SurfaceUnevenness",SITE_COEFFS!$B:$B,$K11)) | N11: =IF($M11="","",SUMIFS(SITE_COEFFS!$C:$C,SITE_COEFFS!$A:$A,"AccessClass",SITE_COEFFS!$B:$B,$M11)) | P11: =IF($O11="","",SUMIFS(SITE_COEFFS!$C:$C,SITE_COEFFS!$A:$A,"TurnSpace",SITE_COEFFS!$B:$B,$O11)) | R11: =IF($Q11="","",SUMIFS(SITE_COEFFS!$C:$C,SITE_COEFFS!$A:$A,"ProximityToBuildings",SITE_COEFFS!$B:$B,$Q11)) | T11: =IF($S11="","",SUMIFS(SITE_COEFFS!$C:$C,SITE_COEFFS!$A:$A,"MachineryAllowed",SITE_COEFFS!$B:$B,$S11)) | W11: =IF($V11="","",SUMIFS(SITE_COEFFS!$C:$C,SITE_COEFFS!$A:$A,"GeometryComplexity",SITE_COEFFS!$B:$B,$V11)) | Y11: =IF($X11="","",SUMIFS(TARIFF_PROFILES!$D:$D,TARIFF_PROFILES!$A:$A,$X11)) | Z11: =IF($X11="","",SUMIFS(TARIFF_PROFILES!$E:$E,TARIFF_PROFILES!$A:$A,$X11)) | AA11: =IF($X11="","",SUMIFS(TARIFF_PROFILES!$F:$F,TARIFF_PROFILES!$A:$A,$X11)) | AB11: =IF($X11="","",SUMIFS(TARIFF_PROFILES!$G:$G,TARIFF_PROFILES!$A:$A,$X11)) | AC11: =IF($X11="","",SUMIFS(TARIFF_PROFILES!$H:$H,TARIFF_PROFILES!$A:$A,$X11)) | AD11: =IF($X11="","",INDEX(TARIFF_PROFILES!$J:$J,MATCH($X11,TARIFF_PROFILES!$A:$A,0))) | AE11: =IF($X11="","",INDEX(TARIFF_PROFILES!$K:$K,MATCH($X11,TARIFF_PROFILES!$A:$A,0))) | AH11: =IF($AG11="","",SUMIFS(OPERATING_COEFFS!$C:$C,OPERATING_COEFFS!$A:$A,"DistanceClass",OPERATING_COEFFS!$B:$B,$AG11)) | AJ11: =IF($AI11="","",SUMIFS(OPERATING_COEFFS!$C:$C,OPERATING_COEFFS!$A:$A,"SeasonClass",OPERATING_COEFFS!$B:$B,$AI11)) | AL11: =IF($AK11="","",SUMIFS(OPERATING_COEFFS!$C:$C,OPERATING_COEFFS!$A:$A,"UrgencyClass",OPERATING_COEFFS!$B:$B,$AK11)) | AN11: =IF($AM11="","",INDEX(TAX_MODES!$B:$B,MATCH($AM11,TAX_MODES!$A:$A,0)))
D12: =IF($C12="","",SUMIFS(SITE_COEFFS!$C:$C,SITE_COEFFS!$A:$A,"SoilWorkability",SITE_COEFFS!$B:$B,$C12)) | F12: =IF($E12="","",SUMIFS(SITE_COEFFS!$C:$C,SITE_COEFFS!$A:$A,"SoilMoisture",SITE_COEFFS!$B:$B,$E12)) | H12: =IF($G12="","",SUMIFS(SITE_COEFFS!$C:$C,SITE_COEFFS!$A:$A,"DebrisLevel",SITE_COEFFS!$B:$B,$G12)) | J12: =IF($I12="","",SUMIFS(SITE_COEFFS!$C:$C,SITE_COEFFS!$A:$A,"SlopeClass",SITE_COEFFS!$B:$B,$I12)) | L12: =IF($K12="","",SUMIFS(SITE_COEFFS!$C:$C,SITE_COEFFS!$A:$A,"SurfaceUnevenness",SITE_COEFFS!$B:$B,$K12)) | N12: =IF($M12="","",SUMIFS(SITE_COEFFS!$C:$C,SITE_COEFFS!$A:$A,"AccessClass",SITE_COEFFS!$B:$B,$M12)) | P12: =IF($O12="","",SUMIFS(SITE_COEFFS!$C:$C,SITE_COEFFS!$A:$A,"TurnSpace",SITE_COEFFS!$B:$B,$O12)) | R12: =IF($Q12="","",SUMIFS(SITE_COEFFS!$C:$C,SITE_COEFFS!$A:$A,"ProximityToBuildings",SITE_COEFFS!$B:$B,$Q12)) | T12: =IF($S12="","",SUMIFS(SITE_COEFFS!$C:$C,SITE_COEFFS!$A:$A,"MachineryAllowed",SITE_COEFFS!$B:$B,$S12)) | W12: =IF($V12="","",SUMIFS(SITE_COEFFS!$C:$C,SITE_COEFFS!$A:$A,"GeometryComplexity",SITE_COEFFS!$B:$B,$V12)) | Y12: =IF($X12="","",SUMIFS(TARIFF_PROFILES!$D:$D,TARIFF_PROFILES!$A:$A,$X12)) | Z12: =IF($X12="","",SUMIFS(TARIFF_PROFILES!$E:$E,TARIFF_PROFILES!$A:$A,$X12)) | AA12: =IF($X12="","",SUMIFS(TARIFF_PROFILES!$F:$F,TARIFF_PROFILES!$A:$A,$X12)) | AB12: =IF($X12="","",SUMIFS(TARIFF_PROFILES!$G:$G,TARIFF_PROFILES!$A:$A,$X12)) | AC12: =IF($X12="","",SUMIFS(TARIFF_PROFILES!$H:$H,TARIFF_PROFILES!$A:$A,$X12)) | AD12: =IF($X12="","",INDEX(TARIFF_PROFILES!$J:$J,MATCH($X12,TARIFF_PROFILES!$A:$A,0))) | AE12: =IF($X12="","",INDEX(TARIFF_PROFILES!$K:$K,MATCH($X12,TARIFF_PROFILES!$A:$A,0))) | AH12: =IF($AG12="","",SUMIFS(OPERATING_COEFFS!$C:$C,OPERATING_COEFFS!$A:$A,"DistanceClass",OPERATING_COEFFS!$B:$B,$AG12)) | AJ12: =IF($AI12="","",SUMIFS(OPERATING_COEFFS!$C:$C,OPERATING_COEFFS!$A:$A,"SeasonClass",OPERATING_COEFFS!$B:$B,$AI12)) | AL12: =IF($AK12="","",SUMIFS(OPERATING_COEFFS!$C:$C,OPERATING_COEFFS!$A:$A,"UrgencyClass",OPERATING_COEFFS!$B:$B,$AK12)) | AN12: =IF($AM12="","",INDEX(TAX_MODES!$B:$B,MATCH($AM12,TAX_MODES!$A:$A,0)))
D13: =IF($C13="","",SUMIFS(SITE_COEFFS!$C:$C,SITE_COEFFS!$A:$A,"SoilWorkability",SITE_COEFFS!$B:$B,$C13)) | F13: =IF($E13="","",SUMIFS(SITE_COEFFS!$C:$C,SITE_COEFFS!$A:$A,"SoilMoisture",SITE_COEFFS!$B:$B,$E13)) | H13: =IF($G13="","",SUMIFS(SITE_COEFFS!$C:$C,SITE_COEFFS!$A:$A,"DebrisLevel",SITE_COEFFS!$B:$B,$G13)) | J13: =IF($I13="","",SUMIFS(SITE_COEFFS!$C:$C,SITE_COEFFS!$A:$A,"SlopeClass",SITE_COEFFS!$B:$B,$I13)) | L13: =IF($K13="","",SUMIFS(SITE_COEFFS!$C:$C,SITE_COEFFS!$A:$A,"SurfaceUnevenness",SITE_COEFFS!$B:$B,$K13)) | N13: =IF($M13="","",SUMIFS(SITE_COEFFS!$C:$C,SITE_COEFFS!$A:$A,"AccessClass",SITE_COEFFS!$B:$B,$M13)) | P13: =IF($O13="","",SUMIFS(SITE_COEFFS!$C:$C,SITE_COEFFS!$A:$A,"TurnSpace",SITE_COEFFS!$B:$B,$O13)) | R13: =IF($Q13="","",SUMIFS(SITE_COEFFS!$C:$C,SITE_COEFFS!$A:$A,"ProximityToBuildings",SITE_COEFFS!$B:$B,$Q13)) | T13: =IF($S13="","",SUMIFS(SITE_COEFFS!$C:$C,SITE_COEFFS!$A:$A,"MachineryAllowed",SITE_COEFFS!$B:$B,$S13)) | W13: =IF($V13="","",SUMIFS(SITE_COEFFS!$C:$C,SITE_COEFFS!$A:$A,"GeometryComplexity",SITE_COEFFS!$B:$B,$V13)) | Y13: =IF($X13="","",SUMIFS(TARIFF_PROFILES!$D:$D,TARIFF_PROFILES!$A:$A,$X13)) | Z13: =IF($X13="","",SUMIFS(TARIFF_PROFILES!$E:$E,TARIFF_PROFILES!$A:$A,$X13)) | AA13: =IF($X13="","",SUMIFS(TARIFF_PROFILES!$F:$F,TARIFF_PROFILES!$A:$A,$X13)) | AB13: =IF($X13="","",SUMIFS(TARIFF_PROFILES!$G:$G,TARIFF_PROFILES!$A:$A,$X13)) | AC13: =IF($X13="","",SUMIFS(TARIFF_PROFILES!$H:$H,TARIFF_PROFILES!$A:$A,$X13)) | AD13: =IF($X13="","",INDEX(TARIFF_PROFILES!$J:$J,MATCH($X13,TARIFF_PROFILES!$A:$A,0))) | AE13: =IF($X13="","",INDEX(TARIFF_PROFILES!$K:$K,MATCH($X13,TARIFF_PROFILES!$A:$A,0))) | AH13: =IF($AG13="","",SUMIFS(OPERATING_COEFFS!$C:$C,OPERATING_COEFFS!$A:$A,"DistanceClass",OPERATING_COEFFS!$B:$B,$AG13)) | AJ13: =IF($AI13="","",SUMIFS(OPERATING_COEFFS!$C:$C,OPERATING_COEFFS!$A:$A,"SeasonClass",OPERATING_COEFFS!$B:$B,$AI13)) | AL13: =IF($AK13="","",SUMIFS(OPERATING_COEFFS!$C:$C,OPERATING_COEFFS!$A:$A,"UrgencyClass",OPERATING_COEFFS!$B:$B,$AK13)) | AN13: =IF($AM13="","",INDEX(TAX_MODES!$B:$B,MATCH($AM13,TAX_MODES!$A:$A,0)))
D14: =IF($C14="","",SUMIFS(SITE_COEFFS!$C:$C,SITE_COEFFS!$A:$A,"SoilWorkability",SITE_COEFFS!$B:$B,$C14)) | F14: =IF($E14="","",SUMIFS(SITE_COEFFS!$C:$C,SITE_COEFFS!$A:$A,"SoilMoisture",SITE_COEFFS!$B:$B,$E14)) | H14: =IF($G14="","",SUMIFS(SITE_COEFFS!$C:$C,SITE_COEFFS!$A:$A,"DebrisLevel",SITE_COEFFS!$B:$B,$G14)) | J14: =IF($I14="","",SUMIFS(SITE_COEFFS!$C:$C,SITE_COEFFS!$A:$A,"SlopeClass",SITE_COEFFS!$B:$B,$I14)) | L14: =IF($K14="","",SUMIFS(SITE_COEFFS!$C:$C,SITE_COEFFS!$A:$A,"SurfaceUnevenness",SITE_COEFFS!$B:$B,$K14)) | N14: =IF($M14="","",SUMIFS(SITE_COEFFS!$C:$C,SITE_COEFFS!$A:$A,"AccessClass",SITE_COEFFS!$B:$B,$M14)) | P14: =IF($O14="","",SUMIFS(SITE_COEFFS!$C:$C,SITE_COEFFS!$A:$A,"TurnSpace",SITE_COEFFS!$B:$B,$O14)) | R14: =IF($Q14="","",SUMIFS(SITE_COEFFS!$C:$C,SITE_COEFFS!$A:$A,"ProximityToBuildings",SITE_COEFFS!$B:$B,$Q14)) | T14: =IF($S14="","",SUMIFS(SITE_COEFFS!$C:$C,SITE_COEFFS!$A:$A,"MachineryAllowed",SITE_COEFFS!$B:$B,$S14)) | W14: =IF($V14="","",SUMIFS(SITE_COEFFS!$C:$C,SITE_COEFFS!$A:$A,"GeometryComplexity",SITE_COEFFS!$B:$B,$V14)) | Y14: =IF($X14="","",SUMIFS(TARIFF_PROFILES!$D:$D,TARIFF_PROFILES!$A:$A,$X14)) | Z14: =IF($X14="","",SUMIFS(TARIFF_PROFILES!$E:$E,TARIFF_PROFILES!$A:$A,$X14)) | AA14: =IF($X14="","",SUMIFS(TARIFF_PROFILES!$F:$F,TARIFF_PROFILES!$A:$A,$X14)) | AB14: =IF($X14="","",SUMIFS(TARIFF_PROFILES!$G:$G,TARIFF_PROFILES!$A:$A,$X14)) | AC14: =IF($X14="","",SUMIFS(TARIFF_PROFILES!$H:$H,TARIFF_PROFILES!$A:$A,$X14)) | AD14: =IF($X14="","",INDEX(TARIFF_PROFILES!$J:$J,MATCH($X14,TARIFF_PROFILES!$A:$A,0))) | AE14: =IF($X14="","",INDEX(TARIFF_PROFILES!$K:$K,MATCH($X14,TARIFF_PROFILES!$A:$A,0))) | AH14: =IF($AG14="","",SUMIFS(OPERATING_COEFFS!$C:$C,OPERATING_COEFFS!$A:$A,"DistanceClass",OPERATING_COEFFS!$B:$B,$AG14)) | AJ14: =IF($AI14="","",SUMIFS(OPERATING_COEFFS!$C:$C,OPERATING_COEFFS!$A:$A,"SeasonClass",OPERATING_COEFFS!$B:$B,$AI14)) | AL14: =IF($AK14="","",SUMIFS(OPERATING_COEFFS!$C:$C,OPERATING_COEFFS!$A:$A,"UrgencyClass",OPERATING_COEFFS!$B:$B,$AK14)) | AN14: =IF($AM14="","",INDEX(TAX_MODES!$B:$B,MATCH($AM14,TAX_MODES!$A:$A,0)))
D15: =IF($C15="","",SUMIFS(SITE_COEFFS!$C:$C,SITE_COEFFS!$A:$A,"SoilWorkability",SITE_COEFFS!$B:$B,$C15)) | F15: =IF($E15="","",SUMIFS(SITE_COEFFS!$C:$C,SITE_COEFFS!$A:$A,"SoilMoisture",SITE_COEFFS!$B:$B,$E15)) | H15: =IF($G15="","",SUMIFS(SITE_COEFFS!$C:$C,SITE_COEFFS!$A:$A,"DebrisLevel",SITE_COEFFS!$B:$B,$G15)) | J15: =IF($I15="","",SUMIFS(SITE_COEFFS!$C:$C,SITE_COEFFS!$A:$A,"SlopeClass",SITE_COEFFS!$B:$B,$I15)) | L15: =IF($K15="","",SUMIFS(SITE_COEFFS!$C:$C,SITE_COEFFS!$A:$A,"SurfaceUnevenness",SITE_COEFFS!$B:$B,$K15)) | N15: =IF($M15="","",SUMIFS(SITE_COEFFS!$C:$C,SITE_COEFFS!$A:$A,"AccessClass",SITE_COEFFS!$B:$B,$M15)) | P15: =IF($O15="","",SUMIFS(SITE_COEFFS!$C:$C,SITE_COEFFS!$A:$A,"TurnSpace",SITE_COEFFS!$B:$B,$O15)) | R15: =IF($Q15="","",SUMIFS(SITE_COEFFS!$C:$C,SITE_COEFFS!$A:$A,"ProximityToBuildings",SITE_COEFFS!$B:$B,$Q15)) | T15: =IF($S15="","",SUMIFS(SITE_COEFFS!$C:$C,SITE_COEFFS!$A:$A,"MachineryAllowed",SITE_COEFFS!$B:$B,$S15)) | W15: =IF($V15="","",SUMIFS(SITE_COEFFS!$C:$C,SITE_COEFFS!$A:$A,"GeometryComplexity",SITE_COEFFS!$B:$B,$V15)) | Y15: =IF($X15="","",SUMIFS(TARIFF_PROFILES!$D:$D,TARIFF_PROFILES!$A:$A,$X15)) | Z15: =IF($X15="","",SUMIFS(TARIFF_PROFILES!$E:$E,TARIFF_PROFILES!$A:$A,$X15)) | AA15: =IF($X15="","",SUMIFS(TARIFF_PROFILES!$F:$F,TARIFF_PROFILES!$A:$A,$X15)) | AB15: =IF($X15="","",SUMIFS(TARIFF_PROFILES!$G:$G,TARIFF_PROFILES!$A:$A,$X15)) | AC15: =IF($X15="","",SUMIFS(TARIFF_PROFILES!$H:$H,TARIFF_PROFILES!$A:$A,$X15)) | AD15: =IF($X15="","",INDEX(TARIFF_PROFILES!$J:$J,MATCH($X15,TARIFF_PROFILES!$A:$A,0))) | AE15: =IF($X15="","",INDEX(TARIFF_PROFILES!$K:$K,MATCH($X15,TARIFF_PROFILES!$A:$A,0))) | AH15: =IF($AG15="","",SUMIFS(OPERATING_COEFFS!$C:$C,OPERATING_COEFFS!$A:$A,"DistanceClass",OPERATING_COEFFS!$B:$B,$AG15)) | AJ15: =IF($AI15="","",SUMIFS(OPERATING_COEFFS!$C:$C,OPERATING_COEFFS!$A:$A,"SeasonClass",OPERATING_COEFFS!$B:$B,$AI15)) | AL15: =IF($AK15="","",SUMIFS(OPERATING_COEFFS!$C:$C,OPERATING_COEFFS!$A:$A,"UrgencyClass",OPERATING_COEFFS!$B:$B,$AK15)) | AN15: =IF($AM15="","",INDEX(TAX_MODES!$B:$B,MATCH($AM15,TAX_MODES!$A:$A,0)))
... D150: =IF($C150="","",SUMIFS(SITE_COEFFS!$C:$C,SITE_COEFFS!$A:$A,"SoilWorkability",SITE_COEFFS!$B:$B,$C150)) | F150: =IF($E150="","",SUMIFS(SITE_COEFFS!$C:$C,SITE_COEFFS!$A:$A,"SoilMoisture",SITE_COEFFS!$B:$B,$E150)) | H150: =IF($G150="","",SUMIFS(SITE_COEFFS!$C:$C,SITE_COEFFS!$A:$A,"DebrisLevel",SITE_COEFFS!$B:$B,$G150)) | J150: =IF($I150="","",SUMIFS(SITE_COEFFS!$C:$C,SITE_COEFFS!$A:$A,"SlopeClass",SITE_COEFFS!$B:$B,$I150)) | L150: =IF($K150="","",SUMIFS(SITE_COEFFS!$C:$C,SITE_COEFFS!$A:$A,"SurfaceUnevenness",SITE_COEFFS!$B:$B,$K150)) | N150: =IF($M150="","",SUMIFS(SITE_COEFFS!$C:$C,SITE_COEFFS!$A:$A,"AccessClass",SITE_COEFFS!$B:$B,$M150)) | P150: =IF($O150="","",SUMIFS(SITE_COEFFS!$C:$C,SITE_COEFFS!$A:$A,"TurnSpace",SITE_COEFFS!$B:$B,$O150)) | R150: =IF($Q150="","",SUMIFS(SITE_COEFFS!$C:$C,SITE_COEFFS!$A:$A,"ProximityToBuildings",SITE_COEFFS!$B:$B,$Q150)) | T150: =IF($S150="","",SUMIFS(SITE_COEFFS!$C:$C,SITE_COEFFS!$A:$A,"MachineryAllowed",SITE_COEFFS!$B:$B,$S150)) | W150: =IF($V150="","",SUMIFS(SITE_COEFFS!$C:$C,SITE_COEFFS!$A:$A,"GeometryComplexity",SITE_COEFFS!$B:$B,$V150)) | Y150: =IF($X150="","",SUMIFS(TARIFF_PROFILES!$D:$D,TARIFF_PROFILES!$A:$A,$X150)) | Z150: =IF($X150="","",SUMIFS(TARIFF_PROFILES!$E:$E,TARIFF_PROFILES!$A:$A,$X150)) | AA150: =IF($X150="","",SUMIFS(TARIFF_PROFILES!$F:$F,TARIFF_PROFILES!$A:$A,$X150)) | AB150: =IF($X150="","",SUMIFS(TARIFF_PROFILES!$G:$G,TARIFF_PROFILES!$A:$A,$X150)) | AC150: =IF($X150="","",SUMIFS(TARIFF_PROFILES!$H:$H,TARIFF_PROFILES!$A:$A,$X150)) | AD150: =IF($X150="","",INDEX(TARIFF_PROFILES!$J:$J,MATCH($X150,TARIFF_PROFILES!$A:$A,0))) | AE150: =IF($X150="","",INDEX(TARIFF_PROFILES!$K:$K,MATCH($X150,TARIFF_PROFILES!$A:$A,0))) | AH150: =IF($AG150="","",SUMIFS(OPERATING_COEFFS!$C:$C,OPERATING_COEFFS!$A:$A,"DistanceClass",OPERATING_COEFFS!$B:$B,$AG150)) | AJ150: =IF($AI150="","",SUMIFS(OPERATING_COEFFS!$C:$C,OPERATING_COEFFS!$A:$A,"SeasonClass",OPERATING_COEFFS!$B:$B,$AI150)) | AL150: =IF($AK150="","",SUMIFS(OPERATING_COEFFS!$C:$C,OPERATING_COEFFS!$A:$A,"UrgencyClass",OPERATING_COEFFS!$B:$B,$AK150)) | AN150: =IF($AM150="","",INDEX(TAX_MODES!$B:$B,MATCH($AM150,TAX_MODES!$A:$A,0)))
Y151: =IF($X151="","",SUMIFS(TARIFF_PROFILES!$D:$D,TARIFF_PROFILES!$A:$A,$X151)) | Z151: =IF($X151="","",SUMIFS(TARIFF_PROFILES!$E:$E,TARIFF_PROFILES!$A:$A,$X151)) | AA151: =IF($X151="","",SUMIFS(TARIFF_PROFILES!$F:$F,TARIFF_PROFILES!$A:$A,$X151)) | AB151: =IF($X151="","",SUMIFS(TARIFF_PROFILES!$G:$G,TARIFF_PROFILES!$A:$A,$X151)) | AC151: =IF($X151="","",SUMIFS(TARIFF_PROFILES!$H:$H,TARIFF_PROFILES!$A:$A,$X151)) | AD151: =IF($X151="","",INDEX(TARIFF_PROFILES!$J:$J,MATCH($X151,TARIFF_PROFILES!$A:$A,0))) | AE151: =IF($X151="","",INDEX(TARIFF_PROFILES!$K:$K,MATCH($X151,TARIFF_PROFILES!$A:$A,0))) | AH151: =IF($AG151="","",SUMIFS(OPERATING_COEFFS!$C:$C,OPERATING_COEFFS!$A:$A,"DistanceClass",OPERATING_COEFFS!$B:$B,$AG151)) | AJ151: =IF($AI151="","",SUMIFS(OPERATING_COEFFS!$C:$C,OPERATING_COEFFS!$A:$A,"SeasonClass",OPERATING_COEFFS!$B:$B,$AI151)) | AL151: =IF($AK151="","",SUMIFS(OPERATING_COEFFS!$C:$C,OPERATING_COEFFS!$A:$A,"UrgencyClass",OPERATING_COEFFS!$B:$B,$AK151)) | AN151: =IF($AM151="","",INDEX(TAX_MODES!$B:$B,MATCH($AM151,TAX_MODES!$A:$A,0)))
Y152: =IF($X152="","",SUMIFS(TARIFF_PROFILES!$D:$D,TARIFF_PROFILES!$A:$A,$X152)) | Z152: =IF($X152="","",SUMIFS(TARIFF_PROFILES!$E:$E,TARIFF_PROFILES!$A:$A,$X152)) | AA152: =IF($X152="","",SUMIFS(TARIFF_PROFILES!$F:$F,TARIFF_PROFILES!$A:$A,$X152)) | AB152: =IF($X152="","",SUMIFS(TARIFF_PROFILES!$G:$G,TARIFF_PROFILES!$A:$A,$X152)) | AC152: =IF($X152="","",SUMIFS(TARIFF_PROFILES!$H:$H,TARIFF_PROFILES!$A:$A,$X152)) | AD152: =IF($X152="","",INDEX(TARIFF_PROFILES!$J:$J,MATCH($X152,TARIFF_PROFILES!$A:$A,0))) | AE152: =IF($X152="","",INDEX(TARIFF_PROFILES!$K:$K,MATCH($X152,TARIFF_PROFILES!$A:$A,0))) | AH152: =IF($AG152="","",SUMIFS(OPERATING_COEFFS!$C:$C,OPERATING_COEFFS!$A:$A,"DistanceClass",OPERATING_COEFFS!$B:$B,$AG152)) | AJ152: =IF($AI152="","",SUMIFS(OPERATING_COEFFS!$C:$C,OPERATING_COEFFS!$A:$A,"SeasonClass",OPERATING_COEFFS!$B:$B,$AI152)) | AL152: =IF($AK152="","",SUMIFS(OPERATING_COEFFS!$C:$C,OPERATING_COEFFS!$A:$A,"UrgencyClass",OPERATING_COEFFS!$B:$B,$AK152)) | AN152: =IF($AM152="","",INDEX(TAX_MODES!$B:$B,MATCH($AM152,TAX_MODES!$A:$A,0)))
Y153: =IF($X153="","",SUMIFS(TARIFF_PROFILES!$D:$D,TARIFF_PROFILES!$A:$A,$X153)) | Z153: =IF($X153="","",SUMIFS(TARIFF_PROFILES!$E:$E,TARIFF_PROFILES!$A:$A,$X153)) | AA153: =IF($X153="","",SUMIFS(TARIFF_PROFILES!$F:$F,TARIFF_PROFILES!$A:$A,$X153)) | AB153: =IF($X153="","",SUMIFS(TARIFF_PROFILES!$G:$G,TARIFF_PROFILES!$A:$A,$X153)) | AC153: =IF($X153="","",SUMIFS(TARIFF_PROFILES!$H:$H,TARIFF_PROFILES!$A:$A,$X153)) | AD153: =IF($X153="","",INDEX(TARIFF_PROFILES!$J:$J,MATCH($X153,TARIFF_PROFILES!$A:$A,0))) | AE153: =IF($X153="","",INDEX(TARIFF_PROFILES!$K:$K,MATCH($X153,TARIFF_PROFILES!$A:$A,0))) | AH153: =IF($AG153="","",SUMIFS(OPERATING_COEFFS!$C:$C,OPERATING_COEFFS!$A:$A,"DistanceClass",OPERATING_COEFFS!$B:$B,$AG153)) | AJ153: =IF($AI153="","",SUMIFS(OPERATING_COEFFS!$C:$C,OPERATING_COEFFS!$A:$A,"SeasonClass",OPERATING_COEFFS!$B:$B,$AI153)) | AL153: =IF($AK153="","",SUMIFS(OPERATING_COEFFS!$C:$C,OPERATING_COEFFS!$A:$A,"UrgencyClass",OPERATING_COEFFS!$B:$B,$AK153)) | AN153: =IF($AM153="","",INDEX(TAX_MODES!$B:$B,MATCH($AM153,TAX_MODES!$A:$A,0)))
Y154: =IF($X154="","",SUMIFS(TARIFF_PROFILES!$D:$D,TARIFF_PROFILES!$A:$A,$X154)) | Z154: =IF($X154="","",SUMIFS(TARIFF_PROFILES!$E:$E,TARIFF_PROFILES!$A:$A,$X154)) | AA154: =IF($X154="","",SUMIFS(TARIFF_PROFILES!$F:$F,TARIFF_PROFILES!$A:$A,$X154)) | AB154: =IF($X154="","",SUMIFS(TARIFF_PROFILES!$G:$G,TARIFF_PROFILES!$A:$A,$X154)) | AC154: =IF($X154="","",SUMIFS(TARIFF_PROFILES!$H:$H,TARIFF_PROFILES!$A:$A,$X154)) | AD154: =IF($X154="","",INDEX(TARIFF_PROFILES!$J:$J,MATCH($X154,TARIFF_PROFILES!$A:$A,0))) | AE154: =IF($X154="","",INDEX(TARIFF_PROFILES!$K:$K,MATCH($X154,TARIFF_PROFILES!$A:$A,0))) | AH154: =IF($AG154="","",SUMIFS(OPERATING_COEFFS!$C:$C,OPERATING_COEFFS!$A:$A,"DistanceClass",OPERATING_COEFFS!$B:$B,$AG154)) | AJ154: =IF($AI154="","",SUMIFS(OPERATING_COEFFS!$C:$C,OPERATING_COEFFS!$A:$A,"SeasonClass",OPERATING_COEFFS!$B:$B,$AI154)) | AL154: =IF($AK154="","",SUMIFS(OPERATING_COEFFS!$C:$C,OPERATING_COEFFS!$A:$A,"UrgencyClass",OPERATING_COEFFS!$B:$B,$AK154)) | AN154: =IF($AM154="","",INDEX(TAX_MODES!$B:$B,MATCH($AM154,TAX_MODES!$A:$A,0)))
Y155: =IF($X155="","",SUMIFS(TARIFF_PROFILES!$D:$D,TARIFF_PROFILES!$A:$A,$X155)) | Z155: =IF($X155="","",SUMIFS(TARIFF_PROFILES!$E:$E,TARIFF_PROFILES!$A:$A,$X155)) | AA155: =IF($X155="","",SUMIFS(TARIFF_PROFILES!$F:$F,TARIFF_PROFILES!$A:$A,$X155)) | AB155: =IF($X155="","",SUMIFS(TARIFF_PROFILES!$G:$G,TARIFF_PROFILES!$A:$A,$X155)) | AC155: =IF($X155="","",SUMIFS(TARIFF_PROFILES!$H:$H,TARIFF_PROFILES!$A:$A,$X155)) | AD155: =IF($X155="","",INDEX(TARIFF_PROFILES!$J:$J,MATCH($X155,TARIFF_PROFILES!$A:$A,0))) | AE155: =IF($X155="","",INDEX(TARIFF_PROFILES!$K:$K,MATCH($X155,TARIFF_PROFILES!$A:$A,0))) | AH155: =IF($AG155="","",SUMIFS(OPERATING_COEFFS!$C:$C,OPERATING_COEFFS!$A:$A,"DistanceClass",OPERATING_COEFFS!$B:$B,$AG155)) | AJ155: =IF($AI155="","",SUMIFS(OPERATING_COEFFS!$C:$C,OPERATING_COEFFS!$A:$A,"SeasonClass",OPERATING_COEFFS!$B:$B,$AI155)) | AL155: =IF($AK155="","",SUMIFS(OPERATING_COEFFS!$C:$C,OPERATING_COEFFS!$A:$A,"UrgencyClass",OPERATING_COEFFS!$B:$B,$AK155)) | AN155: =IF($AM155="","",INDEX(TAX_MODES!$B:$B,MATCH($AM155,TAX_MODES!$A:$A,0)))
Y156: =IF($X156="","",SUMIFS(TARIFF_PROFILES!$D:$D,TARIFF_PROFILES!$A:$A,$X156)) | Z156: =IF($X156="","",SUMIFS(TARIFF_PROFILES!$E:$E,TARIFF_PROFILES!$A:$A,$X156)) | AA156: =IF($X156="","",SUMIFS(TARIFF_PROFILES!$F:$F,TARIFF_PROFILES!$A:$A,$X156)) | AB156: =IF($X156="","",SUMIFS(TARIFF_PROFILES!$G:$G,TARIFF_PROFILES!$A:$A,$X156)) | AC156: =IF($X156="","",SUMIFS(TARIFF_PROFILES!$H:$H,TARIFF_PROFILES!$A:$A,$X156)) | AD156: =IF($X156="","",INDEX(TARIFF_PROFILES!$J:$J,MATCH($X156,TARIFF_PROFILES!$A:$A,0))) | AE156: =IF($X156="","",INDEX(TARIFF_PROFILES!$K:$K,MATCH($X156,TARIFF_PROFILES!$A:$A,0))) | AH156: =IF($AG156="","",SUMIFS(OPERATING_COEFFS!$C:$C,OPERATING_COEFFS!$A:$A,"DistanceClass",OPERATING_COEFFS!$B:$B,$AG156)) | AJ156: =IF($AI156="","",SUMIFS(OPERATING_COEFFS!$C:$C,OPERATING_COEFFS!$A:$A,"SeasonClass",OPERATING_COEFFS!$B:$B,$AI156)) | AL156: =IF($AK156="","",SUMIFS(OPERATING_COEFFS!$C:$C,OPERATING_COEFFS!$A:$A,"UrgencyClass",OPERATING_COEFFS!$B:$B,$AK156)) | AN156: =IF($AM156="","",INDEX(TAX_MODES!$B:$B,MATCH($AM156,TAX_MODES!$A:$A,0)))
Y157: =IF($X157="","",SUMIFS(TARIFF_PROFILES!$D:$D,TARIFF_PROFILES!$A:$A,$X157)) | Z157: =IF($X157="","",SUMIFS(TARIFF_PROFILES!$E:$E,TARIFF_PROFILES!$A:$A,$X157)) | AA157: =IF($X157="","",SUMIFS(TARIFF_PROFILES!$F:$F,TARIFF_PROFILES!$A:$A,$X157)) | AB157: =IF($X157="","",SUMIFS(TARIFF_PROFILES!$G:$G,TARIFF_PROFILES!$A:$A,$X157)) | AC157: =IF($X157="","",SUMIFS(TARIFF_PROFILES!$H:$H,TARIFF_PROFILES!$A:$A,$X157)) | AD157: =IF($X157="","",INDEX(TARIFF_PROFILES!$J:$J,MATCH($X157,TARIFF_PROFILES!$A:$A,0))) | AE157: =IF($X157="","",INDEX(TARIFF_PROFILES!$K:$K,MATCH($X157,TARIFF_PROFILES!$A:$A,0))) | AH157: =IF($AG157="","",SUMIFS(OPERATING_COEFFS!$C:$C,OPERATING_COEFFS!$A:$A,"DistanceClass",OPERATING_COEFFS!$B:$B,$AG157)) | AJ157: =IF($AI157="","",SUMIFS(OPERATING_COEFFS!$C:$C,OPERATING_COEFFS!$A:$A,"SeasonClass",OPERATING_COEFFS!$B:$B,$AI157)) | AL157: =IF($AK157="","",SUMIFS(OPERATING_COEFFS!$C:$C,OPERATING_COEFFS!$A:$A,"UrgencyClass",OPERATING_COEFFS!$B:$B,$AK157)) | AN157: =IF($AM157="","",INDEX(TAX_MODES!$B:$B,MATCH($AM157,TAX_MODES!$A:$A,0)))
Y158: =IF($X158="","",SUMIFS(TARIFF_PROFILES!$D:$D,TARIFF_PROFILES!$A:$A,$X158)) | Z158: =IF($X158="","",SUMIFS(TARIFF_PROFILES!$E:$E,TARIFF_PROFILES!$A:$A,$X158)) | AA158: =IF($X158="","",SUMIFS(TARIFF_PROFILES!$F:$F,TARIFF_PROFILES!$A:$A,$X158)) | AB158: =IF($X158="","",SUMIFS(TARIFF_PROFILES!$G:$G,TARIFF_PROFILES!$A:$A,$X158)) | AC158: =IF($X158="","",SUMIFS(TARIFF_PROFILES!$H:$H,TARIFF_PROFILES!$A:$A,$X158)) | AD158: =IF($X158="","",INDEX(TARIFF_PROFILES!$J:$J,MATCH($X158,TARIFF_PROFILES!$A:$A,0))) | AE158: =IF($X158="","",INDEX(TARIFF_PROFILES!$K:$K,MATCH($X158,TARIFF_PROFILES!$A:$A,0))) | AH158: =IF($AG158="","",SUMIFS(OPERATING_COEFFS!$C:$C,OPERATING_COEFFS!$A:$A,"DistanceClass",OPERATING_COEFFS!$B:$B,$AG158)) | AJ158: =IF($AI158="","",SUMIFS(OPERATING_COEFFS!$C:$C,OPERATING_COEFFS!$A:$A,"SeasonClass",OPERATING_COEFFS!$B:$B,$AI158)) | AL158: =IF($AK158="","",SUMIFS(OPERATING_COEFFS!$C:$C,OPERATING_COEFFS!$A:$A,"UrgencyClass",OPERATING_COEFFS!$B:$B,$AK158)) | AN158: =IF($AM158="","",INDEX(TAX_MODES!$B:$B,MATCH($AM158,TAX_MODES!$A:$A,0)))
Y159: =IF($X159="","",SUMIFS(TARIFF_PROFILES!$D:$D,TARIFF_PROFILES!$A:$A,$X159)) | Z159: =IF($X159="","",SUMIFS(TARIFF_PROFILES!$E:$E,TARIFF_PROFILES!$A:$A,$X159)) | AA159: =IF($X159="","",SUMIFS(TARIFF_PROFILES!$F:$F,TARIFF_PROFILES!$A:$A,$X159)) | AB159: =IF($X159="","",SUMIFS(TARIFF_PROFILES!$G:$G,TARIFF_PROFILES!$A:$A,$X159)) | AC159: =IF($X159="","",SUMIFS(TARIFF_PROFILES!$H:$H,TARIFF_PROFILES!$A:$A,$X159)) | AD159: =IF($X159="","",INDEX(TARIFF_PROFILES!$J:$J,MATCH($X159,TARIFF_PROFILES!$A:$A,0))) | AE159: =IF($X159="","",INDEX(TARIFF_PROFILES!$K:$K,MATCH($X159,TARIFF_PROFILES!$A:$A,0))) | AH159: =IF($AG159="","",SUMIFS(OPERATING_COEFFS!$C:$C,OPERATING_COEFFS!$A:$A,"DistanceClass",OPERATING_COEFFS!$B:$B,$AG159)) | AJ159: =IF($AI159="","",SUMIFS(OPERATING_COEFFS!$C:$C,OPERATING_COEFFS!$A:$A,"SeasonClass",OPERATING_COEFFS!$B:$B,$AI159)) | AL159: =IF($AK159="","",SUMIFS(OPERATING_COEFFS!$C:$C,OPERATING_COEFFS!$A:$A,"UrgencyClass",OPERATING_COEFFS!$B:$B,$AK159)) | AN159: =IF($AM159="","",INDEX(TAX_MODES!$B:$B,MATCH($AM159,TAX_MODES!$A:$A,0)))
Y160: =IF($X160="","",SUMIFS(TARIFF_PROFILES!$D:$D,TARIFF_PROFILES!$A:$A,$X160)) | Z160: =IF($X160="","",SUMIFS(TARIFF_PROFILES!$E:$E,TARIFF_PROFILES!$A:$A,$X160)) | AA160: =IF($X160="","",SUMIFS(TARIFF_PROFILES!$F:$F,TARIFF_PROFILES!$A:$A,$X160)) | AB160: =IF($X160="","",SUMIFS(TARIFF_PROFILES!$G:$G,TARIFF_PROFILES!$A:$A,$X160)) | AC160: =IF($X160="","",SUMIFS(TARIFF_PROFILES!$H:$H,TARIFF_PROFILES!$A:$A,$X160)) | AD160: =IF($X160="","",INDEX(TARIFF_PROFILES!$J:$J,MATCH($X160,TARIFF_PROFILES!$A:$A,0))) | AE160: =IF($X160="","",INDEX(TARIFF_PROFILES!$K:$K,MATCH($X160,TARIFF_PROFILES!$A:$A,0))) | AH160: =IF($AG160="","",SUMIFS(OPERATING_COEFFS!$C:$C,OPERATING_COEFFS!$A:$A,"DistanceClass",OPERATING_COEFFS!$B:$B,$AG160)) | AJ160: =IF($AI160="","",SUMIFS(OPERATING_COEFFS!$C:$C,OPERATING_COEFFS!$A:$A,"SeasonClass",OPERATING_COEFFS!$B:$B,$AI160)) | AL160: =IF($AK160="","",SUMIFS(OPERATING_COEFFS!$C:$C,OPERATING_COEFFS!$A:$A,"UrgencyClass",OPERATING_COEFFS!$B:$B,$AK160)) | AN160: =IF($AM160="","",INDEX(TAX_MODES!$B:$B,MATCH($AM160,TAX_MODES!$A:$A,0)))
Y161: =IF($X161="","",SUMIFS(TARIFF_PROFILES!$D:$D,TARIFF_PROFILES!$A:$A,$X161)) | Z161: =IF($X161="","",SUMIFS(TARIFF_PROFILES!$E:$E,TARIFF_PROFILES!$A:$A,$X161)) | AA161: =IF($X161="","",SUMIFS(TARIFF_PROFILES!$F:$F,TARIFF_PROFILES!$A:$A,$X161)) | AB161: =IF($X161="","",SUMIFS(TARIFF_PROFILES!$G:$G,TARIFF_PROFILES!$A:$A,$X161)) | AC161: =IF($X161="","",SUMIFS(TARIFF_PROFILES!$H:$H,TARIFF_PROFILES!$A:$A,$X161)) | AD161: =IF($X161="","",INDEX(TARIFF_PROFILES!$J:$J,MATCH($X161,TARIFF_PROFILES!$A:$A,0))) | AE161: =IF($X161="","",INDEX(TARIFF_PROFILES!$K:$K,MATCH($X161,TARIFF_PROFILES!$A:$A,0))) | AH161: =IF($AG161="","",SUMIFS(OPERATING_COEFFS!$C:$C,OPERATING_COEFFS!$A:$A,"DistanceClass",OPERATING_COEFFS!$B:$B,$AG161)) | AJ161: =IF($AI161="","",SUMIFS(OPERATING_COEFFS!$C:$C,OPERATING_COEFFS!$A:$A,"SeasonClass",OPERATING_COEFFS!$B:$B,$AI161)) | AL161: =IF($AK161="","",SUMIFS(OPERATING_COEFFS!$C:$C,OPERATING_COEFFS!$A:$A,"UrgencyClass",OPERATING_COEFFS!$B:$B,$AK161)) | AN161: =IF($AM161="","",INDEX(TAX_MODES!$B:$B,MATCH($AM161,TAX_MODES!$A:$A,0)))
Y162: =IF($X162="","",SUMIFS(TARIFF_PROFILES!$D:$D,TARIFF_PROFILES!$A:$A,$X162)) | Z162: =IF($X162="","",SUMIFS(TARIFF_PROFILES!$E:$E,TARIFF_PROFILES!$A:$A,$X162)) | AA162: =IF($X162="","",SUMIFS(TARIFF_PROFILES!$F:$F,TARIFF_PROFILES!$A:$A,$X162)) | AB162: =IF($X162="","",SUMIFS(TARIFF_PROFILES!$G:$G,TARIFF_PROFILES!$A:$A,$X162)) | AC162: =IF($X162="","",SUMIFS(TARIFF_PROFILES!$H:$H,TARIFF_PROFILES!$A:$A,$X162)) | AD162: =IF($X162="","",INDEX(TARIFF_PROFILES!$J:$J,MATCH($X162,TARIFF_PROFILES!$A:$A,0))) | AE162: =IF($X162="","",INDEX(TARIFF_PROFILES!$K:$K,MATCH($X162,TARIFF_PROFILES!$A:$A,0))) | AH162: =IF($AG162="","",SUMIFS(OPERATING_COEFFS!$C:$C,OPERATING_COEFFS!$A:$A,"DistanceClass",OPERATING_COEFFS!$B:$B,$AG162)) | AJ162: =IF($AI162="","",SUMIFS(OPERATING_COEFFS!$C:$C,OPERATING_COEFFS!$A:$A,"SeasonClass",OPERATING_COEFFS!$B:$B,$AI162)) | AL162: =IF($AK162="","",SUMIFS(OPERATING_COEFFS!$C:$C,OPERATING_COEFFS!$A:$A,"UrgencyClass",OPERATING_COEFFS!$B:$B,$AK162)) | AN162: =IF($AM162="","",INDEX(TAX_MODES!$B:$B,MATCH($AM162,TAX_MODES!$A:$A,0)))
... Y1000: =IF($X1000="","",SUMIFS(TARIFF_PROFILES!$D:$D,TARIFF_PROFILES!$A:$A,$X1000)) | Z1000: =IF($X1000="","",SUMIFS(TARIFF_PROFILES!$E:$E,TARIFF_PROFILES!$A:$A,$X1000)) | AA1000: =IF($X1000="","",SUMIFS(TARIFF_PROFILES!$F:$F,TARIFF_PROFILES!$A:$A,$X1000)) | AB1000: =IF($X1000="","",SUMIFS(TARIFF_PROFILES!$G:$G,TARIFF_PROFILES!$A:$A,$X1000)) | AC1000: =IF($X1000="","",SUMIFS(TARIFF_PROFILES!$H:$H,TARIFF_PROFILES!$A:$A,$X1000)) | AD1000: =IF($X1000="","",INDEX(TARIFF_PROFILES!$J:$J,MATCH($X1000,TARIFF_PROFILES!$A:$A,0))) | AE1000: =IF($X1000="","",INDEX(TARIFF_PROFILES!$K:$K,MATCH($X1000,TARIFF_PROFILES!$A:$A,0))) | AH1000: =IF($AG1000="","",SUMIFS(OPERATING_COEFFS!$C:$C,OPERATING_COEFFS!$A:$A,"DistanceClass",OPERATING_COEFFS!$B:$B,$AG1000)) | AJ1000: =IF($AI1000="","",SUMIFS(OPERATING_COEFFS!$C:$C,OPERATING_COEFFS!$A:$A,"SeasonClass",OPERATING_COEFFS!$B:$B,$AI1000)) | AL1000: =IF($AK1000="","",SUMIFS(OPERATING_COEFFS!$C:$C,OPERATING_COEFFS!$A:$A,"UrgencyClass",OPERATING_COEFFS!$B:$B,$AK1000)) | AN1000: =IF($AM1000="","",INDEX(TAX_MODES!$B:$B,MATCH($AM1000,TAX_MODES!$A:$A,0)))

Sheet SITE_COEFFS
A1: FactorType | B1: FactorClass | C1: Coefficient | D1: UseCase | E1: Notes
A2: SoilWorkability | B2: Лёгкая | C2: 0.95 | D2: Песок, лёгкая супесь | E2: Стартовая гипотеза; обычно работать легче
A3: SoilWorkability | B3: Средняя | C3: 1 | D3: Супесь / суглинок средней плотности | E3: Базовый класс участка
A4: SoilWorkability | B4: Тяжёлая | C4: 1.12 | D4: Тяжёлый суглинок / глина | E4: Ожидаемое снижение производительности
A5: SoilWorkability | B5: Очень тяжёлая | C5: 1.22 | D5: Плотная глина, смешанный грунт, камни | E5: Требует ручной доработки и/или спецтехники
A6: SoilMoisture | B6: Сухая | C6: 0.98 | D6: Подсушенный грунт | E6: Часто работать чуть легче
A7: SoilMoisture | B7: Нормальная | C7: 1 | D7: Нормальные условия | E7: Базовый класс
A8: SoilMoisture | B8: Влажная | C8: 1.06 | D8: Повышенная влажность | E8: Риск замедления и налипания
A9: SoilMoisture | B9: Переувлажнённая | C9: 1.15 | D9: Очень мокрый грунт | E9: Часто меняет и цену, и состав решения
A10: DebrisLevel | B10: Нет | C10: 1 | D10: Чистый грунт | E10: Базовый класс
A11: DebrisLevel | B11: Умеренно | C11: 1.08 | D11: Местами корни, мусор, камни | E11: Умеренное усложнение разработки
A12: DebrisLevel | B12: Высоко | C12: 1.18 | D12: Строительный мусор, много корней, камни | E12: Сильное удорожание ручных операций
A13: SlopeClass | B13: 0-3% | C13: 1 | D13: Почти ровно | E13: Базовый класс
... A35: GeometryComplexity | B35: Очень сложная | C35: 1.12 | D35: Ломаная геометрия, много обходов и узлов | E35: Высокий риск перерасхода на подгонку

Sheet OPERATING_COEFFS
A1: FactorType | B1: FactorClass | C1: Coefficient | D1: AppliesTo | E1: UseCase | F1: Notes
A2: DistanceClass | B2: До 10 км | C2: 1 | D2: Логистика/выезд | E2: Базовая зона
A3: DistanceClass | B3: 10-30 км | C3: 1.05 | D3: Логистика/выезд | E3: Умеренное плечо
A4: DistanceClass | B4: 30-60 км | C4: 1.12 | D4: Логистика/выезд | E4: Дальняя доставка
A5: DistanceClass | B5: 60+ км | C5: 1.22 | D5: Логистика/выезд | E5: Очень дальняя зона
A6: SeasonClass | B6: Базовый сезон | C6: 1 | D6: Работы | E6: Типовой период
A7: SeasonClass | B7: Низкий сезон | C7: 0.97 | D7: Работы | E7: Стимулирующий период
A8: SeasonClass | B8: Высокий сезон | C8: 1.08 | D8: Работы | E8: Пиковая загрузка
A9: SeasonClass | B9: Зимние условия | C9: 1.18 | D9: Работы | E9: Сложность производства
A10: UrgencyClass | B10: Планово | C10: 1 | D10: Работы/логистика | E10: Нормальное планирование
A11: UrgencyClass | B11: Ускоренно | C11: 1.07 | D11: Работы/логистика | E11: Сжатые сроки
A12: UrgencyClass | B12: Срочно | C12: 1.15 | D12: Работы/логистика | E12: Срочная мобилизация

Sheet TAX_MODES
A1: TaxMode | B1: VATRate | C1: PricePresentation | D1: Notes
A2: Без НДС | B2: 0 | C2: Цена без НДС = цена для клиента | D2: УСН/без НДС
A3: С НДС 20% | B3: 0.2 | C3: Показывать цену с НДС 20% | D3: Стандартный режим
A4: С НДС 10% | B4: 0.1 | C4: Показывать цену с НДС 10% | D4: Редкий кейс для отдельных товаров/услуг

Sheet WORK_FACTOR_APPLICABILITY
A1: WorkID | B1: CanonicalWork | C1: SoilWeight | D1: MoistureWeight | E1: DebrisWeight | F1: SlopeWeight | G1: UnevennessWeight | H1: AccessWeight | I1: TurnSpaceWeight | J1: ProximityWeight | K1: MachineryWeight | L1: PriceRuleEnabled | M1: CompositionRuleEnabled | N1: SampleObjectID | O1: SiteCoeffExample | P1: Notes
A2: WORK-0001 | B2: Выборка ложа | C2: 0.9 | D2: 0.7 | E2: 0.6 | F2: 0.5 | G2: 0.4 | H2: 0.4 | I2: 0.3 | J2: 0.3 | K2: 0.5 | L2: Да | M2: Да | N2: OBJ-0001 | O2: =IF($N2="","",ROUND(1+($C2*(SUMIFS(OBJECT_CONDITIONS!$D:$D,OBJECT_CONDITIONS!$A:$A,$N2)-1))+($D2*(SUMIFS(OBJECT_CONDITIONS!$F:$F,OBJECT_CONDITIONS!$A:$A,$N2)-1))+($E2*(SUMIFS(OBJECT_CONDITIONS!$H:$H,OBJECT_CONDITIONS!$A:$A,$N2)-1))+($F2*(SUMIFS(OBJECT_CONDITIONS!$J:$J,OBJECT_CONDITIONS!$A:$A,$N2)-1))+($G2*(SUMIFS(OBJECT_CONDITIONS!$L:$L,OBJECT_CONDITIONS!$A:$A,$N2)-1))+($H2*(SUMIFS(OBJECT_CONDITIONS!$N:$N,OBJECT_CONDITIONS!$A:$A,$N2)-1))+($I2*(SUMIFS(OBJECT_CONDITIONS!$P:$P,OBJECT_CONDITIONS!$A:$A,$N2)-1))+($J2*(SUMIFS(OBJECT_CONDITIONS!$R:$R,OBJECT_CONDITIONS!$A:$A,$N2)-1))+($K2*(SUMIFS(OBJECT_CONDITIONS!$T:$T,OBJECT_CONDITIONS!$A:$A,$N2)-1)),3)) | P2: Высокая чувствительность к грунту и механизации
A3: WORK-0002 | B3: Устройство газонного ложа | C3: 0.7 | D3: 0.5 | E3: 0.3 | F3: 0.4 | G3: 0.4 | H3: 0.3 | I3: 0.2 | J3: 0.1 | K3: 0.3 | L3: Да | M3: Да | N3: OBJ-0001 | O3: =IF($N3="","",ROUND(1+($C3*(SUMIFS(OBJECT_CONDITIONS!$D:$D,OBJECT_CONDITIONS!$A:$A,$N3)-1))+($D3*(SUMIFS(OBJECT_CONDITIONS!$F:$F,OBJECT_CONDITIONS!$A:$A,$N3)-1))+($E3*(SUMIFS(OBJECT_CONDITIONS!$H:$H,OBJECT_CONDITIONS!$A:$A,$N3)-1))+($F3*(SUMIFS(OBJECT_CONDITIONS!$J:$J,OBJECT_CONDITIONS!$A:$A,$N3)-1))+($G3*(SUMIFS(OBJECT_CONDITIONS!$L:$L,OBJECT_CONDITIONS!$A:$A,$N3)-1))+($H3*(SUMIFS(OBJECT_CONDITIONS!$N:$N,OBJECT_CONDITIONS!$A:$A,$N3)-1))+($I3*(SUMIFS(OBJECT_CONDITIONS!$P:$P,OBJECT_CONDITIONS!$A:$A,$N3)-1))+($J3*(SUMIFS(OBJECT_CONDITIONS!$R:$R,OBJECT_CONDITIONS!$A:$A,$N3)-1))+($K3*(SUMIFS(OBJECT_CONDITIONS!$T:$T,OBJECT_CONDITIONS!$A:$A,$N3)-1)),3)) | P3: Сильнее реагирует на грунт и рельеф, чем на близость построек
A4: WORK-0003 | B4: Копка траншеи | C4: 0.9 | D4: 0.8 | E4: 0.6 | F4: 0.3 | G4: 0.2 | H4: 0.6 | I4: 0.5 | J4: 0.6 | K4: 0.7 | L4: Да | M4: Да | N4: OBJ-0001 | O4: =IF($N4="","",ROUND(1+($C4*(SUMIFS(OBJECT_CONDITIONS!$D:$D,OBJECT_CONDITIONS!$A:$A,$N4)-1))+($D4*(SUMIFS(OBJECT_CONDITIONS!$F:$F,OBJECT_CONDITIONS!$A:$A,$N4)-1))+($E4*(SUMIFS(OBJECT_CONDITIONS!$H:$H,OBJECT_CONDITIONS!$A:$A,$N4)-1))+($F4*(SUMIFS(OBJECT_CONDITIONS!$J:$J,OBJECT_CONDITIONS!$A:$A,$N4)-1))+($G4*(SUMIFS(OBJECT_CONDITIONS!$L:$L,OBJECT_CONDITIONS!$A:$A,$N4)-1))+($H4*(SUMIFS(OBJECT_CONDITIONS!$N:$N,OBJECT_CONDITIONS!$A:$A,$N4)-1))+($I4*(SUMIFS(OBJECT_CONDITIONS!$P:$P,OBJECT_CONDITIONS!$A:$A,$N4)-1))+($J4*(SUMIFS(OBJECT_CONDITIONS!$R:$R,OBJECT_CONDITIONS!$A:$A,$N4)-1))+($K4*(SUMIFS(OBJECT_CONDITIONS!$T:$T,OBJECT_CONDITIONS!$A:$A,$N4)-1)),3)) | P4: Очень чувствительна к доступу, грунту и близости построек
A5: WORK-0004 | B5: Монтаж бордюра бетонного | C5: 0.1 | D5: 0.1 | E5: 0.1 | F5: 0.4 | G5: 0.3 | H5: 0.2 | I5: 0.1 | J5: 0.2 | K5: 0.1 | L5: Да | M5: Нет | N5: OBJ-0001 | O5: =IF($N5="","",ROUND(1+($C5*(SUMIFS(OBJECT_CONDITIONS!$D:$D,OBJECT_CONDITIONS!$A:$A,$N5)-1))+($D5*(SUMIFS(OBJECT_CONDITIONS!$F:$F,OBJECT_CONDITIONS!$A:$A,$N5)-1))+($E5*(SUMIFS(OBJECT_CONDITIONS!$H:$H,OBJECT_CONDITIONS!$A:$A,$N5)-1))+($F5*(SUMIFS(OBJECT_CONDITIONS!$J:$J,OBJECT_CONDITIONS!$A:$A,$N5)-1))+($G5*(SUMIFS(OBJECT_CONDITIONS!$L:$L,OBJECT_CONDITIONS!$A:$A,$N5)-1))+($H5*(SUMIFS(OBJECT_CONDITIONS!$N:$N,OBJECT_CONDITIONS!$A:$A,$N5)-1))+($I5*(SUMIFS(OBJECT_CONDITIONS!$P:$P,OBJECT_CONDITIONS!$A:$A,$N5)-1))+($J5*(SUMIFS(OBJECT_CONDITIONS!$R:$R,OBJECT_CONDITIONS!$A:$A,$N5)-1))+($K5*(SUMIFS(OBJECT_CONDITIONS!$T:$T,OBJECT_CONDITIONS!$A:$A,$N5)-1)),3)) | P5: Больше зависит от геометрии и рельефа, чем от типа грунта
O6: =IF($N6="","",ROUND(1+($C6*(SUMIFS(OBJECT_CONDITIONS!$D:$D,OBJECT_CONDITIONS!$A:$A,$N6)-1))+($D6*(SUMIFS(OBJECT_CONDITIONS!$F:$F,OBJECT_CONDITIONS!$A:$A,$N6)-1))+($E6*(SUMIFS(OBJECT_CONDITIONS!$H:$H,OBJECT_CONDITIONS!$A:$A,$N6)-1))+($F6*(SUMIFS(OBJECT_CONDITIONS!$J:$J,OBJECT_CONDITIONS!$A:$A,$N6)-1))+($G6*(SUMIFS(OBJECT_CONDITIONS!$L:$L,OBJECT_CONDITIONS!$A:$A,$N6)-1))+($H6*(SUMIFS(OBJECT_CONDITIONS!$N:$N,OBJECT_CONDITIONS!$A:$A,$N6)-1))+($I6*(SUMIFS(OBJECT_CONDITIONS!$P:$P,OBJECT_CONDITIONS!$A:$A,$N6)-1))+($J6*(SUMIFS(OBJECT_CONDITIONS!$R:$R,OBJECT_CONDITIONS!$A:$A,$N6)-1))+($K6*(SUMIFS(OBJECT_CONDITIONS!$T:$T,OBJECT_CONDITIONS!$A:$A,$N6)-1)),3))
O7: =IF($N7="","",ROUND(1+($C7*(SUMIFS(OBJECT_CONDITIONS!$D:$D,OBJECT_CONDITIONS!$A:$A,$N7)-1))+($D7*(SUMIFS(OBJECT_CONDITIONS!$F:$F,OBJECT_CONDITIONS!$A:$A,$N7)-1))+($E7*(SUMIFS(OBJECT_CONDITIONS!$H:$H,OBJECT_CONDITIONS!$A:$A,$N7)-1))+($F7*(SUMIFS(OBJECT_CONDITIONS!$J:$J,OBJECT_CONDITIONS!$A:$A,$N7)-1))+($G7*(SUMIFS(OBJECT_CONDITIONS!$L:$L,OBJECT_CONDITIONS!$A:$A,$N7)-1))+($H7*(SUMIFS(OBJECT_CONDITIONS!$N:$N,OBJECT_CONDITIONS!$A:$A,$N7)-1))+($I7*(SUMIFS(OBJECT_CONDITIONS!$P:$P,OBJECT_CONDITIONS!$A:$A,$N7)-1))+($J7*(SUMIFS(OBJECT_CONDITIONS!$R:$R,OBJECT_CONDITIONS!$A:$A,$N7)-1))+($K7*(SUMIFS(OBJECT_CONDITIONS!$T:$T,OBJECT_CONDITIONS!$A:$A,$N7)-1)),3))
O8: =IF($N8="","",ROUND(1+($C8*(SUMIFS(OBJECT_CONDITIONS!$D:$D,OBJECT_CONDITIONS!$A:$A,$N8)-1))+($D8*(SUMIFS(OBJECT_CONDITIONS!$F:$F,OBJECT_CONDITIONS!$A:$A,$N8)-1))+($E8*(SUMIFS(OBJECT_CONDITIONS!$H:$H,OBJECT_CONDITIONS!$A:$A,$N8)-1))+($F8*(SUMIFS(OBJECT_CONDITIONS!$J:$J,OBJECT_CONDITIONS!$A:$A,$N8)-1))+($G8*(SUMIFS(OBJECT_CONDITIONS!$L:$L,OBJECT_CONDITIONS!$A:$A,$N8)-1))+($H8*(SUMIFS(OBJECT_CONDITIONS!$N:$N,OBJECT_CONDITIONS!$A:$A,$N8)-1))+($I8*(SUMIFS(OBJECT_CONDITIONS!$P:$P,OBJECT_CONDITIONS!$A:$A,$N8)-1))+($J8*(SUMIFS(OBJECT_CONDITIONS!$R:$R,OBJECT_CONDITIONS!$A:$A,$N8)-1))+($K8*(SUMIFS(OBJECT_CONDITIONS!$T:$T,OBJECT_CONDITIONS!$A:$A,$N8)-1)),3))
O9: =IF($N9="","",ROUND(1+($C9*(SUMIFS(OBJECT_CONDITIONS!$D:$D,OBJECT_CONDITIONS!$A:$A,$N9)-1))+($D9*(SUMIFS(OBJECT_CONDITIONS!$F:$F,OBJECT_CONDITIONS!$A:$A,$N9)-1))+($E9*(SUMIFS(OBJECT_CONDITIONS!$H:$H,OBJECT_CONDITIONS!$A:$A,$N9)-1))+($F9*(SUMIFS(OBJECT_CONDITIONS!$J:$J,OBJECT_CONDITIONS!$A:$A,$N9)-1))+($G9*(SUMIFS(OBJECT_CONDITIONS!$L:$L,OBJECT_CONDITIONS!$A:$A,$N9)-1))+($H9*(SUMIFS(OBJECT_CONDITIONS!$N:$N,OBJECT_CONDITIONS!$A:$A,$N9)-1))+($I9*(SUMIFS(OBJECT_CONDITIONS!$P:$P,OBJECT_CONDITIONS!$A:$A,$N9)-1))+($J9*(SUMIFS(OBJECT_CONDITIONS!$R:$R,OBJECT_CONDITIONS!$A:$A,$N9)-1))+($K9*(SUMIFS(OBJECT_CONDITIONS!$T:$T,OBJECT_CONDITIONS!$A:$A,$N9)-1)),3))
O10: =IF($N10="","",ROUND(1+($C10*(SUMIFS(OBJECT_CONDITIONS!$D:$D,OBJECT_CONDITIONS!$A:$A,$N10)-1))+($D10*(SUMIFS(OBJECT_CONDITIONS!$F:$F,OBJECT_CONDITIONS!$A:$A,$N10)-1))+($E10*(SUMIFS(OBJECT_CONDITIONS!$H:$H,OBJECT_CONDITIONS!$A:$A,$N10)-1))+($F10*(SUMIFS(OBJECT_CONDITIONS!$J:$J,OBJECT_CONDITIONS!$A:$A,$N10)-1))+($G10*(SUMIFS(OBJECT_CONDITIONS!$L:$L,OBJECT_CONDITIONS!$A:$A,$N10)-1))+($H10*(SUMIFS(OBJECT_CONDITIONS!$N:$N,OBJECT_CONDITIONS!$A:$A,$N10)-1))+($I10*(SUMIFS(OBJECT_CONDITIONS!$P:$P,OBJECT_CONDITIONS!$A:$A,$N10)-1))+($J10*(SUMIFS(OBJECT_CONDITIONS!$R:$R,OBJECT_CONDITIONS!$A:$A,$N10)-1))+($K10*(SUMIFS(OBJECT_CONDITIONS!$T:$T,OBJECT_CONDITIONS!$A:$A,$N10)-1)),3))
O11: =IF($N11="","",ROUND(1+($C11*(SUMIFS(OBJECT_CONDITIONS!$D:$D,OBJECT_CONDITIONS!$A:$A,$N11)-1))+($D11*(SUMIFS(OBJECT_CONDITIONS!$F:$F,OBJECT_CONDITIONS!$A:$A,$N11)-1))+($E11*(SUMIFS(OBJECT_CONDITIONS!$H:$H,OBJECT_CONDITIONS!$A:$A,$N11)-1))+($F11*(SUMIFS(OBJECT_CONDITIONS!$J:$J,OBJECT_CONDITIONS!$A:$A,$N11)-1))+($G11*(SUMIFS(OBJECT_CONDITIONS!$L:$L,OBJECT_CONDITIONS!$A:$A,$N11)-1))+($H11*(SUMIFS(OBJECT_CONDITIONS!$N:$N,OBJECT_CONDITIONS!$A:$A,$N11)-1))+($I11*(SUMIFS(OBJECT_CONDITIONS!$P:$P,OBJECT_CONDITIONS!$A:$A,$N11)-1))+($J11*(SUMIFS(OBJECT_CONDITIONS!$R:$R,OBJECT_CONDITIONS!$A:$A,$N11)-1))+($K11*(SUMIFS(OBJECT_CONDITIONS!$T:$T,OBJECT_CONDITIONS!$A:$A,$N11)-1)),3))
O12: =IF($N12="","",ROUND(1+($C12*(SUMIFS(OBJECT_CONDITIONS!$D:$D,OBJECT_CONDITIONS!$A:$A,$N12)-1))+($D12*(SUMIFS(OBJECT_CONDITIONS!$F:$F,OBJECT_CONDITIONS!$A:$A,$N12)-1))+($E12*(SUMIFS(OBJECT_CONDITIONS!$H:$H,OBJECT_CONDITIONS!$A:$A,$N12)-1))+($F12*(SUMIFS(OBJECT_CONDITIONS!$J:$J,OBJECT_CONDITIONS!$A:$A,$N12)-1))+($G12*(SUMIFS(OBJECT_CONDITIONS!$L:$L,OBJECT_CONDITIONS!$A:$A,$N12)-1))+($H12*(SUMIFS(OBJECT_CONDITIONS!$N:$N,OBJECT_CONDITIONS!$A:$A,$N12)-1))+($I12*(SUMIFS(OBJECT_CONDITIONS!$P:$P,OBJECT_CONDITIONS!$A:$A,$N12)-1))+($J12*(SUMIFS(OBJECT_CONDITIONS!$R:$R,OBJECT_CONDITIONS!$A:$A,$N12)-1))+($K12*(SUMIFS(OBJECT_CONDITIONS!$T:$T,OBJECT_CONDITIONS!$A:$A,$N12)-1)),3))
O13: =IF($N13="","",ROUND(1+($C13*(SUMIFS(OBJECT_CONDITIONS!$D:$D,OBJECT_CONDITIONS!$A:$A,$N13)-1))+($D13*(SUMIFS(OBJECT_CONDITIONS!$F:$F,OBJECT_CONDITIONS!$A:$A,$N13)-1))+($E13*(SUMIFS(OBJECT_CONDITIONS!$H:$H,OBJECT_CONDITIONS!$A:$A,$N13)-1))+($F13*(SUMIFS(OBJECT_CONDITIONS!$J:$J,OBJECT_CONDITIONS!$A:$A,$N13)-1))+($G13*(SUMIFS(OBJECT_CONDITIONS!$L:$L,OBJECT_CONDITIONS!$A:$A,$N13)-1))+($H13*(SUMIFS(OBJECT_CONDITIONS!$N:$N,OBJECT_CONDITIONS!$A:$A,$N13)-1))+($I13*(SUMIFS(OBJECT_CONDITIONS!$P:$P,OBJECT_CONDITIONS!$A:$A,$N13)-1))+($J13*(SUMIFS(OBJECT_CONDITIONS!$R:$R,OBJECT_CONDITIONS!$A:$A,$N13)-1))+($K13*(SUMIFS(OBJECT_CONDITIONS!$T:$T,OBJECT_CONDITIONS!$A:$A,$N13)-1)),3))
O14: =IF($N14="","",ROUND(1+($C14*(SUMIFS(OBJECT_CONDITIONS!$D:$D,OBJECT_CONDITIONS!$A:$A,$N14)-1))+($D14*(SUMIFS(OBJECT_CONDITIONS!$F:$F,OBJECT_CONDITIONS!$A:$A,$N14)-1))+($E14*(SUMIFS(OBJECT_CONDITIONS!$H:$H,OBJECT_CONDITIONS!$A:$A,$N14)-1))+($F14*(SUMIFS(OBJECT_CONDITIONS!$J:$J,OBJECT_CONDITIONS!$A:$A,$N14)-1))+($G14*(SUMIFS(OBJECT_CONDITIONS!$L:$L,OBJECT_CONDITIONS!$A:$A,$N14)-1))+($H14*(SUMIFS(OBJECT_CONDITIONS!$N:$N,OBJECT_CONDITIONS!$A:$A,$N14)-1))+($I14*(SUMIFS(OBJECT_CONDITIONS!$P:$P,OBJECT_CONDITIONS!$A:$A,$N14)-1))+($J14*(SUMIFS(OBJECT_CONDITIONS!$R:$R,OBJECT_CONDITIONS!$A:$A,$N14)-1))+($K14*(SUMIFS(OBJECT_CONDITIONS!$T:$T,OBJECT_CONDITIONS!$A:$A,$N14)-1)),3))
O15: =IF($N15="","",ROUND(1+($C15*(SUMIFS(OBJECT_CONDITIONS!$D:$D,OBJECT_CONDITIONS!$A:$A,$N15)-1))+($D15*(SUMIFS(OBJECT_CONDITIONS!$F:$F,OBJECT_CONDITIONS!$A:$A,$N15)-1))+($E15*(SUMIFS(OBJECT_CONDITIONS!$H:$H,OBJECT_CONDITIONS!$A:$A,$N15)-1))+($F15*(SUMIFS(OBJECT_CONDITIONS!$J:$J,OBJECT_CONDITIONS!$A:$A,$N15)-1))+($G15*(SUMIFS(OBJECT_CONDITIONS!$L:$L,OBJECT_CONDITIONS!$A:$A,$N15)-1))+($H15*(SUMIFS(OBJECT_CONDITIONS!$N:$N,OBJECT_CONDITIONS!$A:$A,$N15)-1))+($I15*(SUMIFS(OBJECT_CONDITIONS!$P:$P,OBJECT_CONDITIONS!$A:$A,$N15)-1))+($J15*(SUMIFS(OBJECT_CONDITIONS!$R:$R,OBJECT_CONDITIONS!$A:$A,$N15)-1))+($K15*(SUMIFS(OBJECT_CONDITIONS!$T:$T,OBJECT_CONDITIONS!$A:$A,$N15)-1)),3))
O16: =IF($N16="","",ROUND(1+($C16*(SUMIFS(OBJECT_CONDITIONS!$D:$D,OBJECT_CONDITIONS!$A:$A,$N16)-1))+($D16*(SUMIFS(OBJECT_CONDITIONS!$F:$F,OBJECT_CONDITIONS!$A:$A,$N16)-1))+($E16*(SUMIFS(OBJECT_CONDITIONS!$H:$H,OBJECT_CONDITIONS!$A:$A,$N16)-1))+($F16*(SUMIFS(OBJECT_CONDITIONS!$J:$J,OBJECT_CONDITIONS!$A:$A,$N16)-1))+($G16*(SUMIFS(OBJECT_CONDITIONS!$L:$L,OBJECT_CONDITIONS!$A:$A,$N16)-1))+($H16*(SUMIFS(OBJECT_CONDITIONS!$N:$N,OBJECT_CONDITIONS!$A:$A,$N16)-1))+($I16*(SUMIFS(OBJECT_CONDITIONS!$P:$P,OBJECT_CONDITIONS!$A:$A,$N16)-1))+($J16*(SUMIFS(OBJECT_CONDITIONS!$R:$R,OBJECT_CONDITIONS!$A:$A,$N16)-1))+($K16*(SUMIFS(OBJECT_CONDITIONS!$T:$T,OBJECT_CONDITIONS!$A:$A,$N16)-1)),3))
O17: =IF($N17="","",ROUND(1+($C17*(SUMIFS(OBJECT_CONDITIONS!$D:$D,OBJECT_CONDITIONS!$A:$A,$N17)-1))+($D17*(SUMIFS(OBJECT_CONDITIONS!$F:$F,OBJECT_CONDITIONS!$A:$A,$N17)-1))+($E17*(SUMIFS(OBJECT_CONDITIONS!$H:$H,OBJECT_CONDITIONS!$A:$A,$N17)-1))+($F17*(SUMIFS(OBJECT_CONDITIONS!$J:$J,OBJECT_CONDITIONS!$A:$A,$N17)-1))+($G17*(SUMIFS(OBJECT_CONDITIONS!$L:$L,OBJECT_CONDITIONS!$A:$A,$N17)-1))+($H17*(SUMIFS(OBJECT_CONDITIONS!$N:$N,OBJECT_CONDITIONS!$A:$A,$N17)-1))+($I17*(SUMIFS(OBJECT_CONDITIONS!$P:$P,OBJECT_CONDITIONS!$A:$A,$N17)-1))+($J17*(SUMIFS(OBJECT_CONDITIONS!$R:$R,OBJECT_CONDITIONS!$A:$A,$N17)-1))+($K17*(SUMIFS(OBJECT_CONDITIONS!$T:$T,OBJECT_CONDITIONS!$A:$A,$N17)-1)),3))
... O150: =IF($N150="","",ROUND(1+($C150*(SUMIFS(OBJECT_CONDITIONS!$D:$D,OBJECT_CONDITIONS!$A:$A,$N150)-1))+($D150*(SUMIFS(OBJECT_CONDITIONS!$F:$F,OBJECT_CONDITIONS!$A:$A,$N150)-1))+($E150*(SUMIFS(OBJECT_CONDITIONS!$H:$H,OBJECT_CONDITIONS!$A:$A,$N150)-1))+($F150*(SUMIFS(OBJECT_CONDITIONS!$J:$J,OBJECT_CONDITIONS!$A:$A,$N150)-1))+($G150*(SUMIFS(OBJECT_CONDITIONS!$L:$L,OBJECT_CONDITIONS!$A:$A,$N150)-1))+($H150*(SUMIFS(OBJECT_CONDITIONS!$N:$N,OBJECT_CONDITIONS!$A:$A,$N150)-1))+($I150*(SUMIFS(OBJECT_CONDITIONS!$P:$P,OBJECT_CONDITIONS!$A:$A,$N150)-1))+($J150*(SUMIFS(OBJECT_CONDITIONS!$R:$R,OBJECT_CONDITIONS!$A:$A,$N150)-1))+($K150*(SUMIFS(OBJECT_CONDITIONS!$T:$T,OBJECT_CONDITIONS!$A:$A,$N150)-1)),3))

Sheet CONDITION_RULES
A1: RuleID | B1: ScopeType | C1: ScopeValue | D1: ConditionField1 | E1: ConditionValue1 | F1: ConditionField2 | G1: ConditionValue2 | H1: ActionType | I1: ActionValue | J1: TargetEntityType | K1: TargetID | L1: Priority | M1: IsActive | N1: Notes
A2: CR-0001 | B2: Work | C2: WORK-0001 | D2: MachineryAllowed | E2: Нет | H2: ForceMethod | I2: Ручной | J2: Work | K2: WORK-0001 | L2: 1 | M2: Да | N2: Если механизация невозможна, вариант принудительно становится ручным
A3: CR-0002 | B3: Work | C3: WORK-0001 | D3: AccessClass | E3: Свободный | F3: MachineryAllowed | G3: Да | H3: PreferMethod | I3: Механизированный | J3: Work | K3: WORK-0001 | L3: 2 | M3: Да | N3: При хорошем доступе механизированный способ предпочтителен
A4: CR-0003 | B4: Section | C4: Мощение | D4: SoilMoisture | E4: Переувлажнённая | F4: SoilWorkability | G4: Тяжёлая | H4: AddNote | I4: Проверить усиление основания, геотекстиль и дренаж | J4: Work | L4: 3 | M4: Да | N4: Не только цена, но и состав решения требуют пересмотра
A5: CR-0004 | B5: Section | C5: Мощение | D5: SlopeClass | E5: 8-15% | H5: AddNote | I5: Проверить ручную подработку, удержание кромки и геометрию покрытия | J5: Work | L5: 4 | M5: Да | N5: Уклон выше стандартного часто меняет трудоёмкость
A6: CR-0005 | B6: Work | C6: WORK-0004 | D6: ProximityToBuildings | E6: Очень близко | F6: MachineryAllowed | G6: Частично | H6: AddNote | I6: Уточнить деликатную разработку и ручные подрезки вдоль построек | J6: Work | K6: WORK-0004 | L6: 5 | M6: Да | N6: Близость построек повышает риск повреждений и снижает темп

Sheet DEPENDENCY_RULES
A1: RuleID | B1: TriggerType | C1: TriggerID | D1: ConditionField | E1: ConditionValue | F1: ActionType | G1: TargetType | H1: TargetID | I1: QtyLogic | J1: Priority | K1: IsActive | L1: Notes
A2: DR-0001 | B2: Work | C2: WORK-0001 | D2: MachineryAllowed | E2: Нет | F2: ForceMethod | G2: Work | H2: Ручной | I2: 1:1 | J2: High | K2: Да | L2: Если механизация невозможна, ручной способ обязателен
A3: DR-0002 | B3: Material | C3: MAT-0001 | D3: SelectedTariff | E3: Премиум | F3: PreferVariant | G3: Material | H3: MV-0003 | I3: 1:1 | J3: Medium | K3: Да | L3: Премиум чаще тянет лучший вариант покрытия
A4: DR-0003 | B4: Material | C4: MAT-0001 | D4: LoadClass | E4: Легковой транспорт | F4: FlagIfBelow | G4: Material | H4: Thickness>=60 | I4: - | J4: High | K4: Да | L4: Не позволять пешеходный вариант на въезде
A5: DR-0004 | B5: Work | C5: WORK-0002 | D5: SlopeClass | E5: 8-15% | F5: AddWork | G5: Work | H5: WORK-0001 | I5: 0.15 x area | J5: Medium | K5: Да | L5: При уклоне усиливаем подготовку
A6: DR-0005 | B6: Material | C6: MAT-0003 | D6: GeometryComplexity | E6: Сложная | F6: AddMaterial | G6: Material | H6: MAT-0004 | I6: 0.03 x area | J6: Low | K6: Да | L6: Пример добавления вспомогательного материала

Sheet MATERIAL_ALLOWANCES
A1: RuleID | B1: AllowanceGroup | C1: AllowanceType | D1: ScopeType | E1: ScopeValue | F1: ComponentCoeff | G1: IncludedInBaseCoeff | H1: ExampleUse | I1: Notes
A2: MA-0001 | B2: Сыпучие с уплотнением | C2: Разрыхление/уплотнение | D2: MaterialType | E2: Сыпучий материал | F2: 1.18 | G2: Да | H2: Щебень, песок, отсев от проектного уплотненного объема | I2: Коэффициент уже включает переход от проектного объема к закупке
A3: MA-0002 | B3: Штучное покрытие | C3: Запас на подрезку | D3: MaterialFamily | E3: Брусчатка бетонная | F3: 1.05 | G3: Да | H3: Брусчатка и схожие штучные покрытия | I3: Стартовая гипотеза; для сложной геометрии доп. запас даёт SiteReserveCoeff
A4: MA-0003 | B4: Рулонный текстиль | C4: Запас на нахлест | D4: MaterialType | E4: Сетка / текстиль | F4: 1.1 | G4: Да | H4: Геотекстиль, геосетка | I4: Отдельный компонент базового коэффициента
A5: MA-0004 | B5: Рулонный текстиль | C5: Запас на подрезку | D5: MaterialType | E5: Сетка / текстиль | F5: 1.03 | G5: Да | H5: Геотекстиль, геосетка | I5: В сумме с нахлестом даёт базовый коэффициент 1.133
A6: MA-0005 | B6: Рулонный газон / турф | C6: Запас на стыковку/подгонку | D6: MaterialFamily | E6: Газон рулонный | F6: 1.05 | G6: Да | H6: Рулонный газон / turf | I6: Обычно зависит от геометрии участка и примыканий
A7: MA-0006 | B7: Пленка / мембрана | C7: Запас на нахлест | D7: MaterialType | E7: Пленка / мембрана | F7: 1.12 | G7: Да | H7: Пленки, мембраны, изоляция | I7: Ширина нахлеста зависит от материала и производителя
A8: MA-0007 | B8: Пленка / мембрана | C8: Запас на подрезку | D8: MaterialType | E8: Пленка / мембрана | F8: 1.03 | G8: Да | H8: Пленки, мембраны, изоляция | I8: В сумме с нахлестом даёт базовый коэффициент 1.154
A9: MA-0008 | B9: Погонаж / доска | C9: Торцовка/раскрой | D9: MaterialType | E9: Погонаж / доска | F9: 1.1 | G9: Да | H9: Террасная доска, доска настила | I9: На узких и ломаных зонах запас растёт
A10: MA-0009 | B10: Линейный / штучный без существенной подрезки | C10: Технологический запас | D10: MaterialFamily | E10: Бордюр бетонный | F10: 1.02 | G10: Да | H10: Бордюр, некоторые линейные элементы | I10: Минимальный запас на бой/добор

Sheet PROCUREMENT_RULES
A1: RuleID | B1: ScopeType | C1: ScopeValue | D1: PurchaseUnit | E1: RoundMode | F1: RoundBasis | G1: PackSize | H1: MinOrderQty | I1: OrderStepQty | J1: PalletQty | K1: ReserveAppliedBeforeRounding | L1: FreeSpareCoeff | M1: LeadTimeDays | N1: Notes
A2: PR-0001 | B2: AllowanceGroup | C2: Сыпучие / с разрыхлением | D2: м3 | E2: UP | F2: Без округления | G2: 1 | H2: 0 | I2: 0.1 | J2: 0 | K2: Да | L2: 0 | M2: 2 | N2: Закупка по м3 с округлением вверх до 0,1 м3
A3: PR-0002 | B3: AllowanceGroup | C3: Рулон / лист / нахлест | D3: рулон | E3: UP | F3: По рулону/листу | G3: 1 | H3: 1 | I3: 1 | J3: 0 | K3: Да | L3: 0 | M3: 3 | N3: Сначала площадь с запасом, потом округление в целые рулоны
A4: PR-0003 | B4: AllowanceGroup | C4: Штучный материал / подрезка | D4: м2 | E4: UP | F4: По паллете | G4: 1 | H4: 0 | I4: 1 | J4: 12 | K4: Да | L4: 0.01 | M4: 5 | N4: Подрезка + технологический запас + округление к паллете
A5: PR-0004 | B5: AllowanceGroup | C5: Погонаж / доска / раскрой | D5: шт | E5: UP | F5: По упаковке | G5: 1 | H5: 0 | I5: 5 | J5: 0 | K5: Да | L5: 0.03 | M5: 4 | N5: Запас на раскрой и торцовку
A6: PR-0005 | B6: ScopeType | C6: MV-0003 | D6: м2 | E6: UP | F6: По паллете | G6: 1 | H6: 0 | I6: 1 | J6: 12 | K6: Да | L6: 0.02 | M6: 5 | N6: Пример точечного правила на конкретный вариант

Sheet MATERIAL_FACTOR_APPLICABILITY
A1: MaterialID | B1: CanonicalMaterial | C1: AllowanceGroup | D1: GeometryWeight | E1: SlopeWeight | F1: UnevennessWeight | G1: AccessWeight | H1: ProximityWeight | I1: ExampleObjectID | J1: SiteReserveCoeffExample | K1: Notes
A2: MAT-0001 | B2: Брусчатка бетонная 200x100 | C2: Штучное покрытие | D2: 0.6 | E2: 0.1 | F2: 0.1 | G2: 0 | H2: 0 | I2: OBJ-0001 | J2: =IF($I2="","",ROUND(1+($D2*(SUMIFS(OBJECT_CONDITIONS!$W:$W,OBJECT_CONDITIONS!$A:$A,$I2)-1))+($E2*(SUMIFS(OBJECT_CONDITIONS!$J:$J,OBJECT_CONDITIONS!$A:$A,$I2)-1))+($F2*(SUMIFS(OBJECT_CONDITIONS!$L:$L,OBJECT_CONDITIONS!$A:$A,$I2)-1))+($G2*(SUMIFS(OBJECT_CONDITIONS!$N:$N,OBJECT_CONDITIONS!$A:$A,$I2)-1))+($H2*(SUMIFS(OBJECT_CONDITIONS!$R:$R,OBJECT_CONDITIONS!$A:$A,$I2)-1)),3)) | K2: Подрезка зависит в первую очередь от геометрии рисунка и контуров
A3: MAT-0002 | B3: Бордюр бетонный 1000x200x80 | C3: Линейный / штучный без существенной подрезки | D3: 0.3 | E3: 0.1 | F3: 0.1 | G3: 0 | H3: 0 | I3: OBJ-0001 | J3: =IF($I3="","",ROUND(1+($D3*(SUMIFS(OBJECT_CONDITIONS!$W:$W,OBJECT_CONDITIONS!$A:$A,$I3)-1))+($E3*(SUMIFS(OBJECT_CONDITIONS!$J:$J,OBJECT_CONDITIONS!$A:$A,$I3)-1))+($F3*(SUMIFS(OBJECT_CONDITIONS!$L:$L,OBJECT_CONDITIONS!$A:$A,$I3)-1))+($G3*(SUMIFS(OBJECT_CONDITIONS!$N:$N,OBJECT_CONDITIONS!$A:$A,$I3)-1))+($H3*(SUMIFS(OBJECT_CONDITIONS!$R:$R,OBJECT_CONDITIONS!$A:$A,$I3)-1)),3)) | K3: Небольшой рост запаса на ломаных контурах и доборах
A4: MAT-0003 | B4: Геотекстиль 200 г/м2 | C4: Рулонный текстиль | D4: 0.8 | E4: 0.2 | F4: 0.4 | G4: 0.1 | H4: 0 | I4: OBJ-0001 | J4: =IF($I4="","",ROUND(1+($D4*(SUMIFS(OBJECT_CONDITIONS!$W:$W,OBJECT_CONDITIONS!$A:$A,$I4)-1))+($E4*(SUMIFS(OBJECT_CONDITIONS!$J:$J,OBJECT_CONDITIONS!$A:$A,$I4)-1))+($F4*(SUMIFS(OBJECT_CONDITIONS!$L:$L,OBJECT_CONDITIONS!$A:$A,$I4)-1))+($G4*(SUMIFS(OBJECT_CONDITIONS!$N:$N,OBJECT_CONDITIONS!$A:$A,$I4)-1))+($H4*(SUMIFS(OBJECT_CONDITIONS!$R:$R,OBJECT_CONDITIONS!$A:$A,$I4)-1)),3)) | K4: Сильная зависимость от геометрии, нахлестов и неровностей
A5: MAT-0004 | B5: Газон рулонный стандарт | C5: Рулонный газон / турф | D5: 0.9 | E5: 0.3 | F5: 0.3 | G5: 0.1 | H5: 0 | I5: OBJ-0001 | J5: =IF($I5="","",ROUND(1+($D5*(SUMIFS(OBJECT_CONDITIONS!$W:$W,OBJECT_CONDITIONS!$A:$A,$I5)-1))+($E5*(SUMIFS(OBJECT_CONDITIONS!$J:$J,OBJECT_CONDITIONS!$A:$A,$I5)-1))+($F5*(SUMIFS(OBJECT_CONDITIONS!$L:$L,OBJECT_CONDITIONS!$A:$A,$I5)-1))+($G5*(SUMIFS(OBJECT_CONDITIONS!$N:$N,OBJECT_CONDITIONS!$A:$A,$I5)-1))+($H5*(SUMIFS(OBJECT_CONDITIONS!$R:$R,OBJECT_CONDITIONS!$A:$A,$I5)-1)),3)) | K5: Сложные контуры и уклон заметно увеличивают подрезку
A6: MAT-0005 | B6: Пленка / мембрана защитная | C6: Пленка / мембрана | D6: 0.8 | E6: 0.4 | F6: 0.3 | G6: 0.1 | H6: 0 | I6: OBJ-0001 | J6: =IF($I6="","",ROUND(1+($D6*(SUMIFS(OBJECT_CONDITIONS!$W:$W,OBJECT_CONDITIONS!$A:$A,$I6)-1))+($E6*(SUMIFS(OBJECT_CONDITIONS!$J:$J,OBJECT_CONDITIONS!$A:$A,$I6)-1))+($F6*(SUMIFS(OBJECT_CONDITIONS!$L:$L,OBJECT_CONDITIONS!$A:$A,$I6)-1))+($G6*(SUMIFS(OBJECT_CONDITIONS!$N:$N,OBJECT_CONDITIONS!$A:$A,$I6)-1))+($H6*(SUMIFS(OBJECT_CONDITIONS!$R:$R,OBJECT_CONDITIONS!$A:$A,$I6)-1)),3)) | K6: Рост нахлестов и подрезки на сложных зонах
A7: MAT-0006 | B7: Террасная доска стандарт | C7: Погонаж / доска | D7: 0.7 | E7: 0.2 | F7: 0.2 | G7: 0.1 | H7: 0 | I7: OBJ-0001 | J7: =IF($I7="","",ROUND(1+($D7*(SUMIFS(OBJECT_CONDITIONS!$W:$W,OBJECT_CONDITIONS!$A:$A,$I7)-1))+($E7*(SUMIFS(OBJECT_CONDITIONS!$J:$J,OBJECT_CONDITIONS!$A:$A,$I7)-1))+($F7*(SUMIFS(OBJECT_CONDITIONS!$L:$L,OBJECT_CONDITIONS!$A:$A,$I7)-1))+($G7*(SUMIFS(OBJECT_CONDITIONS!$N:$N,OBJECT_CONDITIONS!$A:$A,$I7)-1))+($H7*(SUMIFS(OBJECT_CONDITIONS!$R:$R,OBJECT_CONDITIONS!$A:$A,$I7)-1)),3)) | K7: Торцовка и доборы сильнее зависят от контуров, чем от уклона
A8: MAT-0007 | B8: Щебень фр. 20-40 | C8: Сыпучие с уплотнением | D8: 0.1 | E8: 0.3 | F8: 0.2 | G8: 0.2 | H8: 0 | I8: OBJ-0001 | J8: =IF($I8="","",ROUND(1+($D8*(SUMIFS(OBJECT_CONDITIONS!$W:$W,OBJECT_CONDITIONS!$A:$A,$I8)-1))+($E8*(SUMIFS(OBJECT_CONDITIONS!$J:$J,OBJECT_CONDITIONS!$A:$A,$I8)-1))+($F8*(SUMIFS(OBJECT_CONDITIONS!$L:$L,OBJECT_CONDITIONS!$A:$A,$I8)-1))+($G8*(SUMIFS(OBJECT_CONDITIONS!$N:$N,OBJECT_CONDITIONS!$A:$A,$I8)-1))+($H8*(SUMIFS(OBJECT_CONDITIONS!$R:$R,OBJECT_CONDITIONS!$A:$A,$I8)-1)),3)) | K8: Для сыпучих важнее уклон, потери на подачу и условия разгрузки
J9: =IF($I9="","",ROUND(1+($D9*(SUMIFS(OBJECT_CONDITIONS!$W:$W,OBJECT_CONDITIONS!$A:$A,$I9)-1))+($E9*(SUMIFS(OBJECT_CONDITIONS!$J:$J,OBJECT_CONDITIONS!$A:$A,$I9)-1))+($F9*(SUMIFS(OBJECT_CONDITIONS!$L:$L,OBJECT_CONDITIONS!$A:$A,$I9)-1))+($G9*(SUMIFS(OBJECT_CONDITIONS!$N:$N,OBJECT_CONDITIONS!$A:$A,$I9)-1))+($H9*(SUMIFS(OBJECT_CONDITIONS!$R:$R,OBJECT_CONDITIONS!$A:$A,$I9)-1)),3))
J10: =IF($I10="","",ROUND(1+($D10*(SUMIFS(OBJECT_CONDITIONS!$W:$W,OBJECT_CONDITIONS!$A:$A,$I10)-1))+($E10*(SUMIFS(OBJECT_CONDITIONS!$J:$J,OBJECT_CONDITIONS!$A:$A,$I10)-1))+($F10*(SUMIFS(OBJECT_CONDITIONS!$L:$L,OBJECT_CONDITIONS!$A:$A,$I10)-1))+($G10*(SUMIFS(OBJECT_CONDITIONS!$N:$N,OBJECT_CONDITIONS!$A:$A,$I10)-1))+($H10*(SUMIFS(OBJECT_CONDITIONS!$R:$R,OBJECT_CONDITIONS!$A:$A,$I10)-1)),3))
J11: =IF($I11="","",ROUND(1+($D11*(SUMIFS(OBJECT_CONDITIONS!$W:$W,OBJECT_CONDITIONS!$A:$A,$I11)-1))+($E11*(SUMIFS(OBJECT_CONDITIONS!$J:$J,OBJECT_CONDITIONS!$A:$A,$I11)-1))+($F11*(SUMIFS(OBJECT_CONDITIONS!$L:$L,OBJECT_CONDITIONS!$A:$A,$I11)-1))+($G11*(SUMIFS(OBJECT_CONDITIONS!$N:$N,OBJECT_CONDITIONS!$A:$A,$I11)-1))+($H11*(SUMIFS(OBJECT_CONDITIONS!$R:$R,OBJECT_CONDITIONS!$A:$A,$I11)-1)),3))
J12: =IF($I12="","",ROUND(1+($D12*(SUMIFS(OBJECT_CONDITIONS!$W:$W,OBJECT_CONDITIONS!$A:$A,$I12)-1))+($E12*(SUMIFS(OBJECT_CONDITIONS!$J:$J,OBJECT_CONDITIONS!$A:$A,$I12)-1))+($F12*(SUMIFS(OBJECT_CONDITIONS!$L:$L,OBJECT_CONDITIONS!$A:$A,$I12)-1))+($G12*(SUMIFS(OBJECT_CONDITIONS!$N:$N,OBJECT_CONDITIONS!$A:$A,$I12)-1))+($H12*(SUMIFS(OBJECT_CONDITIONS!$R:$R,OBJECT_CONDITIONS!$A:$A,$I12)-1)),3))
J13: =IF($I13="","",ROUND(1+($D13*(SUMIFS(OBJECT_CONDITIONS!$W:$W,OBJECT_CONDITIONS!$A:$A,$I13)-1))+($E13*(SUMIFS(OBJECT_CONDITIONS!$J:$J,OBJECT_CONDITIONS!$A:$A,$I13)-1))+($F13*(SUMIFS(OBJECT_CONDITIONS!$L:$L,OBJECT_CONDITIONS!$A:$A,$I13)-1))+($G13*(SUMIFS(OBJECT_CONDITIONS!$N:$N,OBJECT_CONDITIONS!$A:$A,$I13)-1))+($H13*(SUMIFS(OBJECT_CONDITIONS!$R:$R,OBJECT_CONDITIONS!$A:$A,$I13)-1)),3))
J14: =IF($I14="","",ROUND(1+($D14*(SUMIFS(OBJECT_CONDITIONS!$W:$W,OBJECT_CONDITIONS!$A:$A,$I14)-1))+($E14*(SUMIFS(OBJECT_CONDITIONS!$J:$J,OBJECT_CONDITIONS!$A:$A,$I14)-1))+($F14*(SUMIFS(OBJECT_CONDITIONS!$L:$L,OBJECT_CONDITIONS!$A:$A,$I14)-1))+($G14*(SUMIFS(OBJECT_CONDITIONS!$N:$N,OBJECT_CONDITIONS!$A:$A,$I14)-1))+($H14*(SUMIFS(OBJECT_CONDITIONS!$R:$R,OBJECT_CONDITIONS!$A:$A,$I14)-1)),3))
J15: =IF($I15="","",ROUND(1+($D15*(SUMIFS(OBJECT_CONDITIONS!$W:$W,OBJECT_CONDITIONS!$A:$A,$I15)-1))+($E15*(SUMIFS(OBJECT_CONDITIONS!$J:$J,OBJECT_CONDITIONS!$A:$A,$I15)-1))+($F15*(SUMIFS(OBJECT_CONDITIONS!$L:$L,OBJECT_CONDITIONS!$A:$A,$I15)-1))+($G15*(SUMIFS(OBJECT_CONDITIONS!$N:$N,OBJECT_CONDITIONS!$A:$A,$I15)-1))+($H15*(SUMIFS(OBJECT_CONDITIONS!$R:$R,OBJECT_CONDITIONS!$A:$A,$I15)-1)),3))
J16: =IF($I16="","",ROUND(1+($D16*(SUMIFS(OBJECT_CONDITIONS!$W:$W,OBJECT_CONDITIONS!$A:$A,$I16)-1))+($E16*(SUMIFS(OBJECT_CONDITIONS!$J:$J,OBJECT_CONDITIONS!$A:$A,$I16)-1))+($F16*(SUMIFS(OBJECT_CONDITIONS!$L:$L,OBJECT_CONDITIONS!$A:$A,$I16)-1))+($G16*(SUMIFS(OBJECT_CONDITIONS!$N:$N,OBJECT_CONDITIONS!$A:$A,$I16)-1))+($H16*(SUMIFS(OBJECT_CONDITIONS!$R:$R,OBJECT_CONDITIONS!$A:$A,$I16)-1)),3))
J17: =IF($I17="","",ROUND(1+($D17*(SUMIFS(OBJECT_CONDITIONS!$W:$W,OBJECT_CONDITIONS!$A:$A,$I17)-1))+($E17*(SUMIFS(OBJECT_CONDITIONS!$J:$J,OBJECT_CONDITIONS!$A:$A,$I17)-1))+($F17*(SUMIFS(OBJECT_CONDITIONS!$L:$L,OBJECT_CONDITIONS!$A:$A,$I17)-1))+($G17*(SUMIFS(OBJECT_CONDITIONS!$N:$N,OBJECT_CONDITIONS!$A:$A,$I17)-1))+($H17*(SUMIFS(OBJECT_CONDITIONS!$R:$R,OBJECT_CONDITIONS!$A:$A,$I17)-1)),3))
J18: =IF($I18="","",ROUND(1+($D18*(SUMIFS(OBJECT_CONDITIONS!$W:$W,OBJECT_CONDITIONS!$A:$A,$I18)-1))+($E18*(SUMIFS(OBJECT_CONDITIONS!$J:$J,OBJECT_CONDITIONS!$A:$A,$I18)-1))+($F18*(SUMIFS(OBJECT_CONDITIONS!$L:$L,OBJECT_CONDITIONS!$A:$A,$I18)-1))+($G18*(SUMIFS(OBJECT_CONDITIONS!$N:$N,OBJECT_CONDITIONS!$A:$A,$I18)-1))+($H18*(SUMIFS(OBJECT_CONDITIONS!$R:$R,OBJECT_CONDITIONS!$A:$A,$I18)-1)),3))
J19: =IF($I19="","",ROUND(1+($D19*(SUMIFS(OBJECT_CONDITIONS!$W:$W,OBJECT_CONDITIONS!$A:$A,$I19)-1))+($E19*(SUMIFS(OBJECT_CONDITIONS!$J:$J,OBJECT_CONDITIONS!$A:$A,$I19)-1))+($F19*(SUMIFS(OBJECT_CONDITIONS!$L:$L,OBJECT_CONDITIONS!$A:$A,$I19)-1))+($G19*(SUMIFS(OBJECT_CONDITIONS!$N:$N,OBJECT_CONDITIONS!$A:$A,$I19)-1))+($H19*(SUMIFS(OBJECT_CONDITIONS!$R:$R,OBJECT_CONDITIONS!$A:$A,$I19)-1)),3))
J20: =IF($I20="","",ROUND(1+($D20*(SUMIFS(OBJECT_CONDITIONS!$W:$W,OBJECT_CONDITIONS!$A:$A,$I20)-1))+($E20*(SUMIFS(OBJECT_CONDITIONS!$J:$J,OBJECT_CONDITIONS!$A:$A,$I20)-1))+($F20*(SUMIFS(OBJECT_CONDITIONS!$L:$L,OBJECT_CONDITIONS!$A:$A,$I20)-1))+($G20*(SUMIFS(OBJECT_CONDITIONS!$N:$N,OBJECT_CONDITIONS!$A:$A,$I20)-1))+($H20*(SUMIFS(OBJECT_CONDITIONS!$R:$R,OBJECT_CONDITIONS!$A:$A,$I20)-1)),3))
... J150: =IF($I150="","",ROUND(1+($D150*(SUMIFS(OBJECT_CONDITIONS!$W:$W,OBJECT_CONDITIONS!$A:$A,$I150)-1))+($E150*(SUMIFS(OBJECT_CONDITIONS!$J:$J,OBJECT_CONDITIONS!$A:$A,$I150)-1))+($F150*(SUMIFS(OBJECT_CONDITIONS!$L:$L,OBJECT_CONDITIONS!$A:$A,$I150)-1))+($G150*(SUMIFS(OBJECT_CONDITIONS!$N:$N,OBJECT_CONDITIONS!$A:$A,$I150)-1))+($H150*(SUMIFS(OBJECT_CONDITIONS!$R:$R,OBJECT_CONDITIONS!$A:$A,$I150)-1)),3))

Sheet MATERIAL_QUANTITY_EXAMPLE
A1: CalcID | B1: ObjectID | C1: MaterialID | D1: VariantID | E1: NetQty | F1: NetUnit | G1: AllowanceGroup | H1: BaseReserveCoeff | I1: GeometryWeight | J1: SlopeWeight | K1: UnevennessWeight | L1: AccessWeight | M1: ProximityWeight | N1: SiteReserveCoeff | O1: ManualAdjCoeff | P1: FinalReserveCoeff | Q1: FinalQty | R1: PurchaseUnit | S1: CoveragePerPurchaseUnit | T1: PurchaseQty | U1: Notes
A2: MC-0001 | B2: OBJ-0001 | C2: MAT-0003 | D2: MV-0004 | E2: 180 | F2: м2 | G2: =IF($C2="","",INDEX(MATERIAL_MASTER!$O:$O,MATCH($C2,MATERIAL_MASTER!$A:$A,0))) | H2: =IF($C2="","",INDEX(MATERIAL_MASTER!$P:$P,MATCH($C2,MATERIAL_MASTER!$A:$A,0))) | I2: =IF($C2="","",INDEX(MATERIAL_FACTOR_APPLICABILITY!$D:$D,MATCH($C2,MATERIAL_FACTOR_APPLICABILITY!$A:$A,0))) | J2: =IF($C2="","",INDEX(MATERIAL_FACTOR_APPLICABILITY!$E:$E,MATCH($C2,MATERIAL_FACTOR_APPLICABILITY!$A:$A,0))) | K2: =IF($C2="","",INDEX(MATERIAL_FACTOR_APPLICABILITY!$F:$F,MATCH($C2,MATERIAL_FACTOR_APPLICABILITY!$A:$A,0))) | L2: =IF($C2="","",INDEX(MATERIAL_FACTOR_APPLICABILITY!$G:$G,MATCH($C2,MATERIAL_FACTOR_APPLICABILITY!$A:$A,0))) | M2: =IF($C2="","",INDEX(MATERIAL_FACTOR_APPLICABILITY!$H:$H,MATCH($C2,MATERIAL_FACTOR_APPLICABILITY!$A:$A,0))) | N2: =IF($B2="","",ROUND(1+($I2*(SUMIFS(OBJECT_CONDITIONS!$W:$W,OBJECT_CONDITIONS!$A:$A,$B2)-1))+($J2*(SUMIFS(OBJECT_CONDITIONS!$J:$J,OBJECT_CONDITIONS!$A:$A,$B2)-1))+($K2*(SUMIFS(OBJECT_CONDITIONS!$L:$L,OBJECT_CONDITIONS!$A:$A,$B2)-1))+($L2*(SUMIFS(OBJECT_CONDITIONS!$N:$N,OBJECT_CONDITIONS!$A:$A,$B2)-1))+($M2*(SUMIFS(OBJECT_CONDITIONS!$R:$R,OBJECT_CONDITIONS!$A:$A,$B2)-1)),3)) | O2: 1 | P2: =IF(OR($H2="",$N2=""),"",ROUND($H2*$N2*IF($O2="",1,$O2),3)) | Q2: =IF(OR($E2="",$P2=""),"",ROUND($E2*$P2,3)) | R2: =IF($D2="","",IFERROR(INDEX(MATERIAL_VARIANTS!$O:$O,MATCH($D2,MATERIAL_VARIANTS!$A:$A,0)),"")) | S2: =IF($D2="","",IFERROR(INDEX(MATERIAL_VARIANTS!$P:$P,MATCH($D2,MATERIAL_VARIANTS!$A:$A,0)),"")) | T2: =IF(OR($Q2="",$S2="",$S2=0),"",ROUNDUP($Q2/$S2,0)) | U2: Геотекстиль на сложном участке
A3: MC-0002 | B3: OBJ-0001 | C3: MAT-0004 | D3: MV-0005 | E3: 240 | F3: м2 | G3: =IF($C3="","",INDEX(MATERIAL_MASTER!$O:$O,MATCH($C3,MATERIAL_MASTER!$A:$A,0))) | H3: =IF($C3="","",INDEX(MATERIAL_MASTER!$P:$P,MATCH($C3,MATERIAL_MASTER!$A:$A,0))) | I3: =IF($C3="","",INDEX(MATERIAL_FACTOR_APPLICABILITY!$D:$D,MATCH($C3,MATERIAL_FACTOR_APPLICABILITY!$A:$A,0))) | J3: =IF($C3="","",INDEX(MATERIAL_FACTOR_APPLICABILITY!$E:$E,MATCH($C3,MATERIAL_FACTOR_APPLICABILITY!$A:$A,0))) | K3: =IF($C3="","",INDEX(MATERIAL_FACTOR_APPLICABILITY!$F:$F,MATCH($C3,MATERIAL_FACTOR_APPLICABILITY!$A:$A,0))) | L3: =IF($C3="","",INDEX(MATERIAL_FACTOR_APPLICABILITY!$G:$G,MATCH($C3,MATERIAL_FACTOR_APPLICABILITY!$A:$A,0))) | M3: =IF($C3="","",INDEX(MATERIAL_FACTOR_APPLICABILITY!$H:$H,MATCH($C3,MATERIAL_FACTOR_APPLICABILITY!$A:$A,0))) | N3: =IF($B3="","",ROUND(1+($I3*(SUMIFS(OBJECT_CONDITIONS!$W:$W,OBJECT_CONDITIONS!$A:$A,$B3)-1))+($J3*(SUMIFS(OBJECT_CONDITIONS!$J:$J,OBJECT_CONDITIONS!$A:$A,$B3)-1))+($K3*(SUMIFS(OBJECT_CONDITIONS!$L:$L,OBJECT_CONDITIONS!$A:$A,$B3)-1))+($L3*(SUMIFS(OBJECT_CONDITIONS!$N:$N,OBJECT_CONDITIONS!$A:$A,$B3)-1))+($M3*(SUMIFS(OBJECT_CONDITIONS!$R:$R,OBJECT_CONDITIONS!$A:$A,$B3)-1)),3)) | O3: 1 | P3: =IF(OR($H3="",$N3=""),"",ROUND($H3*$N3*IF($O3="",1,$O3),3)) | Q3: =IF(OR($E3="",$P3=""),"",ROUND($E3*$P3,3)) | R3: =IF($D3="","",IFERROR(INDEX(MATERIAL_VARIANTS!$O:$O,MATCH($D3,MATERIAL_VARIANTS!$A:$A,0)),"")) | S3: =IF($D3="","",IFERROR(INDEX(MATERIAL_VARIANTS!$P:$P,MATCH($D3,MATERIAL_VARIANTS!$A:$A,0)),"")) | T3: =IF(OR($Q3="",$S3="",$S3=0),"",ROUNDUP($Q3/$S3,0)) | U3: Рулонный газон на сложном участке
A4: MC-0003 | B4: OBJ-0001 | C4: MAT-0001 | D4: MV-0002 | E4: 95 | F4: м2 | G4: =IF($C4="","",INDEX(MATERIAL_MASTER!$O:$O,MATCH($C4,MATERIAL_MASTER!$A:$A,0))) | H4: =IF($C4="","",INDEX(MATERIAL_MASTER!$P:$P,MATCH($C4,MATERIAL_MASTER!$A:$A,0))) | I4: =IF($C4="","",INDEX(MATERIAL_FACTOR_APPLICABILITY!$D:$D,MATCH($C4,MATERIAL_FACTOR_APPLICABILITY!$A:$A,0))) | J4: =IF($C4="","",INDEX(MATERIAL_FACTOR_APPLICABILITY!$E:$E,MATCH($C4,MATERIAL_FACTOR_APPLICABILITY!$A:$A,0))) | K4: =IF($C4="","",INDEX(MATERIAL_FACTOR_APPLICABILITY!$F:$F,MATCH($C4,MATERIAL_FACTOR_APPLICABILITY!$A:$A,0))) | L4: =IF($C4="","",INDEX(MATERIAL_FACTOR_APPLICABILITY!$G:$G,MATCH($C4,MATERIAL_FACTOR_APPLICABILITY!$A:$A,0))) | M4: =IF($C4="","",INDEX(MATERIAL_FACTOR_APPLICABILITY!$H:$H,MATCH($C4,MATERIAL_FACTOR_APPLICABILITY!$A:$A,0))) | N4: =IF($B4="","",ROUND(1+($I4*(SUMIFS(OBJECT_CONDITIONS!$W:$W,OBJECT_CONDITIONS!$A:$A,$B4)-1))+($J4*(SUMIFS(OBJECT_CONDITIONS!$J:$J,OBJECT_CONDITIONS!$A:$A,$B4)-1))+($K4*(SUMIFS(OBJECT_CONDITIONS!$L:$L,OBJECT_CONDITIONS!$A:$A,$B4)-1))+($L4*(SUMIFS(OBJECT_CONDITIONS!$N:$N,OBJECT_CONDITIONS!$A:$A,$B4)-1))+($M4*(SUMIFS(OBJECT_CONDITIONS!$R:$R,OBJECT_CONDITIONS!$A:$A,$B4)-1)),3)) | O4: 1 | P4: =IF(OR($H4="",$N4=""),"",ROUND($H4*$N4*IF($O4="",1,$O4),3)) | Q4: =IF(OR($E4="",$P4=""),"",ROUND($E4*$P4,3)) | R4: =IF($D4="","",IFERROR(INDEX(MATERIAL_VARIANTS!$O:$O,MATCH($D4,MATERIAL_VARIANTS!$A:$A,0)),"")) | S4: =IF($D4="","",IFERROR(INDEX(MATERIAL_VARIANTS!$P:$P,MATCH($D4,MATERIAL_VARIANTS!$A:$A,0)),"")) | T4: =IF(OR($Q4="",$S4="",$S4=0),"",ROUNDUP($Q4/$S4,0)) | U4: Брусчатка с подрезкой по контурам
A5: MC-0004 | B5: OBJ-0001 | C5: MAT-0007 | D5: MV-0008 | E5: 32 | F5: м3 | G5: =IF($C5="","",INDEX(MATERIAL_MASTER!$O:$O,MATCH($C5,MATERIAL_MASTER!$A:$A,0))) | H5: =IF($C5="","",INDEX(MATERIAL_MASTER!$P:$P,MATCH($C5,MATERIAL_MASTER!$A:$A,0))) | I5: =IF($C5="","",INDEX(MATERIAL_FACTOR_APPLICABILITY!$D:$D,MATCH($C5,MATERIAL_FACTOR_APPLICABILITY!$A:$A,0))) | J5: =IF($C5="","",INDEX(MATERIAL_FACTOR_APPLICABILITY!$E:$E,MATCH($C5,MATERIAL_FACTOR_APPLICABILITY!$A:$A,0))) | K5: =IF($C5="","",INDEX(MATERIAL_FACTOR_APPLICABILITY!$F:$F,MATCH($C5,MATERIAL_FACTOR_APPLICABILITY!$A:$A,0))) | L5: =IF($C5="","",INDEX(MATERIAL_FACTOR_APPLICABILITY!$G:$G,MATCH($C5,MATERIAL_FACTOR_APPLICABILITY!$A:$A,0))) | M5: =IF($C5="","",INDEX(MATERIAL_FACTOR_APPLICABILITY!$H:$H,MATCH($C5,MATERIAL_FACTOR_APPLICABILITY!$A:$A,0))) | N5: =IF($B5="","",ROUND(1+($I5*(SUMIFS(OBJECT_CONDITIONS!$W:$W,OBJECT_CONDITIONS!$A:$A,$B5)-1))+($J5*(SUMIFS(OBJECT_CONDITIONS!$J:$J,OBJECT_CONDITIONS!$A:$A,$B5)-1))+($K5*(SUMIFS(OBJECT_CONDITIONS!$L:$L,OBJECT_CONDITIONS!$A:$A,$B5)-1))+($L5*(SUMIFS(OBJECT_CONDITIONS!$N:$N,OBJECT_CONDITIONS!$A:$A,$B5)-1))+($M5*(SUMIFS(OBJECT_CONDITIONS!$R:$R,OBJECT_CONDITIONS!$A:$A,$B5)-1)),3)) | O5: 1 | P5: =IF(OR($H5="",$N5=""),"",ROUND($H5*$N5*IF($O5="",1,$O5),3)) | Q5: =IF(OR($E5="",$P5=""),"",ROUND($E5*$P5,3)) | R5: =IF($D5="","",IFERROR(INDEX(MATERIAL_VARIANTS!$O:$O,MATCH($D5,MATERIAL_VARIANTS!$A:$A,0)),"")) | S5: =IF($D5="","",IFERROR(INDEX(MATERIAL_VARIANTS!$P:$P,MATCH($D5,MATERIAL_VARIANTS!$A:$A,0)),"")) | T5: =IF(OR($Q5="",$S5="",$S5=0),"",ROUNDUP($Q5/$S5,0)) | U5: Щебень от проектного уплотненного объема
G6: =IF($C6="","",INDEX(MATERIAL_MASTER!$O:$O,MATCH($C6,MATERIAL_MASTER!$A:$A,0))) | H6: =IF($C6="","",INDEX(MATERIAL_MASTER!$P:$P,MATCH($C6,MATERIAL_MASTER!$A:$A,0))) | I6: =IF($C6="","",INDEX(MATERIAL_FACTOR_APPLICABILITY!$D:$D,MATCH($C6,MATERIAL_FACTOR_APPLICABILITY!$A:$A,0))) | J6: =IF($C6="","",INDEX(MATERIAL_FACTOR_APPLICABILITY!$E:$E,MATCH($C6,MATERIAL_FACTOR_APPLICABILITY!$A:$A,0))) | K6: =IF($C6="","",INDEX(MATERIAL_FACTOR_APPLICABILITY!$F:$F,MATCH($C6,MATERIAL_FACTOR_APPLICABILITY!$A:$A,0))) | L6: =IF($C6="","",INDEX(MATERIAL_FACTOR_APPLICABILITY!$G:$G,MATCH($C6,MATERIAL_FACTOR_APPLICABILITY!$A:$A,0))) | M6: =IF($C6="","",INDEX(MATERIAL_FACTOR_APPLICABILITY!$H:$H,MATCH($C6,MATERIAL_FACTOR_APPLICABILITY!$A:$A,0))) | N6: =IF($B6="","",ROUND(1+($I6*(SUMIFS(OBJECT_CONDITIONS!$W:$W,OBJECT_CONDITIONS!$A:$A,$B6)-1))+($J6*(SUMIFS(OBJECT_CONDITIONS!$J:$J,OBJECT_CONDITIONS!$A:$A,$B6)-1))+($K6*(SUMIFS(OBJECT_CONDITIONS!$L:$L,OBJECT_CONDITIONS!$A:$A,$B6)-1))+($L6*(SUMIFS(OBJECT_CONDITIONS!$N:$N,OBJECT_CONDITIONS!$A:$A,$B6)-1))+($M6*(SUMIFS(OBJECT_CONDITIONS!$R:$R,OBJECT_CONDITIONS!$A:$A,$B6)-1)),3)) | P6: =IF(OR($H6="",$N6=""),"",ROUND($H6*$N6*IF($O6="",1,$O6),3)) | Q6: =IF(OR($E6="",$P6=""),"",ROUND($E6*$P6,3)) | R6: =IF($D6="","",IFERROR(INDEX(MATERIAL_VARIANTS!$O:$O,MATCH($D6,MATERIAL_VARIANTS!$A:$A,0)),"")) | S6: =IF($D6="","",IFERROR(INDEX(MATERIAL_VARIANTS!$P:$P,MATCH($D6,MATERIAL_VARIANTS!$A:$A,0)),"")) | T6: =IF(OR($Q6="",$S6="",$S6=0),"",ROUNDUP($Q6/$S6,0))
G7: =IF($C7="","",INDEX(MATERIAL_MASTER!$O:$O,MATCH($C7,MATERIAL_MASTER!$A:$A,0))) | H7: =IF($C7="","",INDEX(MATERIAL_MASTER!$P:$P,MATCH($C7,MATERIAL_MASTER!$A:$A,0))) | I7: =IF($C7="","",INDEX(MATERIAL_FACTOR_APPLICABILITY!$D:$D,MATCH($C7,MATERIAL_FACTOR_APPLICABILITY!$A:$A,0))) | J7: =IF($C7="","",INDEX(MATERIAL_FACTOR_APPLICABILITY!$E:$E,MATCH($C7,MATERIAL_FACTOR_APPLICABILITY!$A:$A,0))) | K7: =IF($C7="","",INDEX(MATERIAL_FACTOR_APPLICABILITY!$F:$F,MATCH($C7,MATERIAL_FACTOR_APPLICABILITY!$A:$A,0))) | L7: =IF($C7="","",INDEX(MATERIAL_FACTOR_APPLICABILITY!$G:$G,MATCH($C7,MATERIAL_FACTOR_APPLICABILITY!$A:$A,0))) | M7: =IF($C7="","",INDEX(MATERIAL_FACTOR_APPLICABILITY!$H:$H,MATCH($C7,MATERIAL_FACTOR_APPLICABILITY!$A:$A,0))) | N7: =IF($B7="","",ROUND(1+($I7*(SUMIFS(OBJECT_CONDITIONS!$W:$W,OBJECT_CONDITIONS!$A:$A,$B7)-1))+($J7*(SUMIFS(OBJECT_CONDITIONS!$J:$J,OBJECT_CONDITIONS!$A:$A,$B7)-1))+($K7*(SUMIFS(OBJECT_CONDITIONS!$L:$L,OBJECT_CONDITIONS!$A:$A,$B7)-1))+($L7*(SUMIFS(OBJECT_CONDITIONS!$N:$N,OBJECT_CONDITIONS!$A:$A,$B7)-1))+($M7*(SUMIFS(OBJECT_CONDITIONS!$R:$R,OBJECT_CONDITIONS!$A:$A,$B7)-1)),3)) | P7: =IF(OR($H7="",$N7=""),"",ROUND($H7*$N7*IF($O7="",1,$O7),3)) | Q7: =IF(OR($E7="",$P7=""),"",ROUND($E7*$P7,3)) | R7: =IF($D7="","",IFERROR(INDEX(MATERIAL_VARIANTS!$O:$O,MATCH($D7,MATERIAL_VARIANTS!$A:$A,0)),"")) | S7: =IF($D7="","",IFERROR(INDEX(MATERIAL_VARIANTS!$P:$P,MATCH($D7,MATERIAL_VARIANTS!$A:$A,0)),"")) | T7: =IF(OR($Q7="",$S7="",$S7=0),"",ROUNDUP($Q7/$S7,0))
G8: =IF($C8="","",INDEX(MATERIAL_MASTER!$O:$O,MATCH($C8,MATERIAL_MASTER!$A:$A,0))) | H8: =IF($C8="","",INDEX(MATERIAL_MASTER!$P:$P,MATCH($C8,MATERIAL_MASTER!$A:$A,0))) | I8: =IF($C8="","",INDEX(MATERIAL_FACTOR_APPLICABILITY!$D:$D,MATCH($C8,MATERIAL_FACTOR_APPLICABILITY!$A:$A,0))) | J8: =IF($C8="","",INDEX(MATERIAL_FACTOR_APPLICABILITY!$E:$E,MATCH($C8,MATERIAL_FACTOR_APPLICABILITY!$A:$A,0))) | K8: =IF($C8="","",INDEX(MATERIAL_FACTOR_APPLICABILITY!$F:$F,MATCH($C8,MATERIAL_FACTOR_APPLICABILITY!$A:$A,0))) | L8: =IF($C8="","",INDEX(MATERIAL_FACTOR_APPLICABILITY!$G:$G,MATCH($C8,MATERIAL_FACTOR_APPLICABILITY!$A:$A,0))) | M8: =IF($C8="","",INDEX(MATERIAL_FACTOR_APPLICABILITY!$H:$H,MATCH($C8,MATERIAL_FACTOR_APPLICABILITY!$A:$A,0))) | N8: =IF($B8="","",ROUND(1+($I8*(SUMIFS(OBJECT_CONDITIONS!$W:$W,OBJECT_CONDITIONS!$A:$A,$B8)-1))+($J8*(SUMIFS(OBJECT_CONDITIONS!$J:$J,OBJECT_CONDITIONS!$A:$A,$B8)-1))+($K8*(SUMIFS(OBJECT_CONDITIONS!$L:$L,OBJECT_CONDITIONS!$A:$A,$B8)-1))+($L8*(SUMIFS(OBJECT_CONDITIONS!$N:$N,OBJECT_CONDITIONS!$A:$A,$B8)-1))+($M8*(SUMIFS(OBJECT_CONDITIONS!$R:$R,OBJECT_CONDITIONS!$A:$A,$B8)-1)),3)) | P8: =IF(OR($H8="",$N8=""),"",ROUND($H8*$N8*IF($O8="",1,$O8),3)) | Q8: =IF(OR($E8="",$P8=""),"",ROUND($E8*$P8,3)) | R8: =IF($D8="","",IFERROR(INDEX(MATERIAL_VARIANTS!$O:$O,MATCH($D8,MATERIAL_VARIANTS!$A:$A,0)),"")) | S8: =IF($D8="","",IFERROR(INDEX(MATERIAL_VARIANTS!$P:$P,MATCH($D8,MATERIAL_VARIANTS!$A:$A,0)),"")) | T8: =IF(OR($Q8="",$S8="",$S8=0),"",ROUNDUP($Q8/$S8,0))
G9: =IF($C9="","",INDEX(MATERIAL_MASTER!$O:$O,MATCH($C9,MATERIAL_MASTER!$A:$A,0))) | H9: =IF($C9="","",INDEX(MATERIAL_MASTER!$P:$P,MATCH($C9,MATERIAL_MASTER!$A:$A,0))) | I9: =IF($C9="","",INDEX(MATERIAL_FACTOR_APPLICABILITY!$D:$D,MATCH($C9,MATERIAL_FACTOR_APPLICABILITY!$A:$A,0))) | J9: =IF($C9="","",INDEX(MATERIAL_FACTOR_APPLICABILITY!$E:$E,MATCH($C9,MATERIAL_FACTOR_APPLICABILITY!$A:$A,0))) | K9: =IF($C9="","",INDEX(MATERIAL_FACTOR_APPLICABILITY!$F:$F,MATCH($C9,MATERIAL_FACTOR_APPLICABILITY!$A:$A,0))) | L9: =IF($C9="","",INDEX(MATERIAL_FACTOR_APPLICABILITY!$G:$G,MATCH($C9,MATERIAL_FACTOR_APPLICABILITY!$A:$A,0))) | M9: =IF($C9="","",INDEX(MATERIAL_FACTOR_APPLICABILITY!$H:$H,MATCH($C9,MATERIAL_FACTOR_APPLICABILITY!$A:$A,0))) | N9: =IF($B9="","",ROUND(1+($I9*(SUMIFS(OBJECT_CONDITIONS!$W:$W,OBJECT_CONDITIONS!$A:$A,$B9)-1))+($J9*(SUMIFS(OBJECT_CONDITIONS!$J:$J,OBJECT_CONDITIONS!$A:$A,$B9)-1))+($K9*(SUMIFS(OBJECT_CONDITIONS!$L:$L,OBJECT_CONDITIONS!$A:$A,$B9)-1))+($L9*(SUMIFS(OBJECT_CONDITIONS!$N:$N,OBJECT_CONDITIONS!$A:$A,$B9)-1))+($M9*(SUMIFS(OBJECT_CONDITIONS!$R:$R,OBJECT_CONDITIONS!$A:$A,$B9)-1)),3)) | P9: =IF(OR($H9="",$N9=""),"",ROUND($H9*$N9*IF($O9="",1,$O9),3)) | Q9: =IF(OR($E9="",$P9=""),"",ROUND($E9*$P9,3)) | R9: =IF($D9="","",IFERROR(INDEX(MATERIAL_VARIANTS!$O:$O,MATCH($D9,MATERIAL_VARIANTS!$A:$A,0)),"")) | S9: =IF($D9="","",IFERROR(INDEX(MATERIAL_VARIANTS!$P:$P,MATCH($D9,MATERIAL_VARIANTS!$A:$A,0)),"")) | T9: =IF(OR($Q9="",$S9="",$S9=0),"",ROUNDUP($Q9/$S9,0))
G10: =IF($C10="","",INDEX(MATERIAL_MASTER!$O:$O,MATCH($C10,MATERIAL_MASTER!$A:$A,0))) | H10: =IF($C10="","",INDEX(MATERIAL_MASTER!$P:$P,MATCH($C10,MATERIAL_MASTER!$A:$A,0))) | I10: =IF($C10="","",INDEX(MATERIAL_FACTOR_APPLICABILITY!$D:$D,MATCH($C10,MATERIAL_FACTOR_APPLICABILITY!$A:$A,0))) | J10: =IF($C10="","",INDEX(MATERIAL_FACTOR_APPLICABILITY!$E:$E,MATCH($C10,MATERIAL_FACTOR_APPLICABILITY!$A:$A,0))) | K10: =IF($C10="","",INDEX(MATERIAL_FACTOR_APPLICABILITY!$F:$F,MATCH($C10,MATERIAL_FACTOR_APPLICABILITY!$A:$A,0))) | L10: =IF($C10="","",INDEX(MATERIAL_FACTOR_APPLICABILITY!$G:$G,MATCH($C10,MATERIAL_FACTOR_APPLICABILITY!$A:$A,0))) | M10: =IF($C10="","",INDEX(MATERIAL_FACTOR_APPLICABILITY!$H:$H,MATCH($C10,MATERIAL_FACTOR_APPLICABILITY!$A:$A,0))) | N10: =IF($B10="","",ROUND(1+($I10*(SUMIFS(OBJECT_CONDITIONS!$W:$W,OBJECT_CONDITIONS!$A:$A,$B10)-1))+($J10*(SUMIFS(OBJECT_CONDITIONS!$J:$J,OBJECT_CONDITIONS!$A:$A,$B10)-1))+($K10*(SUMIFS(OBJECT_CONDITIONS!$L:$L,OBJECT_CONDITIONS!$A:$A,$B10)-1))+($L10*(SUMIFS(OBJECT_CONDITIONS!$N:$N,OBJECT_CONDITIONS!$A:$A,$B10)-1))+($M10*(SUMIFS(OBJECT_CONDITIONS!$R:$R,OBJECT_CONDITIONS!$A:$A,$B10)-1)),3)) | P10: =IF(OR($H10="",$N10=""),"",ROUND($H10*$N10*IF($O10="",1,$O10),3)) | Q10: =IF(OR($E10="",$P10=""),"",ROUND($E10*$P10,3)) | R10: =IF($D10="","",IFERROR(INDEX(MATERIAL_VARIANTS!$O:$O,MATCH($D10,MATERIAL_VARIANTS!$A:$A,0)),"")) | S10: =IF($D10="","",IFERROR(INDEX(MATERIAL_VARIANTS!$P:$P,MATCH($D10,MATERIAL_VARIANTS!$A:$A,0)),"")) | T10: =IF(OR($Q10="",$S10="",$S10=0),"",ROUNDUP($Q10/$S10,0))
G11: =IF($C11="","",INDEX(MATERIAL_MASTER!$O:$O,MATCH($C11,MATERIAL_MASTER!$A:$A,0))) | H11: =IF($C11="","",INDEX(MATERIAL_MASTER!$P:$P,MATCH($C11,MATERIAL_MASTER!$A:$A,0))) | I11: =IF($C11="","",INDEX(MATERIAL_FACTOR_APPLICABILITY!$D:$D,MATCH($C11,MATERIAL_FACTOR_APPLICABILITY!$A:$A,0))) | J11: =IF($C11="","",INDEX(MATERIAL_FACTOR_APPLICABILITY!$E:$E,MATCH($C11,MATERIAL_FACTOR_APPLICABILITY!$A:$A,0))) | K11: =IF($C11="","",INDEX(MATERIAL_FACTOR_APPLICABILITY!$F:$F,MATCH($C11,MATERIAL_FACTOR_APPLICABILITY!$A:$A,0))) | L11: =IF($C11="","",INDEX(MATERIAL_FACTOR_APPLICABILITY!$G:$G,MATCH($C11,MATERIAL_FACTOR_APPLICABILITY!$A:$A,0))) | M11: =IF($C11="","",INDEX(MATERIAL_FACTOR_APPLICABILITY!$H:$H,MATCH($C11,MATERIAL_FACTOR_APPLICABILITY!$A:$A,0))) | N11: =IF($B11="","",ROUND(1+($I11*(SUMIFS(OBJECT_CONDITIONS!$W:$W,OBJECT_CONDITIONS!$A:$A,$B11)-1))+($J11*(SUMIFS(OBJECT_CONDITIONS!$J:$J,OBJECT_CONDITIONS!$A:$A,$B11)-1))+($K11*(SUMIFS(OBJECT_CONDITIONS!$L:$L,OBJECT_CONDITIONS!$A:$A,$B11)-1))+($L11*(SUMIFS(OBJECT_CONDITIONS!$N:$N,OBJECT_CONDITIONS!$A:$A,$B11)-1))+($M11*(SUMIFS(OBJECT_CONDITIONS!$R:$R,OBJECT_CONDITIONS!$A:$A,$B11)-1)),3)) | P11: =IF(OR($H11="",$N11=""),"",ROUND($H11*$N11*IF($O11="",1,$O11),3)) | Q11: =IF(OR($E11="",$P11=""),"",ROUND($E11*$P11,3)) | R11: =IF($D11="","",IFERROR(INDEX(MATERIAL_VARIANTS!$O:$O,MATCH($D11,MATERIAL_VARIANTS!$A:$A,0)),"")) | S11: =IF($D11="","",IFERROR(INDEX(MATERIAL_VARIANTS!$P:$P,MATCH($D11,MATERIAL_VARIANTS!$A:$A,0)),"")) | T11: =IF(OR($Q11="",$S11="",$S11=0),"",ROUNDUP($Q11/$S11,0))
G12: =IF($C12="","",INDEX(MATERIAL_MASTER!$O:$O,MATCH($C12,MATERIAL_MASTER!$A:$A,0))) | H12: =IF($C12="","",INDEX(MATERIAL_MASTER!$P:$P,MATCH($C12,MATERIAL_MASTER!$A:$A,0))) | I12: =IF($C12="","",INDEX(MATERIAL_FACTOR_APPLICABILITY!$D:$D,MATCH($C12,MATERIAL_FACTOR_APPLICABILITY!$A:$A,0))) | J12: =IF($C12="","",INDEX(MATERIAL_FACTOR_APPLICABILITY!$E:$E,MATCH($C12,MATERIAL_FACTOR_APPLICABILITY!$A:$A,0))) | K12: =IF($C12="","",INDEX(MATERIAL_FACTOR_APPLICABILITY!$F:$F,MATCH($C12,MATERIAL_FACTOR_APPLICABILITY!$A:$A,0))) | L12: =IF($C12="","",INDEX(MATERIAL_FACTOR_APPLICABILITY!$G:$G,MATCH($C12,MATERIAL_FACTOR_APPLICABILITY!$A:$A,0))) | M12: =IF($C12="","",INDEX(MATERIAL_FACTOR_APPLICABILITY!$H:$H,MATCH($C12,MATERIAL_FACTOR_APPLICABILITY!$A:$A,0))) | N12: =IF($B12="","",ROUND(1+($I12*(SUMIFS(OBJECT_CONDITIONS!$W:$W,OBJECT_CONDITIONS!$A:$A,$B12)-1))+($J12*(SUMIFS(OBJECT_CONDITIONS!$J:$J,OBJECT_CONDITIONS!$A:$A,$B12)-1))+($K12*(SUMIFS(OBJECT_CONDITIONS!$L:$L,OBJECT_CONDITIONS!$A:$A,$B12)-1))+($L12*(SUMIFS(OBJECT_CONDITIONS!$N:$N,OBJECT_CONDITIONS!$A:$A,$B12)-1))+($M12*(SUMIFS(OBJECT_CONDITIONS!$R:$R,OBJECT_CONDITIONS!$A:$A,$B12)-1)),3)) | P12: =IF(OR($H12="",$N12=""),"",ROUND($H12*$N12*IF($O12="",1,$O12),3)) | Q12: =IF(OR($E12="",$P12=""),"",ROUND($E12*$P12,3)) | R12: =IF($D12="","",IFERROR(INDEX(MATERIAL_VARIANTS!$O:$O,MATCH($D12,MATERIAL_VARIANTS!$A:$A,0)),"")) | S12: =IF($D12="","",IFERROR(INDEX(MATERIAL_VARIANTS!$P:$P,MATCH($D12,MATERIAL_VARIANTS!$A:$A,0)),"")) | T12: =IF(OR($Q12="",$S12="",$S12=0),"",ROUNDUP($Q12/$S12,0))
G13: =IF($C13="","",INDEX(MATERIAL_MASTER!$O:$O,MATCH($C13,MATERIAL_MASTER!$A:$A,0))) | H13: =IF($C13="","",INDEX(MATERIAL_MASTER!$P:$P,MATCH($C13,MATERIAL_MASTER!$A:$A,0))) | I13: =IF($C13="","",INDEX(MATERIAL_FACTOR_APPLICABILITY!$D:$D,MATCH($C13,MATERIAL_FACTOR_APPLICABILITY!$A:$A,0))) | J13: =IF($C13="","",INDEX(MATERIAL_FACTOR_APPLICABILITY!$E:$E,MATCH($C13,MATERIAL_FACTOR_APPLICABILITY!$A:$A,0))) | K13: =IF($C13="","",INDEX(MATERIAL_FACTOR_APPLICABILITY!$F:$F,MATCH($C13,MATERIAL_FACTOR_APPLICABILITY!$A:$A,0))) | L13: =IF($C13="","",INDEX(MATERIAL_FACTOR_APPLICABILITY!$G:$G,MATCH($C13,MATERIAL_FACTOR_APPLICABILITY!$A:$A,0))) | M13: =IF($C13="","",INDEX(MATERIAL_FACTOR_APPLICABILITY!$H:$H,MATCH($C13,MATERIAL_FACTOR_APPLICABILITY!$A:$A,0))) | N13: =IF($B13="","",ROUND(1+($I13*(SUMIFS(OBJECT_CONDITIONS!$W:$W,OBJECT_CONDITIONS!$A:$A,$B13)-1))+($J13*(SUMIFS(OBJECT_CONDITIONS!$J:$J,OBJECT_CONDITIONS!$A:$A,$B13)-1))+($K13*(SUMIFS(OBJECT_CONDITIONS!$L:$L,OBJECT_CONDITIONS!$A:$A,$B13)-1))+($L13*(SUMIFS(OBJECT_CONDITIONS!$N:$N,OBJECT_CONDITIONS!$A:$A,$B13)-1))+($M13*(SUMIFS(OBJECT_CONDITIONS!$R:$R,OBJECT_CONDITIONS!$A:$A,$B13)-1)),3)) | P13: =IF(OR($H13="",$N13=""),"",ROUND($H13*$N13*IF($O13="",1,$O13),3)) | Q13: =IF(OR($E13="",$P13=""),"",ROUND($E13*$P13,3)) | R13: =IF($D13="","",IFERROR(INDEX(MATERIAL_VARIANTS!$O:$O,MATCH($D13,MATERIAL_VARIANTS!$A:$A,0)),"")) | S13: =IF($D13="","",IFERROR(INDEX(MATERIAL_VARIANTS!$P:$P,MATCH($D13,MATERIAL_VARIANTS!$A:$A,0)),"")) | T13: =IF(OR($Q13="",$S13="",$S13=0),"",ROUNDUP($Q13/$S13,0))
G14: =IF($C14="","",INDEX(MATERIAL_MASTER!$O:$O,MATCH($C14,MATERIAL_MASTER!$A:$A,0))) | H14: =IF($C14="","",INDEX(MATERIAL_MASTER!$P:$P,MATCH($C14,MATERIAL_MASTER!$A:$A,0))) | I14: =IF($C14="","",INDEX(MATERIAL_FACTOR_APPLICABILITY!$D:$D,MATCH($C14,MATERIAL_FACTOR_APPLICABILITY!$A:$A,0))) | J14: =IF($C14="","",INDEX(MATERIAL_FACTOR_APPLICABILITY!$E:$E,MATCH($C14,MATERIAL_FACTOR_APPLICABILITY!$A:$A,0))) | K14: =IF($C14="","",INDEX(MATERIAL_FACTOR_APPLICABILITY!$F:$F,MATCH($C14,MATERIAL_FACTOR_APPLICABILITY!$A:$A,0))) | L14: =IF($C14="","",INDEX(MATERIAL_FACTOR_APPLICABILITY!$G:$G,MATCH($C14,MATERIAL_FACTOR_APPLICABILITY!$A:$A,0))) | M14: =IF($C14="","",INDEX(MATERIAL_FACTOR_APPLICABILITY!$H:$H,MATCH($C14,MATERIAL_FACTOR_APPLICABILITY!$A:$A,0))) | N14: =IF($B14="","",ROUND(1+($I14*(SUMIFS(OBJECT_CONDITIONS!$W:$W,OBJECT_CONDITIONS!$A:$A,$B14)-1))+($J14*(SUMIFS(OBJECT_CONDITIONS!$J:$J,OBJECT_CONDITIONS!$A:$A,$B14)-1))+($K14*(SUMIFS(OBJECT_CONDITIONS!$L:$L,OBJECT_CONDITIONS!$A:$A,$B14)-1))+($L14*(SUMIFS(OBJECT_CONDITIONS!$N:$N,OBJECT_CONDITIONS!$A:$A,$B14)-1))+($M14*(SUMIFS(OBJECT_CONDITIONS!$R:$R,OBJECT_CONDITIONS!$A:$A,$B14)-1)),3)) | P14: =IF(OR($H14="",$N14=""),"",ROUND($H14*$N14*IF($O14="",1,$O14),3)) | Q14: =IF(OR($E14="",$P14=""),"",ROUND($E14*$P14,3)) | R14: =IF($D14="","",IFERROR(INDEX(MATERIAL_VARIANTS!$O:$O,MATCH($D14,MATERIAL_VARIANTS!$A:$A,0)),"")) | S14: =IF($D14="","",IFERROR(INDEX(MATERIAL_VARIANTS!$P:$P,MATCH($D14,MATERIAL_VARIANTS!$A:$A,0)),"")) | T14: =IF(OR($Q14="",$S14="",$S14=0),"",ROUNDUP($Q14/$S14,0))
G15: =IF($C15="","",INDEX(MATERIAL_MASTER!$O:$O,MATCH($C15,MATERIAL_MASTER!$A:$A,0))) | H15: =IF($C15="","",INDEX(MATERIAL_MASTER!$P:$P,MATCH($C15,MATERIAL_MASTER!$A:$A,0))) | I15: =IF($C15="","",INDEX(MATERIAL_FACTOR_APPLICABILITY!$D:$D,MATCH($C15,MATERIAL_FACTOR_APPLICABILITY!$A:$A,0))) | J15: =IF($C15="","",INDEX(MATERIAL_FACTOR_APPLICABILITY!$E:$E,MATCH($C15,MATERIAL_FACTOR_APPLICABILITY!$A:$A,0))) | K15: =IF($C15="","",INDEX(MATERIAL_FACTOR_APPLICABILITY!$F:$F,MATCH($C15,MATERIAL_FACTOR_APPLICABILITY!$A:$A,0))) | L15: =IF($C15="","",INDEX(MATERIAL_FACTOR_APPLICABILITY!$G:$G,MATCH($C15,MATERIAL_FACTOR_APPLICABILITY!$A:$A,0))) | M15: =IF($C15="","",INDEX(MATERIAL_FACTOR_APPLICABILITY!$H:$H,MATCH($C15,MATERIAL_FACTOR_APPLICABILITY!$A:$A,0))) | N15: =IF($B15="","",ROUND(1+($I15*(SUMIFS(OBJECT_CONDITIONS!$W:$W,OBJECT_CONDITIONS!$A:$A,$B15)-1))+($J15*(SUMIFS(OBJECT_CONDITIONS!$J:$J,OBJECT_CONDITIONS!$A:$A,$B15)-1))+($K15*(SUMIFS(OBJECT_CONDITIONS!$L:$L,OBJECT_CONDITIONS!$A:$A,$B15)-1))+($L15*(SUMIFS(OBJECT_CONDITIONS!$N:$N,OBJECT_CONDITIONS!$A:$A,$B15)-1))+($M15*(SUMIFS(OBJECT_CONDITIONS!$R:$R,OBJECT_CONDITIONS!$A:$A,$B15)-1)),3)) | P15: =IF(OR($H15="",$N15=""),"",ROUND($H15*$N15*IF($O15="",1,$O15),3)) | Q15: =IF(OR($E15="",$P15=""),"",ROUND($E15*$P15,3)) | R15: =IF($D15="","",IFERROR(INDEX(MATERIAL_VARIANTS!$O:$O,MATCH($D15,MATERIAL_VARIANTS!$A:$A,0)),"")) | S15: =IF($D15="","",IFERROR(INDEX(MATERIAL_VARIANTS!$P:$P,MATCH($D15,MATERIAL_VARIANTS!$A:$A,0)),"")) | T15: =IF(OR($Q15="",$S15="",$S15=0),"",ROUNDUP($Q15/$S15,0))
G16: =IF($C16="","",INDEX(MATERIAL_MASTER!$O:$O,MATCH($C16,MATERIAL_MASTER!$A:$A,0))) | H16: =IF($C16="","",INDEX(MATERIAL_MASTER!$P:$P,MATCH($C16,MATERIAL_MASTER!$A:$A,0))) | I16: =IF($C16="","",INDEX(MATERIAL_FACTOR_APPLICABILITY!$D:$D,MATCH($C16,MATERIAL_FACTOR_APPLICABILITY!$A:$A,0))) | J16: =IF($C16="","",INDEX(MATERIAL_FACTOR_APPLICABILITY!$E:$E,MATCH($C16,MATERIAL_FACTOR_APPLICABILITY!$A:$A,0))) | K16: =IF($C16="","",INDEX(MATERIAL_FACTOR_APPLICABILITY!$F:$F,MATCH($C16,MATERIAL_FACTOR_APPLICABILITY!$A:$A,0))) | L16: =IF($C16="","",INDEX(MATERIAL_FACTOR_APPLICABILITY!$G:$G,MATCH($C16,MATERIAL_FACTOR_APPLICABILITY!$A:$A,0))) | M16: =IF($C16="","",INDEX(MATERIAL_FACTOR_APPLICABILITY!$H:$H,MATCH($C16,MATERIAL_FACTOR_APPLICABILITY!$A:$A,0))) | N16: =IF($B16="","",ROUND(1+($I16*(SUMIFS(OBJECT_CONDITIONS!$W:$W,OBJECT_CONDITIONS!$A:$A,$B16)-1))+($J16*(SUMIFS(OBJECT_CONDITIONS!$J:$J,OBJECT_CONDITIONS!$A:$A,$B16)-1))+($K16*(SUMIFS(OBJECT_CONDITIONS!$L:$L,OBJECT_CONDITIONS!$A:$A,$B16)-1))+($L16*(SUMIFS(OBJECT_CONDITIONS!$N:$N,OBJECT_CONDITIONS!$A:$A,$B16)-1))+($M16*(SUMIFS(OBJECT_CONDITIONS!$R:$R,OBJECT_CONDITIONS!$A:$A,$B16)-1)),3)) | P16: =IF(OR($H16="",$N16=""),"",ROUND($H16*$N16*IF($O16="",1,$O16),3)) | Q16: =IF(OR($E16="",$P16=""),"",ROUND($E16*$P16,3)) | R16: =IF($D16="","",IFERROR(INDEX(MATERIAL_VARIANTS!$O:$O,MATCH($D16,MATERIAL_VARIANTS!$A:$A,0)),"")) | S16: =IF($D16="","",IFERROR(INDEX(MATERIAL_VARIANTS!$P:$P,MATCH($D16,MATERIAL_VARIANTS!$A:$A,0)),"")) | T16: =IF(OR($Q16="",$S16="",$S16=0),"",ROUNDUP($Q16/$S16,0))
G17: =IF($C17="","",INDEX(MATERIAL_MASTER!$O:$O,MATCH($C17,MATERIAL_MASTER!$A:$A,0))) | H17: =IF($C17="","",INDEX(MATERIAL_MASTER!$P:$P,MATCH($C17,MATERIAL_MASTER!$A:$A,0))) | I17: =IF($C17="","",INDEX(MATERIAL_FACTOR_APPLICABILITY!$D:$D,MATCH($C17,MATERIAL_FACTOR_APPLICABILITY!$A:$A,0))) | J17: =IF($C17="","",INDEX(MATERIAL_FACTOR_APPLICABILITY!$E:$E,MATCH($C17,MATERIAL_FACTOR_APPLICABILITY!$A:$A,0))) | K17: =IF($C17="","",INDEX(MATERIAL_FACTOR_APPLICABILITY!$F:$F,MATCH($C17,MATERIAL_FACTOR_APPLICABILITY!$A:$A,0))) | L17: =IF($C17="","",INDEX(MATERIAL_FACTOR_APPLICABILITY!$G:$G,MATCH($C17,MATERIAL_FACTOR_APPLICABILITY!$A:$A,0))) | M17: =IF($C17="","",INDEX(MATERIAL_FACTOR_APPLICABILITY!$H:$H,MATCH($C17,MATERIAL_FACTOR_APPLICABILITY!$A:$A,0))) | N17: =IF($B17="","",ROUND(1+($I17*(SUMIFS(OBJECT_CONDITIONS!$W:$W,OBJECT_CONDITIONS!$A:$A,$B17)-1))+($J17*(SUMIFS(OBJECT_CONDITIONS!$J:$J,OBJECT_CONDITIONS!$A:$A,$B17)-1))+($K17*(SUMIFS(OBJECT_CONDITIONS!$L:$L,OBJECT_CONDITIONS!$A:$A,$B17)-1))+($L17*(SUMIFS(OBJECT_CONDITIONS!$N:$N,OBJECT_CONDITIONS!$A:$A,$B17)-1))+($M17*(SUMIFS(OBJECT_CONDITIONS!$R:$R,OBJECT_CONDITIONS!$A:$A,$B17)-1)),3)) | P17: =IF(OR($H17="",$N17=""),"",ROUND($H17*$N17*IF($O17="",1,$O17),3)) | Q17: =IF(OR($E17="",$P17=""),"",ROUND($E17*$P17,3)) | R17: =IF($D17="","",IFERROR(INDEX(MATERIAL_VARIANTS!$O:$O,MATCH($D17,MATERIAL_VARIANTS!$A:$A,0)),"")) | S17: =IF($D17="","",IFERROR(INDEX(MATERIAL_VARIANTS!$P:$P,MATCH($D17,MATERIAL_VARIANTS!$A:$A,0)),"")) | T17: =IF(OR($Q17="",$S17="",$S17=0),"",ROUNDUP($Q17/$S17,0))
... G150: =IF($C150="","",INDEX(MATERIAL_MASTER!$O:$O,MATCH($C150,MATERIAL_MASTER!$A:$A,0))) | H150: =IF($C150="","",INDEX(MATERIAL_MASTER!$P:$P,MATCH($C150,MATERIAL_MASTER!$A:$A,0))) | I150: =IF($C150="","",INDEX(MATERIAL_FACTOR_APPLICABILITY!$D:$D,MATCH($C150,MATERIAL_FACTOR_APPLICABILITY!$A:$A,0))) | J150: =IF($C150="","",INDEX(MATERIAL_FACTOR_APPLICABILITY!$E:$E,MATCH($C150,MATERIAL_FACTOR_APPLICABILITY!$A:$A,0))) | K150: =IF($C150="","",INDEX(MATERIAL_FACTOR_APPLICABILITY!$F:$F,MATCH($C150,MATERIAL_FACTOR_APPLICABILITY!$A:$A,0))) | L150: =IF($C150="","",INDEX(MATERIAL_FACTOR_APPLICABILITY!$G:$G,MATCH($C150,MATERIAL_FACTOR_APPLICABILITY!$A:$A,0))) | M150: =IF($C150="","",INDEX(MATERIAL_FACTOR_APPLICABILITY!$H:$H,MATCH($C150,MATERIAL_FACTOR_APPLICABILITY!$A:$A,0))) | N150: =IF($B150="","",ROUND(1+($I150*(SUMIFS(OBJECT_CONDITIONS!$W:$W,OBJECT_CONDITIONS!$A:$A,$B150)-1))+($J150*(SUMIFS(OBJECT_CONDITIONS!$J:$J,OBJECT_CONDITIONS!$A:$A,$B150)-1))+($K150*(SUMIFS(OBJECT_CONDITIONS!$L:$L,OBJECT_CONDITIONS!$A:$A,$B150)-1))+($L150*(SUMIFS(OBJECT_CONDITIONS!$N:$N,OBJECT_CONDITIONS!$A:$A,$B150)-1))+($M150*(SUMIFS(OBJECT_CONDITIONS!$R:$R,OBJECT_CONDITIONS!$A:$A,$B150)-1)),3)) | P150: =IF(OR($H150="",$N150=""),"",ROUND($H150*$N150*IF($O150="",1,$O150),3)) | Q150: =IF(OR($E150="",$P150=""),"",ROUND($E150*$P150,3)) | R150: =IF($D150="","",IFERROR(INDEX(MATERIAL_VARIANTS!$O:$O,MATCH($D150,MATERIAL_VARIANTS!$A:$A,0)),"")) | S150: =IF($D150="","",IFERROR(INDEX(MATERIAL_VARIANTS!$P:$P,MATCH($D150,MATERIAL_VARIANTS!$A:$A,0)),"")) | T150: =IF(OR($Q150="",$S150="",$S150=0),"",ROUNDUP($Q150/$S150,0))

Sheet TARIFF_PROFILES
A1: Tariff | B1: ClientLabel | C1: Description | D1: WorkSellCoeff | E1: MaterialSellCoeff | F1: LogisticsSellCoeff | G1: OverheadCoeff | H1: ReserveBiasCoeff | I1: PreferredQualityIntent | J1: DefaultDisplayMode | K1: Notes
A2: Эконом | B2: Эконом | C2: Минимально достаточная комплектация без излишеств; упор на цену и укрупнение показа | D2: 1 | E2: 0.95 | F2: 1 | G2: 1 | H2: 0.99 | I2: Эконом | J2: Свернуть в раздел | K2: Не считать это автоматической скидкой на всё подряд; состав и замены задаются в правилах
A3: Стандарт | B3: Стандарт | C3: Базовый рекомендуемый уровень для большинства частных объектов | D3: 1 | E3: 1 | F3: 1 | G3: 1 | H3: 1 | I3: Стандарт | J3: Показать строкой | K3: Отправная точка модели
A4: Премиум | B4: Премиум | C4: Улучшенные материалы, больше прозрачности в КП, выше допуски по запасам и качеству | D4: 1.08 | E4: 1.12 | F4: 1.03 | G4: 1 | H4: 1.02 | I4: Премиум | J4: Показать строкой | K4: Премиум меняет не только цену, но и набор/качество материалов

Sheet COMMERCIAL_POLICY
A1: Tariff | B1: MinQuoteValueExVAT | C1: MinCrewDayChargeExVAT | D1: MobilizationChargeExVAT | E1: SiteVisitChargeExVAT | F1: SmallJobFloorCoeff | G1: DefaultDiscountCap | H1: PriceValidityDays | I1: DefaultWarrantyMonths | J1: DefaultPaymentTerms | K1: ApprovalLevel | L1: Notes
A2: Эконом | B2: 150000 | C2: 30000 | D2: 12000 | E2: 8000 | F2: 1.05 | G2: 0.03 | H2: 7 | I2: 6 | J2: 70% аванс / 30% по факту | K2: Менеджер | L2: Сильнее укрупнять и следить за floor для малых объектов
A3: Стандарт | B3: 250000 | C3: 40000 | D3: 15000 | E3: 10000 | F3: 1 | G3: 0.05 | H3: 10 | I3: 12 | J3: 50% аванс / 40% по этапу / 10% закрытие | K3: Прораб | L3: Базовая коммерческая политика
A4: Премиум | B4: 400000 | C4: 55000 | D4: 18000 | E4: 12000 | F4: 1 | G4: 0.07 | H4: 14 | I4: 24 | J4: 50% аванс / 50% по этапам | K4: Финдир | L4: Больше точности, качества и гарантий

Sheet WORK_TARIFF_RULES
A1: WorkID | B1: CanonicalWork | C1: Tariff | D1: IsIncluded | E1: PreferredExecutionMethod | F1: WorkSellCoeffOverride | G1: CommercialNameOverride | H1: DisplayModeOverride | I1: BundleMode | J1: Notes
A2: WORK-0001 | B2: Выборка ложа | C2: Эконом | D2: Да | E2: Механизированный | G2: Подготовка ложа | H2: Свернуть в раздел | I2: Минимум | J2: Для эконома чаще укрупнять и предпочитать механизацию при доступе
A3: WORK-0001 | B3: Выборка ложа | C3: Стандарт | D3: Да | E3: Стандарт | G3: Подготовка ложа | H3: Показать строкой | I3: База
A4: WORK-0001 | B4: Выборка ложа | C4: Премиум | D4: Да | E4: Ручной | F4: 1.08 | G4: Точная подготовка ложа | H4: Показать строкой | I4: Детально | J4: Ручная доработка и более деликатное исполнение при сложной геометрии
A5: WORK-0002 | B5: Устройство газонного ложа | C5: Эконом | D5: Да | E5: Стандарт | G5: Устройство газонного основания | H5: Свернуть в раздел | I5: Минимум
A6: WORK-0002 | B6: Устройство газонного ложа | C6: Стандарт | D6: Да | E6: Стандарт | G6: Устройство газонного основания | H6: Показать строкой | I6: База
A7: WORK-0002 | B7: Устройство газонного ложа | C7: Премиум | D7: Да | E7: Ручной | F7: 1.10 | G7: Подготовка премиального газонного основания | H7: Показать строкой | I7: Детально
A8: WORK-0004 | B8: Монтаж бордюра бетонного | C8: Эконом | D8: Да | E8: Стандарт | G8: Монтаж бордюра | H8: Свернуть в раздел | I8: Минимум
A9: WORK-0004 | B9: Монтаж бордюра бетонного | C9: Стандарт | D9: Да | E9: Стандарт | G9: Монтаж бордюра | H9: Показать строкой | I9: База
A10: WORK-0004 | B10: Монтаж бордюра бетонного | C10: Премиум | D10: Да | E10: Стандарт | F10: 1.05 | G10: Точный монтаж бордюра | H10: Показать строкой | I10: Детально | J10: Более аккуратная геометрия и контроль

Sheet MATERIAL_TARIFF_RULES
A1: MaterialID | B1: CanonicalMaterial | C1: Tariff | D1: PreferredVariantID | E1: MaterialSellCoeffOverride | F1: ReserveBiasOverride | G1: ClientNameOverride | H1: DisplayModeOverride | I1: QualityIntent | J1: Notes
A2: MAT-0001 | B2: Брусчатка бетонная 200x100 | C2: Эконом | D2: MV-0001 | F2: 0.98 | G2: Брусчатка бетонная 200x100x40 мм | H2: Показать строкой | I2: Эконом | J2: Пешеходный вариант
A3: MAT-0001 | B3: Брусчатка бетонная 200x100 | C3: Стандарт | D3: MV-0002 | F3: 1.00 | G3: Брусчатка бетонная 200x100x60 мм | H3: Показать строкой | I3: Стандарт | J3: Базовый частный участок
A4: MAT-0001 | B4: Брусчатка бетонная 200x100 | C4: Премиум | D4: MV-0003 | E4: 1.08 | F4: 1.02 | G4: Брусчатка бетонная 200x100x80 мм | H4: Показать строкой | I4: Премиум | J4: Если по задаче уместно усиленное решение
A5: MAT-0004 | B5: Газон рулонный стандарт | C5: Эконом | D5: MV-0005 | E5: 0.97 | F5: 0.99 | G5: Газон рулонный стандарт | H5: Показать строкой | I5: Эконом | J5: Без премиальной селекции
A6: MAT-0004 | B6: Газон рулонный стандарт | C6: Стандарт | D6: MV-0005 | F6: 1.00 | G6: Газон рулонный стандарт | H6: Показать строкой | I6: Стандарт
A7: MAT-0004 | B7: Газон рулонный стандарт | C7: Премиум | D7: MV-0005 | E7: 1.08 | F7: 1.02 | G7: Газон рулонный премиального отбора | H7: Показать строкой | I7: Премиум | J7: Нужен отдельный прайс поставщика
A8: MAT-0003 | B8: Геотекстиль 200 г/м2 | C8: Эконом | D8: MV-0004 | F8: 0.99 | G8: Геотекстиль 200 г/м2 | H8: Свернуть в раздел | I8: Эконом
A9: MAT-0003 | B9: Геотекстиль 200 г/м2 | C9: Стандарт | D9: MV-0004 | F9: 1.00 | G9: Геотекстиль 200 г/м2 | H9: Свернуть в раздел | I9: Стандарт
A10: MAT-0003 | B10: Геотекстиль 200 г/м2 | C10: Премиум | D10: MV-0004 | E10: 1.03 | F10: 1.01 | G10: Геотекстиль 200 г/м2 | H10: Показать строкой | I10: Премиум | J10: Можно раскрывать материал в клиентской версии

Sheet TARIFF_COMPOSITION_RULES
A1: Tariff | B1: ScopeType | C1: ScopeValue | D1: Action | E1: TargetID | F1: ReplacementID | G1: ClientImpact | H1: Notes
A2: Эконом | B2: Section | C2: Мощение | D2: PreferVariant | E2: MV-0001 | F2: MV-0002 | G2: Снизить толщину/класс материала, если позволяет нагрузка | H2: Проверять по реальной зоне применения
A3: Стандарт | B3: Section | C3: Мощение | D3: PreferVariant | E3: MV-0002 | G3: Базовый вариант
A4: Премиум | B4: Section | C4: Мощение | D4: PreferVariant | E4: MV-0003 | F4: MV-0002 | G4: Усиленный или визуально более качественный вариант | H4: Не применять автоматически без проверки нагрузки
A5: Эконом | B5: Work | C5: WORK-0001 | D5: PreferMethod | E5: Механизированный | G5: Удешевление за счёт механизации при доступе
A6: Премиум | B6: Work | C6: WORK-0001 | D6: PreferMethod | E6: Ручной | G6: Более аккуратная доводка сложных зон
A7: Эконом | B7: Material | C7: MAT-0003 | D7: DisplayMode | E7: Свернуть в раздел | G7: Меньше детализации в КП
A8: Премиум | B8: Material | C8: MAT-0003 | D8: DisplayMode | E8: Показать строкой | G8: Больше прозрачности в составе решения

Sheet OUTPUT_RULES
A1: SortProfile | B1: Section | C1: SortOrder | D1: ClientSectionName | E1: ShowSectionSubtotal | F1: DefaultBundleMode | G1: ShowMaterials | H1: ShowLogistics | I1: ShowOverheads | J1: ShowAssumptionsBlock | K1: ShowExclusionsBlock | L1: Notes
A2: Эконом | B2: Мощение | C2: 10 | D2: Мощение | E2: Да | F2: Минимум | G2: Да | H2: Свернуть | I2: Скрыть | J2: Да | K2: Да | L2: Эконом сильнее укрупняет логистику и накладные
A3: Стандарт | B3: Мощение | C3: 10 | D3: Мощение | E3: Да | F3: База | G3: Да | H3: Показать | I3: Скрыть | J3: Да | K3: Да | L3: Базовый клиентский вывод
A4: Премиум | B4: Мощение | C4: 10 | D4: Премиальное мощение | E4: Да | F4: Детально | G4: Да | H4: Показать | I4: Скрыть | J4: Да | K4: Да | L4: Более подробное описание состава
A5: Внутренний | B5: Мощение | C5: 10 | D5: Мощение | E5: Да | F5: Детально | G5: Да | H5: Показать | I5: Показать | J5: Да | K5: Да | L5: Внутренняя версия сметы
A6: Стандарт | B6: Газон | C6: 20 | D6: Газон | E6: Да | F6: База | G6: Да | H6: Свернуть | I6: Скрыть | J6: Да | K6: Да
A7: Стандарт | B7: Дренаж | C7: 30 | D7: Дренаж | E7: Да | F7: База | G7: Да | H7: Показать | I7: Скрыть | J7: Да | K7: Да

Sheet EXCLUSIONS_LIBRARY
A1: Tariff | B1: Section | C1: InclusionType | D1: ClientText | E1: DefaultForClient | F1: Priority | G1: Notes
A2: Эконом | B2: Общие | C2: Exclusion | D2: Геология, скрытые инженерные сети и непредвиденные подземные препятствия не включены | E2: Да | F2: 10 | G2: Классическая защита от скрытых факторов
A3: Стандарт | B3: Общие | C3: Assumption | D3: Стоимость рассчитана при доступе техники и складировании материалов в пределах участка | E3: Да | F3: 10 | G3: Связь с условиями объекта
A4: Премиум | B4: Общие | C4: Inclusion | D4: Включено более точное сопряжение покрытий, геометрии и финишного контроля | E4: Да | F4: 10 | G4: Подчеркивает отличие премиума
A5: Стандарт | B5: Газон | C5: Exclusion | D5: Подсев/восстановление после эксплуатации третьими лицами не входит в гарантию | E5: Да | F5: 20 | G5: Уточнение гарантийного контура
A6: Стандарт | B6: Мощение | C6: Assumption | D6: Основание и нагрузки приняты по исходным данным заказчика, без статического расчета | E6: Да | F6: 20

Sheet TARIFF_KP_EXAMPLE
A1: ObjectID | B1: Tariff | C1: LineType | D1: RefID | E1: VariantID | F1: Description | G1: NetQty | H1: BaseUnitPrice | I1: SiteCoeff | J1: TariffCoeff | K1: ReserveCoeff | L1: FinalUnitPrice | M1: PurchaseQty | N1: LineTotal | O1: Comments
A2: OBJ-0001 | B2: Премиум | C2: Work | D2: WORK-0002 | F2: =IF($C2="","",IF($C2="Work",IFERROR(IF(SUMIFS(WORK_TARIFF_RULES!$G:$G,WORK_TARIFF_RULES!$A:$A,$D2,WORK_TARIFF_RULES!$C:$C,$B2)<>"",SUMIFS(WORK_TARIFF_RULES!$G:$G,WORK_TARIFF_RULES!$A:$A,$D2,WORK_TARIFF_RULES!$C:$C,$B2),SUMIFS(WORK_MASTER!$C:$C,WORK_MASTER!$A:$A,$D2)),""),IF($C2="Material",IFERROR(IF(SUMIFS(MATERIAL_TARIFF_RULES!$G:$G,MATERIAL_TARIFF_RULES!$A:$A,$D2,MATERIAL_TARIFF_RULES!$C:$C,$B2)<>"",SUMIFS(MATERIAL_TARIFF_RULES!$G:$G,MATERIAL_TARIFF_RULES!$A:$A,$D2,MATERIAL_TARIFF_RULES!$C:$C,$B2),SUMIFS(MATERIAL_VARIANTS!$J:$J,MATERIAL_VARIANTS!$A:$A,$E2)),""),""))) | G2: 120 | H2: =IF($C2="","",IF($C2="Work",IFERROR(SUMIFS(WORK_MASTER!$I:$I,WORK_MASTER!$A:$A,$D2),""),IF($C2="Material",IFERROR(SUMIFS(MATERIAL_VARIANTS!$I:$I,MATERIAL_VARIANTS!$A:$A,$E2),""),""))) | I2: =IF($C2="","",IF($C2="Work",IFERROR(SUMIFS(WORK_FACTOR_APPLICABILITY!$O:$O,WORK_FACTOR_APPLICABILITY!$A:$A,$D2,WORK_FACTOR_APPLICABILITY!$N:$N,$A2),1),IF($C2="Material",IFERROR(ROUND(1+SUMIFS(MATERIAL_FACTOR_APPLICABILITY!$D:$D,MATERIAL_FACTOR_APPLICABILITY!$A:$A,SUMIFS(MATERIAL_MASTER!$O:$O,MATERIAL_MASTER!$A:$A,$D2),MATERIAL_FACTOR_APPLICABILITY!$B:$B,"GeometryComplexity")*(SUMIFS(OBJECT_CONDITIONS!$W:$W,OBJECT_CONDITIONS!$A:$A,$A2)-1),3),1),""))) | J2: =IF($C2="","",IF($C2="Work",IFERROR(IF(SUMIFS(WORK_TARIFF_RULES!$F:$F,WORK_TARIFF_RULES!$A:$A,$D2,WORK_TARIFF_RULES!$C:$C,$B2)<>"",SUMIFS(WORK_TARIFF_RULES!$F:$F,WORK_TARIFF_RULES!$A:$A,$D2,WORK_TARIFF_RULES!$C:$C,$B2),SUMIFS(TARIFF_PROFILES!$D:$D,TARIFF_PROFILES!$A:$A,$B2)),1),IF($C2="Material",IFERROR(IF(SUMIFS(MATERIAL_TARIFF_RULES!$E:$E,MATERIAL_TARIFF_RULES!$A:$A,$D2,MATERIAL_TARIFF_RULES!$C:$C,$B2)<>"",SUMIFS(MATERIAL_TARIFF_RULES!$E:$E,MATERIAL_TARIFF_RULES!$A:$A,$D2,MATERIAL_TARIFF_RULES!$C:$C,$B2),SUMIFS(TARIFF_PROFILES!$E:$E,TARIFF_PROFILES!$A:$A,$B2)),1),""))) | K2: =IF($C2="","",IF($C2="Material",IFERROR(SUMIFS(MATERIAL_MASTER!$P:$P,MATERIAL_MASTER!$A:$A,$D2)*IF(SUMIFS(MATERIAL_TARIFF_RULES!$F:$F,MATERIAL_TARIFF_RULES!$A:$A,$D2,MATERIAL_TARIFF_RULES!$C:$C,$B2)="",SUMIFS(TARIFF_PROFILES!$H:$H,TARIFF_PROFILES!$A:$A,$B2),SUMIFS(MATERIAL_TARIFF_RULES!$F:$F,MATERIAL_TARIFF_RULES!$A:$A,$D2,MATERIAL_TARIFF_RULES!$C:$C,$B2)),1),1)) | L2: =IF($C2="","",IF($C2="Work",N($H2)*N($I2)*N($J2),IF($C2="Material",N($H2)*N($I2)*N($J2),""))) | M2: =IF($C2="","",IF($C2="Material",N($G2)*N($K2),N($G2))) | N2: =IF($C2="","",N($L2)*N($M2)) | O2: =IF($C2="","",IF($C2="Work","Тариф влияет на способ/детализацию и коэффициент работ",IF($C2="Material","Тариф влияет на вариант, качество, запас и показ материала","")))
A3: OBJ-0001 | B3: Премиум | C3: Material | D3: MAT-0001 | E3: MV-0003 | F3: =IF($C3="","",IF($C3="Work",IFERROR(IF(SUMIFS(WORK_TARIFF_RULES!$G:$G,WORK_TARIFF_RULES!$A:$A,$D3,WORK_TARIFF_RULES!$C:$C,$B3)<>"",SUMIFS(WORK_TARIFF_RULES!$G:$G,WORK_TARIFF_RULES!$A:$A,$D3,WORK_TARIFF_RULES!$C:$C,$B3),SUMIFS(WORK_MASTER!$C:$C,WORK_MASTER!$A:$A,$D3)),""),IF($C3="Material",IFERROR(IF(SUMIFS(MATERIAL_TARIFF_RULES!$G:$G,MATERIAL_TARIFF_RULES!$A:$A,$D3,MATERIAL_TARIFF_RULES!$C:$C,$B3)<>"",SUMIFS(MATERIAL_TARIFF_RULES!$G:$G,MATERIAL_TARIFF_RULES!$A:$A,$D3,MATERIAL_TARIFF_RULES!$C:$C,$B3),SUMIFS(MATERIAL_VARIANTS!$J:$J,MATERIAL_VARIANTS!$A:$A,$E3)),""),""))) | G3: 120 | H3: =IF($C3="","",IF($C3="Work",IFERROR(SUMIFS(WORK_MASTER!$I:$I,WORK_MASTER!$A:$A,$D3),""),IF($C3="Material",IFERROR(SUMIFS(MATERIAL_VARIANTS!$I:$I,MATERIAL_VARIANTS!$A:$A,$E3),""),""))) | I3: =IF($C3="","",IF($C3="Work",IFERROR(SUMIFS(WORK_FACTOR_APPLICABILITY!$O:$O,WORK_FACTOR_APPLICABILITY!$A:$A,$D3,WORK_FACTOR_APPLICABILITY!$N:$N,$A3),1),IF($C3="Material",IFERROR(ROUND(1+SUMIFS(MATERIAL_FACTOR_APPLICABILITY!$D:$D,MATERIAL_FACTOR_APPLICABILITY!$A:$A,SUMIFS(MATERIAL_MASTER!$O:$O,MATERIAL_MASTER!$A:$A,$D3),MATERIAL_FACTOR_APPLICABILITY!$B:$B,"GeometryComplexity")*(SUMIFS(OBJECT_CONDITIONS!$W:$W,OBJECT_CONDITIONS!$A:$A,$A3)-1),3),1),""))) | J3: =IF($C3="","",IF($C3="Work",IFERROR(IF(SUMIFS(WORK_TARIFF_RULES!$F:$F,WORK_TARIFF_RULES!$A:$A,$D3,WORK_TARIFF_RULES!$C:$C,$B3)<>"",SUMIFS(WORK_TARIFF_RULES!$F:$F,WORK_TARIFF_RULES!$A:$A,$D3,WORK_TARIFF_RULES!$C:$C,$B3),SUMIFS(TARIFF_PROFILES!$D:$D,TARIFF_PROFILES!$A:$A,$B3)),1),IF($C3="Material",IFERROR(IF(SUMIFS(MATERIAL_TARIFF_RULES!$E:$E,MATERIAL_TARIFF_RULES!$A:$A,$D3,MATERIAL_TARIFF_RULES!$C:$C,$B3)<>"",SUMIFS(MATERIAL_TARIFF_RULES!$E:$E,MATERIAL_TARIFF_RULES!$A:$A,$D3,MATERIAL_TARIFF_RULES!$C:$C,$B3),SUMIFS(TARIFF_PROFILES!$E:$E,TARIFF_PROFILES!$A:$A,$B3)),1),""))) | K3: =IF($C3="","",IF($C3="Material",IFERROR(SUMIFS(MATERIAL_MASTER!$P:$P,MATERIAL_MASTER!$A:$A,$D3)*IF(SUMIFS(MATERIAL_TARIFF_RULES!$F:$F,MATERIAL_TARIFF_RULES!$A:$A,$D3,MATERIAL_TARIFF_RULES!$C:$C,$B3)="",SUMIFS(TARIFF_PROFILES!$H:$H,TARIFF_PROFILES!$A:$A,$B3),SUMIFS(MATERIAL_TARIFF_RULES!$F:$F,MATERIAL_TARIFF_RULES!$A:$A,$D3,MATERIAL_TARIFF_RULES!$C:$C,$B3)),1),1)) | L3: =IF($C3="","",IF($C3="Work",N($H3)*N($I3)*N($J3),IF($C3="Material",N($H3)*N($I3)*N($J3),""))) | M3: =IF($C3="","",IF($C3="Material",N($G3)*N($K3),N($G3))) | N3: =IF($C3="","",N($L3)*N($M3)) | O3: =IF($C3="","",IF($C3="Work","Тариф влияет на способ/детализацию и коэффициент работ",IF($C3="Material","Тариф влияет на вариант, качество, запас и показ материала","")))
A4: OBJ-0002 | B4: Эконом | C4: Work | D4: WORK-0001 | F4: =IF($C4="","",IF($C4="Work",IFERROR(IF(SUMIFS(WORK_TARIFF_RULES!$G:$G,WORK_TARIFF_RULES!$A:$A,$D4,WORK_TARIFF_RULES!$C:$C,$B4)<>"",SUMIFS(WORK_TARIFF_RULES!$G:$G,WORK_TARIFF_RULES!$A:$A,$D4,WORK_TARIFF_RULES!$C:$C,$B4),SUMIFS(WORK_MASTER!$C:$C,WORK_MASTER!$A:$A,$D4)),""),IF($C4="Material",IFERROR(IF(SUMIFS(MATERIAL_TARIFF_RULES!$G:$G,MATERIAL_TARIFF_RULES!$A:$A,$D4,MATERIAL_TARIFF_RULES!$C:$C,$B4)<>"",SUMIFS(MATERIAL_TARIFF_RULES!$G:$G,MATERIAL_TARIFF_RULES!$A:$A,$D4,MATERIAL_TARIFF_RULES!$C:$C,$B4),SUMIFS(MATERIAL_VARIANTS!$J:$J,MATERIAL_VARIANTS!$A:$A,$E4)),""),""))) | G4: 200 | H4: =IF($C4="","",IF($C4="Work",IFERROR(SUMIFS(WORK_MASTER!$I:$I,WORK_MASTER!$A:$A,$D4),""),IF($C4="Material",IFERROR(SUMIFS(MATERIAL_VARIANTS!$I:$I,MATERIAL_VARIANTS!$A:$A,$E4),""),""))) | I4: =IF($C4="","",IF($C4="Work",IFERROR(SUMIFS(WORK_FACTOR_APPLICABILITY!$O:$O,WORK_FACTOR_APPLICABILITY!$A:$A,$D4,WORK_FACTOR_APPLICABILITY!$N:$N,$A4),1),IF($C4="Material",IFERROR(ROUND(1+SUMIFS(MATERIAL_FACTOR_APPLICABILITY!$D:$D,MATERIAL_FACTOR_APPLICABILITY!$A:$A,SUMIFS(MATERIAL_MASTER!$O:$O,MATERIAL_MASTER!$A:$A,$D4),MATERIAL_FACTOR_APPLICABILITY!$B:$B,"GeometryComplexity")*(SUMIFS(OBJECT_CONDITIONS!$W:$W,OBJECT_CONDITIONS!$A:$A,$A4)-1),3),1),""))) | J4: =IF($C4="","",IF($C4="Work",IFERROR(IF(SUMIFS(WORK_TARIFF_RULES!$F:$F,WORK_TARIFF_RULES!$A:$A,$D4,WORK_TARIFF_RULES!$C:$C,$B4)<>"",SUMIFS(WORK_TARIFF_RULES!$F:$F,WORK_TARIFF_RULES!$A:$A,$D4,WORK_TARIFF_RULES!$C:$C,$B4),SUMIFS(TARIFF_PROFILES!$D:$D,TARIFF_PROFILES!$A:$A,$B4)),1),IF($C4="Material",IFERROR(IF(SUMIFS(MATERIAL_TARIFF_RULES!$E:$E,MATERIAL_TARIFF_RULES!$A:$A,$D4,MATERIAL_TARIFF_RULES!$C:$C,$B4)<>"",SUMIFS(MATERIAL_TARIFF_RULES!$E:$E,MATERIAL_TARIFF_RULES!$A:$A,$D4,MATERIAL_TARIFF_RULES!$C:$C,$B4),SUMIFS(TARIFF_PROFILES!$E:$E,TARIFF_PROFILES!$A:$A,$B4)),1),""))) | K4: =IF($C4="","",IF($C4="Material",IFERROR(SUMIFS(MATERIAL_MASTER!$P:$P,MATERIAL_MASTER!$A:$A,$D4)*IF(SUMIFS(MATERIAL_TARIFF_RULES!$F:$F,MATERIAL_TARIFF_RULES!$A:$A,$D4,MATERIAL_TARIFF_RULES!$C:$C,$B4)="",SUMIFS(TARIFF_PROFILES!$H:$H,TARIFF_PROFILES!$A:$A,$B4),SUMIFS(MATERIAL_TARIFF_RULES!$F:$F,MATERIAL_TARIFF_RULES!$A:$A,$D4,MATERIAL_TARIFF_RULES!$C:$C,$B4)),1),1)) | L4: =IF($C4="","",IF($C4="Work",N($H4)*N($I4)*N($J4),IF($C4="Material",N($H4)*N($I4)*N($J4),""))) | M4: =IF($C4="","",IF($C4="Material",N($G4)*N($K4),N($G4))) | N4: =IF($C4="","",N($L4)*N($M4)) | O4: =IF($C4="","",IF($C4="Work","Тариф влияет на способ/детализацию и коэффициент работ",IF($C4="Material","Тариф влияет на вариант, качество, запас и показ материала","")))
A5: OBJ-0002 | B5: Эконом | C5: Material | D5: MAT-0003 | E5: MV-0004 | F5: =IF($C5="","",IF($C5="Work",IFERROR(IF(SUMIFS(WORK_TARIFF_RULES!$G:$G,WORK_TARIFF_RULES!$A:$A,$D5,WORK_TARIFF_RULES!$C:$C,$B5)<>"",SUMIFS(WORK_TARIFF_RULES!$G:$G,WORK_TARIFF_RULES!$A:$A,$D5,WORK_TARIFF_RULES!$C:$C,$B5),SUMIFS(WORK_MASTER!$C:$C,WORK_MASTER!$A:$A,$D5)),""),IF($C5="Material",IFERROR(IF(SUMIFS(MATERIAL_TARIFF_RULES!$G:$G,MATERIAL_TARIFF_RULES!$A:$A,$D5,MATERIAL_TARIFF_RULES!$C:$C,$B5)<>"",SUMIFS(MATERIAL_TARIFF_RULES!$G:$G,MATERIAL_TARIFF_RULES!$A:$A,$D5,MATERIAL_TARIFF_RULES!$C:$C,$B5),SUMIFS(MATERIAL_VARIANTS!$J:$J,MATERIAL_VARIANTS!$A:$A,$E5)),""),""))) | G5: 200 | H5: =IF($C5="","",IF($C5="Work",IFERROR(SUMIFS(WORK_MASTER!$I:$I,WORK_MASTER!$A:$A,$D5),""),IF($C5="Material",IFERROR(SUMIFS(MATERIAL_VARIANTS!$I:$I,MATERIAL_VARIANTS!$A:$A,$E5),""),""))) | I5: =IF($C5="","",IF($C5="Work",IFERROR(SUMIFS(WORK_FACTOR_APPLICABILITY!$O:$O,WORK_FACTOR_APPLICABILITY!$A:$A,$D5,WORK_FACTOR_APPLICABILITY!$N:$N,$A5),1),IF($C5="Material",IFERROR(ROUND(1+SUMIFS(MATERIAL_FACTOR_APPLICABILITY!$D:$D,MATERIAL_FACTOR_APPLICABILITY!$A:$A,SUMIFS(MATERIAL_MASTER!$O:$O,MATERIAL_MASTER!$A:$A,$D5),MATERIAL_FACTOR_APPLICABILITY!$B:$B,"GeometryComplexity")*(SUMIFS(OBJECT_CONDITIONS!$W:$W,OBJECT_CONDITIONS!$A:$A,$A5)-1),3),1),""))) | J5: =IF($C5="","",IF($C5="Work",IFERROR(IF(SUMIFS(WORK_TARIFF_RULES!$F:$F,WORK_TARIFF_RULES!$A:$A,$D5,WORK_TARIFF_RULES!$C:$C,$B5)<>"",SUMIFS(WORK_TARIFF_RULES!$F:$F,WORK_TARIFF_RULES!$A:$A,$D5,WORK_TARIFF_RULES!$C:$C,$B5),SUMIFS(TARIFF_PROFILES!$D:$D,TARIFF_PROFILES!$A:$A,$B5)),1),IF($C5="Material",IFERROR(IF(SUMIFS(MATERIAL_TARIFF_RULES!$E:$E,MATERIAL_TARIFF_RULES!$A:$A,$D5,MATERIAL_TARIFF_RULES!$C:$C,$B5)<>"",SUMIFS(MATERIAL_TARIFF_RULES!$E:$E,MATERIAL_TARIFF_RULES!$A:$A,$D5,MATERIAL_TARIFF_RULES!$C:$C,$B5),SUMIFS(TARIFF_PROFILES!$E:$E,TARIFF_PROFILES!$A:$A,$B5)),1),""))) | K5: =IF($C5="","",IF($C5="Material",IFERROR(SUMIFS(MATERIAL_MASTER!$P:$P,MATERIAL_MASTER!$A:$A,$D5)*IF(SUMIFS(MATERIAL_TARIFF_RULES!$F:$F,MATERIAL_TARIFF_RULES!$A:$A,$D5,MATERIAL_TARIFF_RULES!$C:$C,$B5)="",SUMIFS(TARIFF_PROFILES!$H:$H,TARIFF_PROFILES!$A:$A,$B5),SUMIFS(MATERIAL_TARIFF_RULES!$F:$F,MATERIAL_TARIFF_RULES!$A:$A,$D5,MATERIAL_TARIFF_RULES!$C:$C,$B5)),1),1)) | L5: =IF($C5="","",IF($C5="Work",N($H5)*N($I5)*N($J5),IF($C5="Material",N($H5)*N($I5)*N($J5),""))) | M5: =IF($C5="","",IF($C5="Material",N($G5)*N($K5),N($G5))) | N5: =IF($C5="","",N($L5)*N($M5)) | O5: =IF($C5="","",IF($C5="Work","Тариф влияет на способ/детализацию и коэффициент работ",IF($C5="Material","Тариф влияет на вариант, качество, запас и показ материала","")))
F6: =IF($C6="","",IF($C6="Work",IFERROR(IF(SUMIFS(WORK_TARIFF_RULES!$G:$G,WORK_TARIFF_RULES!$A:$A,$D6,WORK_TARIFF_RULES!$C:$C,$B6)<>"",SUMIFS(WORK_TARIFF_RULES!$G:$G,WORK_TARIFF_RULES!$A:$A,$D6,WORK_TARIFF_RULES!$C:$C,$B6),SUMIFS(WORK_MASTER!$C:$C,WORK_MASTER!$A:$A,$D6)),""),IF($C6="Material",IFERROR(IF(SUMIFS(MATERIAL_TARIFF_RULES!$G:$G,MATERIAL_TARIFF_RULES!$A:$A,$D6,MATERIAL_TARIFF_RULES!$C:$C,$B6)<>"",SUMIFS(MATERIAL_TARIFF_RULES!$G:$G,MATERIAL_TARIFF_RULES!$A:$A,$D6,MATERIAL_TARIFF_RULES!$C:$C,$B6),SUMIFS(MATERIAL_VARIANTS!$J:$J,MATERIAL_VARIANTS!$A:$A,$E6)),""),""))) | H6: =IF($C6="","",IF($C6="Work",IFERROR(SUMIFS(WORK_MASTER!$I:$I,WORK_MASTER!$A:$A,$D6),""),IF($C6="Material",IFERROR(SUMIFS(MATERIAL_VARIANTS!$I:$I,MATERIAL_VARIANTS!$A:$A,$E6),""),""))) | I6: =IF($C6="","",IF($C6="Work",IFERROR(SUMIFS(WORK_FACTOR_APPLICABILITY!$O:$O,WORK_FACTOR_APPLICABILITY!$A:$A,$D6,WORK_FACTOR_APPLICABILITY!$N:$N,$A6),1),IF($C6="Material",IFERROR(ROUND(1+SUMIFS(MATERIAL_FACTOR_APPLICABILITY!$D:$D,MATERIAL_FACTOR_APPLICABILITY!$A:$A,SUMIFS(MATERIAL_MASTER!$O:$O,MATERIAL_MASTER!$A:$A,$D6),MATERIAL_FACTOR_APPLICABILITY!$B:$B,"GeometryComplexity")*(SUMIFS(OBJECT_CONDITIONS!$W:$W,OBJECT_CONDITIONS!$A:$A,$A6)-1),3),1),""))) | J6: =IF($C6="","",IF($C6="Work",IFERROR(IF(SUMIFS(WORK_TARIFF_RULES!$F:$F,WORK_TARIFF_RULES!$A:$A,$D6,WORK_TARIFF_RULES!$C:$C,$B6)<>"",SUMIFS(WORK_TARIFF_RULES!$F:$F,WORK_TARIFF_RULES!$A:$A,$D6,WORK_TARIFF_RULES!$C:$C,$B6),SUMIFS(TARIFF_PROFILES!$D:$D,TARIFF_PROFILES!$A:$A,$B6)),1),IF($C6="Material",IFERROR(IF(SUMIFS(MATERIAL_TARIFF_RULES!$E:$E,MATERIAL_TARIFF_RULES!$A:$A,$D6,MATERIAL_TARIFF_RULES!$C:$C,$B6)<>"",SUMIFS(MATERIAL_TARIFF_RULES!$E:$E,MATERIAL_TARIFF_RULES!$A:$A,$D6,MATERIAL_TARIFF_RULES!$C:$C,$B6),SUMIFS(TARIFF_PROFILES!$E:$E,TARIFF_PROFILES!$A:$A,$B6)),1),""))) | K6: =IF($C6="","",IF($C6="Material",IFERROR(SUMIFS(MATERIAL_MASTER!$P:$P,MATERIAL_MASTER!$A:$A,$D6)*IF(SUMIFS(MATERIAL_TARIFF_RULES!$F:$F,MATERIAL_TARIFF_RULES!$A:$A,$D6,MATERIAL_TARIFF_RULES!$C:$C,$B6)="",SUMIFS(TARIFF_PROFILES!$H:$H,TARIFF_PROFILES!$A:$A,$B6),SUMIFS(MATERIAL_TARIFF_RULES!$F:$F,MATERIAL_TARIFF_RULES!$A:$A,$D6,MATERIAL_TARIFF_RULES!$C:$C,$B6)),1),1)) | L6: =IF($C6="","",IF($C6="Work",N($H6)*N($I6)*N($J6),IF($C6="Material",N($H6)*N($I6)*N($J6),""))) | M6: =IF($C6="","",IF($C6="Material",N($G6)*N($K6),N($G6))) | N6: =IF($C6="","",N($L6)*N($M6)) | O6: =IF($C6="","",IF($C6="Work","Тариф влияет на способ/детализацию и коэффициент работ",IF($C6="Material","Тариф влияет на вариант, качество, запас и показ материала","")))
F7: =IF($C7="","",IF($C7="Work",IFERROR(IF(SUMIFS(WORK_TARIFF_RULES!$G:$G,WORK_TARIFF_RULES!$A:$A,$D7,WORK_TARIFF_RULES!$C:$C,$B7)<>"",SUMIFS(WORK_TARIFF_RULES!$G:$G,WORK_TARIFF_RULES!$A:$A,$D7,WORK_TARIFF_RULES!$C:$C,$B7),SUMIFS(WORK_MASTER!$C:$C,WORK_MASTER!$A:$A,$D7)),""),IF($C7="Material",IFERROR(IF(SUMIFS(MATERIAL_TARIFF_RULES!$G:$G,MATERIAL_TARIFF_RULES!$A:$A,$D7,MATERIAL_TARIFF_RULES!$C:$C,$B7)<>"",SUMIFS(MATERIAL_TARIFF_RULES!$G:$G,MATERIAL_TARIFF_RULES!$A:$A,$D7,MATERIAL_TARIFF_RULES!$C:$C,$B7),SUMIFS(MATERIAL_VARIANTS!$J:$J,MATERIAL_VARIANTS!$A:$A,$E7)),""),""))) | H7: =IF($C7="","",IF($C7="Work",IFERROR(SUMIFS(WORK_MASTER!$I:$I,WORK_MASTER!$A:$A,$D7),""),IF($C7="Material",IFERROR(SUMIFS(MATERIAL_VARIANTS!$I:$I,MATERIAL_VARIANTS!$A:$A,$E7),""),""))) | I7: =IF($C7="","",IF($C7="Work",IFERROR(SUMIFS(WORK_FACTOR_APPLICABILITY!$O:$O,WORK_FACTOR_APPLICABILITY!$A:$A,$D7,WORK_FACTOR_APPLICABILITY!$N:$N,$A7),1),IF($C7="Material",IFERROR(ROUND(1+SUMIFS(MATERIAL_FACTOR_APPLICABILITY!$D:$D,MATERIAL_FACTOR_APPLICABILITY!$A:$A,SUMIFS(MATERIAL_MASTER!$O:$O,MATERIAL_MASTER!$A:$A,$D7),MATERIAL_FACTOR_APPLICABILITY!$B:$B,"GeometryComplexity")*(SUMIFS(OBJECT_CONDITIONS!$W:$W,OBJECT_CONDITIONS!$A:$A,$A7)-1),3),1),""))) | J7: =IF($C7="","",IF($C7="Work",IFERROR(IF(SUMIFS(WORK_TARIFF_RULES!$F:$F,WORK_TARIFF_RULES!$A:$A,$D7,WORK_TARIFF_RULES!$C:$C,$B7)<>"",SUMIFS(WORK_TARIFF_RULES!$F:$F,WORK_TARIFF_RULES!$A:$A,$D7,WORK_TARIFF_RULES!$C:$C,$B7),SUMIFS(TARIFF_PROFILES!$D:$D,TARIFF_PROFILES!$A:$A,$B7)),1),IF($C7="Material",IFERROR(IF(SUMIFS(MATERIAL_TARIFF_RULES!$E:$E,MATERIAL_TARIFF_RULES!$A:$A,$D7,MATERIAL_TARIFF_RULES!$C:$C,$B7)<>"",SUMIFS(MATERIAL_TARIFF_RULES!$E:$E,MATERIAL_TARIFF_RULES!$A:$A,$D7,MATERIAL_TARIFF_RULES!$C:$C,$B7),SUMIFS(TARIFF_PROFILES!$E:$E,TARIFF_PROFILES!$A:$A,$B7)),1),""))) | K7: =IF($C7="","",IF($C7="Material",IFERROR(SUMIFS(MATERIAL_MASTER!$P:$P,MATERIAL_MASTER!$A:$A,$D7)*IF(SUMIFS(MATERIAL_TARIFF_RULES!$F:$F,MATERIAL_TARIFF_RULES!$A:$A,$D7,MATERIAL_TARIFF_RULES!$C:$C,$B7)="",SUMIFS(TARIFF_PROFILES!$H:$H,TARIFF_PROFILES!$A:$A,$B7),SUMIFS(MATERIAL_TARIFF_RULES!$F:$F,MATERIAL_TARIFF_RULES!$A:$A,$D7,MATERIAL_TARIFF_RULES!$C:$C,$B7)),1),1)) | L7: =IF($C7="","",IF($C7="Work",N($H7)*N($I7)*N($J7),IF($C7="Material",N($H7)*N($I7)*N($J7),""))) | M7: =IF($C7="","",IF($C7="Material",N($G7)*N($K7),N($G7))) | N7: =IF($C7="","",N($L7)*N($M7)) | O7: =IF($C7="","",IF($C7="Work","Тариф влияет на способ/детализацию и коэффициент работ",IF($C7="Material","Тариф влияет на вариант, качество, запас и показ материала","")))
F8: =IF($C8="","",IF($C8="Work",IFERROR(IF(SUMIFS(WORK_TARIFF_RULES!$G:$G,WORK_TARIFF_RULES!$A:$A,$D8,WORK_TARIFF_RULES!$C:$C,$B8)<>"",SUMIFS(WORK_TARIFF_RULES!$G:$G,WORK_TARIFF_RULES!$A:$A,$D8,WORK_TARIFF_RULES!$C:$C,$B8),SUMIFS(WORK_MASTER!$C:$C,WORK_MASTER!$A:$A,$D8)),""),IF($C8="Material",IFERROR(IF(SUMIFS(MATERIAL_TARIFF_RULES!$G:$G,MATERIAL_TARIFF_RULES!$A:$A,$D8,MATERIAL_TARIFF_RULES!$C:$C,$B8)<>"",SUMIFS(MATERIAL_TARIFF_RULES!$G:$G,MATERIAL_TARIFF_RULES!$A:$A,$D8,MATERIAL_TARIFF_RULES!$C:$C,$B8),SUMIFS(MATERIAL_VARIANTS!$J:$J,MATERIAL_VARIANTS!$A:$A,$E8)),""),""))) | H8: =IF($C8="","",IF($C8="Work",IFERROR(SUMIFS(WORK_MASTER!$I:$I,WORK_MASTER!$A:$A,$D8),""),IF($C8="Material",IFERROR(SUMIFS(MATERIAL_VARIANTS!$I:$I,MATERIAL_VARIANTS!$A:$A,$E8),""),""))) | I8: =IF($C8="","",IF($C8="Work",IFERROR(SUMIFS(WORK_FACTOR_APPLICABILITY!$O:$O,WORK_FACTOR_APPLICABILITY!$A:$A,$D8,WORK_FACTOR_APPLICABILITY!$N:$N,$A8),1),IF($C8="Material",IFERROR(ROUND(1+SUMIFS(MATERIAL_FACTOR_APPLICABILITY!$D:$D,MATERIAL_FACTOR_APPLICABILITY!$A:$A,SUMIFS(MATERIAL_MASTER!$O:$O,MATERIAL_MASTER!$A:$A,$D8),MATERIAL_FACTOR_APPLICABILITY!$B:$B,"GeometryComplexity")*(SUMIFS(OBJECT_CONDITIONS!$W:$W,OBJECT_CONDITIONS!$A:$A,$A8)-1),3),1),""))) | J8: =IF($C8="","",IF($C8="Work",IFERROR(IF(SUMIFS(WORK_TARIFF_RULES!$F:$F,WORK_TARIFF_RULES!$A:$A,$D8,WORK_TARIFF_RULES!$C:$C,$B8)<>"",SUMIFS(WORK_TARIFF_RULES!$F:$F,WORK_TARIFF_RULES!$A:$A,$D8,WORK_TARIFF_RULES!$C:$C,$B8),SUMIFS(TARIFF_PROFILES!$D:$D,TARIFF_PROFILES!$A:$A,$B8)),1),IF($C8="Material",IFERROR(IF(SUMIFS(MATERIAL_TARIFF_RULES!$E:$E,MATERIAL_TARIFF_RULES!$A:$A,$D8,MATERIAL_TARIFF_RULES!$C:$C,$B8)<>"",SUMIFS(MATERIAL_TARIFF_RULES!$E:$E,MATERIAL_TARIFF_RULES!$A:$A,$D8,MATERIAL_TARIFF_RULES!$C:$C,$B8),SUMIFS(TARIFF_PROFILES!$E:$E,TARIFF_PROFILES!$A:$A,$B8)),1),""))) | K8: =IF($C8="","",IF($C8="Material",IFERROR(SUMIFS(MATERIAL_MASTER!$P:$P,MATERIAL_MASTER!$A:$A,$D8)*IF(SUMIFS(MATERIAL_TARIFF_RULES!$F:$F,MATERIAL_TARIFF_RULES!$A:$A,$D8,MATERIAL_TARIFF_RULES!$C:$C,$B8)="",SUMIFS(TARIFF_PROFILES!$H:$H,TARIFF_PROFILES!$A:$A,$B8),SUMIFS(MATERIAL_TARIFF_RULES!$F:$F,MATERIAL_TARIFF_RULES!$A:$A,$D8,MATERIAL_TARIFF_RULES!$C:$C,$B8)),1),1)) | L8: =IF($C8="","",IF($C8="Work",N($H8)*N($I8)*N($J8),IF($C8="Material",N($H8)*N($I8)*N($J8),""))) | M8: =IF($C8="","",IF($C8="Material",N($G8)*N($K8),N($G8))) | N8: =IF($C8="","",N($L8)*N($M8)) | O8: =IF($C8="","",IF($C8="Work","Тариф влияет на способ/детализацию и коэффициент работ",IF($C8="Material","Тариф влияет на вариант, качество, запас и показ материала","")))
F9: =IF($C9="","",IF($C9="Work",IFERROR(IF(SUMIFS(WORK_TARIFF_RULES!$G:$G,WORK_TARIFF_RULES!$A:$A,$D9,WORK_TARIFF_RULES!$C:$C,$B9)<>"",SUMIFS(WORK_TARIFF_RULES!$G:$G,WORK_TARIFF_RULES!$A:$A,$D9,WORK_TARIFF_RULES!$C:$C,$B9),SUMIFS(WORK_MASTER!$C:$C,WORK_MASTER!$A:$A,$D9)),""),IF($C9="Material",IFERROR(IF(SUMIFS(MATERIAL_TARIFF_RULES!$G:$G,MATERIAL_TARIFF_RULES!$A:$A,$D9,MATERIAL_TARIFF_RULES!$C:$C,$B9)<>"",SUMIFS(MATERIAL_TARIFF_RULES!$G:$G,MATERIAL_TARIFF_RULES!$A:$A,$D9,MATERIAL_TARIFF_RULES!$C:$C,$B9),SUMIFS(MATERIAL_VARIANTS!$J:$J,MATERIAL_VARIANTS!$A:$A,$E9)),""),""))) | H9: =IF($C9="","",IF($C9="Work",IFERROR(SUMIFS(WORK_MASTER!$I:$I,WORK_MASTER!$A:$A,$D9),""),IF($C9="Material",IFERROR(SUMIFS(MATERIAL_VARIANTS!$I:$I,MATERIAL_VARIANTS!$A:$A,$E9),""),""))) | I9: =IF($C9="","",IF($C9="Work",IFERROR(SUMIFS(WORK_FACTOR_APPLICABILITY!$O:$O,WORK_FACTOR_APPLICABILITY!$A:$A,$D9,WORK_FACTOR_APPLICABILITY!$N:$N,$A9),1),IF($C9="Material",IFERROR(ROUND(1+SUMIFS(MATERIAL_FACTOR_APPLICABILITY!$D:$D,MATERIAL_FACTOR_APPLICABILITY!$A:$A,SUMIFS(MATERIAL_MASTER!$O:$O,MATERIAL_MASTER!$A:$A,$D9),MATERIAL_FACTOR_APPLICABILITY!$B:$B,"GeometryComplexity")*(SUMIFS(OBJECT_CONDITIONS!$W:$W,OBJECT_CONDITIONS!$A:$A,$A9)-1),3),1),""))) | J9: =IF($C9="","",IF($C9="Work",IFERROR(IF(SUMIFS(WORK_TARIFF_RULES!$F:$F,WORK_TARIFF_RULES!$A:$A,$D9,WORK_TARIFF_RULES!$C:$C,$B9)<>"",SUMIFS(WORK_TARIFF_RULES!$F:$F,WORK_TARIFF_RULES!$A:$A,$D9,WORK_TARIFF_RULES!$C:$C,$B9),SUMIFS(TARIFF_PROFILES!$D:$D,TARIFF_PROFILES!$A:$A,$B9)),1),IF($C9="Material",IFERROR(IF(SUMIFS(MATERIAL_TARIFF_RULES!$E:$E,MATERIAL_TARIFF_RULES!$A:$A,$D9,MATERIAL_TARIFF_RULES!$C:$C,$B9)<>"",SUMIFS(MATERIAL_TARIFF_RULES!$E:$E,MATERIAL_TARIFF_RULES!$A:$A,$D9,MATERIAL_TARIFF_RULES!$C:$C,$B9),SUMIFS(TARIFF_PROFILES!$E:$E,TARIFF_PROFILES!$A:$A,$B9)),1),""))) | K9: =IF($C9="","",IF($C9="Material",IFERROR(SUMIFS(MATERIAL_MASTER!$P:$P,MATERIAL_MASTER!$A:$A,$D9)*IF(SUMIFS(MATERIAL_TARIFF_RULES!$F:$F,MATERIAL_TARIFF_RULES!$A:$A,$D9,MATERIAL_TARIFF_RULES!$C:$C,$B9)="",SUMIFS(TARIFF_PROFILES!$H:$H,TARIFF_PROFILES!$A:$A,$B9),SUMIFS(MATERIAL_TARIFF_RULES!$F:$F,MATERIAL_TARIFF_RULES!$A:$A,$D9,MATERIAL_TARIFF_RULES!$C:$C,$B9)),1),1)) | L9: =IF($C9="","",IF($C9="Work",N($H9)*N($I9)*N($J9),IF($C9="Material",N($H9)*N($I9)*N($J9),""))) | M9: =IF($C9="","",IF($C9="Material",N($G9)*N($K9),N($G9))) | N9: =IF($C9="","",N($L9)*N($M9)) | O9: =IF($C9="","",IF($C9="Work","Тариф влияет на способ/детализацию и коэффициент работ",IF($C9="Material","Тариф влияет на вариант, качество, запас и показ материала","")))
F10: =IF($C10="","",IF($C10="Work",IFERROR(IF(SUMIFS(WORK_TARIFF_RULES!$G:$G,WORK_TARIFF_RULES!$A:$A,$D10,WORK_TARIFF_RULES!$C:$C,$B10)<>"",SUMIFS(WORK_TARIFF_RULES!$G:$G,WORK_TARIFF_RULES!$A:$A,$D10,WORK_TARIFF_RULES!$C:$C,$B10),SUMIFS(WORK_MASTER!$C:$C,WORK_MASTER!$A:$A,$D10)),""),IF($C10="Material",IFERROR(IF(SUMIFS(MATERIAL_TARIFF_RULES!$G:$G,MATERIAL_TARIFF_RULES!$A:$A,$D10,MATERIAL_TARIFF_RULES!$C:$C,$B10)<>"",SUMIFS(MATERIAL_TARIFF_RULES!$G:$G,MATERIAL_TARIFF_RULES!$A:$A,$D10,MATERIAL_TARIFF_RULES!$C:$C,$B10),SUMIFS(MATERIAL_VARIANTS!$J:$J,MATERIAL_VARIANTS!$A:$A,$E10)),""),""))) | H10: =IF($C10="","",IF($C10="Work",IFERROR(SUMIFS(WORK_MASTER!$I:$I,WORK_MASTER!$A:$A,$D10),""),IF($C10="Material",IFERROR(SUMIFS(MATERIAL_VARIANTS!$I:$I,MATERIAL_VARIANTS!$A:$A,$E10),""),""))) | I10: =IF($C10="","",IF($C10="Work",IFERROR(SUMIFS(WORK_FACTOR_APPLICABILITY!$O:$O,WORK_FACTOR_APPLICABILITY!$A:$A,$D10,WORK_FACTOR_APPLICABILITY!$N:$N,$A10),1),IF($C10="Material",IFERROR(ROUND(1+SUMIFS(MATERIAL_FACTOR_APPLICABILITY!$D:$D,MATERIAL_FACTOR_APPLICABILITY!$A:$A,SUMIFS(MATERIAL_MASTER!$O:$O,MATERIAL_MASTER!$A:$A,$D10),MATERIAL_FACTOR_APPLICABILITY!$B:$B,"GeometryComplexity")*(SUMIFS(OBJECT_CONDITIONS!$W:$W,OBJECT_CONDITIONS!$A:$A,$A10)-1),3),1),""))) | J10: =IF($C10="","",IF($C10="Work",IFERROR(IF(SUMIFS(WORK_TARIFF_RULES!$F:$F,WORK_TARIFF_RULES!$A:$A,$D10,WORK_TARIFF_RULES!$C:$C,$B10)<>"",SUMIFS(WORK_TARIFF_RULES!$F:$F,WORK_TARIFF_RULES!$A:$A,$D10,WORK_TARIFF_RULES!$C:$C,$B10),SUMIFS(TARIFF_PROFILES!$D:$D,TARIFF_PROFILES!$A:$A,$B10)),1),IF($C10="Material",IFERROR(IF(SUMIFS(MATERIAL_TARIFF_RULES!$E:$E,MATERIAL_TARIFF_RULES!$A:$A,$D10,MATERIAL_TARIFF_RULES!$C:$C,$B10)<>"",SUMIFS(MATERIAL_TARIFF_RULES!$E:$E,MATERIAL_TARIFF_RULES!$A:$A,$D10,MATERIAL_TARIFF_RULES!$C:$C,$B10),SUMIFS(TARIFF_PROFILES!$E:$E,TARIFF_PROFILES!$A:$A,$B10)),1),""))) | K10: =IF($C10="","",IF($C10="Material",IFERROR(SUMIFS(MATERIAL_MASTER!$P:$P,MATERIAL_MASTER!$A:$A,$D10)*IF(SUMIFS(MATERIAL_TARIFF_RULES!$F:$F,MATERIAL_TARIFF_RULES!$A:$A,$D10,MATERIAL_TARIFF_RULES!$C:$C,$B10)="",SUMIFS(TARIFF_PROFILES!$H:$H,TARIFF_PROFILES!$A:$A,$B10),SUMIFS(MATERIAL_TARIFF_RULES!$F:$F,MATERIAL_TARIFF_RULES!$A:$A,$D10,MATERIAL_TARIFF_RULES!$C:$C,$B10)),1),1)) | L10: =IF($C10="","",IF($C10="Work",N($H10)*N($I10)*N($J10),IF($C10="Material",N($H10)*N($I10)*N($J10),""))) | M10: =IF($C10="","",IF($C10="Material",N($G10)*N($K10),N($G10))) | N10: =IF($C10="","",N($L10)*N($M10)) | O10: =IF($C10="","",IF($C10="Work","Тариф влияет на способ/детализацию и коэффициент работ",IF($C10="Material","Тариф влияет на вариант, качество, запас и показ материала","")))
F11: =IF($C11="","",IF($C11="Work",IFERROR(IF(SUMIFS(WORK_TARIFF_RULES!$G:$G,WORK_TARIFF_RULES!$A:$A,$D11,WORK_TARIFF_RULES!$C:$C,$B11)<>"",SUMIFS(WORK_TARIFF_RULES!$G:$G,WORK_TARIFF_RULES!$A:$A,$D11,WORK_TARIFF_RULES!$C:$C,$B11),SUMIFS(WORK_MASTER!$C:$C,WORK_MASTER!$A:$A,$D11)),""),IF($C11="Material",IFERROR(IF(SUMIFS(MATERIAL_TARIFF_RULES!$G:$G,MATERIAL_TARIFF_RULES!$A:$A,$D11,MATERIAL_TARIFF_RULES!$C:$C,$B11)<>"",SUMIFS(MATERIAL_TARIFF_RULES!$G:$G,MATERIAL_TARIFF_RULES!$A:$A,$D11,MATERIAL_TARIFF_RULES!$C:$C,$B11),SUMIFS(MATERIAL_VARIANTS!$J:$J,MATERIAL_VARIANTS!$A:$A,$E11)),""),""))) | H11: =IF($C11="","",IF($C11="Work",IFERROR(SUMIFS(WORK_MASTER!$I:$I,WORK_MASTER!$A:$A,$D11),""),IF($C11="Material",IFERROR(SUMIFS(MATERIAL_VARIANTS!$I:$I,MATERIAL_VARIANTS!$A:$A,$E11),""),""))) | I11: =IF($C11="","",IF($C11="Work",IFERROR(SUMIFS(WORK_FACTOR_APPLICABILITY!$O:$O,WORK_FACTOR_APPLICABILITY!$A:$A,$D11,WORK_FACTOR_APPLICABILITY!$N:$N,$A11),1),IF($C11="Material",IFERROR(ROUND(1+SUMIFS(MATERIAL_FACTOR_APPLICABILITY!$D:$D,MATERIAL_FACTOR_APPLICABILITY!$A:$A,SUMIFS(MATERIAL_MASTER!$O:$O,MATERIAL_MASTER!$A:$A,$D11),MATERIAL_FACTOR_APPLICABILITY!$B:$B,"GeometryComplexity")*(SUMIFS(OBJECT_CONDITIONS!$W:$W,OBJECT_CONDITIONS!$A:$A,$A11)-1),3),1),""))) | J11: =IF($C11="","",IF($C11="Work",IFERROR(IF(SUMIFS(WORK_TARIFF_RULES!$F:$F,WORK_TARIFF_RULES!$A:$A,$D11,WORK_TARIFF_RULES!$C:$C,$B11)<>"",SUMIFS(WORK_TARIFF_RULES!$F:$F,WORK_TARIFF_RULES!$A:$A,$D11,WORK_TARIFF_RULES!$C:$C,$B11),SUMIFS(TARIFF_PROFILES!$D:$D,TARIFF_PROFILES!$A:$A,$B11)),1),IF($C11="Material",IFERROR(IF(SUMIFS(MATERIAL_TARIFF_RULES!$E:$E,MATERIAL_TARIFF_RULES!$A:$A,$D11,MATERIAL_TARIFF_RULES!$C:$C,$B11)<>"",SUMIFS(MATERIAL_TARIFF_RULES!$E:$E,MATERIAL_TARIFF_RULES!$A:$A,$D11,MATERIAL_TARIFF_RULES!$C:$C,$B11),SUMIFS(TARIFF_PROFILES!$E:$E,TARIFF_PROFILES!$A:$A,$B11)),1),""))) | K11: =IF($C11="","",IF($C11="Material",IFERROR(SUMIFS(MATERIAL_MASTER!$P:$P,MATERIAL_MASTER!$A:$A,$D11)*IF(SUMIFS(MATERIAL_TARIFF_RULES!$F:$F,MATERIAL_TARIFF_RULES!$A:$A,$D11,MATERIAL_TARIFF_RULES!$C:$C,$B11)="",SUMIFS(TARIFF_PROFILES!$H:$H,TARIFF_PROFILES!$A:$A,$B11),SUMIFS(MATERIAL_TARIFF_RULES!$F:$F,MATERIAL_TARIFF_RULES!$A:$A,$D11,MATERIAL_TARIFF_RULES!$C:$C,$B11)),1),1)) | L11: =IF($C11="","",IF($C11="Work",N($H11)*N($I11)*N($J11),IF($C11="Material",N($H11)*N($I11)*N($J11),""))) | M11: =IF($C11="","",IF($C11="Material",N($G11)*N($K11),N($G11))) | N11: =IF($C11="","",N($L11)*N($M11)) | O11: =IF($C11="","",IF($C11="Work","Тариф влияет на способ/детализацию и коэффициент работ",IF($C11="Material","Тариф влияет на вариант, качество, запас и показ материала","")))
F12: =IF($C12="","",IF($C12="Work",IFERROR(IF(SUMIFS(WORK_TARIFF_RULES!$G:$G,WORK_TARIFF_RULES!$A:$A,$D12,WORK_TARIFF_RULES!$C:$C,$B12)<>"",SUMIFS(WORK_TARIFF_RULES!$G:$G,WORK_TARIFF_RULES!$A:$A,$D12,WORK_TARIFF_RULES!$C:$C,$B12),SUMIFS(WORK_MASTER!$C:$C,WORK_MASTER!$A:$A,$D12)),""),IF($C12="Material",IFERROR(IF(SUMIFS(MATERIAL_TARIFF_RULES!$G:$G,MATERIAL_TARIFF_RULES!$A:$A,$D12,MATERIAL_TARIFF_RULES!$C:$C,$B12)<>"",SUMIFS(MATERIAL_TARIFF_RULES!$G:$G,MATERIAL_TARIFF_RULES!$A:$A,$D12,MATERIAL_TARIFF_RULES!$C:$C,$B12),SUMIFS(MATERIAL_VARIANTS!$J:$J,MATERIAL_VARIANTS!$A:$A,$E12)),""),""))) | H12: =IF($C12="","",IF($C12="Work",IFERROR(SUMIFS(WORK_MASTER!$I:$I,WORK_MASTER!$A:$A,$D12),""),IF($C12="Material",IFERROR(SUMIFS(MATERIAL_VARIANTS!$I:$I,MATERIAL_VARIANTS!$A:$A,$E12),""),""))) | I12: =IF($C12="","",IF($C12="Work",IFERROR(SUMIFS(WORK_FACTOR_APPLICABILITY!$O:$O,WORK_FACTOR_APPLICABILITY!$A:$A,$D12,WORK_FACTOR_APPLICABILITY!$N:$N,$A12),1),IF($C12="Material",IFERROR(ROUND(1+SUMIFS(MATERIAL_FACTOR_APPLICABILITY!$D:$D,MATERIAL_FACTOR_APPLICABILITY!$A:$A,SUMIFS(MATERIAL_MASTER!$O:$O,MATERIAL_MASTER!$A:$A,$D12),MATERIAL_FACTOR_APPLICABILITY!$B:$B,"GeometryComplexity")*(SUMIFS(OBJECT_CONDITIONS!$W:$W,OBJECT_CONDITIONS!$A:$A,$A12)-1),3),1),""))) | J12: =IF($C12="","",IF($C12="Work",IFERROR(IF(SUMIFS(WORK_TARIFF_RULES!$F:$F,WORK_TARIFF_RULES!$A:$A,$D12,WORK_TARIFF_RULES!$C:$C,$B12)<>"",SUMIFS(WORK_TARIFF_RULES!$F:$F,WORK_TARIFF_RULES!$A:$A,$D12,WORK_TARIFF_RULES!$C:$C,$B12),SUMIFS(TARIFF_PROFILES!$D:$D,TARIFF_PROFILES!$A:$A,$B12)),1),IF($C12="Material",IFERROR(IF(SUMIFS(MATERIAL_TARIFF_RULES!$E:$E,MATERIAL_TARIFF_RULES!$A:$A,$D12,MATERIAL_TARIFF_RULES!$C:$C,$B12)<>"",SUMIFS(MATERIAL_TARIFF_RULES!$E:$E,MATERIAL_TARIFF_RULES!$A:$A,$D12,MATERIAL_TARIFF_RULES!$C:$C,$B12),SUMIFS(TARIFF_PROFILES!$E:$E,TARIFF_PROFILES!$A:$A,$B12)),1),""))) | K12: =IF($C12="","",IF($C12="Material",IFERROR(SUMIFS(MATERIAL_MASTER!$P:$P,MATERIAL_MASTER!$A:$A,$D12)*IF(SUMIFS(MATERIAL_TARIFF_RULES!$F:$F,MATERIAL_TARIFF_RULES!$A:$A,$D12,MATERIAL_TARIFF_RULES!$C:$C,$B12)="",SUMIFS(TARIFF_PROFILES!$H:$H,TARIFF_PROFILES!$A:$A,$B12),SUMIFS(MATERIAL_TARIFF_RULES!$F:$F,MATERIAL_TARIFF_RULES!$A:$A,$D12,MATERIAL_TARIFF_RULES!$C:$C,$B12)),1),1)) | L12: =IF($C12="","",IF($C12="Work",N($H12)*N($I12)*N($J12),IF($C12="Material",N($H12)*N($I12)*N($J12),""))) | M12: =IF($C12="","",IF($C12="Material",N($G12)*N($K12),N($G12))) | N12: =IF($C12="","",N($L12)*N($M12)) | O12: =IF($C12="","",IF($C12="Work","Тариф влияет на способ/детализацию и коэффициент работ",IF($C12="Material","Тариф влияет на вариант, качество, запас и показ материала","")))
F13: =IF($C13="","",IF($C13="Work",IFERROR(IF(SUMIFS(WORK_TARIFF_RULES!$G:$G,WORK_TARIFF_RULES!$A:$A,$D13,WORK_TARIFF_RULES!$C:$C,$B13)<>"",SUMIFS(WORK_TARIFF_RULES!$G:$G,WORK_TARIFF_RULES!$A:$A,$D13,WORK_TARIFF_RULES!$C:$C,$B13),SUMIFS(WORK_MASTER!$C:$C,WORK_MASTER!$A:$A,$D13)),""),IF($C13="Material",IFERROR(IF(SUMIFS(MATERIAL_TARIFF_RULES!$G:$G,MATERIAL_TARIFF_RULES!$A:$A,$D13,MATERIAL_TARIFF_RULES!$C:$C,$B13)<>"",SUMIFS(MATERIAL_TARIFF_RULES!$G:$G,MATERIAL_TARIFF_RULES!$A:$A,$D13,MATERIAL_TARIFF_RULES!$C:$C,$B13),SUMIFS(MATERIAL_VARIANTS!$J:$J,MATERIAL_VARIANTS!$A:$A,$E13)),""),""))) | H13: =IF($C13="","",IF($C13="Work",IFERROR(SUMIFS(WORK_MASTER!$I:$I,WORK_MASTER!$A:$A,$D13),""),IF($C13="Material",IFERROR(SUMIFS(MATERIAL_VARIANTS!$I:$I,MATERIAL_VARIANTS!$A:$A,$E13),""),""))) | I13: =IF($C13="","",IF($C13="Work",IFERROR(SUMIFS(WORK_FACTOR_APPLICABILITY!$O:$O,WORK_FACTOR_APPLICABILITY!$A:$A,$D13,WORK_FACTOR_APPLICABILITY!$N:$N,$A13),1),IF($C13="Material",IFERROR(ROUND(1+SUMIFS(MATERIAL_FACTOR_APPLICABILITY!$D:$D,MATERIAL_FACTOR_APPLICABILITY!$A:$A,SUMIFS(MATERIAL_MASTER!$O:$O,MATERIAL_MASTER!$A:$A,$D13),MATERIAL_FACTOR_APPLICABILITY!$B:$B,"GeometryComplexity")*(SUMIFS(OBJECT_CONDITIONS!$W:$W,OBJECT_CONDITIONS!$A:$A,$A13)-1),3),1),""))) | J13: =IF($C13="","",IF($C13="Work",IFERROR(IF(SUMIFS(WORK_TARIFF_RULES!$F:$F,WORK_TARIFF_RULES!$A:$A,$D13,WORK_TARIFF_RULES!$C:$C,$B13)<>"",SUMIFS(WORK_TARIFF_RULES!$F:$F,WORK_TARIFF_RULES!$A:$A,$D13,WORK_TARIFF_RULES!$C:$C,$B13),SUMIFS(TARIFF_PROFILES!$D:$D,TARIFF_PROFILES!$A:$A,$B13)),1),IF($C13="Material",IFERROR(IF(SUMIFS(MATERIAL_TARIFF_RULES!$E:$E,MATERIAL_TARIFF_RULES!$A:$A,$D13,MATERIAL_TARIFF_RULES!$C:$C,$B13)<>"",SUMIFS(MATERIAL_TARIFF_RULES!$E:$E,MATERIAL_TARIFF_RULES!$A:$A,$D13,MATERIAL_TARIFF_RULES!$C:$C,$B13),SUMIFS(TARIFF_PROFILES!$E:$E,TARIFF_PROFILES!$A:$A,$B13)),1),""))) | K13: =IF($C13="","",IF($C13="Material",IFERROR(SUMIFS(MATERIAL_MASTER!$P:$P,MATERIAL_MASTER!$A:$A,$D13)*IF(SUMIFS(MATERIAL_TARIFF_RULES!$F:$F,MATERIAL_TARIFF_RULES!$A:$A,$D13,MATERIAL_TARIFF_RULES!$C:$C,$B13)="",SUMIFS(TARIFF_PROFILES!$H:$H,TARIFF_PROFILES!$A:$A,$B13),SUMIFS(MATERIAL_TARIFF_RULES!$F:$F,MATERIAL_TARIFF_RULES!$A:$A,$D13,MATERIAL_TARIFF_RULES!$C:$C,$B13)),1),1)) | L13: =IF($C13="","",IF($C13="Work",N($H13)*N($I13)*N($J13),IF($C13="Material",N($H13)*N($I13)*N($J13),""))) | M13: =IF($C13="","",IF($C13="Material",N($G13)*N($K13),N($G13))) | N13: =IF($C13="","",N($L13)*N($M13)) | O13: =IF($C13="","",IF($C13="Work","Тариф влияет на способ/детализацию и коэффициент работ",IF($C13="Material","Тариф влияет на вариант, качество, запас и показ материала","")))
F14: =IF($C14="","",IF($C14="Work",IFERROR(IF(SUMIFS(WORK_TARIFF_RULES!$G:$G,WORK_TARIFF_RULES!$A:$A,$D14,WORK_TARIFF_RULES!$C:$C,$B14)<>"",SUMIFS(WORK_TARIFF_RULES!$G:$G,WORK_TARIFF_RULES!$A:$A,$D14,WORK_TARIFF_RULES!$C:$C,$B14),SUMIFS(WORK_MASTER!$C:$C,WORK_MASTER!$A:$A,$D14)),""),IF($C14="Material",IFERROR(IF(SUMIFS(MATERIAL_TARIFF_RULES!$G:$G,MATERIAL_TARIFF_RULES!$A:$A,$D14,MATERIAL_TARIFF_RULES!$C:$C,$B14)<>"",SUMIFS(MATERIAL_TARIFF_RULES!$G:$G,MATERIAL_TARIFF_RULES!$A:$A,$D14,MATERIAL_TARIFF_RULES!$C:$C,$B14),SUMIFS(MATERIAL_VARIANTS!$J:$J,MATERIAL_VARIANTS!$A:$A,$E14)),""),""))) | H14: =IF($C14="","",IF($C14="Work",IFERROR(SUMIFS(WORK_MASTER!$I:$I,WORK_MASTER!$A:$A,$D14),""),IF($C14="Material",IFERROR(SUMIFS(MATERIAL_VARIANTS!$I:$I,MATERIAL_VARIANTS!$A:$A,$E14),""),""))) | I14: =IF($C14="","",IF($C14="Work",IFERROR(SUMIFS(WORK_FACTOR_APPLICABILITY!$O:$O,WORK_FACTOR_APPLICABILITY!$A:$A,$D14,WORK_FACTOR_APPLICABILITY!$N:$N,$A14),1),IF($C14="Material",IFERROR(ROUND(1+SUMIFS(MATERIAL_FACTOR_APPLICABILITY!$D:$D,MATERIAL_FACTOR_APPLICABILITY!$A:$A,SUMIFS(MATERIAL_MASTER!$O:$O,MATERIAL_MASTER!$A:$A,$D14),MATERIAL_FACTOR_APPLICABILITY!$B:$B,"GeometryComplexity")*(SUMIFS(OBJECT_CONDITIONS!$W:$W,OBJECT_CONDITIONS!$A:$A,$A14)-1),3),1),""))) | J14: =IF($C14="","",IF($C14="Work",IFERROR(IF(SUMIFS(WORK_TARIFF_RULES!$F:$F,WORK_TARIFF_RULES!$A:$A,$D14,WORK_TARIFF_RULES!$C:$C,$B14)<>"",SUMIFS(WORK_TARIFF_RULES!$F:$F,WORK_TARIFF_RULES!$A:$A,$D14,WORK_TARIFF_RULES!$C:$C,$B14),SUMIFS(TARIFF_PROFILES!$D:$D,TARIFF_PROFILES!$A:$A,$B14)),1),IF($C14="Material",IFERROR(IF(SUMIFS(MATERIAL_TARIFF_RULES!$E:$E,MATERIAL_TARIFF_RULES!$A:$A,$D14,MATERIAL_TARIFF_RULES!$C:$C,$B14)<>"",SUMIFS(MATERIAL_TARIFF_RULES!$E:$E,MATERIAL_TARIFF_RULES!$A:$A,$D14,MATERIAL_TARIFF_RULES!$C:$C,$B14),SUMIFS(TARIFF_PROFILES!$E:$E,TARIFF_PROFILES!$A:$A,$B14)),1),""))) | K14: =IF($C14="","",IF($C14="Material",IFERROR(SUMIFS(MATERIAL_MASTER!$P:$P,MATERIAL_MASTER!$A:$A,$D14)*IF(SUMIFS(MATERIAL_TARIFF_RULES!$F:$F,MATERIAL_TARIFF_RULES!$A:$A,$D14,MATERIAL_TARIFF_RULES!$C:$C,$B14)="",SUMIFS(TARIFF_PROFILES!$H:$H,TARIFF_PROFILES!$A:$A,$B14),SUMIFS(MATERIAL_TARIFF_RULES!$F:$F,MATERIAL_TARIFF_RULES!$A:$A,$D14,MATERIAL_TARIFF_RULES!$C:$C,$B14)),1),1)) | L14: =IF($C14="","",IF($C14="Work",N($H14)*N($I14)*N($J14),IF($C14="Material",N($H14)*N($I14)*N($J14),""))) | M14: =IF($C14="","",IF($C14="Material",N($G14)*N($K14),N($G14))) | N14: =IF($C14="","",N($L14)*N($M14)) | O14: =IF($C14="","",IF($C14="Work","Тариф влияет на способ/детализацию и коэффициент работ",IF($C14="Material","Тариф влияет на вариант, качество, запас и показ материала","")))
F15: =IF($C15="","",IF($C15="Work",IFERROR(IF(SUMIFS(WORK_TARIFF_RULES!$G:$G,WORK_TARIFF_RULES!$A:$A,$D15,WORK_TARIFF_RULES!$C:$C,$B15)<>"",SUMIFS(WORK_TARIFF_RULES!$G:$G,WORK_TARIFF_RULES!$A:$A,$D15,WORK_TARIFF_RULES!$C:$C,$B15),SUMIFS(WORK_MASTER!$C:$C,WORK_MASTER!$A:$A,$D15)),""),IF($C15="Material",IFERROR(IF(SUMIFS(MATERIAL_TARIFF_RULES!$G:$G,MATERIAL_TARIFF_RULES!$A:$A,$D15,MATERIAL_TARIFF_RULES!$C:$C,$B15)<>"",SUMIFS(MATERIAL_TARIFF_RULES!$G:$G,MATERIAL_TARIFF_RULES!$A:$A,$D15,MATERIAL_TARIFF_RULES!$C:$C,$B15),SUMIFS(MATERIAL_VARIANTS!$J:$J,MATERIAL_VARIANTS!$A:$A,$E15)),""),""))) | H15: =IF($C15="","",IF($C15="Work",IFERROR(SUMIFS(WORK_MASTER!$I:$I,WORK_MASTER!$A:$A,$D15),""),IF($C15="Material",IFERROR(SUMIFS(MATERIAL_VARIANTS!$I:$I,MATERIAL_VARIANTS!$A:$A,$E15),""),""))) | I15: =IF($C15="","",IF($C15="Work",IFERROR(SUMIFS(WORK_FACTOR_APPLICABILITY!$O:$O,WORK_FACTOR_APPLICABILITY!$A:$A,$D15,WORK_FACTOR_APPLICABILITY!$N:$N,$A15),1),IF($C15="Material",IFERROR(ROUND(1+SUMIFS(MATERIAL_FACTOR_APPLICABILITY!$D:$D,MATERIAL_FACTOR_APPLICABILITY!$A:$A,SUMIFS(MATERIAL_MASTER!$O:$O,MATERIAL_MASTER!$A:$A,$D15),MATERIAL_FACTOR_APPLICABILITY!$B:$B,"GeometryComplexity")*(SUMIFS(OBJECT_CONDITIONS!$W:$W,OBJECT_CONDITIONS!$A:$A,$A15)-1),3),1),""))) | J15: =IF($C15="","",IF($C15="Work",IFERROR(IF(SUMIFS(WORK_TARIFF_RULES!$F:$F,WORK_TARIFF_RULES!$A:$A,$D15,WORK_TARIFF_RULES!$C:$C,$B15)<>"",SUMIFS(WORK_TARIFF_RULES!$F:$F,WORK_TARIFF_RULES!$A:$A,$D15,WORK_TARIFF_RULES!$C:$C,$B15),SUMIFS(TARIFF_PROFILES!$D:$D,TARIFF_PROFILES!$A:$A,$B15)),1),IF($C15="Material",IFERROR(IF(SUMIFS(MATERIAL_TARIFF_RULES!$E:$E,MATERIAL_TARIFF_RULES!$A:$A,$D15,MATERIAL_TARIFF_RULES!$C:$C,$B15)<>"",SUMIFS(MATERIAL_TARIFF_RULES!$E:$E,MATERIAL_TARIFF_RULES!$A:$A,$D15,MATERIAL_TARIFF_RULES!$C:$C,$B15),SUMIFS(TARIFF_PROFILES!$E:$E,TARIFF_PROFILES!$A:$A,$B15)),1),""))) | K15: =IF($C15="","",IF($C15="Material",IFERROR(SUMIFS(MATERIAL_MASTER!$P:$P,MATERIAL_MASTER!$A:$A,$D15)*IF(SUMIFS(MATERIAL_TARIFF_RULES!$F:$F,MATERIAL_TARIFF_RULES!$A:$A,$D15,MATERIAL_TARIFF_RULES!$C:$C,$B15)="",SUMIFS(TARIFF_PROFILES!$H:$H,TARIFF_PROFILES!$A:$A,$B15),SUMIFS(MATERIAL_TARIFF_RULES!$F:$F,MATERIAL_TARIFF_RULES!$A:$A,$D15,MATERIAL_TARIFF_RULES!$C:$C,$B15)),1),1)) | L15: =IF($C15="","",IF($C15="Work",N($H15)*N($I15)*N($J15),IF($C15="Material",N($H15)*N($I15)*N($J15),""))) | M15: =IF($C15="","",IF($C15="Material",N($G15)*N($K15),N($G15))) | N15: =IF($C15="","",N($L15)*N($M15)) | O15: =IF($C15="","",IF($C15="Work","Тариф влияет на способ/детализацию и коэффициент работ",IF($C15="Material","Тариф влияет на вариант, качество, запас и показ материала","")))
F16: =IF($C16="","",IF($C16="Work",IFERROR(IF(SUMIFS(WORK_TARIFF_RULES!$G:$G,WORK_TARIFF_RULES!$A:$A,$D16,WORK_TARIFF_RULES!$C:$C,$B16)<>"",SUMIFS(WORK_TARIFF_RULES!$G:$G,WORK_TARIFF_RULES!$A:$A,$D16,WORK_TARIFF_RULES!$C:$C,$B16),SUMIFS(WORK_MASTER!$C:$C,WORK_MASTER!$A:$A,$D16)),""),IF($C16="Material",IFERROR(IF(SUMIFS(MATERIAL_TARIFF_RULES!$G:$G,MATERIAL_TARIFF_RULES!$A:$A,$D16,MATERIAL_TARIFF_RULES!$C:$C,$B16)<>"",SUMIFS(MATERIAL_TARIFF_RULES!$G:$G,MATERIAL_TARIFF_RULES!$A:$A,$D16,MATERIAL_TARIFF_RULES!$C:$C,$B16),SUMIFS(MATERIAL_VARIANTS!$J:$J,MATERIAL_VARIANTS!$A:$A,$E16)),""),""))) | H16: =IF($C16="","",IF($C16="Work",IFERROR(SUMIFS(WORK_MASTER!$I:$I,WORK_MASTER!$A:$A,$D16),""),IF($C16="Material",IFERROR(SUMIFS(MATERIAL_VARIANTS!$I:$I,MATERIAL_VARIANTS!$A:$A,$E16),""),""))) | I16: =IF($C16="","",IF($C16="Work",IFERROR(SUMIFS(WORK_FACTOR_APPLICABILITY!$O:$O,WORK_FACTOR_APPLICABILITY!$A:$A,$D16,WORK_FACTOR_APPLICABILITY!$N:$N,$A16),1),IF($C16="Material",IFERROR(ROUND(1+SUMIFS(MATERIAL_FACTOR_APPLICABILITY!$D:$D,MATERIAL_FACTOR_APPLICABILITY!$A:$A,SUMIFS(MATERIAL_MASTER!$O:$O,MATERIAL_MASTER!$A:$A,$D16),MATERIAL_FACTOR_APPLICABILITY!$B:$B,"GeometryComplexity")*(SUMIFS(OBJECT_CONDITIONS!$W:$W,OBJECT_CONDITIONS!$A:$A,$A16)-1),3),1),""))) | J16: =IF($C16="","",IF($C16="Work",IFERROR(IF(SUMIFS(WORK_TARIFF_RULES!$F:$F,WORK_TARIFF_RULES!$A:$A,$D16,WORK_TARIFF_RULES!$C:$C,$B16)<>"",SUMIFS(WORK_TARIFF_RULES!$F:$F,WORK_TARIFF_RULES!$A:$A,$D16,WORK_TARIFF_RULES!$C:$C,$B16),SUMIFS(TARIFF_PROFILES!$D:$D,TARIFF_PROFILES!$A:$A,$B16)),1),IF($C16="Material",IFERROR(IF(SUMIFS(MATERIAL_TARIFF_RULES!$E:$E,MATERIAL_TARIFF_RULES!$A:$A,$D16,MATERIAL_TARIFF_RULES!$C:$C,$B16)<>"",SUMIFS(MATERIAL_TARIFF_RULES!$E:$E,MATERIAL_TARIFF_RULES!$A:$A,$D16,MATERIAL_TARIFF_RULES!$C:$C,$B16),SUMIFS(TARIFF_PROFILES!$E:$E,TARIFF_PROFILES!$A:$A,$B16)),1),""))) | K16: =IF($C16="","",IF($C16="Material",IFERROR(SUMIFS(MATERIAL_MASTER!$P:$P,MATERIAL_MASTER!$A:$A,$D16)*IF(SUMIFS(MATERIAL_TARIFF_RULES!$F:$F,MATERIAL_TARIFF_RULES!$A:$A,$D16,MATERIAL_TARIFF_RULES!$C:$C,$B16)="",SUMIFS(TARIFF_PROFILES!$H:$H,TARIFF_PROFILES!$A:$A,$B16),SUMIFS(MATERIAL_TARIFF_RULES!$F:$F,MATERIAL_TARIFF_RULES!$A:$A,$D16,MATERIAL_TARIFF_RULES!$C:$C,$B16)),1),1)) | L16: =IF($C16="","",IF($C16="Work",N($H16)*N($I16)*N($J16),IF($C16="Material",N($H16)*N($I16)*N($J16),""))) | M16: =IF($C16="","",IF($C16="Material",N($G16)*N($K16),N($G16))) | N16: =IF($C16="","",N($L16)*N($M16)) | O16: =IF($C16="","",IF($C16="Work","Тариф влияет на способ/детализацию и коэффициент работ",IF($C16="Material","Тариф влияет на вариант, качество, запас и показ материала","")))
F17: =IF($C17="","",IF($C17="Work",IFERROR(IF(SUMIFS(WORK_TARIFF_RULES!$G:$G,WORK_TARIFF_RULES!$A:$A,$D17,WORK_TARIFF_RULES!$C:$C,$B17)<>"",SUMIFS(WORK_TARIFF_RULES!$G:$G,WORK_TARIFF_RULES!$A:$A,$D17,WORK_TARIFF_RULES!$C:$C,$B17),SUMIFS(WORK_MASTER!$C:$C,WORK_MASTER!$A:$A,$D17)),""),IF($C17="Material",IFERROR(IF(SUMIFS(MATERIAL_TARIFF_RULES!$G:$G,MATERIAL_TARIFF_RULES!$A:$A,$D17,MATERIAL_TARIFF_RULES!$C:$C,$B17)<>"",SUMIFS(MATERIAL_TARIFF_RULES!$G:$G,MATERIAL_TARIFF_RULES!$A:$A,$D17,MATERIAL_TARIFF_RULES!$C:$C,$B17),SUMIFS(MATERIAL_VARIANTS!$J:$J,MATERIAL_VARIANTS!$A:$A,$E17)),""),""))) | H17: =IF($C17="","",IF($C17="Work",IFERROR(SUMIFS(WORK_MASTER!$I:$I,WORK_MASTER!$A:$A,$D17),""),IF($C17="Material",IFERROR(SUMIFS(MATERIAL_VARIANTS!$I:$I,MATERIAL_VARIANTS!$A:$A,$E17),""),""))) | I17: =IF($C17="","",IF($C17="Work",IFERROR(SUMIFS(WORK_FACTOR_APPLICABILITY!$O:$O,WORK_FACTOR_APPLICABILITY!$A:$A,$D17,WORK_FACTOR_APPLICABILITY!$N:$N,$A17),1),IF($C17="Material",IFERROR(ROUND(1+SUMIFS(MATERIAL_FACTOR_APPLICABILITY!$D:$D,MATERIAL_FACTOR_APPLICABILITY!$A:$A,SUMIFS(MATERIAL_MASTER!$O:$O,MATERIAL_MASTER!$A:$A,$D17),MATERIAL_FACTOR_APPLICABILITY!$B:$B,"GeometryComplexity")*(SUMIFS(OBJECT_CONDITIONS!$W:$W,OBJECT_CONDITIONS!$A:$A,$A17)-1),3),1),""))) | J17: =IF($C17="","",IF($C17="Work",IFERROR(IF(SUMIFS(WORK_TARIFF_RULES!$F:$F,WORK_TARIFF_RULES!$A:$A,$D17,WORK_TARIFF_RULES!$C:$C,$B17)<>"",SUMIFS(WORK_TARIFF_RULES!$F:$F,WORK_TARIFF_RULES!$A:$A,$D17,WORK_TARIFF_RULES!$C:$C,$B17),SUMIFS(TARIFF_PROFILES!$D:$D,TARIFF_PROFILES!$A:$A,$B17)),1),IF($C17="Material",IFERROR(IF(SUMIFS(MATERIAL_TARIFF_RULES!$E:$E,MATERIAL_TARIFF_RULES!$A:$A,$D17,MATERIAL_TARIFF_RULES!$C:$C,$B17)<>"",SUMIFS(MATERIAL_TARIFF_RULES!$E:$E,MATERIAL_TARIFF_RULES!$A:$A,$D17,MATERIAL_TARIFF_RULES!$C:$C,$B17),SUMIFS(TARIFF_PROFILES!$E:$E,TARIFF_PROFILES!$A:$A,$B17)),1),""))) | K17: =IF($C17="","",IF($C17="Material",IFERROR(SUMIFS(MATERIAL_MASTER!$P:$P,MATERIAL_MASTER!$A:$A,$D17)*IF(SUMIFS(MATERIAL_TARIFF_RULES!$F:$F,MATERIAL_TARIFF_RULES!$A:$A,$D17,MATERIAL_TARIFF_RULES!$C:$C,$B17)="",SUMIFS(TARIFF_PROFILES!$H:$H,TARIFF_PROFILES!$A:$A,$B17),SUMIFS(MATERIAL_TARIFF_RULES!$F:$F,MATERIAL_TARIFF_RULES!$A:$A,$D17,MATERIAL_TARIFF_RULES!$C:$C,$B17)),1),1)) | L17: =IF($C17="","",IF($C17="Work",N($H17)*N($I17)*N($J17),IF($C17="Material",N($H17)*N($I17)*N($J17),""))) | M17: =IF($C17="","",IF($C17="Material",N($G17)*N($K17),N($G17))) | N17: =IF($C17="","",N($L17)*N($M17)) | O17: =IF($C17="","",IF($C17="Work","Тариф влияет на способ/детализацию и коэффициент работ",IF($C17="Material","Тариф влияет на вариант, качество, запас и показ материала","")))
... F100: =IF($C100="","",IF($C100="Work",IFERROR(IF(SUMIFS(WORK_TARIFF_RULES!$G:$G,WORK_TARIFF_RULES!$A:$A,$D100,WORK_TARIFF_RULES!$C:$C,$B100)<>"",SUMIFS(WORK_TARIFF_RULES!$G:$G,WORK_TARIFF_RULES!$A:$A,$D100,WORK_TARIFF_RULES!$C:$C,$B100),SUMIFS(WORK_MASTER!$C:$C,WORK_MASTER!$A:$A,$D100)),""),IF($C100="Material",IFERROR(IF(SUMIFS(MATERIAL_TARIFF_RULES!$G:$G,MATERIAL_TARIFF_RULES!$A:$A,$D100,MATERIAL_TARIFF_RULES!$C:$C,$B100)<>"",SUMIFS(MATERIAL_TARIFF_RULES!$G:$G,MATERIAL_TARIFF_RULES!$A:$A,$D100,MATERIAL_TARIFF_RULES!$C:$C,$B100),SUMIFS(MATERIAL_VARIANTS!$J:$J,MATERIAL_VARIANTS!$A:$A,$E100)),""),""))) | H100: =IF($C100="","",IF($C100="Work",IFERROR(SUMIFS(WORK_MASTER!$I:$I,WORK_MASTER!$A:$A,$D100),""),IF($C100="Material",IFERROR(SUMIFS(MATERIAL_VARIANTS!$I:$I,MATERIAL_VARIANTS!$A:$A,$E100),""),""))) | I100: =IF($C100="","",IF($C100="Work",IFERROR(SUMIFS(WORK_FACTOR_APPLICABILITY!$O:$O,WORK_FACTOR_APPLICABILITY!$A:$A,$D100,WORK_FACTOR_APPLICABILITY!$N:$N,$A100),1),IF($C100="Material",IFERROR(ROUND(1+SUMIFS(MATERIAL_FACTOR_APPLICABILITY!$D:$D,MATERIAL_FACTOR_APPLICABILITY!$A:$A,SUMIFS(MATERIAL_MASTER!$O:$O,MATERIAL_MASTER!$A:$A,$D100),MATERIAL_FACTOR_APPLICABILITY!$B:$B,"GeometryComplexity")*(SUMIFS(OBJECT_CONDITIONS!$W:$W,OBJECT_CONDITIONS!$A:$A,$A100)-1),3),1),""))) | J100: =IF($C100="","",IF($C100="Work",IFERROR(IF(SUMIFS(WORK_TARIFF_RULES!$F:$F,WORK_TARIFF_RULES!$A:$A,$D100,WORK_TARIFF_RULES!$C:$C,$B100)<>"",SUMIFS(WORK_TARIFF_RULES!$F:$F,WORK_TARIFF_RULES!$A:$A,$D100,WORK_TARIFF_RULES!$C:$C,$B100),SUMIFS(TARIFF_PROFILES!$D:$D,TARIFF_PROFILES!$A:$A,$B100)),1),IF($C100="Material",IFERROR(IF(SUMIFS(MATERIAL_TARIFF_RULES!$E:$E,MATERIAL_TARIFF_RULES!$A:$A,$D100,MATERIAL_TARIFF_RULES!$C:$C,$B100)<>"",SUMIFS(MATERIAL_TARIFF_RULES!$E:$E,MATERIAL_TARIFF_RULES!$A:$A,$D100,MATERIAL_TARIFF_RULES!$C:$C,$B100),SUMIFS(TARIFF_PROFILES!$E:$E,TARIFF_PROFILES!$A:$A,$B100)),1),""))) | K100: =IF($C100="","",IF($C100="Material",IFERROR(SUMIFS(MATERIAL_MASTER!$P:$P,MATERIAL_MASTER!$A:$A,$D100)*IF(SUMIFS(MATERIAL_TARIFF_RULES!$F:$F,MATERIAL_TARIFF_RULES!$A:$A,$D100,MATERIAL_TARIFF_RULES!$C:$C,$B100)="",SUMIFS(TARIFF_PROFILES!$H:$H,TARIFF_PROFILES!$A:$A,$B100),SUMIFS(MATERIAL_TARIFF_RULES!$F:$F,MATERIAL_TARIFF_RULES!$A:$A,$D100,MATERIAL_TARIFF_RULES!$C:$C,$B100)),1),1)) | L100: =IF($C100="","",IF($C100="Work",N($H100)*N($I100)*N($J100),IF($C100="Material",N($H100)*N($I100)*N($J100),""))) | M100: =IF($C100="","",IF($C100="Material",N($G100)*N($K100),N($G100))) | N100: =IF($C100="","",N($L100)*N($M100)) | O100: =IF($C100="","",IF($C100="Work","Тариф влияет на способ/детализацию и коэффициент работ",IF($C100="Material","Тариф влияет на вариант, качество, запас и показ материала","")))

Sheet KP_ENGINE_V5_EXAMPLE
A1: ObjectID | B1: Tariff | C1: LineType | D1: RefID | E1: VariantID | F1: Description | G1: NetQty | H1: NetUnit | I1: BaseUnitPriceExVAT | J1: MethodOrVariantCoeff | K1: SiteCoeff | L1: OperatingCoeff | M1: TariffCoeff | N1: ReserveCoeff | O1: RoundedPurchaseQty | P1: CommercialFloorAdj | Q1: LineTotalExVAT | R1: TaxMode | S1: VATRate | T1: LineTotalIncVAT | U1: CalcComment
A2: OBJ-0001 | B2: Премиум | C2: Work | D2: WORK-0002 | E2: WV-0002 | F2: =IF($C2="","",IF($C2="Work",IFERROR(IF(SUMIFS(WORK_TARIFF_RULES!$G:$G,WORK_TARIFF_RULES!$A:$A,$D2,WORK_TARIFF_RULES!$C:$C,$B2)<>"",SUMIFS(WORK_TARIFF_RULES!$G:$G,WORK_TARIFF_RULES!$A:$A,$D2,WORK_TARIFF_RULES!$C:$C,$B2),SUMIFS(WORK_MASTER!$C:$C,WORK_MASTER!$A:$A,$D2)),""),IF($C2="Material",IFERROR(IF(SUMIFS(MATERIAL_TARIFF_RULES!$G:$G,MATERIAL_TARIFF_RULES!$A:$A,$D2,MATERIAL_TARIFF_RULES!$C:$C,$B2)<>"",SUMIFS(MATERIAL_TARIFF_RULES!$G:$G,MATERIAL_TARIFF_RULES!$A:$A,$D2,MATERIAL_TARIFF_RULES!$C:$C,$B2),SUMIFS(MATERIAL_VARIANTS!$J:$J,MATERIAL_VARIANTS!$A:$A,$E2)),""),IF($C2="Logistics","Мобилизация и логистика объекта","")))) | G2: 120 | H2: м2 | I2: =IF($C2="","",IF($C2="Work",IFERROR(SUMIFS(WORK_MASTER!$I:$I,WORK_MASTER!$A:$A,$D2),0),IF($C2="Material",IFERROR(SUMIFS(MATERIAL_VARIANTS!$I:$I,MATERIAL_VARIANTS!$A:$A,$E2),0),0))) | J2: =IF($C2="","",IF($C2="Work",IF($E2<>"",IFERROR(SUMIFS(WORK_VARIANTS!$H:$H,WORK_VARIANTS!$A:$A,$E2),1),1),1)) | K2: =IF($C2="","",IF($C2="Work",IFERROR(SUMIFS(WORK_FACTOR_APPLICABILITY!$O:$O,WORK_FACTOR_APPLICABILITY!$A:$A,$D2,WORK_FACTOR_APPLICABILITY!$N:$N,$A2),1),IF($C2="Material",IFERROR(INDEX(MATERIAL_QUANTITY_EXAMPLE!$N:$N,MATCH(1,(MATERIAL_QUANTITY_EXAMPLE!$A:$A=MATERIAL_QUANTITY_EXAMPLE!$A:$A)*(MATERIAL_QUANTITY_EXAMPLE!$B:$B=$A2)*(MATERIAL_QUANTITY_EXAMPLE!$C:$C=$D2),0)),1),1))) | L2: =IF($A2="","",IF($C2="Material",1,IFERROR(INDEX(OBJECT_CONDITIONS!$AH:$AH,MATCH($A2,OBJECT_CONDITIONS!$A:$A,0))*INDEX(OBJECT_CONDITIONS!$AJ:$AJ,MATCH($A2,OBJECT_CONDITIONS!$A:$A,0))*INDEX(OBJECT_CONDITIONS!$AL:$AL,MATCH($A2,OBJECT_CONDITIONS!$A:$A,0)),1))) | M2: =IF($B2="","",IF($C2="Work",IFERROR(IF(SUMIFS(WORK_TARIFF_RULES!$F:$F,WORK_TARIFF_RULES!$A:$A,$D2,WORK_TARIFF_RULES!$C:$C,$B2)<>"",SUMIFS(WORK_TARIFF_RULES!$F:$F,WORK_TARIFF_RULES!$A:$A,$D2,WORK_TARIFF_RULES!$C:$C,$B2),SUMIFS(TARIFF_PROFILES!$D:$D,TARIFF_PROFILES!$A:$A,$B2)),1),IF($C2="Material",IFERROR(IF(SUMIFS(MATERIAL_TARIFF_RULES!$E:$E,MATERIAL_TARIFF_RULES!$A:$A,$D2,MATERIAL_TARIFF_RULES!$C:$C,$B2)<>"",SUMIFS(MATERIAL_TARIFF_RULES!$E:$E,MATERIAL_TARIFF_RULES!$A:$A,$D2,MATERIAL_TARIFF_RULES!$C:$C,$B2),SUMIFS(TARIFF_PROFILES!$E:$E,TARIFF_PROFILES!$A:$A,$B2)),1),SUMIFS(TARIFF_PROFILES!$F:$F,TARIFF_PROFILES!$A:$A,$B2)))) | N2: =IF($C2="Material",IFERROR(SUMIFS(MATERIAL_MASTER!$P:$P,MATERIAL_MASTER!$A:$A,$D2)*IF(SUMIFS(MATERIAL_TARIFF_RULES!$F:$F,MATERIAL_TARIFF_RULES!$A:$A,$D2,MATERIAL_TARIFF_RULES!$C:$C,$B2)="",SUMIFS(TARIFF_PROFILES!$H:$H,TARIFF_PROFILES!$A:$A,$B2),SUMIFS(MATERIAL_TARIFF_RULES!$F:$F,MATERIAL_TARIFF_RULES!$A:$A,$D2,MATERIAL_TARIFF_RULES!$C:$C,$B2)),1),1) | O2: =IF($C2="","",IF($C2="Material",ROUNDUP(N($G2)*N($N2),0),N($G2))) | P2: =IF(ROW()=2,MAX(0,INDEX(COMMERCIAL_POLICY!$B:$B,MATCH($B2,COMMERCIAL_POLICY!$A:$A,0))-SUM($Q$2:$Q$60)),0) | Q2: =IF($C2="","",IF($C2="Material",N($I2)*N($K2)*N($M2)*N($O2),IF($C2="Logistics",INDEX(COMMERCIAL_POLICY!$D:$D,MATCH($B2,COMMERCIAL_POLICY!$A:$A,0))*N($L2),N($I2)*N($J2)*N($K2)*N($L2)*N($M2)*N($G2)))) | R2: =IF($A2="","",INDEX(OBJECT_CONDITIONS!$AM:$AM,MATCH($A2,OBJECT_CONDITIONS!$A:$A,0))) | S2: =IF($R2="","",INDEX(TAX_MODES!$B:$B,MATCH($R2,TAX_MODES!$A:$A,0))) | T2: =IF($Q2="","",N($Q2)*(1+N($S2))) | U2: =IF($C2="","",IF($C2="Material","Net x reserve x rounded purchase logic",IF($C2="Logistics","Mobilization from COMMERCIAL_POLICY x operating coeff","Base x method/variant x site x operating x tariff")) )
A3: OBJ-0001 | B3: Премиум | C3: Material | D3: MAT-0001 | E3: MV-0003 | F3: =IF($C3="","",IF($C3="Work",IFERROR(IF(SUMIFS(WORK_TARIFF_RULES!$G:$G,WORK_TARIFF_RULES!$A:$A,$D3,WORK_TARIFF_RULES!$C:$C,$B3)<>"",SUMIFS(WORK_TARIFF_RULES!$G:$G,WORK_TARIFF_RULES!$A:$A,$D3,WORK_TARIFF_RULES!$C:$C,$B3),SUMIFS(WORK_MASTER!$C:$C,WORK_MASTER!$A:$A,$D3)),""),IF($C3="Material",IFERROR(IF(SUMIFS(MATERIAL_TARIFF_RULES!$G:$G,MATERIAL_TARIFF_RULES!$A:$A,$D3,MATERIAL_TARIFF_RULES!$C:$C,$B3)<>"",SUMIFS(MATERIAL_TARIFF_RULES!$G:$G,MATERIAL_TARIFF_RULES!$A:$A,$D3,MATERIAL_TARIFF_RULES!$C:$C,$B3),SUMIFS(MATERIAL_VARIANTS!$J:$J,MATERIAL_VARIANTS!$A:$A,$E3)),""),IF($C3="Logistics","Мобилизация и логистика объекта","")))) | G3: 120 | H3: м2 | I3: =IF($C3="","",IF($C3="Work",IFERROR(SUMIFS(WORK_MASTER!$I:$I,WORK_MASTER!$A:$A,$D3),0),IF($C3="Material",IFERROR(SUMIFS(MATERIAL_VARIANTS!$I:$I,MATERIAL_VARIANTS!$A:$A,$E3),0),0))) | J3: =IF($C3="","",IF($C3="Work",IF($E3<>"",IFERROR(SUMIFS(WORK_VARIANTS!$H:$H,WORK_VARIANTS!$A:$A,$E3),1),1),1)) | K3: =IF($C3="","",IF($C3="Work",IFERROR(SUMIFS(WORK_FACTOR_APPLICABILITY!$O:$O,WORK_FACTOR_APPLICABILITY!$A:$A,$D3,WORK_FACTOR_APPLICABILITY!$N:$N,$A3),1),IF($C3="Material",IFERROR(INDEX(MATERIAL_QUANTITY_EXAMPLE!$N:$N,MATCH(1,(MATERIAL_QUANTITY_EXAMPLE!$A:$A=MATERIAL_QUANTITY_EXAMPLE!$A:$A)*(MATERIAL_QUANTITY_EXAMPLE!$B:$B=$A3)*(MATERIAL_QUANTITY_EXAMPLE!$C:$C=$D3),0)),1),1))) | L3: =IF($A3="","",IF($C3="Material",1,IFERROR(INDEX(OBJECT_CONDITIONS!$AH:$AH,MATCH($A3,OBJECT_CONDITIONS!$A:$A,0))*INDEX(OBJECT_CONDITIONS!$AJ:$AJ,MATCH($A3,OBJECT_CONDITIONS!$A:$A,0))*INDEX(OBJECT_CONDITIONS!$AL:$AL,MATCH($A3,OBJECT_CONDITIONS!$A:$A,0)),1))) | M3: =IF($B3="","",IF($C3="Work",IFERROR(IF(SUMIFS(WORK_TARIFF_RULES!$F:$F,WORK_TARIFF_RULES!$A:$A,$D3,WORK_TARIFF_RULES!$C:$C,$B3)<>"",SUMIFS(WORK_TARIFF_RULES!$F:$F,WORK_TARIFF_RULES!$A:$A,$D3,WORK_TARIFF_RULES!$C:$C,$B3),SUMIFS(TARIFF_PROFILES!$D:$D,TARIFF_PROFILES!$A:$A,$B3)),1),IF($C3="Material",IFERROR(IF(SUMIFS(MATERIAL_TARIFF_RULES!$E:$E,MATERIAL_TARIFF_RULES!$A:$A,$D3,MATERIAL_TARIFF_RULES!$C:$C,$B3)<>"",SUMIFS(MATERIAL_TARIFF_RULES!$E:$E,MATERIAL_TARIFF_RULES!$A:$A,$D3,MATERIAL_TARIFF_RULES!$C:$C,$B3),SUMIFS(TARIFF_PROFILES!$E:$E,TARIFF_PROFILES!$A:$A,$B3)),1),SUMIFS(TARIFF_PROFILES!$F:$F,TARIFF_PROFILES!$A:$A,$B3)))) | N3: =IF($C3="Material",IFERROR(SUMIFS(MATERIAL_MASTER!$P:$P,MATERIAL_MASTER!$A:$A,$D3)*IF(SUMIFS(MATERIAL_TARIFF_RULES!$F:$F,MATERIAL_TARIFF_RULES!$A:$A,$D3,MATERIAL_TARIFF_RULES!$C:$C,$B3)="",SUMIFS(TARIFF_PROFILES!$H:$H,TARIFF_PROFILES!$A:$A,$B3),SUMIFS(MATERIAL_TARIFF_RULES!$F:$F,MATERIAL_TARIFF_RULES!$A:$A,$D3,MATERIAL_TARIFF_RULES!$C:$C,$B3)),1),1) | O3: =IF($C3="","",IF($C3="Material",ROUNDUP(N($G3)*N($N3),0),N($G3))) | P3: =IF(ROW()=2,MAX(0,INDEX(COMMERCIAL_POLICY!$B:$B,MATCH($B3,COMMERCIAL_POLICY!$A:$A,0))-SUM($Q$2:$Q$60)),0) | Q3: =IF($C3="","",IF($C3="Material",N($I3)*N($K3)*N($M3)*N($O3),IF($C3="Logistics",INDEX(COMMERCIAL_POLICY!$D:$D,MATCH($B3,COMMERCIAL_POLICY!$A:$A,0))*N($L3),N($I3)*N($J3)*N($K3)*N($L3)*N($M3)*N($G3)))) | R3: =IF($A3="","",INDEX(OBJECT_CONDITIONS!$AM:$AM,MATCH($A3,OBJECT_CONDITIONS!$A:$A,0))) | S3: =IF($R3="","",INDEX(TAX_MODES!$B:$B,MATCH($R3,TAX_MODES!$A:$A,0))) | T3: =IF($Q3="","",N($Q3)*(1+N($S3))) | U3: =IF($C3="","",IF($C3="Material","Net x reserve x rounded purchase logic",IF($C3="Logistics","Mobilization from COMMERCIAL_POLICY x operating coeff","Base x method/variant x site x operating x tariff")) )
A4: OBJ-0001 | B4: Премиум | C4: Logistics | D4: LOG-BASE | F4: =IF($C4="","",IF($C4="Work",IFERROR(IF(SUMIFS(WORK_TARIFF_RULES!$G:$G,WORK_TARIFF_RULES!$A:$A,$D4,WORK_TARIFF_RULES!$C:$C,$B4)<>"",SUMIFS(WORK_TARIFF_RULES!$G:$G,WORK_TARIFF_RULES!$A:$A,$D4,WORK_TARIFF_RULES!$C:$C,$B4),SUMIFS(WORK_MASTER!$C:$C,WORK_MASTER!$A:$A,$D4)),""),IF($C4="Material",IFERROR(IF(SUMIFS(MATERIAL_TARIFF_RULES!$G:$G,MATERIAL_TARIFF_RULES!$A:$A,$D4,MATERIAL_TARIFF_RULES!$C:$C,$B4)<>"",SUMIFS(MATERIAL_TARIFF_RULES!$G:$G,MATERIAL_TARIFF_RULES!$A:$A,$D4,MATERIAL_TARIFF_RULES!$C:$C,$B4),SUMIFS(MATERIAL_VARIANTS!$J:$J,MATERIAL_VARIANTS!$A:$A,$E4)),""),IF($C4="Logistics","Мобилизация и логистика объекта","")))) | G4: 1 | H4: компл | I4: =IF($C4="","",IF($C4="Work",IFERROR(SUMIFS(WORK_MASTER!$I:$I,WORK_MASTER!$A:$A,$D4),0),IF($C4="Material",IFERROR(SUMIFS(MATERIAL_VARIANTS!$I:$I,MATERIAL_VARIANTS!$A:$A,$E4),0),0))) | J4: =IF($C4="","",IF($C4="Work",IF($E4<>"",IFERROR(SUMIFS(WORK_VARIANTS!$H:$H,WORK_VARIANTS!$A:$A,$E4),1),1),1)) | K4: =IF($C4="","",IF($C4="Work",IFERROR(SUMIFS(WORK_FACTOR_APPLICABILITY!$O:$O,WORK_FACTOR_APPLICABILITY!$A:$A,$D4,WORK_FACTOR_APPLICABILITY!$N:$N,$A4),1),IF($C4="Material",IFERROR(INDEX(MATERIAL_QUANTITY_EXAMPLE!$N:$N,MATCH(1,(MATERIAL_QUANTITY_EXAMPLE!$A:$A=MATERIAL_QUANTITY_EXAMPLE!$A:$A)*(MATERIAL_QUANTITY_EXAMPLE!$B:$B=$A4)*(MATERIAL_QUANTITY_EXAMPLE!$C:$C=$D4),0)),1),1))) | L4: =IF($A4="","",IF($C4="Material",1,IFERROR(INDEX(OBJECT_CONDITIONS!$AH:$AH,MATCH($A4,OBJECT_CONDITIONS!$A:$A,0))*INDEX(OBJECT_CONDITIONS!$AJ:$AJ,MATCH($A4,OBJECT_CONDITIONS!$A:$A,0))*INDEX(OBJECT_CONDITIONS!$AL:$AL,MATCH($A4,OBJECT_CONDITIONS!$A:$A,0)),1))) | M4: =IF($B4="","",IF($C4="Work",IFERROR(IF(SUMIFS(WORK_TARIFF_RULES!$F:$F,WORK_TARIFF_RULES!$A:$A,$D4,WORK_TARIFF_RULES!$C:$C,$B4)<>"",SUMIFS(WORK_TARIFF_RULES!$F:$F,WORK_TARIFF_RULES!$A:$A,$D4,WORK_TARIFF_RULES!$C:$C,$B4),SUMIFS(TARIFF_PROFILES!$D:$D,TARIFF_PROFILES!$A:$A,$B4)),1),IF($C4="Material",IFERROR(IF(SUMIFS(MATERIAL_TARIFF_RULES!$E:$E,MATERIAL_TARIFF_RULES!$A:$A,$D4,MATERIAL_TARIFF_RULES!$C:$C,$B4)<>"",SUMIFS(MATERIAL_TARIFF_RULES!$E:$E,MATERIAL_TARIFF_RULES!$A:$A,$D4,MATERIAL_TARIFF_RULES!$C:$C,$B4),SUMIFS(TARIFF_PROFILES!$E:$E,TARIFF_PROFILES!$A:$A,$B4)),1),SUMIFS(TARIFF_PROFILES!$F:$F,TARIFF_PROFILES!$A:$A,$B4)))) | N4: =IF($C4="Material",IFERROR(SUMIFS(MATERIAL_MASTER!$P:$P,MATERIAL_MASTER!$A:$A,$D4)*IF(SUMIFS(MATERIAL_TARIFF_RULES!$F:$F,MATERIAL_TARIFF_RULES!$A:$A,$D4,MATERIAL_TARIFF_RULES!$C:$C,$B4)="",SUMIFS(TARIFF_PROFILES!$H:$H,TARIFF_PROFILES!$A:$A,$B4),SUMIFS(MATERIAL_TARIFF_RULES!$F:$F,MATERIAL_TARIFF_RULES!$A:$A,$D4,MATERIAL_TARIFF_RULES!$C:$C,$B4)),1),1) | O4: =IF($C4="","",IF($C4="Material",ROUNDUP(N($G4)*N($N4),0),N($G4))) | P4: =IF(ROW()=2,MAX(0,INDEX(COMMERCIAL_POLICY!$B:$B,MATCH($B4,COMMERCIAL_POLICY!$A:$A,0))-SUM($Q$2:$Q$60)),0) | Q4: =IF($C4="","",IF($C4="Material",N($I4)*N($K4)*N($M4)*N($O4),IF($C4="Logistics",INDEX(COMMERCIAL_POLICY!$D:$D,MATCH($B4,COMMERCIAL_POLICY!$A:$A,0))*N($L4),N($I4)*N($J4)*N($K4)*N($L4)*N($M4)*N($G4)))) | R4: =IF($A4="","",INDEX(OBJECT_CONDITIONS!$AM:$AM,MATCH($A4,OBJECT_CONDITIONS!$A:$A,0))) | S4: =IF($R4="","",INDEX(TAX_MODES!$B:$B,MATCH($R4,TAX_MODES!$A:$A,0))) | T4: =IF($Q4="","",N($Q4)*(1+N($S4))) | U4: =IF($C4="","",IF($C4="Material","Net x reserve x rounded purchase logic",IF($C4="Logistics","Mobilization from COMMERCIAL_POLICY x operating coeff","Base x method/variant x site x operating x tariff")) )
A5: OBJ-0002 | B5: Эконом | C5: Work | D5: WORK-0001 | E5: WV-0001 | F5: =IF($C5="","",IF($C5="Work",IFERROR(IF(SUMIFS(WORK_TARIFF_RULES!$G:$G,WORK_TARIFF_RULES!$A:$A,$D5,WORK_TARIFF_RULES!$C:$C,$B5)<>"",SUMIFS(WORK_TARIFF_RULES!$G:$G,WORK_TARIFF_RULES!$A:$A,$D5,WORK_TARIFF_RULES!$C:$C,$B5),SUMIFS(WORK_MASTER!$C:$C,WORK_MASTER!$A:$A,$D5)),""),IF($C5="Material",IFERROR(IF(SUMIFS(MATERIAL_TARIFF_RULES!$G:$G,MATERIAL_TARIFF_RULES!$A:$A,$D5,MATERIAL_TARIFF_RULES!$C:$C,$B5)<>"",SUMIFS(MATERIAL_TARIFF_RULES!$G:$G,MATERIAL_TARIFF_RULES!$A:$A,$D5,MATERIAL_TARIFF_RULES!$C:$C,$B5),SUMIFS(MATERIAL_VARIANTS!$J:$J,MATERIAL_VARIANTS!$A:$A,$E5)),""),IF($C5="Logistics","Мобилизация и логистика объекта","")))) | G5: 200 | H5: м2 | I5: =IF($C5="","",IF($C5="Work",IFERROR(SUMIFS(WORK_MASTER!$I:$I,WORK_MASTER!$A:$A,$D5),0),IF($C5="Material",IFERROR(SUMIFS(MATERIAL_VARIANTS!$I:$I,MATERIAL_VARIANTS!$A:$A,$E5),0),0))) | J5: =IF($C5="","",IF($C5="Work",IF($E5<>"",IFERROR(SUMIFS(WORK_VARIANTS!$H:$H,WORK_VARIANTS!$A:$A,$E5),1),1),1)) | K5: =IF($C5="","",IF($C5="Work",IFERROR(SUMIFS(WORK_FACTOR_APPLICABILITY!$O:$O,WORK_FACTOR_APPLICABILITY!$A:$A,$D5,WORK_FACTOR_APPLICABILITY!$N:$N,$A5),1),IF($C5="Material",IFERROR(INDEX(MATERIAL_QUANTITY_EXAMPLE!$N:$N,MATCH(1,(MATERIAL_QUANTITY_EXAMPLE!$A:$A=MATERIAL_QUANTITY_EXAMPLE!$A:$A)*(MATERIAL_QUANTITY_EXAMPLE!$B:$B=$A5)*(MATERIAL_QUANTITY_EXAMPLE!$C:$C=$D5),0)),1),1))) | L5: =IF($A5="","",IF($C5="Material",1,IFERROR(INDEX(OBJECT_CONDITIONS!$AH:$AH,MATCH($A5,OBJECT_CONDITIONS!$A:$A,0))*INDEX(OBJECT_CONDITIONS!$AJ:$AJ,MATCH($A5,OBJECT_CONDITIONS!$A:$A,0))*INDEX(OBJECT_CONDITIONS!$AL:$AL,MATCH($A5,OBJECT_CONDITIONS!$A:$A,0)),1))) | M5: =IF($B5="","",IF($C5="Work",IFERROR(IF(SUMIFS(WORK_TARIFF_RULES!$F:$F,WORK_TARIFF_RULES!$A:$A,$D5,WORK_TARIFF_RULES!$C:$C,$B5)<>"",SUMIFS(WORK_TARIFF_RULES!$F:$F,WORK_TARIFF_RULES!$A:$A,$D5,WORK_TARIFF_RULES!$C:$C,$B5),SUMIFS(TARIFF_PROFILES!$D:$D,TARIFF_PROFILES!$A:$A,$B5)),1),IF($C5="Material",IFERROR(IF(SUMIFS(MATERIAL_TARIFF_RULES!$E:$E,MATERIAL_TARIFF_RULES!$A:$A,$D5,MATERIAL_TARIFF_RULES!$C:$C,$B5)<>"",SUMIFS(MATERIAL_TARIFF_RULES!$E:$E,MATERIAL_TARIFF_RULES!$A:$A,$D5,MATERIAL_TARIFF_RULES!$C:$C,$B5),SUMIFS(TARIFF_PROFILES!$E:$E,TARIFF_PROFILES!$A:$A,$B5)),1),SUMIFS(TARIFF_PROFILES!$F:$F,TARIFF_PROFILES!$A:$A,$B5)))) | N5: =IF($C5="Material",IFERROR(SUMIFS(MATERIAL_MASTER!$P:$P,MATERIAL_MASTER!$A:$A,$D5)*IF(SUMIFS(MATERIAL_TARIFF_RULES!$F:$F,MATERIAL_TARIFF_RULES!$A:$A,$D5,MATERIAL_TARIFF_RULES!$C:$C,$B5)="",SUMIFS(TARIFF_PROFILES!$H:$H,TARIFF_PROFILES!$A:$A,$B5),SUMIFS(MATERIAL_TARIFF_RULES!$F:$F,MATERIAL_TARIFF_RULES!$A:$A,$D5,MATERIAL_TARIFF_RULES!$C:$C,$B5)),1),1) | O5: =IF($C5="","",IF($C5="Material",ROUNDUP(N($G5)*N($N5),0),N($G5))) | P5: =IF(ROW()=2,MAX(0,INDEX(COMMERCIAL_POLICY!$B:$B,MATCH($B5,COMMERCIAL_POLICY!$A:$A,0))-SUM($Q$2:$Q$60)),0) | Q5: =IF($C5="","",IF($C5="Material",N($I5)*N($K5)*N($M5)*N($O5),IF($C5="Logistics",INDEX(COMMERCIAL_POLICY!$D:$D,MATCH($B5,COMMERCIAL_POLICY!$A:$A,0))*N($L5),N($I5)*N($J5)*N($K5)*N($L5)*N($M5)*N($G5)))) | R5: =IF($A5="","",INDEX(OBJECT_CONDITIONS!$AM:$AM,MATCH($A5,OBJECT_CONDITIONS!$A:$A,0))) | S5: =IF($R5="","",INDEX(TAX_MODES!$B:$B,MATCH($R5,TAX_MODES!$A:$A,0))) | T5: =IF($Q5="","",N($Q5)*(1+N($S5))) | U5: =IF($C5="","",IF($C5="Material","Net x reserve x rounded purchase logic",IF($C5="Logistics","Mobilization from COMMERCIAL_POLICY x operating coeff","Base x method/variant x site x operating x tariff")) )
F6: =IF($C6="","",IF($C6="Work",IFERROR(IF(SUMIFS(WORK_TARIFF_RULES!$G:$G,WORK_TARIFF_RULES!$A:$A,$D6,WORK_TARIFF_RULES!$C:$C,$B6)<>"",SUMIFS(WORK_TARIFF_RULES!$G:$G,WORK_TARIFF_RULES!$A:$A,$D6,WORK_TARIFF_RULES!$C:$C,$B6),SUMIFS(WORK_MASTER!$C:$C,WORK_MASTER!$A:$A,$D6)),""),IF($C6="Material",IFERROR(IF(SUMIFS(MATERIAL_TARIFF_RULES!$G:$G,MATERIAL_TARIFF_RULES!$A:$A,$D6,MATERIAL_TARIFF_RULES!$C:$C,$B6)<>"",SUMIFS(MATERIAL_TARIFF_RULES!$G:$G,MATERIAL_TARIFF_RULES!$A:$A,$D6,MATERIAL_TARIFF_RULES!$C:$C,$B6),SUMIFS(MATERIAL_VARIANTS!$J:$J,MATERIAL_VARIANTS!$A:$A,$E6)),""),IF($C6="Logistics","Мобилизация и логистика объекта","")))) | I6: =IF($C6="","",IF($C6="Work",IFERROR(SUMIFS(WORK_MASTER!$I:$I,WORK_MASTER!$A:$A,$D6),0),IF($C6="Material",IFERROR(SUMIFS(MATERIAL_VARIANTS!$I:$I,MATERIAL_VARIANTS!$A:$A,$E6),0),0))) | J6: =IF($C6="","",IF($C6="Work",IF($E6<>"",IFERROR(SUMIFS(WORK_VARIANTS!$H:$H,WORK_VARIANTS!$A:$A,$E6),1),1),1)) | K6: =IF($C6="","",IF($C6="Work",IFERROR(SUMIFS(WORK_FACTOR_APPLICABILITY!$O:$O,WORK_FACTOR_APPLICABILITY!$A:$A,$D6,WORK_FACTOR_APPLICABILITY!$N:$N,$A6),1),IF($C6="Material",IFERROR(INDEX(MATERIAL_QUANTITY_EXAMPLE!$N:$N,MATCH(1,(MATERIAL_QUANTITY_EXAMPLE!$A:$A=MATERIAL_QUANTITY_EXAMPLE!$A:$A)*(MATERIAL_QUANTITY_EXAMPLE!$B:$B=$A6)*(MATERIAL_QUANTITY_EXAMPLE!$C:$C=$D6),0)),1),1))) | L6: =IF($A6="","",IF($C6="Material",1,IFERROR(INDEX(OBJECT_CONDITIONS!$AH:$AH,MATCH($A6,OBJECT_CONDITIONS!$A:$A,0))*INDEX(OBJECT_CONDITIONS!$AJ:$AJ,MATCH($A6,OBJECT_CONDITIONS!$A:$A,0))*INDEX(OBJECT_CONDITIONS!$AL:$AL,MATCH($A6,OBJECT_CONDITIONS!$A:$A,0)),1))) | M6: =IF($B6="","",IF($C6="Work",IFERROR(IF(SUMIFS(WORK_TARIFF_RULES!$F:$F,WORK_TARIFF_RULES!$A:$A,$D6,WORK_TARIFF_RULES!$C:$C,$B6)<>"",SUMIFS(WORK_TARIFF_RULES!$F:$F,WORK_TARIFF_RULES!$A:$A,$D6,WORK_TARIFF_RULES!$C:$C,$B6),SUMIFS(TARIFF_PROFILES!$D:$D,TARIFF_PROFILES!$A:$A,$B6)),1),IF($C6="Material",IFERROR(IF(SUMIFS(MATERIAL_TARIFF_RULES!$E:$E,MATERIAL_TARIFF_RULES!$A:$A,$D6,MATERIAL_TARIFF_RULES!$C:$C,$B6)<>"",SUMIFS(MATERIAL_TARIFF_RULES!$E:$E,MATERIAL_TARIFF_RULES!$A:$A,$D6,MATERIAL_TARIFF_RULES!$C:$C,$B6),SUMIFS(TARIFF_PROFILES!$E:$E,TARIFF_PROFILES!$A:$A,$B6)),1),SUMIFS(TARIFF_PROFILES!$F:$F,TARIFF_PROFILES!$A:$A,$B6)))) | N6: =IF($C6="Material",IFERROR(SUMIFS(MATERIAL_MASTER!$P:$P,MATERIAL_MASTER!$A:$A,$D6)*IF(SUMIFS(MATERIAL_TARIFF_RULES!$F:$F,MATERIAL_TARIFF_RULES!$A:$A,$D6,MATERIAL_TARIFF_RULES!$C:$C,$B6)="",SUMIFS(TARIFF_PROFILES!$H:$H,TARIFF_PROFILES!$A:$A,$B6),SUMIFS(MATERIAL_TARIFF_RULES!$F:$F,MATERIAL_TARIFF_RULES!$A:$A,$D6,MATERIAL_TARIFF_RULES!$C:$C,$B6)),1),1) | O6: =IF($C6="","",IF($C6="Material",ROUNDUP(N($G6)*N($N6),0),N($G6))) | P6: =IF(ROW()=2,MAX(0,INDEX(COMMERCIAL_POLICY!$B:$B,MATCH($B6,COMMERCIAL_POLICY!$A:$A,0))-SUM($Q$2:$Q$60)),0) | Q6: =IF($C6="","",IF($C6="Material",N($I6)*N($K6)*N($M6)*N($O6),IF($C6="Logistics",INDEX(COMMERCIAL_POLICY!$D:$D,MATCH($B6,COMMERCIAL_POLICY!$A:$A,0))*N($L6),N($I6)*N($J6)*N($K6)*N($L6)*N($M6)*N($G6)))) | R6: =IF($A6="","",INDEX(OBJECT_CONDITIONS!$AM:$AM,MATCH($A6,OBJECT_CONDITIONS!$A:$A,0))) | S6: =IF($R6="","",INDEX(TAX_MODES!$B:$B,MATCH($R6,TAX_MODES!$A:$A,0))) | T6: =IF($Q6="","",N($Q6)*(1+N($S6))) | U6: =IF($C6="","",IF($C6="Material","Net x reserve x rounded purchase logic",IF($C6="Logistics","Mobilization from COMMERCIAL_POLICY x operating coeff","Base x method/variant x site x operating x tariff")) )
