Workbook

Sheet Расчет
A1: print_flag | B1: section_no | C1: section_name | D1: subsection_name | E1: row_type | F1: sort_order | G1: item_name | H1: unit | I1: qty | J1: unit_price | K1: works_amount | L1: materials_amount | M1: note
A2: да | B2: 1 | C2: Подготовительные земельные работы | E2: work | F2: 1 | G2: Разметка и нивелировка площадей, задание вертикальных уровней и уклона (геодезическая разбивка) | H2: м.кв. | I2: 2540 | J2: 100 | K2: =IF(OR(E2="work",E2="section14_item"),I2*J2,0) | L2: =IF(E2="material",I2*J2,IF(E2="section15_percent",I2/100*(SUMPRODUCT((E$2:E$5000="work")*(B$2:B$5000<>"14")*K$2:K$5000)+SUMPRODUCT((E$2:E$5000="material")*(B$2:B$5000<>"14")*L$2:L$5000)),IF(E2="section15_manual",J2,0)))
A3: да | B3: 1 | C3: Подготовительные земельные работы | E3: work | F3: 2 | G3: Выемка и перемещение грунта и щебня существующего основания для устройства мощения | H3: м.куб. | I3: 110 | J3: 100 | K3: =IF(OR(E3="work",E3="section14_item"),I3*J3,0) | L3: =IF(E3="material",I3*J3,IF(E3="section15_percent",I3/100*(SUMPRODUCT((E$2:E$5000="work")*(B$2:B$5000<>"14")*K$2:K$5000)+SUMPRODUCT((E$2:E$5000="material")*(B$2:B$5000<>"14")*L$2:L$5000)),IF(E3="section15_manual",J3,0)))
A4: да | B4: 1 | C4: Подготовительные земельные работы | E4: work | F4: 3 | G4: Выемка и перемещение грунта для устройства ливневой и дренажной систем | H4: м.куб. | I4: 21 | J4: 100 | K4: =IF(OR(E4="work",E4="section14_item"),I4*J4,0) | L4: =IF(E4="material",I4*J4,IF(E4="section15_percent",I4/100*(SUMPRODUCT((E$2:E$5000="work")*(B$2:B$5000<>"14")*K$2:K$5000)+SUMPRODUCT((E$2:E$5000="material")*(B$2:B$5000<>"14")*L$2:L$5000)),IF(E4="section15_manual",J4,0)))
A5: да | B5: 1 | C5: Подготовительные земельные работы | E5: work | F5: 4 | G5: Обратная засыпка песком после устройства ливневой системы | H5: м.куб. | I5: 12 | J5: 100 | K5: =IF(OR(E5="work",E5="section14_item"),I5*J5,0) | L5: =IF(E5="material",I5*J5,IF(E5="section15_percent",I5/100*(SUMPRODUCT((E$2:E$5000="work")*(B$2:B$5000<>"14")*K$2:K$5000)+SUMPRODUCT((E$2:E$5000="material")*(B$2:B$5000<>"14")*L$2:L$5000)),IF(E5="section15_manual",J5,0)))
A6: да | B6: 1 | C6: Подготовительные земельные работы | E6: material | F6: 5 | G6: Песок намывной (самосвал 20м3) | H6: м.куб. | I6: 13.953488 | J6: 100 | K6: =IF(OR(E6="work",E6="section14_item"),I6*J6,0) | L6: =IF(E6="material",I6*J6,IF(E6="section15_percent",I6/100*(SUMPRODUCT((E$2:E$5000="work")*(B$2:B$5000<>"14")*K$2:K$5000)+SUMPRODUCT((E$2:E$5000="material")*(B$2:B$5000<>"14")*L$2:L$5000)),IF(E6="section15_manual",J6,0))) | M6: 10м3 - 1650р/м3
A7: да | B7: 1 | C7: Подготовительные земельные работы | E7: work | F7: 6 | G7: Разборка существующего покрытия | H7: м.кв. | I7: 250 | J7: 100 | K7: =IF(OR(E7="work",E7="section14_item"),I7*J7,0) | L7: =IF(E7="material",I7*J7,IF(E7="section15_percent",I7/100*(SUMPRODUCT((E$2:E$5000="work")*(B$2:B$5000<>"14")*K$2:K$5000)+SUMPRODUCT((E$2:E$5000="material")*(B$2:B$5000<>"14")*L$2:L$5000)),IF(E7="section15_manual",J7,0)))
A8: да | B8: 1 | C8: Подготовительные земельные работы | E8: work | F8: 7 | G8: Погрузка грунта и мусора и вывоз | H8: м.куб. | I8: 131 | K8: =IF(OR(E8="work",E8="section14_item"),I8*J8,0) | L8: =IF(E8="material",I8*J8,IF(E8="section15_percent",I8/100*(SUMPRODUCT((E$2:E$5000="work")*(B$2:B$5000<>"14")*K$2:K$5000)+SUMPRODUCT((E$2:E$5000="material")*(B$2:B$5000<>"14")*L$2:L$5000)),IF(E8="section15_manual",J8,0)))
A9: да | B9: 1 | C9: Подготовительные земельные работы | E9: subsection | F9: 8 | G9: Нижняя зона участка | K9: =IF(OR(E9="work",E9="section14_item"),I9*J9,0) | L9: =IF(E9="material",I9*J9,IF(E9="section15_percent",I9/100*(SUMPRODUCT((E$2:E$5000="work")*(B$2:B$5000<>"14")*K$2:K$5000)+SUMPRODUCT((E$2:E$5000="material")*(B$2:B$5000<>"14")*L$2:L$5000)),IF(E9="section15_manual",J9,0)))
A10: да | B10: 1 | C10: Подготовительные земельные работы | D10: Нижняя зона участка | E10: work | F10: 9 | G10: Снятие верхнего слоя покрова | H10: м.кв. | I10: 820 | J10: 100 | K10: =IF(OR(E10="work",E10="section14_item"),I10*J10,0) | L10: =IF(E10="material",I10*J10,IF(E10="section15_percent",I10/100*(SUMPRODUCT((E$2:E$5000="work")*(B$2:B$5000<>"14")*K$2:K$5000)+SUMPRODUCT((E$2:E$5000="material")*(B$2:B$5000<>"14")*L$2:L$5000)),IF(E10="section15_manual",J10,0)))
A11: да | B11: 1 | C11: Подготовительные земельные работы | D11: Нижняя зона участка | E11: work | F11: 10 | G11: Перемещение сыпучих материалов на расстояние до 50м вручную (склон) с коэффициентом сложности | H11: м.куб. | I11: 25 | J11: 100 | K11: =IF(OR(E11="work",E11="section14_item"),I11*J11,0) | L11: =IF(E11="material",I11*J11,IF(E11="section15_percent",I11/100*(SUMPRODUCT((E$2:E$5000="work")*(B$2:B$5000<>"14")*K$2:K$5000)+SUMPRODUCT((E$2:E$5000="material")*(B$2:B$5000<>"14")*L$2:L$5000)),IF(E11="section15_manual",J11,0)))
A12: да | B12: 1 | C12: Подготовительные земельные работы | D12: Нижняя зона участка | E12: work | F12: 11 | G12: Погрузка грунта и мусора и вывоз | H12: м.куб. | I12: 82 | K12: =IF(OR(E12="work",E12="section14_item"),I12*J12,0) | L12: =IF(E12="material",I12*J12,IF(E12="section15_percent",I12/100*(SUMPRODUCT((E$2:E$5000="work")*(B$2:B$5000<>"14")*K$2:K$5000)+SUMPRODUCT((E$2:E$5000="material")*(B$2:B$5000<>"14")*L$2:L$5000)),IF(E12="section15_manual",J12,0)))
A13: да | B13: 1 | C13: Подготовительные земельные работы | D13: Нижняя зона участка | E13: work | F13: 12 | G13: Вертикальная планировка | H13: м.куб. | I13: 70 | J13: 100 | K13: =IF(OR(E13="work",E13="section14_item"),I13*J13,0) | L13: =IF(E13="material",I13*J13,IF(E13="section15_percent",I13/100*(SUMPRODUCT((E$2:E$5000="work")*(B$2:B$5000<>"14")*K$2:K$5000)+SUMPRODUCT((E$2:E$5000="material")*(B$2:B$5000<>"14")*L$2:L$5000)),IF(E13="section15_manual",J13,0)))
A14: да | B14: 1 | C14: Подготовительные земельные работы | E14: subsection | F14: 13 | G14: Бассейн | K14: =IF(OR(E14="work",E14="section14_item"),I14*J14,0) | L14: =IF(E14="material",I14*J14,IF(E14="section15_percent",I14/100*(SUMPRODUCT((E$2:E$5000="work")*(B$2:B$5000<>"14")*K$2:K$5000)+SUMPRODUCT((E$2:E$5000="material")*(B$2:B$5000<>"14")*L$2:L$5000)),IF(E14="section15_manual",J14,0)))
A15: да | B15: 1 | C15: Подготовительные земельные работы | D15: Бассейн | E15: work | F15: 14 | G15: Выемка и перемещение существующего грунта для устройства бассейна | H15: м.куб. | I15: 210 | J15: 100 | K15: =IF(OR(E15="work",E15="section14_item"),I15*J15,0) | L15: =IF(E15="material",I15*J15,IF(E15="section15_percent",I15/100*(SUMPRODUCT((E$2:E$5000="work")*(B$2:B$5000<>"14")*K$2:K$5000)+SUMPRODUCT((E$2:E$5000="material")*(B$2:B$5000<>"14")*L$2:L$5000)),IF(E15="section15_manual",J15,0)))
A16: да | B16: 1 | C16: Подготовительные земельные работы | D16: Бассейн | E16: work | F16: 15 | G16: Планировка грунта по склону | H16: м.куб. | I16: 210 | J16: 100 | K16: =IF(OR(E16="work",E16="section14_item"),I16*J16,0) | L16: =IF(E16="material",I16*J16,IF(E16="section15_percent",I16/100*(SUMPRODUCT((E$2:E$5000="work")*(B$2:B$5000<>"14")*K$2:K$5000)+SUMPRODUCT((E$2:E$5000="material")*(B$2:B$5000<>"14")*L$2:L$5000)),IF(E16="section15_manual",J16,0)))
A17: да | B17: 1 | C17: Подготовительные земельные работы | D17: Бассейн | E17: work | F17: 16 | G17: Обратная засыпка песком после устройства ж/б конструкций | H17: м.куб. | I17: 12 | J17: 100 | K17: =IF(OR(E17="work",E17="section14_item"),I17*J17,0) | L17: =IF(E17="material",I17*J17,IF(E17="section15_percent",I17/100*(SUMPRODUCT((E$2:E$5000="work")*(B$2:B$5000<>"14")*K$2:K$5000)+SUMPRODUCT((E$2:E$5000="material")*(B$2:B$5000<>"14")*L$2:L$5000)),IF(E17="section15_manual",J17,0)))
A18: да | B18: 1 | C18: Подготовительные земельные работы | D18: Бассейн | E18: material | F18: 17 | G18: Песок намывной (самосвал 20м3) | H18: м.куб. | I18: 13.953488 | J18: 100 | K18: =IF(OR(E18="work",E18="section14_item"),I18*J18,0) | L18: =IF(E18="material",I18*J18,IF(E18="section15_percent",I18/100*(SUMPRODUCT((E$2:E$5000="work")*(B$2:B$5000<>"14")*K$2:K$5000)+SUMPRODUCT((E$2:E$5000="material")*(B$2:B$5000<>"14")*L$2:L$5000)),IF(E18="section15_manual",J18,0))) | M18: 10м3 - 1650р/м3
A19: да | B19: 1 | C19: Подготовительные земельные работы | D19: Бассейн | E19: material | F19: 18 | G19: Грунт от выемки под автомобильное мощение | H19: м.куб. | I19: 16.224986 | J19: 100 | K19: =IF(OR(E19="work",E19="section14_item"),I19*J19,0) | L19: =IF(E19="material",I19*J19,IF(E19="section15_percent",I19/100*(SUMPRODUCT((E$2:E$5000="work")*(B$2:B$5000<>"14")*K$2:K$5000)+SUMPRODUCT((E$2:E$5000="material")*(B$2:B$5000<>"14")*L$2:L$5000)),IF(E19="section15_manual",J19,0)))
A20: да | B20: 1 | C20: Подготовительные земельные работы | D20: Бассейн | E20: work | F20: 19 | G20: Перемещение сыпучих материалов на расстояние до 50м вручную (склон) с коэффициентом сложности | H20: м.куб. | I20: 25 | J20: 100 | K20: =IF(OR(E20="work",E20="section14_item"),I20*J20,0) | L20: =IF(E20="material",I20*J20,IF(E20="section15_percent",I20/100*(SUMPRODUCT((E$2:E$5000="work")*(B$2:B$5000<>"14")*K$2:K$5000)+SUMPRODUCT((E$2:E$5000="material")*(B$2:B$5000<>"14")*L$2:L$5000)),IF(E20="section15_manual",J20,0)))
A21: да | B21: 2 | C21: Дренажная и ливневая системы. | E21: work | F21: 20 | G21: Монтаж водоприемных колодцев 630мм с выемкой | H21: шт. | I21: 1 | J21: 100 | K21: =IF(OR(E21="work",E21="section14_item"),I21*J21,0) | L21: =IF(E21="material",I21*J21,IF(E21="section15_percent",I21/100*(SUMPRODUCT((E$2:E$5000="work")*(B$2:B$5000<>"14")*K$2:K$5000)+SUMPRODUCT((E$2:E$5000="material")*(B$2:B$5000<>"14")*L$2:L$5000)),IF(E21="section15_manual",J21,0)))
A22: да | B22: 2 | C22: Дренажная и ливневая системы. | E22: material | F22: 21 | G22: Колодец фильтрационный конический 600мм h=2м с крышкой | H22: шт. | I22: 1 | J22: 100 | K22: =IF(OR(E22="work",E22="section14_item"),I22*J22,0) | L22: =IF(E22="material",I22*J22,IF(E22="section15_percent",I22/100*(SUMPRODUCT((E$2:E$5000="work")*(B$2:B$5000<>"14")*K$2:K$5000)+SUMPRODUCT((E$2:E$5000="material")*(B$2:B$5000<>"14")*L$2:L$5000)),IF(E22="section15_manual",J22,0)))
A23: да | B23: 2 | C23: Дренажная и ливневая системы. | E23: material | F23: 22 | G23: Щебень гранитный фр.20-40мм (самосвал 20м3) | H23: м.куб. | I23: 0.5 | J23: 100 | K23: =IF(OR(E23="work",E23="section14_item"),I23*J23,0) | L23: =IF(E23="material",I23*J23,IF(E23="section15_percent",I23/100*(SUMPRODUCT((E$2:E$5000="work")*(B$2:B$5000<>"14")*K$2:K$5000)+SUMPRODUCT((E$2:E$5000="material")*(B$2:B$5000<>"14")*L$2:L$5000)),IF(E23="section15_manual",J23,0)))
A24: да | B24: 2 | C24: Дренажная и ливневая системы. | E24: material | F24: 23 | G24: Геотекстиль плотность 200г/м2 | H24: м.кв. | I24: 25 | J24: 100 | K24: =IF(OR(E24="work",E24="section14_item"),I24*J24,0) | L24: =IF(E24="material",I24*J24,IF(E24="section15_percent",I24/100*(SUMPRODUCT((E$2:E$5000="work")*(B$2:B$5000<>"14")*K$2:K$5000)+SUMPRODUCT((E$2:E$5000="material")*(B$2:B$5000<>"14")*L$2:L$5000)),IF(E24="section15_manual",J24,0)))
A25: да | B25: 2 | C25: Дренажная и ливневая системы. | E25: work | F25: 24 | G25: Устройство врезок в существующий колодец | H25: шт. | I25: 3 | J25: 100 | K25: =IF(OR(E25="work",E25="section14_item"),I25*J25,0) | L25: =IF(E25="material",I25*J25,IF(E25="section15_percent",I25/100*(SUMPRODUCT((E$2:E$5000="work")*(B$2:B$5000<>"14")*K$2:K$5000)+SUMPRODUCT((E$2:E$5000="material")*(B$2:B$5000<>"14")*L$2:L$5000)),IF(E25="section15_manual",J25,0)))
A26: да | B26: 2 | C26: Дренажная и ливневая системы. | E26: work | F26: 25 | G26: Монтаж колодцев инспекционных 315мм | H26: шт. | I26: 1 | J26: 100 | K26: =IF(OR(E26="work",E26="section14_item"),I26*J26,0) | L26: =IF(E26="material",I26*J26,IF(E26="section15_percent",I26/100*(SUMPRODUCT((E$2:E$5000="work")*(B$2:B$5000<>"14")*K$2:K$5000)+SUMPRODUCT((E$2:E$5000="material")*(B$2:B$5000<>"14")*L$2:L$5000)),IF(E26="section15_manual",J26,0)))
A27: да | B27: 2 | C27: Дренажная и ливневая системы. | E27: material | F27: 26 | G27: Колодец инспекционный 315мм h=2м с крышкой и дном | H27: шт. | I27: 1 | J27: 100 | K27: =IF(OR(E27="work",E27="section14_item"),I27*J27,0) | L27: =IF(E27="material",I27*J27,IF(E27="section15_percent",I27/100*(SUMPRODUCT((E$2:E$5000="work")*(B$2:B$5000<>"14")*K$2:K$5000)+SUMPRODUCT((E$2:E$5000="material")*(B$2:B$5000<>"14")*L$2:L$5000)),IF(E27="section15_manual",J27,0)))
A28: да | B28: 2 | C28: Дренажная и ливневая системы. | E28: work | F28: 27 | G28: Устройство дренажной системы с обратной засыпкой (глубина до 700мм) | H28: м.п. | I28: 42.3 | J28: 100 | K28: =IF(OR(E28="work",E28="section14_item"),I28*J28,0) | L28: =IF(E28="material",I28*J28,IF(E28="section15_percent",I28/100*(SUMPRODUCT((E$2:E$5000="work")*(B$2:B$5000<>"14")*K$2:K$5000)+SUMPRODUCT((E$2:E$5000="material")*(B$2:B$5000<>"14")*L$2:L$5000)),IF(E28="section15_manual",J28,0)))
A29: да | B29: 2 | C29: Дренажная и ливневая системы. | E29: material | F29: 28 | G29: Геотекстиль плотность 200г/м2 | H29: м.кв. | I29: 25 | J29: 100 | K29: =IF(OR(E29="work",E29="section14_item"),I29*J29,0) | L29: =IF(E29="material",I29*J29,IF(E29="section15_percent",I29/100*(SUMPRODUCT((E$2:E$5000="work")*(B$2:B$5000<>"14")*K$2:K$5000)+SUMPRODUCT((E$2:E$5000="material")*(B$2:B$5000<>"14")*L$2:L$5000)),IF(E29="section15_manual",J29,0)))
A30: да | B30: 2 | C30: Дренажная и ливневая системы. | E30: material | F30: 29 | G30: Труба дренажная 110мм перфорир. в фильтре (бухта 50м) | H30: бухта | I30: 4 | J30: 100 | K30: =IF(OR(E30="work",E30="section14_item"),I30*J30,0) | L30: =IF(E30="material",I30*J30,IF(E30="section15_percent",I30/100*(SUMPRODUCT((E$2:E$5000="work")*(B$2:B$5000<>"14")*K$2:K$5000)+SUMPRODUCT((E$2:E$5000="material")*(B$2:B$5000<>"14")*L$2:L$5000)),IF(E30="section15_manual",J30,0)))
A31: да | B31: 2 | C31: Дренажная и ливневая системы. | E31: material | F31: 30 | G31: Щебень гранитный фр.20-40мм (самосвал 20м3) | H31: м.куб. | I31: 7 | J31: 100 | K31: =IF(OR(E31="work",E31="section14_item"),I31*J31,0) | L31: =IF(E31="material",I31*J31,IF(E31="section15_percent",I31/100*(SUMPRODUCT((E$2:E$5000="work")*(B$2:B$5000<>"14")*K$2:K$5000)+SUMPRODUCT((E$2:E$5000="material")*(B$2:B$5000<>"14")*L$2:L$5000)),IF(E31="section15_manual",J31,0)))
A32: да | B32: 2 | C32: Дренажная и ливневая системы. | E32: material | F32: 31 | G32: Песок намывной (самосвал 20м3) | H32: м.куб. | I32: 7 | J32: 100 | K32: =IF(OR(E32="work",E32="section14_item"),I32*J32,0) | L32: =IF(E32="material",I32*J32,IF(E32="section15_percent",I32/100*(SUMPRODUCT((E$2:E$5000="work")*(B$2:B$5000<>"14")*K$2:K$5000)+SUMPRODUCT((E$2:E$5000="material")*(B$2:B$5000<>"14")*L$2:L$5000)),IF(E32="section15_manual",J32,0)))
... A46: да | B46: 2 | C46: Дренажная и ливневая системы. | E46: material | F46: 45 | G46: Цемент М400, 50кг | H46: меш. | I46: 1 | J46: 100 | K46: =IF(OR(E46="work",E46="section14_item"),I46*J46,0) | L46: =IF(E46="material",I46*J46,IF(E46="section15_percent",I46/100*(SUMPRODUCT((E$2:E$5000="work")*(B$2:B$5000<>"14")*K$2:K$5000)+SUMPRODUCT((E$2:E$5000="material")*(B$2:B$5000<>"14")*L$2:L$5000)),IF(E46="section15_manual",J46,0)))
A47: да | B47: 3 | C47: Монолитные железобетонные конструкции | E47: subsection | F47: 46 | G47: Плита основания - 75м2 | K47: =IF(OR(E47="work",E47="section14_item"),I47*J47,0) | L47: =IF(E47="material",I47*J47,IF(E47="section15_percent",I47/100*(SUMPRODUCT((E$2:E$5000="work")*(B$2:B$5000<>"14")*K$2:K$5000)+SUMPRODUCT((E$2:E$5000="material")*(B$2:B$5000<>"14")*L$2:L$5000)),IF(E47="section15_manual",J47,0)))
A48: да | B48: 3 | C48: Монолитные железобетонные конструкции | D48: Плита основания - 75м2 | E48: work | F48: 47 | G48: Устройство выравнивающих оснований из песка с трамбованием вручную | H48: м.куб. | I48: 9 | J48: 100 | K48: =IF(OR(E48="work",E48="section14_item"),I48*J48,0) | L48: =IF(E48="material",I48*J48,IF(E48="section15_percent",I48/100*(SUMPRODUCT((E$2:E$5000="work")*(B$2:B$5000<>"14")*K$2:K$5000)+SUMPRODUCT((E$2:E$5000="material")*(B$2:B$5000<>"14")*L$2:L$5000)),IF(E48="section15_manual",J48,0)))
A49: да | B49: 3 | C49: Монолитные железобетонные конструкции | D49: Плита основания - 75м2 | E49: material | F49: 48 | G49: Песок намывной (самосвал 20м3) | H49: м.куб. | I49: 11.7 | J49: 100 | K49: =IF(OR(E49="work",E49="section14_item"),I49*J49,0) | L49: =IF(E49="material",I49*J49,IF(E49="section15_percent",I49/100*(SUMPRODUCT((E$2:E$5000="work")*(B$2:B$5000<>"14")*K$2:K$5000)+SUMPRODUCT((E$2:E$5000="material")*(B$2:B$5000<>"14")*L$2:L$5000)),IF(E49="section15_manual",J49,0)))
A50: да | B50: 3 | C50: Монолитные железобетонные конструкции | D50: Плита основания - 75м2 | E50: work | F50: 49 | G50: Аренда виброплиты 250кг | H50: смена | I50: 1 | J50: 100 | K50: =IF(OR(E50="work",E50="section14_item"),I50*J50,0) | L50: =IF(E50="material",I50*J50,IF(E50="section15_percent",I50/100*(SUMPRODUCT((E$2:E$5000="work")*(B$2:B$5000<>"14")*K$2:K$5000)+SUMPRODUCT((E$2:E$5000="material")*(B$2:B$5000<>"14")*L$2:L$5000)),IF(E50="section15_manual",J50,0)))
A51: да | B51: 3 | C51: Монолитные железобетонные конструкции | D51: Плита основания - 75м2 | E51: work | F51: 50 | G51: Укладка геотекстиля | H51: м.кв. | I51: 90 | J51: 100 | K51: =IF(OR(E51="work",E51="section14_item"),I51*J51,0) | L51: =IF(E51="material",I51*J51,IF(E51="section15_percent",I51/100*(SUMPRODUCT((E$2:E$5000="work")*(B$2:B$5000<>"14")*K$2:K$5000)+SUMPRODUCT((E$2:E$5000="material")*(B$2:B$5000<>"14")*L$2:L$5000)),IF(E51="section15_manual",J51,0)))
A52: да | B52: 3 | C52: Монолитные железобетонные конструкции | D52: Плита основания - 75м2 | E52: material | F52: 51 | G52: Геотекстиль плотность 200г/м2 | H52: м.кв. | I52: 108 | J52: 100 | K52: =IF(OR(E52="work",E52="section14_item"),I52*J52,0) | L52: =IF(E52="material",I52*J52,IF(E52="section15_percent",I52/100*(SUMPRODUCT((E$2:E$5000="work")*(B$2:B$5000<>"14")*K$2:K$5000)+SUMPRODUCT((E$2:E$5000="material")*(B$2:B$5000<>"14")*L$2:L$5000)),IF(E52="section15_manual",J52,0)))
A53: да | B53: 3 | C53: Монолитные железобетонные конструкции | D53: Плита основания - 75м2 | E53: work | F53: 52 | G53: Устройство оснований из щебня с трамбованием, расклинцовкой вручную | H53: м.куб. | I53: 13.5 | J53: 100 | K53: =IF(OR(E53="work",E53="section14_item"),I53*J53,0) | L53: =IF(E53="material",I53*J53,IF(E53="section15_percent",I53/100*(SUMPRODUCT((E$2:E$5000="work")*(B$2:B$5000<>"14")*K$2:K$5000)+SUMPRODUCT((E$2:E$5000="material")*(B$2:B$5000<>"14")*L$2:L$5000)),IF(E53="section15_manual",J53,0)))
A54: да | B54: 3 | C54: Монолитные железобетонные конструкции | D54: Плита основания - 75м2 | E54: material | F54: 53 | G54: Щебень гранитный фр.20-40мм (самосвал 20м3) | H54: м.куб. | I54: 18.2 | J54: 100 | K54: =IF(OR(E54="work",E54="section14_item"),I54*J54,0) | L54: =IF(E54="material",I54*J54,IF(E54="section15_percent",I54/100*(SUMPRODUCT((E$2:E$5000="work")*(B$2:B$5000<>"14")*K$2:K$5000)+SUMPRODUCT((E$2:E$5000="material")*(B$2:B$5000<>"14")*L$2:L$5000)),IF(E54="section15_manual",J54,0)))
A55: да | B55: 3 | C55: Монолитные железобетонные конструкции | D55: Плита основания - 75м2 | E55: material | F55: 54 | G55: Щебень гранитный (фракция 5-20мм) для расклинцовки | H55: м.куб. | I55: 3.6 | J55: 100 | K55: =IF(OR(E55="work",E55="section14_item"),I55*J55,0) | L55: =IF(E55="material",I55*J55,IF(E55="section15_percent",I55/100*(SUMPRODUCT((E$2:E$5000="work")*(B$2:B$5000<>"14")*K$2:K$5000)+SUMPRODUCT((E$2:E$5000="material")*(B$2:B$5000<>"14")*L$2:L$5000)),IF(E55="section15_manual",J55,0)))
A56: да | B56: 3 | C56: Монолитные железобетонные конструкции | D56: Плита основания - 75м2 | E56: work | F56: 55 | G56: Аренда виброплиты 250кг | H56: смена | I56: 1 | J56: 100 | K56: =IF(OR(E56="work",E56="section14_item"),I56*J56,0) | L56: =IF(E56="material",I56*J56,IF(E56="section15_percent",I56/100*(SUMPRODUCT((E$2:E$5000="work")*(B$2:B$5000<>"14")*K$2:K$5000)+SUMPRODUCT((E$2:E$5000="material")*(B$2:B$5000<>"14")*L$2:L$5000)),IF(E56="section15_manual",J56,0)))
A57: да | B57: 3 | C57: Монолитные железобетонные конструкции | D57: Плита основания - 75м2 | E57: work | F57: 56 | G57: Перемещение сыпучих материалов на расстояние до 50м вручную (склон) с коэффициентом сложности | H57: м.куб. | I57: 33.5 | J57: 100 | K57: =IF(OR(E57="work",E57="section14_item"),I57*J57,0) | L57: =IF(E57="material",I57*J57,IF(E57="section15_percent",I57/100*(SUMPRODUCT((E$2:E$5000="work")*(B$2:B$5000<>"14")*K$2:K$5000)+SUMPRODUCT((E$2:E$5000="material")*(B$2:B$5000<>"14")*L$2:L$5000)),IF(E57="section15_manual",J57,0)))
A58: да | B58: 3 | C58: Монолитные железобетонные конструкции | D58: Плита основания - 75м2 | E58: work | F58: 57 | G58: Устройство гидроизоляции подкладочной | H58: м.кв. | I58: 90 | J58: 100 | K58: =IF(OR(E58="work",E58="section14_item"),I58*J58,0) | L58: =IF(E58="material",I58*J58,IF(E58="section15_percent",I58/100*(SUMPRODUCT((E$2:E$5000="work")*(B$2:B$5000<>"14")*K$2:K$5000)+SUMPRODUCT((E$2:E$5000="material")*(B$2:B$5000<>"14")*L$2:L$5000)),IF(E58="section15_manual",J58,0)))
A59: да | B59: 3 | C59: Монолитные железобетонные конструкции | D59: Плита основания - 75м2 | E59: material | F59: 58 | G59: Рубероид РКП-350 ГОСТ | H59: м.кв. | I59: 112.5 | J59: 100 | K59: =IF(OR(E59="work",E59="section14_item"),I59*J59,0) | L59: =IF(E59="material",I59*J59,IF(E59="section15_percent",I59/100*(SUMPRODUCT((E$2:E$5000="work")*(B$2:B$5000<>"14")*K$2:K$5000)+SUMPRODUCT((E$2:E$5000="material")*(B$2:B$5000<>"14")*L$2:L$5000)),IF(E59="section15_manual",J59,0)))
... A73: да | B73: 3 | C73: Монолитные железобетонные конструкции | D73: Плита основания - 75м2 | E73: material | F73: 72 | G73: Мастика гидроизоляционная Bitumast 18кг/21,5л | H73: шт. | I73: 4 | J73: 100 | K73: =IF(OR(E73="work",E73="section14_item"),I73*J73,0) | L73: =IF(E73="material",I73*J73,IF(E73="section15_percent",I73/100*(SUMPRODUCT((E$2:E$5000="work")*(B$2:B$5000<>"14")*K$2:K$5000)+SUMPRODUCT((E$2:E$5000="material")*(B$2:B$5000<>"14")*L$2:L$5000)),IF(E73="section15_manual",J73,0)))
A74: да | B74: 3 | C74: Монолитные железобетонные конструкции | E74: subsection | F74: 73 | G74: Стены подпорные, стены бассейна | K74: =IF(OR(E74="work",E74="section14_item"),I74*J74,0) | L74: =IF(E74="material",I74*J74,IF(E74="section15_percent",I74/100*(SUMPRODUCT((E$2:E$5000="work")*(B$2:B$5000<>"14")*K$2:K$5000)+SUMPRODUCT((E$2:E$5000="material")*(B$2:B$5000<>"14")*L$2:L$5000)),IF(E74="section15_manual",J74,0)))
A75: да | B75: 3 | C75: Монолитные железобетонные конструкции | D75: Стены подпорные, стены бассейна | E75: work | F75: 74 | G75: Сборка щитов опалубки, выставление опалубки, снятие опалубки | H75: м.кв. | I75: 206 | J75: 100 | K75: =IF(OR(E75="work",E75="section14_item"),I75*J75,0) | L75: =IF(E75="material",I75*J75,IF(E75="section15_percent",I75/100*(SUMPRODUCT((E$2:E$5000="work")*(B$2:B$5000<>"14")*K$2:K$5000)+SUMPRODUCT((E$2:E$5000="material")*(B$2:B$5000<>"14")*L$2:L$5000)),IF(E75="section15_manual",J75,0)))
A76: да | B76: 3 | C76: Монолитные железобетонные конструкции | D76: Стены подпорные, стены бассейна | E76: work | F76: 75 | G76: Аренда стеновой опалубки в комплекте (щиты линейные, угловые, подкосы, стойки, замки) | H76: компл. | I76: 1 | J76: 100 | K76: =IF(OR(E76="work",E76="section14_item"),I76*J76,0) | L76: =IF(E76="material",I76*J76,IF(E76="section15_percent",I76/100*(SUMPRODUCT((E$2:E$5000="work")*(B$2:B$5000<>"14")*K$2:K$5000)+SUMPRODUCT((E$2:E$5000="material")*(B$2:B$5000<>"14")*L$2:L$5000)),IF(E76="section15_manual",J76,0)))
A77: да | B77: 3 | C77: Монолитные железобетонные конструкции | D77: Стены подпорные, стены бассейна | E77: material | F77: 76 | G77: Прочие материалы (крепеж, метизы, диски пильные, эмульсия) | H77: м.кв. | I77: 75 | J77: 100 | K77: =IF(OR(E77="work",E77="section14_item"),I77*J77,0) | L77: =IF(E77="material",I77*J77,IF(E77="section15_percent",I77/100*(SUMPRODUCT((E$2:E$5000="work")*(B$2:B$5000<>"14")*K$2:K$5000)+SUMPRODUCT((E$2:E$5000="material")*(B$2:B$5000<>"14")*L$2:L$5000)),IF(E77="section15_manual",J77,0)))
A78: да | B78: 3 | C78: Монолитные железобетонные конструкции | D78: Стены подпорные, стены бассейна | E78: work | F78: 77 | G78: Устройство ж/б стен 200-250мм (армирование, заливка бетона) | H78: м.куб. | I78: 22 | J78: 100 | K78: =IF(OR(E78="work",E78="section14_item"),I78*J78,0) | L78: =IF(E78="material",I78*J78,IF(E78="section15_percent",I78/100*(SUMPRODUCT((E$2:E$5000="work")*(B$2:B$5000<>"14")*K$2:K$5000)+SUMPRODUCT((E$2:E$5000="material")*(B$2:B$5000<>"14")*L$2:L$5000)),IF(E78="section15_manual",J78,0)))
A79: да | B79: 3 | C79: Монолитные железобетонные конструкции | D79: Стены подпорные, стены бассейна | E79: material | F79: 78 | G79: Бетон товарный В25 W8 F150 | H79: м.куб. | I79: 24.2 | J79: 100 | K79: =IF(OR(E79="work",E79="section14_item"),I79*J79,0) | L79: =IF(E79="material",I79*J79,IF(E79="section15_percent",I79/100*(SUMPRODUCT((E$2:E$5000="work")*(B$2:B$5000<>"14")*K$2:K$5000)+SUMPRODUCT((E$2:E$5000="material")*(B$2:B$5000<>"14")*L$2:L$5000)),IF(E79="section15_manual",J79,0)))
A80: да | B80: 3 | C80: Монолитные железобетонные конструкции | D80: Стены подпорные, стены бассейна | E80: work | F80: 79 | G80: Аренда бетононасоса | H80: маш./см. | I80: 1 | J80: 100 | K80: =IF(OR(E80="work",E80="section14_item"),I80*J80,0) | L80: =IF(E80="material",I80*J80,IF(E80="section15_percent",I80/100*(SUMPRODUCT((E$2:E$5000="work")*(B$2:B$5000<>"14")*K$2:K$5000)+SUMPRODUCT((E$2:E$5000="material")*(B$2:B$5000<>"14")*L$2:L$5000)),IF(E80="section15_manual",J80,0)))
A81: да | B81: 3 | C81: Монолитные железобетонные конструкции | D81: Стены подпорные, стены бассейна | E81: material | F81: 80 | G81: Аренда бетононасоса | H81: маш./см. | I81: 1 | J81: 100 | K81: =IF(OR(E81="work",E81="section14_item"),I81*J81,0) | L81: =IF(E81="material",I81*J81,IF(E81="section15_percent",I81/100*(SUMPRODUCT((E$2:E$5000="work")*(B$2:B$5000<>"14")*K$2:K$5000)+SUMPRODUCT((E$2:E$5000="material")*(B$2:B$5000<>"14")*L$2:L$5000)),IF(E81="section15_manual",J81,0)))
A82: да | B82: 3 | C82: Монолитные железобетонные конструкции | D82: Стены подпорные, стены бассейна | E82: work | F82: 81 | G82: Аренда шлангов 30м | H82: маш./см. | I82: 1 | J82: 100 | K82: =IF(OR(E82="work",E82="section14_item"),I82*J82,0) | L82: =IF(E82="material",I82*J82,IF(E82="section15_percent",I82/100*(SUMPRODUCT((E$2:E$5000="work")*(B$2:B$5000<>"14")*K$2:K$5000)+SUMPRODUCT((E$2:E$5000="material")*(B$2:B$5000<>"14")*L$2:L$5000)),IF(E82="section15_manual",J82,0)))
A83: да | B83: 3 | C83: Монолитные железобетонные конструкции | D83: Стены подпорные, стены бассейна | E83: material | F83: 82 | G83: Аренда шлангов 30м | H83: маш./см. | I83: 1 | J83: 100 | K83: =IF(OR(E83="work",E83="section14_item"),I83*J83,0) | L83: =IF(E83="material",I83*J83,IF(E83="section15_percent",I83/100*(SUMPRODUCT((E$2:E$5000="work")*(B$2:B$5000<>"14")*K$2:K$5000)+SUMPRODUCT((E$2:E$5000="material")*(B$2:B$5000<>"14")*L$2:L$5000)),IF(E83="section15_manual",J83,0)))
A84: да | B84: 3 | C84: Монолитные железобетонные конструкции | D84: Стены подпорные, стены бассейна | E84: material | F84: 83 | G84: Прочие материалы (бруски, метизы, вязальная проволока, фиксаторы для арматуры, диски алмазные, отрезные) | H84: м.кв. | I84: 206 | J84: 100 | K84: =IF(OR(E84="work",E84="section14_item"),I84*J84,0) | L84: =IF(E84="material",I84*J84,IF(E84="section15_percent",I84/100*(SUMPRODUCT((E$2:E$5000="work")*(B$2:B$5000<>"14")*K$2:K$5000)+SUMPRODUCT((E$2:E$5000="material")*(B$2:B$5000<>"14")*L$2:L$5000)),IF(E84="section15_manual",J84,0)))
A85: да | B85: 3 | C85: Монолитные железобетонные конструкции | D85: Стены подпорные, стены бассейна | E85: work | F85: 84 | G85: Уход за бетоном | H85: м.кв. | I85: 74 | J85: 100 | K85: =IF(OR(E85="work",E85="section14_item"),I85*J85,0) | L85: =IF(E85="material",I85*J85,IF(E85="section15_percent",I85/100*(SUMPRODUCT((E$2:E$5000="work")*(B$2:B$5000<>"14")*K$2:K$5000)+SUMPRODUCT((E$2:E$5000="material")*(B$2:B$5000<>"14")*L$2:L$5000)),IF(E85="section15_manual",J85,0)))
A86: да | B86: 3 | C86: Монолитные железобетонные конструкции | D86: Стены подпорные, стены бассейна | E86: material | F86: 85 | G86: Пленка техническая полиэтиленовая 200мк | H86: м.кв. | I86: 90 | J86: 100 | K86: =IF(OR(E86="work",E86="section14_item"),I86*J86,0) | L86: =IF(E86="material",I86*J86,IF(E86="section15_percent",I86/100*(SUMPRODUCT((E$2:E$5000="work")*(B$2:B$5000<>"14")*K$2:K$5000)+SUMPRODUCT((E$2:E$5000="material")*(B$2:B$5000<>"14")*L$2:L$5000)),IF(E86="section15_manual",J86,0)))
... A91: да | B91: 3 | C91: Монолитные железобетонные конструкции | D91: Стены подпорные, стены бассейна | E91: material | F91: 90 | G91: Гидроизоляционный материал Акваблокер Bostik, 14кг | H91: шт. | I91: 3.5 | J91: 100 | K91: =IF(OR(E91="work",E91="section14_item"),I91*J91,0) | L91: =IF(E91="material",I91*J91,IF(E91="section15_percent",I91/100*(SUMPRODUCT((E$2:E$5000="work")*(B$2:B$5000<>"14")*K$2:K$5000)+SUMPRODUCT((E$2:E$5000="material")*(B$2:B$5000<>"14")*L$2:L$5000)),IF(E91="section15_manual",J91,0)))
A92: да | B92: 3 | C92: Монолитные железобетонные конструкции | E92: subsection | F92: 91 | G92: Плита перекрытия (частично на основании) 76м.кв., верхняя площадка 23,5м.кв. (на основании) | K92: =IF(OR(E92="work",E92="section14_item"),I92*J92,0) | L92: =IF(E92="material",I92*J92,IF(E92="section15_percent",I92/100*(SUMPRODUCT((E$2:E$5000="work")*(B$2:B$5000<>"14")*K$2:K$5000)+SUMPRODUCT((E$2:E$5000="material")*(B$2:B$5000<>"14")*L$2:L$5000)),IF(E92="section15_manual",J92,0)))
A93: да | B93: 3 | C93: Монолитные железобетонные конструкции | D93: Плита перекрытия (частично на основании) 76м.кв., верхняя площадка 23,5м.кв. (на основании) | E93: work | F93: 92 | G93: Устройство выравнивающих оснований из песка с трамбованием вручную | H93: м.куб. | I93: 8.4 | J93: 100 | K93: =IF(OR(E93="work",E93="section14_item"),I93*J93,0) | L93: =IF(E93="material",I93*J93,IF(E93="section15_percent",I93/100*(SUMPRODUCT((E$2:E$5000="work")*(B$2:B$5000<>"14")*K$2:K$5000)+SUMPRODUCT((E$2:E$5000="material")*(B$2:B$5000<>"14")*L$2:L$5000)),IF(E93="section15_manual",J93,0)))
A94: да | B94: 3 | C94: Монолитные железобетонные конструкции | D94: Плита перекрытия (частично на основании) 76м.кв., верхняя площадка 23,5м.кв. (на основании) | E94: material | F94: 93 | G94: Песок намывной (самосвал 20м3) | H94: м.куб. | I94: 11 | J94: 100 | K94: =IF(OR(E94="work",E94="section14_item"),I94*J94,0) | L94: =IF(E94="material",I94*J94,IF(E94="section15_percent",I94/100*(SUMPRODUCT((E$2:E$5000="work")*(B$2:B$5000<>"14")*K$2:K$5000)+SUMPRODUCT((E$2:E$5000="material")*(B$2:B$5000<>"14")*L$2:L$5000)),IF(E94="section15_manual",J94,0)))
A95: да | B95: 3 | C95: Монолитные железобетонные конструкции | D95: Плита перекрытия (частично на основании) 76м.кв., верхняя площадка 23,5м.кв. (на основании) | E95: work | F95: 94 | G95: Аренда виброплиты 250кг | H95: смена | I95: 0.3 | J95: 100 | K95: =IF(OR(E95="work",E95="section14_item"),I95*J95,0) | L95: =IF(E95="material",I95*J95,IF(E95="section15_percent",I95/100*(SUMPRODUCT((E$2:E$5000="work")*(B$2:B$5000<>"14")*K$2:K$5000)+SUMPRODUCT((E$2:E$5000="material")*(B$2:B$5000<>"14")*L$2:L$5000)),IF(E95="section15_manual",J95,0)))
A96: да | B96: 3 | C96: Монолитные железобетонные конструкции | D96: Плита перекрытия (частично на основании) 76м.кв., верхняя площадка 23,5м.кв. (на основании) | E96: work | F96: 95 | G96: Укладка геотекстиля | H96: м.кв. | I96: 84.4 | J96: 100 | K96: =IF(OR(E96="work",E96="section14_item"),I96*J96,0) | L96: =IF(E96="material",I96*J96,IF(E96="section15_percent",I96/100*(SUMPRODUCT((E$2:E$5000="work")*(B$2:B$5000<>"14")*K$2:K$5000)+SUMPRODUCT((E$2:E$5000="material")*(B$2:B$5000<>"14")*L$2:L$5000)),IF(E96="section15_manual",J96,0)))
A97: да | B97: 3 | C97: Монолитные железобетонные конструкции | D97: Плита перекрытия (частично на основании) 76м.кв., верхняя площадка 23,5м.кв. (на основании) | E97: material | F97: 96 | G97: Геотекстиль плотность 200г/м2 | H97: м.кв. | I97: 101.2 | J97: 100 | K97: =IF(OR(E97="work",E97="section14_item"),I97*J97,0) | L97: =IF(E97="material",I97*J97,IF(E97="section15_percent",I97/100*(SUMPRODUCT((E$2:E$5000="work")*(B$2:B$5000<>"14")*K$2:K$5000)+SUMPRODUCT((E$2:E$5000="material")*(B$2:B$5000<>"14")*L$2:L$5000)),IF(E97="section15_manual",J97,0)))
A98: да | B98: 3 | C98: Монолитные железобетонные конструкции | D98: Плита перекрытия (частично на основании) 76м.кв., верхняя площадка 23,5м.кв. (на основании) | E98: work | F98: 97 | G98: Устройство оснований из щебня с расклинцовкой вручную | H98: м.куб. | I98: 12.7 | J98: 100 | K98: =IF(OR(E98="work",E98="section14_item"),I98*J98,0) | L98: =IF(E98="material",I98*J98,IF(E98="section15_percent",I98/100*(SUMPRODUCT((E$2:E$5000="work")*(B$2:B$5000<>"14")*K$2:K$5000)+SUMPRODUCT((E$2:E$5000="material")*(B$2:B$5000<>"14")*L$2:L$5000)),IF(E98="section15_manual",J98,0)))
A99: да | B99: 3 | C99: Монолитные железобетонные конструкции | D99: Плита перекрытия (частично на основании) 76м.кв., верхняя площадка 23,5м.кв. (на основании) | E99: material | F99: 98 | G99: Щебень гранитный фр.20-40мм (самосвал 20м3) | H99: м.куб. | I99: 17.1 | J99: 100 | K99: =IF(OR(E99="work",E99="section14_item"),I99*J99,0) | L99: =IF(E99="material",I99*J99,IF(E99="section15_percent",I99/100*(SUMPRODUCT((E$2:E$5000="work")*(B$2:B$5000<>"14")*K$2:K$5000)+SUMPRODUCT((E$2:E$5000="material")*(B$2:B$5000<>"14")*L$2:L$5000)),IF(E99="section15_manual",J99,0)))
A100: да | B100: 3 | C100: Монолитные железобетонные конструкции | D100: Плита перекрытия (частично на основании) 76м.кв., верхняя площадка 23,5м.кв. (на основании) | E100: material | F100: 99 | G100: Щебень гранитный (фракция 5-20мм) для расклинцовки | H100: м.куб. | I100: 3.4 | J100: 100 | K100: =IF(OR(E100="work",E100="section14_item"),I100*J100,0) | L100: =IF(E100="material",I100*J100,IF(E100="section15_percent",I100/100*(SUMPRODUCT((E$2:E$5000="work")*(B$2:B$5000<>"14")*K$2:K$5000)+SUMPRODUCT((E$2:E$5000="material")*(B$2:B$5000<>"14")*L$2:L$5000)),IF(E100="section15_manual",J100,0)))
A101: да | B101: 3 | C101: Монолитные железобетонные конструкции | D101: Плита перекрытия (частично на основании) 76м.кв., верхняя площадка 23,5м.кв. (на основании) | E101: work | F101: 100 | G101: Аренда виброплиты 250кг | H101: смена | I101: 1 | J101: 100 | K101: =IF(OR(E101="work",E101="section14_item"),I101*J101,0) | L101: =IF(E101="material",I101*J101,IF(E101="section15_percent",I101/100*(SUMPRODUCT((E$2:E$5000="work")*(B$2:B$5000<>"14")*K$2:K$5000)+SUMPRODUCT((E$2:E$5000="material")*(B$2:B$5000<>"14")*L$2:L$5000)),IF(E101="section15_manual",J101,0)))
A102: да | B102: 3 | C102: Монолитные железобетонные конструкции | D102: Плита перекрытия (частично на основании) 76м.кв., верхняя площадка 23,5м.кв. (на основании) | E102: work | F102: 101 | G102: Перемещение сыпучих материалов на расстояние до 50м вручную (склон) с коэффициентом сложности | H102: м.куб. | I102: 31.4 | J102: 100 | K102: =IF(OR(E102="work",E102="section14_item"),I102*J102,0) | L102: =IF(E102="material",I102*J102,IF(E102="section15_percent",I102/100*(SUMPRODUCT((E$2:E$5000="work")*(B$2:B$5000<>"14")*K$2:K$5000)+SUMPRODUCT((E$2:E$5000="material")*(B$2:B$5000<>"14")*L$2:L$5000)),IF(E102="section15_manual",J102,0)))
A103: да | B103: 3 | C103: Монолитные железобетонные конструкции | D103: Плита перекрытия (частично на основании) 76м.кв., верхняя площадка 23,5м.кв. (на основании) | E103: work | F103: 102 | G103: Устройство гидроизоляции подкладочной | H103: м.кв. | I103: 84.4 | J103: 100 | K103: =IF(OR(E103="work",E103="section14_item"),I103*J103,0) | L103: =IF(E103="material",I103*J103,IF(E103="section15_percent",I103/100*(SUMPRODUCT((E$2:E$5000="work")*(B$2:B$5000<>"14")*K$2:K$5000)+SUMPRODUCT((E$2:E$5000="material")*(B$2:B$5000<>"14")*L$2:L$5000)),IF(E103="section15_manual",J103,0)))
A104: да | B104: 3 | C104: Монолитные железобетонные конструкции | D104: Плита перекрытия (частично на основании) 76м.кв., верхняя площадка 23,5м.кв. (на основании) | E104: material | F104: 103 | G104: Рубероид РКП-350 ГОСТ | H104: м.кв. | I104: 105.5 | J104: 100 | K104: =IF(OR(E104="work",E104="section14_item"),I104*J104,0) | L104: =IF(E104="material",I104*J104,IF(E104="section15_percent",I104/100*(SUMPRODUCT((E$2:E$5000="work")*(B$2:B$5000<>"14")*K$2:K$5000)+SUMPRODUCT((E$2:E$5000="material")*(B$2:B$5000<>"14")*L$2:L$5000)),IF(E104="section15_manual",J104,0)))
... A114: да | B114: 3 | C114: Монолитные железобетонные конструкции | D114: Плита перекрытия (частично на основании) 76м.кв., верхняя площадка 23,5м.кв. (на основании) | E114: material | F114: 113 | G114: Пленка техническая полиэтиленовая 200мк | H114: м.кв. | I114: 119.4 | J114: 100 | K114: =IF(OR(E114="work",E114="section14_item"),I114*J114,0) | L114: =IF(E114="material",I114*J114,IF(E114="section15_percent",I114/100*(SUMPRODUCT((E$2:E$5000="work")*(B$2:B$5000<>"14")*K$2:K$5000)+SUMPRODUCT((E$2:E$5000="material")*(B$2:B$5000<>"14")*L$2:L$5000)),IF(E114="section15_manual",J114,0)))
A115: да | B115: 3 | C115: Монолитные железобетонные конструкции | E115: subsection | F115: 114 | G115: Лестницы - бассейн, к бассейну, на террасу, подпорная верхняя стенка | K115: =IF(OR(E115="work",E115="section14_item"),I115*J115,0) | L115: =IF(E115="material",I115*J115,IF(E115="section15_percent",I115/100*(SUMPRODUCT((E$2:E$5000="work")*(B$2:B$5000<>"14")*K$2:K$5000)+SUMPRODUCT((E$2:E$5000="material")*(B$2:B$5000<>"14")*L$2:L$5000)),IF(E115="section15_manual",J115,0)))
A116: да | B116: 3 | C116: Монолитные железобетонные конструкции | D116: Лестницы - бассейн, к бассейну, на террасу, подпорная верхняя стенка | E116: work | F116: 115 | G116: Сборка щитов опалубки, выставление опалубки, снятие опалубки | H116: м.кв. | I116: 24.8 | J116: 100 | K116: =IF(OR(E116="work",E116="section14_item"),I116*J116,0) | L116: =IF(E116="material",I116*J116,IF(E116="section15_percent",I116/100*(SUMPRODUCT((E$2:E$5000="work")*(B$2:B$5000<>"14")*K$2:K$5000)+SUMPRODUCT((E$2:E$5000="material")*(B$2:B$5000<>"14")*L$2:L$5000)),IF(E116="section15_manual",J116,0)))
A117: да | B117: 3 | C117: Монолитные железобетонные конструкции | D117: Лестницы - бассейн, к бассейну, на террасу, подпорная верхняя стенка | E117: material | F117: 116 | G117: Фанера ламинированная 18мм, доски | H117: м.кв. | I117: 24.8 | J117: 100 | K117: =IF(OR(E117="work",E117="section14_item"),I117*J117,0) | L117: =IF(E117="material",I117*J117,IF(E117="section15_percent",I117/100*(SUMPRODUCT((E$2:E$5000="work")*(B$2:B$5000<>"14")*K$2:K$5000)+SUMPRODUCT((E$2:E$5000="material")*(B$2:B$5000<>"14")*L$2:L$5000)),IF(E117="section15_manual",J117,0)))
A118: да | B118: 3 | C118: Монолитные железобетонные конструкции | D118: Лестницы - бассейн, к бассейну, на террасу, подпорная верхняя стенка | E118: material | F118: 117 | G118: Прочие материалы (крепеж, метизы, диски пильные, эмульсия) | H118: м.кв. | I118: 24.8 | J118: 100 | K118: =IF(OR(E118="work",E118="section14_item"),I118*J118,0) | L118: =IF(E118="material",I118*J118,IF(E118="section15_percent",I118/100*(SUMPRODUCT((E$2:E$5000="work")*(B$2:B$5000<>"14")*K$2:K$5000)+SUMPRODUCT((E$2:E$5000="material")*(B$2:B$5000<>"14")*L$2:L$5000)),IF(E118="section15_manual",J118,0)))
A119: да | B119: 3 | C119: Монолитные железобетонные конструкции | D119: Лестницы - бассейн, к бассейну, на террасу, подпорная верхняя стенка | E119: work | F119: 118 | G119: Устройство ж/б лестниц (армирование, заливка бетона) | H119: м.куб. | I119: 7.4 | J119: 100 | K119: =IF(OR(E119="work",E119="section14_item"),I119*J119,0) | L119: =IF(E119="material",I119*J119,IF(E119="section15_percent",I119/100*(SUMPRODUCT((E$2:E$5000="work")*(B$2:B$5000<>"14")*K$2:K$5000)+SUMPRODUCT((E$2:E$5000="material")*(B$2:B$5000<>"14")*L$2:L$5000)),IF(E119="section15_manual",J119,0)))
A120: да | B120: 3 | C120: Монолитные железобетонные конструкции | D120: Лестницы - бассейн, к бассейну, на террасу, подпорная верхняя стенка | E120: material | F120: 119 | G120: Бетон товарный В25 W8 F150 | H120: м.куб. | I120: 8.1 | J120: 100 | K120: =IF(OR(E120="work",E120="section14_item"),I120*J120,0) | L120: =IF(E120="material",I120*J120,IF(E120="section15_percent",I120/100*(SUMPRODUCT((E$2:E$5000="work")*(B$2:B$5000<>"14")*K$2:K$5000)+SUMPRODUCT((E$2:E$5000="material")*(B$2:B$5000<>"14")*L$2:L$5000)),IF(E120="section15_manual",J120,0)))
A121: да | B121: 3 | C121: Монолитные железобетонные конструкции | D121: Лестницы - бассейн, к бассейну, на террасу, подпорная верхняя стенка | E121: work | F121: 120 | G121: Аренда бетононасоса | H121: маш./см. | I121: 2 | J121: 100 | K121: =IF(OR(E121="work",E121="section14_item"),I121*J121,0) | L121: =IF(E121="material",I121*J121,IF(E121="section15_percent",I121/100*(SUMPRODUCT((E$2:E$5000="work")*(B$2:B$5000<>"14")*K$2:K$5000)+SUMPRODUCT((E$2:E$5000="material")*(B$2:B$5000<>"14")*L$2:L$5000)),IF(E121="section15_manual",J121,0)))
A122: да | B122: 3 | C122: Монолитные железобетонные конструкции | D122: Лестницы - бассейн, к бассейну, на террасу, подпорная верхняя стенка | E122: work | F122: 121 | G122: Аренда шлангов 30м | H122: маш./см. | I122: 2 | J122: 100 | K122: =IF(OR(E122="work",E122="section14_item"),I122*J122,0) | L122: =IF(E122="material",I122*J122,IF(E122="section15_percent",I122/100*(SUMPRODUCT((E$2:E$5000="work")*(B$2:B$5000<>"14")*K$2:K$5000)+SUMPRODUCT((E$2:E$5000="material")*(B$2:B$5000<>"14")*L$2:L$5000)),IF(E122="section15_manual",J122,0)))
A123: да | B123: 3 | C123: Монолитные железобетонные конструкции | D123: Лестницы - бассейн, к бассейну, на террасу, подпорная верхняя стенка | E123: material | F123: 122 | G123: Прочие материалы (бруски, метизы, вязальная проволока, фиксаторы для арматуры, диски алмазные, отрезные) | H123: м.кв. | I123: 24.8 | J123: 100 | K123: =IF(OR(E123="work",E123="section14_item"),I123*J123,0) | L123: =IF(E123="material",I123*J123,IF(E123="section15_percent",I123/100*(SUMPRODUCT((E$2:E$5000="work")*(B$2:B$5000<>"14")*K$2:K$5000)+SUMPRODUCT((E$2:E$5000="material")*(B$2:B$5000<>"14")*L$2:L$5000)),IF(E123="section15_manual",J123,0)))
A124: да | B124: 3 | C124: Монолитные железобетонные конструкции | D124: Лестницы - бассейн, к бассейну, на террасу, подпорная верхняя стенка | E124: work | F124: 123 | G124: Уход за бетоном | H124: м.кв. | I124: 24.8 | J124: 100 | K124: =IF(OR(E124="work",E124="section14_item"),I124*J124,0) | L124: =IF(E124="material",I124*J124,IF(E124="section15_percent",I124/100*(SUMPRODUCT((E$2:E$5000="work")*(B$2:B$5000<>"14")*K$2:K$5000)+SUMPRODUCT((E$2:E$5000="material")*(B$2:B$5000<>"14")*L$2:L$5000)),IF(E124="section15_manual",J124,0)))
A125: да | B125: 3 | C125: Монолитные железобетонные конструкции | D125: Лестницы - бассейн, к бассейну, на террасу, подпорная верхняя стенка | E125: material | F125: 124 | G125: Пленка техническая полиэтиленовая 200мк | H125: м.кв. | I125: 29.76 | J125: 100 | K125: =IF(OR(E125="work",E125="section14_item"),I125*J125,0) | L125: =IF(E125="material",I125*J125,IF(E125="section15_percent",I125/100*(SUMPRODUCT((E$2:E$5000="work")*(B$2:B$5000<>"14")*K$2:K$5000)+SUMPRODUCT((E$2:E$5000="material")*(B$2:B$5000<>"14")*L$2:L$5000)),IF(E125="section15_manual",J125,0)))
A126: да | B126: 3 | C126: Монолитные железобетонные конструкции | D126: Лестницы - бассейн, к бассейну, на террасу, подпорная верхняя стенка | E126: work | F126: 125 | G126: Гидроизоляция ж/б конструкций обмазочная | H126: м.кв. | I126: 5 | J126: 100 | K126: =IF(OR(E126="work",E126="section14_item"),I126*J126,0) | L126: =IF(E126="material",I126*J126,IF(E126="section15_percent",I126/100*(SUMPRODUCT((E$2:E$5000="work")*(B$2:B$5000<>"14")*K$2:K$5000)+SUMPRODUCT((E$2:E$5000="material")*(B$2:B$5000<>"14")*L$2:L$5000)),IF(E126="section15_manual",J126,0)))
A127: да | B127: 3 | C127: Монолитные железобетонные конструкции | D127: Лестницы - бассейн, к бассейну, на террасу, подпорная верхняя стенка | E127: material | F127: 126 | G127: Гидроизоляционный материал Акваблокер Bostik, 14кг | H127: шт. | I127: 0.5 | J127: 100 | K127: =IF(OR(E127="work",E127="section14_item"),I127*J127,0) | L127: =IF(E127="material",I127*J127,IF(E127="section15_percent",I127/100*(SUMPRODUCT((E$2:E$5000="work")*(B$2:B$5000<>"14")*K$2:K$5000)+SUMPRODUCT((E$2:E$5000="material")*(B$2:B$5000<>"14")*L$2:L$5000)),IF(E127="section15_manual",J127,0)))
... A131: да | B131: 3 | C131: Монолитные железобетонные конструкции | D131: Лестницы - бассейн, к бассейну, на террасу, подпорная верхняя стенка | E131: material | F131: 130 | G131: Ж/б сваи забивные, фанера щиты | H131: м.п. | I131: 25 | J131: 100 | K131: =IF(OR(E131="work",E131="section14_item"),I131*J131,0) | L131: =IF(E131="material",I131*J131,IF(E131="section15_percent",I131/100*(SUMPRODUCT((E$2:E$5000="work")*(B$2:B$5000<>"14")*K$2:K$5000)+SUMPRODUCT((E$2:E$5000="material")*(B$2:B$5000<>"14")*L$2:L$5000)),IF(E131="section15_manual",J131,0)))
A132: да | B132: 4 | C132: Подпорные стенки, ступени - верхняя зона | E132: work | F132: 131 | G132: Устройство выравнивающего слоя под облицовку парапета гранитными плитами | H132: м.п. | I132: 36 | J132: 100 | K132: =IF(OR(E132="work",E132="section14_item"),I132*J132,0) | L132: =IF(E132="material",I132*J132,IF(E132="section15_percent",I132/100*(SUMPRODUCT((E$2:E$5000="work")*(B$2:B$5000<>"14")*K$2:K$5000)+SUMPRODUCT((E$2:E$5000="material")*(B$2:B$5000<>"14")*L$2:L$5000)),IF(E132="section15_manual",J132,0)))
A133: да | B133: 4 | C133: Подпорные стенки, ступени - верхняя зона | E133: material | F133: 132 | G133: Грунт, ЦПС М300 | H133: компл. | I133: 1 | J133: 100 | K133: =IF(OR(E133="work",E133="section14_item"),I133*J133,0) | L133: =IF(E133="material",I133*J133,IF(E133="section15_percent",I133/100*(SUMPRODUCT((E$2:E$5000="work")*(B$2:B$5000<>"14")*K$2:K$5000)+SUMPRODUCT((E$2:E$5000="material")*(B$2:B$5000<>"14")*L$2:L$5000)),IF(E133="section15_manual",J133,0)))
A134: да | B134: 4 | C134: Подпорные стенки, ступени - верхняя зона | E134: work | F134: 133 | G134: Герметизация примыканий полиуретановым герметиком - примыкание плит перепета по периметру | H134: м.п. | I134: 65 | J134: 100 | K134: =IF(OR(E134="work",E134="section14_item"),I134*J134,0) | L134: =IF(E134="material",I134*J134,IF(E134="section15_percent",I134/100*(SUMPRODUCT((E$2:E$5000="work")*(B$2:B$5000<>"14")*K$2:K$5000)+SUMPRODUCT((E$2:E$5000="material")*(B$2:B$5000<>"14")*L$2:L$5000)),IF(E134="section15_manual",J134,0)))
A135: да | B135: 4 | C135: Подпорные стенки, ступени - верхняя зона | E135: material | F135: 134 | G135: Герметик полиуретановый, 600мл | H135: шт. | I135: 14 | J135: 100 | K135: =IF(OR(E135="work",E135="section14_item"),I135*J135,0) | L135: =IF(E135="material",I135*J135,IF(E135="section15_percent",I135/100*(SUMPRODUCT((E$2:E$5000="work")*(B$2:B$5000<>"14")*K$2:K$5000)+SUMPRODUCT((E$2:E$5000="material")*(B$2:B$5000<>"14")*L$2:L$5000)),IF(E135="section15_manual",J135,0)))
A136: да | B136: 4 | C136: Подпорные стенки, ступени - верхняя зона | E136: work | F136: 135 | G136: Облицовка гранитными плитами парапета | H136: м.п. | I136: 36 | J136: 100 | K136: =IF(OR(E136="work",E136="section14_item"),I136*J136,0) | L136: =IF(E136="material",I136*J136,IF(E136="section15_percent",I136/100*(SUMPRODUCT((E$2:E$5000="work")*(B$2:B$5000<>"14")*K$2:K$5000)+SUMPRODUCT((E$2:E$5000="material")*(B$2:B$5000<>"14")*L$2:L$5000)),IF(E136="section15_manual",J136,0)))
A137: да | B137: 4 | C137: Подпорные стенки, ступени - верхняя зона | E137: material | F137: 136 | G137: Плиты гранитные 1000*350*80мм (термообработанные верх, торцы, фаска, капельник) | H137: м.п. | I137: 36 | J137: 100 | K137: =IF(OR(E137="work",E137="section14_item"),I137*J137,0) | L137: =IF(E137="material",I137*J137,IF(E137="section15_percent",I137/100*(SUMPRODUCT((E$2:E$5000="work")*(B$2:B$5000<>"14")*K$2:K$5000)+SUMPRODUCT((E$2:E$5000="material")*(B$2:B$5000<>"14")*L$2:L$5000)),IF(E137="section15_manual",J137,0)))
A138: да | B138: 4 | C138: Подпорные стенки, ступени - верхняя зона | E138: material | F138: 137 | G138: Диски алмазные | H138: шт. | I138: 1 | J138: 100 | K138: =IF(OR(E138="work",E138="section14_item"),I138*J138,0) | L138: =IF(E138="material",I138*J138,IF(E138="section15_percent",I138/100*(SUMPRODUCT((E$2:E$5000="work")*(B$2:B$5000<>"14")*K$2:K$5000)+SUMPRODUCT((E$2:E$5000="material")*(B$2:B$5000<>"14")*L$2:L$5000)),IF(E138="section15_manual",J138,0)))
A139: да | B139: 4 | C139: Подпорные стенки, ступени - верхняя зона | E139: material | F139: 138 | G139: Клей для плитки, керамогранита, мозаики и камня Weber Vetonit Ultra fix серый (класс С2), 25кг | H139: меш. | I139: 10 | J139: 100 | K139: =IF(OR(E139="work",E139="section14_item"),I139*J139,0) | L139: =IF(E139="material",I139*J139,IF(E139="section15_percent",I139/100*(SUMPRODUCT((E$2:E$5000="work")*(B$2:B$5000<>"14")*K$2:K$5000)+SUMPRODUCT((E$2:E$5000="material")*(B$2:B$5000<>"14")*L$2:L$5000)),IF(E139="section15_manual",J139,0)))
A140: да | B140: 4 | C140: Подпорные стенки, ступени - верхняя зона | E140: material | F140: 139 | G140: Затирка Литокол Старлайк 2,5кг | H140: шт. | I140: 2 | J140: 100 | K140: =IF(OR(E140="work",E140="section14_item"),I140*J140,0) | L140: =IF(E140="material",I140*J140,IF(E140="section15_percent",I140/100*(SUMPRODUCT((E$2:E$5000="work")*(B$2:B$5000<>"14")*K$2:K$5000)+SUMPRODUCT((E$2:E$5000="material")*(B$2:B$5000<>"14")*L$2:L$5000)),IF(E140="section15_manual",J140,0)))
A141: да | B141: 4 | C141: Подпорные стенки, ступени - верхняя зона | E141: material | F141: 140 | G141: Доставка плит манипулятором (учтено в разделе "Орг.затраты") | H141: кол-во раз | I141: 1 | K141: =IF(OR(E141="work",E141="section14_item"),I141*J141,0) | L141: =IF(E141="material",I141*J141,IF(E141="section15_percent",I141/100*(SUMPRODUCT((E$2:E$5000="work")*(B$2:B$5000<>"14")*K$2:K$5000)+SUMPRODUCT((E$2:E$5000="material")*(B$2:B$5000<>"14")*L$2:L$5000)),IF(E141="section15_manual",J141,0)))
A142: да | B142: 4 | C142: Подпорные стенки, ступени - верхняя зона | E142: work | F142: 141 | G142: Облицовка гранитными плитами ступеней | H142: м.п. | I142: 21 | J142: 100 | K142: =IF(OR(E142="work",E142="section14_item"),I142*J142,0) | L142: =IF(E142="material",I142*J142,IF(E142="section15_percent",I142/100*(SUMPRODUCT((E$2:E$5000="work")*(B$2:B$5000<>"14")*K$2:K$5000)+SUMPRODUCT((E$2:E$5000="material")*(B$2:B$5000<>"14")*L$2:L$5000)),IF(E142="section15_manual",J142,0)))
...

Sheet Печатная форма
C1: Ландшафтная студия БОТАНИК Бухарестская ул., д. 110, к. 1 Санкт-Петербург, 192288
B8: Коммерческое предложение №__________.
B9: Расчет цен произведен __.___.202__г. (цены действительны в течение 7 календарных дней с даты расчета).
B11: Заказчик: ____________________________________________________________
B12: Исполнитель: Ландшафтная студия БОТАНИК
B13: Адрес проведения работ:
B15: Сроки проведения работ:
B16: начало
B17: окончание
B19: Работы по благоустройству.
B20: Наименование работ | G20: Стоимость
A21: 1 | B21: Подготовительные земельные работы | G21: =SUMIFS(Расчет!K:K,Расчет!B:B,"1",Расчет!E:E,"work")+SUMIFS(Расчет!K:K,Расчет!B:B,"1",Расчет!E:E,"section14_item")+SUMIFS(Расчет!L:L,Расчет!B:B,"1")
A22: 2 | B22: Дренажная и ливневая системы. | G22: =SUMIFS(Расчет!K:K,Расчет!B:B,"2",Расчет!E:E,"work")+SUMIFS(Расчет!K:K,Расчет!B:B,"2",Расчет!E:E,"section14_item")+SUMIFS(Расчет!L:L,Расчет!B:B,"2")
A23: 3 | B23: Монолитные железобетонные конструкции | G23: =SUMIFS(Расчет!K:K,Расчет!B:B,"3",Расчет!E:E,"work")+SUMIFS(Расчет!K:K,Расчет!B:B,"3",Расчет!E:E,"section14_item")+SUMIFS(Расчет!L:L,Расчет!B:B,"3")
A24: 4 | B24: Подпорные стенки, ступени - верхняя зона | G24: =SUMIFS(Расчет!K:K,Расчет!B:B,"4",Расчет!E:E,"work")+SUMIFS(Расчет!K:K,Расчет!B:B,"4",Расчет!E:E,"section14_item")+SUMIFS(Расчет!L:L,Расчет!B:B,"4")
A25: 5 | B25: Покрытия. | G25: =SUMIFS(Расчет!K:K,Расчет!B:B,"5",Расчет!E:E,"work")+SUMIFS(Расчет!K:K,Расчет!B:B,"5",Расчет!E:E,"section14_item")+SUMIFS(Расчет!L:L,Расчет!B:B,"5")
A26: 6 | B26: Лестница в нижнюю часть участка | G26: =SUMIFS(Расчет!K:K,Расчет!B:B,"6",Расчет!E:E,"work")+SUMIFS(Расчет!K:K,Расчет!B:B,"6",Расчет!E:E,"section14_item")+SUMIFS(Расчет!L:L,Расчет!B:B,"6")
A27: 7 | B27: Террасные настилы. | G27: =SUMIFS(Расчет!K:K,Расчет!B:B,"7",Расчет!E:E,"work")+SUMIFS(Расчет!K:K,Расчет!B:B,"7",Расчет!E:E,"section14_item")+SUMIFS(Расчет!L:L,Расчет!B:B,"7")
A28: 8 | B28: Освещение. | G28: =SUMIFS(Расчет!K:K,Расчет!B:B,"8",Расчет!E:E,"work")+SUMIFS(Расчет!K:K,Расчет!B:B,"8",Расчет!E:E,"section14_item")+SUMIFS(Расчет!L:L,Расчет!B:B,"8")
A29: 9 | B29: Газон. | G29: =SUMIFS(Расчет!K:K,Расчет!B:B,"9",Расчет!E:E,"work")+SUMIFS(Расчет!K:K,Расчет!B:B,"9",Расчет!E:E,"section14_item")+SUMIFS(Расчет!L:L,Расчет!B:B,"9")
A30: 10 | B30: Ограждение стеклянное | G30: =SUMIFS(Расчет!K:K,Расчет!B:B,"10",Расчет!E:E,"work")+SUMIFS(Расчет!K:K,Расчет!B:B,"10",Расчет!E:E,"section14_item")+SUMIFS(Расчет!L:L,Расчет!B:B,"10")
A31: 11 | B31: Автополив | G31: =SUMIFS(Расчет!K:K,Расчет!B:B,"11",Расчет!E:E,"work")+SUMIFS(Расчет!K:K,Расчет!B:B,"11",Расчет!E:E,"section14_item")+SUMIFS(Расчет!L:L,Расчет!B:B,"11")
A32: 12 | B32: Бассейн | G32: =SUMIFS(Расчет!K:K,Расчет!B:B,"12",Расчет!E:E,"work")+SUMIFS(Расчет!K:K,Расчет!B:B,"12",Расчет!E:E,"section14_item")+SUMIFS(Расчет!L:L,Расчет!B:B,"12")
A33: 13 | B33: Антиобледенение | G33: =SUMIFS(Расчет!K:K,Расчет!B:B,"13",Расчет!E:E,"work")+SUMIFS(Расчет!K:K,Расчет!B:B,"13",Расчет!E:E,"section14_item")+SUMIFS(Расчет!L:L,Расчет!B:B,"13")
A34: 14 | B34: Вывоз грунта (по факту) | G34: =SUMIFS(Расчет!K:K,Расчет!B:B,"14",Расчет!E:E,"work")+SUMIFS(Расчет!K:K,Расчет!B:B,"14",Расчет!E:E,"section14_item")+SUMIFS(Расчет!L:L,Расчет!B:B,"14")
A35: 15 | B35: Организационные затраты (предварительно) | G35: =SUMIFS(Расчет!K:K,Расчет!B:B,"15",Расчет!E:E,"work")+SUMIFS(Расчет!K:K,Расчет!B:B,"15",Расчет!E:E,"section14_item")+SUMIFS(Расчет!L:L,Расчет!B:B,"15")
B36: ВСЕГО по смете: | G36: =SUM(G21:G35)
A39: 1. | B39: Подготовительные земельные работы | C39: Ед. изм. | D39: Кол-во | E39: Цена | F39: Работы | G39: Материалы | H39: Примечание
A40: 1 | B40: =Расчет!G2 | C40: =Расчет!H2 | D40: =Расчет!I2 | E40: =Расчет!J2 | F40: =Расчет!K2 | H40: =Расчет!M2
A41: 2 | B41: =Расчет!G3 | C41: =Расчет!H3 | D41: =Расчет!I3 | E41: =Расчет!J3 | F41: =Расчет!K3 | H41: =Расчет!M3
A42: 3 | B42: =Расчет!G4 | C42: =Расчет!H4 | D42: =Расчет!I4 | E42: =Расчет!J4 | F42: =Расчет!K4 | H42: =Расчет!M4
A43: 4 | B43: =Расчет!G5 | C43: =Расчет!H5 | D43: =Расчет!I5 | E43: =Расчет!J5 | F43: =Расчет!K5 | H43: =Расчет!M5
B44: =Расчет!G6 | C44: =Расчет!H6 | D44: =Расчет!I6 | E44: =Расчет!J6 | G44: =Расчет!L6 | H44: =Расчет!M6
A45: 5 | B45: =Расчет!G7 | C45: =Расчет!H7 | D45: =Расчет!I7 | E45: =Расчет!J7 | F45: =Расчет!K7 | H45: =Расчет!M7
A46: 6 | B46: =Расчет!G8 | C46: =Расчет!H8 | D46: =Расчет!I8 | E46: =Расчет!J8 | F46: =Расчет!K8 | H46: =Расчет!M8
B47: Нижняя зона участка
A48: 7 | B48: =Расчет!G10 | C48: =Расчет!H10 | D48: =Расчет!I10 | E48: =Расчет!J10 | F48: =Расчет!K10 | H48: =Расчет!M10
A49: 8 | B49: =Расчет!G11 | C49: =Расчет!H11 | D49: =Расчет!I11 | E49: =Расчет!J11 | F49: =Расчет!K11 | H49: =Расчет!M11
A50: 9 | B50: =Расчет!G12 | C50: =Расчет!H12 | D50: =Расчет!I12 | E50: =Расчет!J12 | F50: =Расчет!K12 | H50: =Расчет!M12
A51: 10 | B51: =Расчет!G13 | C51: =Расчет!H13 | D51: =Расчет!I13 | E51: =Расчет!J13 | F51: =Расчет!K13 | H51: =Расчет!M13
B52: Бассейн
A53: 11 | B53: =Расчет!G15 | C53: =Расчет!H15 | D53: =Расчет!I15 | E53: =Расчет!J15 | F53: =Расчет!K15 | H53: =Расчет!M15
A54: 12 | B54: =Расчет!G16 | C54: =Расчет!H16 | D54: =Расчет!I16 | E54: =Расчет!J16 | F54: =Расчет!K16 | H54: =Расчет!M16
A55: 13 | B55: =Расчет!G17 | C55: =Расчет!H17 | D55: =Расчет!I17 | E55: =Расчет!J17 | F55: =Расчет!K17 | H55: =Расчет!M17
B56: =Расчет!G18 | C56: =Расчет!H18 | D56: =Расчет!I18 | E56: =Расчет!J18 | G56: =Расчет!L18 | H56: =Расчет!M18
B57: =Расчет!G19 | C57: =Расчет!H19 | D57: =Расчет!I19 | E57: =Расчет!J19 | G57: =Расчет!L19 | H57: =Расчет!M19
A58: 14 | B58: =Расчет!G20 | C58: =Расчет!H20 | D58: =Расчет!I20 | E58: =Расчет!J20 | F58: =Расчет!K20 | H58: =Расчет!M20
B59: ВСЕГО ПО РАЗДЕЛУ: | F59: =SUMIFS(Расчет!K:K,Расчет!B:B,"1",Расчет!E:E,"work")+SUMIFS(Расчет!K:K,Расчет!B:B,"1",Расчет!E:E,"section14_item") | G59: =SUMIFS(Расчет!L:L,Расчет!B:B,"1",Расчет!E:E,"material")
B60: ИТОГО: | G60: =SUMIFS(Расчет!K:K,Расчет!B:B,"1",Расчет!E:E,"work")+SUMIFS(Расчет!K:K,Расчет!B:B,"1",Расчет!E:E,"section14_item")+SUMIFS(Расчет!L:L,Расчет!B:B,"1")
A62: 2. | B62: Дренажная и ливневая системы. | C62: Ед. изм. | D62: Кол-во | E62: Цена | F62: Работы | G62: Материалы | H62: Примечание
A63: 1 | B63: =Расчет!G21 | C63: =Расчет!H21 | D63: =Расчет!I21 | E63: =Расчет!J21 | F63: =Расчет!K21 | H63: =Расчет!M21
B64: =Расчет!G22 | C64: =Расчет!H22 | D64: =Расчет!I22 | E64: =Расчет!J22 | G64: =Расчет!L22 | H64: =Расчет!M22
B65: =Расчет!G23 | C65: =Расчет!H23 | D65: =Расчет!I23 | E65: =Расчет!J23 | G65: =Расчет!L23 | H65: =Расчет!M23
B66: =Расчет!G24 | C66: =Расчет!H24 | D66: =Расчет!I24 | E66: =Расчет!J24 | G66: =Расчет!L24 | H66: =Расчет!M24
A67: 2 | B67: =Расчет!G25 | C67: =Расчет!H25 | D67: =Расчет!I25 | E67: =Расчет!J25 | F67: =Расчет!K25 | H67: =Расчет!M25
A68: 3 | B68: =Расчет!G26 | C68: =Расчет!H26 | D68: =Расчет!I26 | E68: =Расчет!J26 | F68: =Расчет!K26 | H68: =Расчет!M26
B69: =Расчет!G27 | C69: =Расчет!H27 | D69: =Расчет!I27 | E69: =Расчет!J27 | G69: =Расчет!L27 | H69: =Расчет!M27
A70: 4 | B70: =Расчет!G28 | C70: =Расчет!H28 | D70: =Расчет!I28 | E70: =Расчет!J28 | F70: =Расчет!K28 | H70: =Расчет!M28
B71: =Расчет!G29 | C71: =Расчет!H29 | D71: =Расчет!I29 | E71: =Расчет!J29 | G71: =Расчет!L29 | H71: =Расчет!M29
B72: =Расчет!G30 | C72: =Расчет!H30 | D72: =Расчет!I30 | E72: =Расчет!J30 | G72: =Расчет!L30 | H72: =Расчет!M30
B73: =Расчет!G31 | C73: =Расчет!H31 | D73: =Расчет!I31 | E73: =Расчет!J31 | G73: =Расчет!L31 | H73: =Расчет!M31
B74: =Расчет!G32 | C74: =Расчет!H32 | D74: =Расчет!I32 | E74: =Расчет!J32 | G74: =Расчет!L32 | H74: =Расчет!M32
A75: 5 | B75: =Расчет!G33 | C75: =Расчет!H33 | D75: =Расчет!I33 | E75: =Расчет!J33 | F75: =Расчет!K33 | H75: =Расчет!M33
B76: =Расчет!G34 | C76: =Расчет!H34 | D76: =Расчет!I34 | E76: =Расчет!J34 | G76: =Расчет!L34 | H76: =Расчет!M34
B77: =Расчет!G35 | C77: =Расчет!H35 | D77: =Расчет!I35 | E77: =Расчет!J35 | G77: =Расчет!L35 | H77: =Расчет!M35
A78: 6 | B78: =Расчет!G36 | C78: =Расчет!H36 | D78: =Расчет!I36 | E78: =Расчет!J36 | F78: =Расчет!K36 | H78: =Расчет!M36
A79: 7 | B79: =Расчет!G37 | C79: =Расчет!H37 | D79: =Расчет!I37 | E79: =Расчет!J37 | F79: =Расчет!K37 | H79: =Расчет!M37
A80: 8 | B80: =Расчет!G38 | C80: =Расчет!H38 | D80: =Расчет!I38 | E80: =Расчет!J38 | F80: =Расчет!K38 | H80: =Расчет!M38
B81: =Расчет!G39 | C81: =Расчет!H39 | D81: =Расчет!I39 | E81: =Расчет!J39 | G81: =Расчет!L39 | H81: =Расчет!M39
B82: =Расчет!G40 | C82: =Расчет!H40 | D82: =Расчет!I40 | E82: =Расчет!J40 | G82: =Расчет!L40 | H82: =Расчет!M40
A83: 9 | B83: =Расчет!G41 | C83: =Расчет!H41 | D83: =Расчет!I41 | E83: =Расчет!J41 | F83: =Расчет!K41 | H83: =Расчет!M41
B84: =Расчет!G42 | C84: =Расчет!H42 | D84: =Расчет!I42 | E84: =Расчет!J42 | G84: =Расчет!L42 | H84: =Расчет!M42
B85: =Расчет!G43 | C85: =Расчет!H43 | D85: =Расчет!I43 | E85: =Расчет!J43 | G85: =Расчет!L43 | H85: =Расчет!M43
A86: 10 | B86: =Расчет!G44 | C86: =Расчет!H44 | D86: =Расчет!I44 | E86: =Расчет!J44 | F86: =Расчет!K44 | H86: =Расчет!M44
B87: =Расчет!G45 | C87: =Расчет!H45 | D87: =Расчет!I45 | E87: =Расчет!J45 | G87: =Расчет!L45 | H87: =Расчет!M45
B88: =Расчет!G46 | C88: =Расчет!H46 | D88: =Расчет!I46 | E88: =Расчет!J46 | G88: =Расчет!L46 | H88: =Расчет!M46
B89: ВСЕГО ПО РАЗДЕЛУ: | F89: =SUMIFS(Расчет!K:K,Расчет!B:B,"2",Расчет!E:E,"work")+SUMIFS(Расчет!K:K,Расчет!B:B,"2",Расчет!E:E,"section14_item") | G89: =SUMIFS(Расчет!L:L,Расчет!B:B,"2",Расчет!E:E,"material")
B90: ИТОГО: | G90: =SUMIFS(Расчет!K:K,Расчет!B:B,"2",Расчет!E:E,"work")+SUMIFS(Расчет!K:K,Расчет!B:B,"2",Расчет!E:E,"section14_item")+SUMIFS(Расчет!L:L,Расчет!B:B,"2")
A92: 3. | B92: Монолитные железобетонные конструкции | C92: Ед. изм. | D92: Кол-во | E92: Цена | F92: Работы | G92: Материалы | H92: Примечание
B93: Плита основания - 75м2
A94: 1 | B94: =Расчет!G48 | C94: =Расчет!H48 | D94: =Расчет!I48 | E94: =Расчет!J48 | F94: =Расчет!K48 | H94: =Расчет!M48
B95: =Расчет!G49 | C95: =Расчет!H49 | D95: =Расчет!I49 | E95: =Расчет!J49 | G95: =Расчет!L49 | H95: =Расчет!M49
A96: 2 | B96: =Расчет!G50 | C96: =Расчет!H50 | D96: =Расчет!I50 | E96: =Расчет!J50 | F96: =Расчет!K50 | H96: =Расчет!M50
A97: 3 | B97: =Расчет!G51 | C97: =Расчет!H51 | D97: =Расчет!I51 | E97: =Расчет!J51 | F97: =Расчет!K51 | H97: =Расчет!M51
B98: =Расчет!G52 | C98: =Расчет!H52 | D98: =Расчет!I52 | E98: =Расчет!J52 | G98: =Расчет!L52 | H98: =Расчет!M52
A99: 4 | B99: =Расчет!G53 | C99: =Расчет!H53 | D99: =Расчет!I53 | E99: =Расчет!J53 | F99: =Расчет!K53 | H99: =Расчет!M53
B100: =Расчет!G54 | C100: =Расчет!H54 | D100: =Расчет!I54 | E100: =Расчет!J54 | G100: =Расчет!L54 | H100: =Расчет!M54
B101: =Расчет!G55 | C101: =Расчет!H55 | D101: =Расчет!I55 | E101: =Расчет!J55 | G101: =Расчет!L55 | H101: =Расчет!M55
A102: 5 | B102: =Расчет!G56 | C102: =Расчет!H56 | D102: =Расчет!I56 | E102: =Расчет!J56 | F102: =Расчет!K56 | H102: =Расчет!M56
A103: 6 | B103: =Расчет!G57 | C103: =Расчет!H57 | D103: =Расчет!I57 | E103: =Расчет!J57 | F103: =Расчет!K57 | H103: =Расчет!M57
A104: 7 | B104: =Расчет!G58 | C104: =Расчет!H58 | D104: =Расчет!I58 | E104: =Расчет!J58 | F104: =Расчет!K58 | H104: =Расчет!M58
B105: =Расчет!G59 | C105: =Расчет!H59 | D105: =Расчет!I59 | E105: =Расчет!J59 | G105: =Расчет!L59 | H105: =Расчет!M59
A106: 8 | B106: =Расчет!G60 | C106: =Расчет!H60 | D106: =Расчет!I60 | E106: =Расчет!J60 | F106: =Расчет!K60 | H106: =Расчет!M60
B107: =Расчет!G61 | C107: =Расчет!H61 | D107: =Расчет!I61 | E107: =Расчет!J61 | G107: =Расчет!L61 | H107: =Расчет!M61
B108: =Расчет!G62 | C108: =Расчет!H62 | D108: =Расчет!I62 | E108: =Расчет!J62 | G108: =Расчет!L62 | H108: =Расчет!M62
A109: 9 | B109: =Расчет!G63 | C109: =Расчет!H63 | D109: =Расчет!I63 | E109: =Расчет!J63 | F109: =Расчет!K63 | H109: =Расчет!M63
B110: =Расчет!G64 | C110: =Расчет!H64 | D110: =Расчет!I64 | E110: =Расчет!J64 | G110: =Расчет!L64 | H110: =Расчет!M64
B111: =Расчет!G65 | C111: =Расчет!H65 | D111: =Расчет!I65 | E111: =Расчет!J65 | G111: =Расчет!L65 | H111: =Расчет!M65
A112: 10 | B112: =Расчет!G66 | C112: =Расчет!H66 | D112: =Расчет!I66 | E112: =Расчет!J66 | F112: =Расчет!K66 | H112: =Расчет!M66
A113: 11 | B113: =Расчет!G67 | C113: =Расчет!H67 | D113: =Расчет!I67 | E113: =Расчет!J67 | F113: =Расчет!K67 | H113: =Расчет!M67
...
